Workbook
Name _Toc95402285: Отель2!#REF!
Name _Toc95402285: Отель3!#REF!
Name _Toc95402285: Отель4!#REF!
Name _Toc95402285: Отель5!#REF!
Name _Toc95402285: Резиденции!#REF!
Name _Toc95402285: Хостел!#REF!
Name _Toc95402285: Шале!$C$12
Name flag: TRUE
Name vat: [1]Вводные!$D$10
Name vat: [2]Вводные!$D$9
Name vat: [3]Вводные!$D$10
Name vat: [1]Вводные!$D$10

Sheet PEAK'ING ---->>

Sheet Отель5
A1: 1
C2: Вводные технико-экономические показатели | E2: Гостиница 5* | F2: =F14 -> Mövenpick
E3: Ед. измерения | F3: Значение | J3: Предложения CW | N3: Комментарий CW
C4: 1 | D4: Предварительная общая площадь | E4: кв.м | F4: =Бюджет_Синара!B41 -> 11947.619 | N4: Предложение по увеличению количества номеров с сохранением общей площади номерного фонда
C5: =C4+1 -> 2 | D5: Класс объекта по стандартам РФ | F5: Гостиница "5 звезд" | J5: =F4/F6 -> 95.580951 | K5: кв.м общей S/номер
C6: =C5+1 -> 3 | D6: Количество номеров всего | E6: номера | F6: 125 | H6: мест/номер | I6: Мест всего | J6: кв.м/номер | K6: кв.м
D7: в т.ч. номера класса люкс | E7: номера | F7: =ROUND($F$6*G7,0) -> 13 | G7: 0.1 | H7: 4 | I7: =H7*F7 -> 52 | J7: =J8*1.5 -> 54 | K7: =F7*J7 -> 702
D8: в т.ч. номера класса твин и дабл (на 1 и 2 проживающих) | E8: номера | F8: =ROUND($F$6*G8,0) -> 106 | G8: 0.85 | H8: 2 | I8: =H8*F8 -> 212 | J8: 36 | K8: =F8*J8 -> 3816
D9: в т.ч. номера для ЛОВ | E9: номера | F9: =F6-F8-F7 -> 6 | G9: 0.05 | H9: 2 | I9: =H9*F9 -> 12 | J9: =J8 -> 36 | K9: =F9*J9 -> 216
C10: =C6+1 -> 4 | D10: Количество мест для проживающих (человек) | E10: мест | F10: =SUM(I7:I9) -> 276 | G10: =F10/F6 -> 2.208 | J10: S ном.фонда | K10: =SUM(K7:K9) -> 4734
C11: =C10+1 -> 5 | D11: Площадь номерного фонда | E11: кв.м | F11: =Бюджет_Синара!B7 -> 4750 | G11: =F11/F6 -> 38 | H11: кв.м/номер | K11: =K10/F6 -> 37.872 | L11: кв.м/номер
C12: =C11+1 -> 6 | D12: Наличие крытой парковки (количество мест) | F12: =Объекты!E66 -> 37.037037
C13: =C12+1 -> 7 | D13: Наличие СПА с бассейном: 2 бассейна в составе СПА, фитнес-зал | E13: кв.м в составе объекта | F13: =Бюджет_Синара!B19 -> 1943
C14: =C13+1 -> 8 | D14: Бренд | F14: Mövenpick
C15: =C14+1 -> 9 | D15: Ресторан - количество посадочных мест | E15: посадочных мест | F15: 100
C16: =C15+1 -> 10 | D16: Ресторан - площадь зала | E16: кв.м | F16: =Бюджет_Синара!B13 -> 327 | G16: =F16/F15 -> 3.27 | H16: кв.м/п.место
C17: =C16+1 -> 11 | D17: Залы и переговорные | E17: кв.м | F17: =Бюджет_Синара!B21 -> 175
C18: =C17+1 -> 12 | D18: Фойе | E18: кв.м | F18: =Бюджет_Синара!B23 -> 135
C19: =C18+1 -> 13 | D19: Размер номера люкс | F19: В соответствии с требованиями бренда
C20: =C19+1 -> 14 | D20: Размер номера дабл или твин
C21: =C20+1 -> 15 | D21: Этажность | E21: этажей | F21: Не более 5
C22: =C21+1 -> 16 | D22: Особые требования к компоновке объекта | F22: а) Здание должно быть объединено общими технологическими потоками с отелем 4*
F23: б) Между зданиями отель 5* и зданием отель 4* должен быть запланирован канал для инженерных коммуникаций под самым нижним этажом стилобата. Канал требуется разместить в между зданиями под пожарным проездом
F24: в) Executive Lounge и открытый бассейн должны быть расположены с западной стороны отеля
C25: =C22+1 -> 17 | D25: Наличие технологического этажа высотой до 1800 мм между жилыми этажами и этажами с размещением общественных зон | F25: Да, требуется
C26: =C25+1 -> 18 | D26: Дополнительные технологии в составе объекта | F26: Экзекьютив лаудж ( Executive Lounge ) 120 кв.м сблокированный, с панорамным бассейном. Бассейн с совмещенной внутренней и наружной чашей. Оба функционала разместить в составе одного из верхних этажей. Лыжехранилище - 20 кв.м

Sheet Отель4
A1: 1
C2: Вводные технико-экономические показатели | E2: Гостиница 4* | F2: =F13 -> Mercure
E3: Ед. измерения | F3: Значение | H3: Комментарий | K3: Предложения CW | O3: Комментарий CW
C4: 1 | D4: Предварительная общая площадь | E4: кв.м | F4: =Бюджет_Синара!B84 -> 12475 | O4: Предложение по увеличению количества номеров с сохранением общей площади номерного фонда
C5: =C4+1 -> 2 | D5: Класс объекта по стандартам РФ | F5: Гостиница "4 звезды" | K5: =F4/F6 -> 77.96875 | L5: кв.м общей S/номер
C6: =C5+1 -> 3 | D6: Количество номеров всего | E6: номера | F6: 160 | I6: мест/номер | J6: Мест всего | K6: кв.м/номер | L6: кв.м
D7: в т.ч. номера класса люкс | E7: номера | F7: =ROUND($F$6*G7,0) -> 13 | G7: 0.08 | I7: 4 | J7: =I7*F7 -> 52 | K7: =K8*1.25 -> 30 | L7: =F7*K7 -> 390
D8: в т.ч. номера класса твин и дабл (на 1 и 2 проживающих) | E8: номера | F8: =ROUND($F$6*G8,0) -> 147 | G8: 0.92 | I8: 2 | J8: =I8*F8 -> 294 | K8: 24 | L8: =F8*K8 -> 3528
C9: =C6+1 -> 4 | D9: Количество мест для проживающих (человек) | E9: мест | F9: =SUM(J7:J8) -> 346 | G9: =F9/F6 -> 2.1625
C10: =C9+1 -> 5 | D10: Площадь номерного фонда | E10: кв.м | F10: =Бюджет_Синара!B50 -> 3925 | G10: =F10/F6 -> 24.53125 | H10: кв.м/номер | K10: S ном.фонда | L10: =SUM(L7:L9) -> 3918
C11: =C10+1 -> 6 | D11: Наличие крытой парковки (количество мест) | F11: общая с гостиницей 5* | L11: =L10/F6 -> 24.4875 | M11: кв.м/номер
C12: =C11+1 -> 7 | D12: Наличие конференц-залов | E12: кв.м в составе объекта | F12: 300 | G12: Многофункциональный зал с возможностью временной перепланировки раздвижными стенами для организации трех залов с площадями 150, 100 и 50 кв.м
C13: =C12+1 -> 8 | D13: Бренд | F13: Mercure
C14: =C13+1 -> 9 | D14: Наличие СПА | E14: кв.м | F14: =Бюджет_Синара!B62 -> 3561
C15: =C14+1 -> 10 | D15: Ресторан - количество посадочных мест | E15: посадочных мест | F15: 150
C16: =C15+1 -> 11 | D16: Ресторан - площадь зала | E16: кв.м | F16: =Бюджет_Синара!B56 -> 313 | G16: =F16/F15 -> 2.0866667 | H16: кв.м/п.место
C17: =C16+1 -> 12 | D17: Залы и переговорные | E17: кв.м | F17: =Бюджет_Синара!B64 -> 520
C18: =C17+1 -> 13 | D18: Фойе | E18: кв.м | F18: =Бюджет_Синара!B66 -> 135
C19: =C18+1 -> 14 | D19: Размер номера люкс | F19: В соответствии с требованиями бренда
C20: =C19+1 -> 15 | D20: Размер номера дабл или твин
C21: =C20+1 -> 16 | D21: Этажность | E21: этажей | F21: Не более 5
C22: =C21+1 -> 17 | D22: Торговая зона отеля 4* | F22: =Бюджет_Синара!B83 -> 1000
C23: =C22+1 -> 18 | D23: Особые требования к компоновке объекта | F23: а) Здание должно быть объединено общими технологическими потоками с отелем 4*
F24: б) Между зданиями отель 5* и зданием отель 4* должен быть запланирован канал для инженерных коммуникаций под самым нижним этажом стилобата. Канал требуется разместить в между зданиями под пожарным проездом
F25: в) Торговая зона должна быть расположена с южной стороны отеля
C26: =C23+1 -> 19 | D26: Наличие технологического этажа высотой до 1800 мм между жилыми этажами и этажами с размещением общественных зон | F26: Да, требуется
C27: =C26+1 -> 20 | D27: Дополнительные технологии в составе объекта | F27: Торговая зона (1000 кв.м). Детский клуб (200 кв.м). Лыжехранилище 25 кв.м

Sheet Отель3
A1: 1
C2: Вводные технико-экономические показатели | E2: Гостиница 3* | F2: =F11 -> Ibis Styles
E3: Ед. измерения | F3: Значение | G3: Комментарий | K3: Предложения CW | O3: Комментарий CW
C4: 1 | D4: Предварительная общая площадь | E4: кв.м | F4: =Бюджет_Синара!B124 -> 6929 | O4: Предложение по увеличению количества номеров с сохранением общей площади номерного фонда
C5: 2 | D5: Класс объекта по стандартам РФ | F5: Гостиница "3 звезды" | K5: =F4/F6 -> 43.30625 | L5: кв.м общей S/номер
C6: 3 | D6: Количество номеров всего | E6: номера | F6: 160 | I6: мест/номер | J6: Мест всего | K6: кв.м/номер | L6: кв.м
D7: в т.ч. семейные номера на 4 человек (сьют) | E7: номера | F7: 30 | G7: 0.15 | I7: 4 | J7: =I7*F7 -> 120 | K7: =K8*1.35 -> 29.7 | L7: =F7*K7 -> 891
D8: в т.ч. номера класса твин и дабл (на 1 и 2 проживающих) | E8: номера | F8: 130 | G8: 0.85 | I8: 2 | J8: =I8*F8 -> 260 | K8: 22 | L8: =F8*K8 -> 2860
C9: =C6+1 -> 4 | D9: Количество мест для проживающих (человек) | E9: мест | F9: =SUM(J7:J8) -> 380 | G9: =F9/F6 -> 2.375
C10: =C9+1 -> 5 | D10: Площадь номерного фонда | E10: кв.м | F10: =Бюджет_Синара!B93 -> 3780 | G10: =F10/F6 -> 23.625 | H10: кв.м/номер | K10: S ном.фонда | L10: =SUM(L7:L9) -> 3751
C11: =C10+1 -> 6 | D11: Бренд | F11: Ibis Styles | L11: =L10/F6 -> 23.44375 | M11: кв.м/номер
C12: =C11+1 -> 7 | D12: Наличие СПА | E12: кв.м | F12: =Бюджет_Синара!B233 -> 1900 | G12: Отдельно стоящий корпус SPA-комплекса - учитывается в опер.деятельности гостиницы 3*
C13: =C12+1 -> 8 | D13: Ресторан - количество посадочных мест | E13: посадочных мест | F13: 160
C14: =C13+1 -> 9 | D14: Ресторан - площадь зала | E14: кв.м | F14: =Бюджет_Синара!B99 -> 300 | G14: =F14/F13 -> 1.875 | H14: кв.м/п.место
C15: =C14+1 -> 10 | D15: Залы и переговорные | E15: кв.м | F15: =Бюджет_Синара!B105 -> 100
C16: =C15+1 -> 11 | D16: Фойе | E16: кв.м | F16: =Бюджет_Синара!B107 -> 35
C17: =C16+1 -> 12 | D17: Размер номера на 4 проживающих | F17: В соответствии с требованиями бренда
C18: =C17+1 -> 13 | D18: Размер номера дабл или твин
C19: =C18+1 -> 14 | D19: Этажность | E19: этажей | F19: Не более 5
C20: =C19+1 -> 15 | D20: Особые требования к компоновке объекта | F20: Нет
C21: =C20+1 -> 16 | D21: Наличие технологического этажа высотой до 1800 мм между жилыми этажами и этажами с размещением общественных зон | F21: Возможно
C22: =C21+1 -> 17 | D22: Дополнительные технологии в составе объекта | F22: Лыжехранилище - 35 кв.м

Sheet Отель2
A1: 1
C2: Вводные технико-экономические показатели | E2: Гостиница 2* | F2: =F12 -> Ibis Budget
E3: Ед. измерения | F3: Значение | G3: Комментарий | J3: Предложения CW | N3: Комментарий CW
C4: 1 | D4: Предварительная общая площадь | E4: кв.м | F4: =Бюджет_Синара!B164 -> 3346.5 | N4: Предложение по увеличению количества номеров с сохранением общей площади номерного фонда
C5: =C4+1 -> 2 | D5: Класс объекта по стандартам РФ | F5: Гостиница "2 звезды" | J5: =F4/F6 -> 40.810976 | K5: кв.м общей S/номер
C6: =C5+1 -> 3 | D6: Количество номеров всего | E6: номера | F6: 82 | H6: мест/номер | I6: Мест всего | J6: кв.м/номер | K6: кв.м
D7: в т.ч. семейные номера на 4 человек (сьют) | E7: номера | F7: =ROUND($F$6*G7,0) -> 29 | G7: 0.35 | H7: 4 | I7: =H7*F7 -> 116 | J7: =J8*1.5 -> 27 | K7: =F7*J7 -> 783
D8: в т.ч. номера класса твин и дабл (на 1 и 2 проживающих) | E8: номера | F8: =ROUND($F$6*G8,0) -> 49 | G8: 0.6 | H8: 2 | I8: =H8*F8 -> 98 | J8: 18 | K8: =F8*J8 -> 882
D9: в т.ч. номера для ЛОВ | E9: номера | F9: =F6-F8-F7 -> 4 | G9: 0.05 | H9: 2 | I9: =H9*F9 -> 8 | J9: =J8 -> 18 | K9: =F9*J9 -> 72
C10: =C6+1 -> 4 | D10: Количество мест для проживающих (человек) | E10: мест | F10: =SUM(I7:I9) -> 222 | G10: =F10/F6 -> 2.7073171 | J10: S ном.фонда | K10: =SUM(K7:K9) -> 1737
C11: =C10+1 -> 5 | D11: Площадь номерного фонда | E11: кв.м | F11: =Бюджет_Синара!B133 -> 1750 | G11: =F11/F6 -> 21.341463 | H11: кв.м/номер | K11: =K10/F6 -> 21.182927 | L11: кв.м/номер
C12: =C11+1 -> 6 | D12: Бренд | F12: Ibis Budget
C13: =C12+1 -> 7 | D13: Ресторан - количество посадочных мест | E13: посадочных мест | F13: =ROUND(F14/G14,0) -> 20 | G13: сделана корректировка по кол-ву посадочных мест, исходя из площади зала ресторана
C14: =C13+1 -> 8 | D14: Ресторан - площадь зала | E14: кв.м | F14: =Бюджет_Синара!B139 -> 38 | G14: =Отель3!G14 -> 1.875 | H14: кв.м/п.место
C15: =C14+1 -> 9 | D15: Размер номера на 4 проживающих | F15: В соответствии с требованиями бренда
C16: =C15+1 -> 10 | D16: Размер номера дабл или твин
C17: =C16+1 -> 11 | D17: Этажность | E17: этажей | F17: Не более 5
C18: =C17+1 -> 12 | D18: Особые требования к компоновке объекта | F18: Торговая зона с южной стороны
C19: =C18+1 -> 13 | D19: Наличие технологического этажа высотой до 1800 мм между жилыми этажами и этажами с размещением общественных зон | F19: Возможно
C20: =C19+1 -> 14 | D20: Дополнительные технологии в составе объекта | F20: Лыжехранилище - 20 кв.м

Sheet Резиденции
A1: 1
C2: Вводные технико-экономические показатели | E2: Туристские резиденции | F2: =F17 -> Не брендируется
E3: Ед. измерения | F3: Значение | J3: Предложения CW | N3: Комментарий CW
C4: 1 | D4: Предварительная общая площадь | E4: кв.м | F4: =Бюджет_Синара!B206 -> 21950 | G4: =F4/F6 -> 57.012987 | N4: Корректировка по количеству номеров с сохранением общей площади номерного фонда
C5: =C4+1 -> 2 | D5: Класс объекта по стандартам РФ | F5: Гостиница "3 звезды"
C6: =C5+1 -> 3 | D6: Количество номеров всего | E6: номера | F6: =SUM(F7:F9) -> 385 | H6: мест/номер | I6: Мест всего | J6: кв.м/номер | K6: кв.м
D7: в т.ч. апартаменты студии | E7: номера | F7: 220 | G7: =F7/$F$6 -> 0.57142857 | H7: 2 | I7: =H7*F7 -> 440 | J7: 26 | K7: =J7*F7 -> 5720
D8: в т.ч. апартаменты на 1 спальню | E8: номера | F8: 120 | G8: =F8/$F$6 -> 0.31168831 | H8: 3 | I8: =H8*F8 -> 360 | J8: 40 | K8: =J8*F8 -> 4800
D9: в т.ч. апартаменты на 2 спальни | E9: номера | F9: 45 | G9: =F9/$F$6 -> 0.11688312 | H9: 4 | I9: =H9*F9 -> 180 | J9: =J8*1.25 -> 50 | K9: =J9*F9 -> 2250
D10: в т.ч. номера для ЛОВ | E10: номера | F10: 29
C11: =C6+1 -> 4 | D11: Количество мест для проживающих (человек) | E11: мест | F11: =SUM(I7:I9) -> 980 | G11: =F11/F6 -> 2.5454545
C12: =C11+1 -> 5 | D12: Площадь номерного фонда | E12: кв.м | F12: =Бюджет_Синара!B174 -> 14000 | G12: =F12/F6 -> 36.363636 | H12: кв.м/номер | K12: =SUM(K7:K11) -> 12770
C13: =C12+1 -> 6 | D13: Площадь резиденций | J13: S ном.фонда | K13: =K12*1.1 -> 14047
D14: апартаменты студии | E14: кв.м/единица | F14: =J7 -> 26 | K14: =K13/F6 -> 36.485714 | L14: кв.м/номер
D15: апартаменты на 1 спальню | F15: =J8 -> 40
D16: апартаменты на 2 спальни | F16: =J9 -> 50
C17: =C13+1 -> 7 | D17: Бренд | F17: Не брендируется
C18: =C17+1 -> 8 | D18: Ресторан - количество посадочных мест | E18: посадочных мест | F18: 200
C19: =C18+1 -> 9 | D19: Ресторан - площадь зала | E19: кв.м | F19: =Бюджет_Синара!B180 -> 400 | G19: =F19/F18 -> 2 | H19: кв.м/п.место
C20: =C19+1 -> 10 | D20: Торговая зона тур.резиденций | E20: кв.м | F20: 3400
C21: =C20+1 -> 11 | D21: Лыжная школа | E21: кв.м | F21: 200
C22: =C21+1 -> 12 | D22: Этажность | E22: этажей | F22: Не более 5 | G22: 5
C23: =C22+1 -> 13 | D23: Особые требования к компоновке объекта | F23: Выход из торговой зоны на юг. Выход из лыжной школы на север к восточному подъемнику
C24: =C23+1 -> 14 | D24: Наличие технологического этажа высотой до 1800 мм между жилыми этажами и этажами с размещением общественных зон | F24: Да
C25: =C24+1 -> 15 | D25: Дополнительные технологии в составе объекта | F25: Торговая зона 3400 кв.м, лыжная школа 200 кв.м
D28: Предварительная оценка пятнка застройки | E28: кв.м | F28: =F4/G22 -> 4390
D29: Пятно застройки, приходящееся на Резиденции | E29: кв.м | F29: =F12/F4*F28 -> 2800

Sheet Хостел
A1: 1
C2: Вводные технико-экономические показатели | E2: Хостел в составе МФЦ | F2: =F12 -> Jo&JOE
E3: Ед. измерения | F3: Значение | I3: Предложения CW | N3: Комментарий CW
C4: 1 | D4: Предварительная общая площадь | E4: кв.м | F4: =Бюджет_Синара!B221 -> 10800 | N4: Предложение по увеличению количества номеров с сохранением общей площади номерного фонда
C5: =C4+1 -> 2 | D5: Класс объекта по стандартам РФ | F5: Многофункциональное здание в соответствии с СП 160.1325800.2014 | G5: площадь на место
C6: =C5+1 -> 3 | D6: В том числе хостел | E6: кв.м | F6: 2500 | G6: =F6/J12 -> 6.0679612
C7: =C6+1 -> 4 | D7: Количество номеров, всего | E7: номера | F7: =SUM(F8:F11) -> 101 | I7: мест/номер | J7: Мест всего | K7: кв.м
D8: в т.ч. 6-местные номера | E8: номера | F8: 35 | G8: =F8/$F$7 -> 0.34653465 | I8: 6 | J8: =I8*F8 -> 210 | K8: =J8*4 -> 840
D9: в т.ч. 4-местные номера | E9: номера | F9: 35 | G9: =F9/$F$7 -> 0.34653465 | I9: 4 | J9: =I9*F9 -> 140 | K9: =J9*4 -> 560
D10: в т.ч. 2-местные номера | E10: номера | F10: 25 | G10: =F10/$F$7 -> 0.24752475 | I10: 2 | J10: =I10*F10 -> 50 | K10: =J10*4 -> 200
D11: в т.ч. номера для ЛОВ | E11: номера | F11: 6 | G11: =F11/$F$7 -> 0.059405941 | I11: 2 | J11: =I11*F11 -> 12 | K11: =J11*4 -> 48
C12: =C7+1 -> 5 | D12: Бренд | F12: Jo&JOE | J12: =SUM(J8:J11) -> 412 | K12: =SUM(K8:K11) -> 1648
C13: =C12+1 -> 6 | D13: Ресторан - количество посадочных мест | E13: посадочных мест | F13: 70 | K13: =K12*1.5 -> 2472
C14: =C13+1 -> 7 | D14: Ресторан - площадь зала | E14: кв.м | F14: =Бюджет_Синара!B215 -> 150 | G14: =F14/F13 -> 2.1428571
C15: =C14+1 -> 8 | D15: Общежитие служебное | E15: кв.м | F15: =Бюджет_Синара!B217 -> 1800
C16: =C15+1 -> 9 | D16: Общежитие служебное | E16: кол-во мест | F16: 300 | J16: =F16*4*1.3 -> 1560
C17: =C16+1 -> 10 | D17: Этажи для размещения общежития | E17: порядковый номер этажей | F17: 2-3
C18: =C17+1 -> 11 | D18: Торговая зона МФЦ | E18: кв.м | F18: =Бюджет_Синара!B218 -> 4000
C19: =C18+1 -> 12 | D19: Административная зона | E19: кв.м | F19: =Бюджет_Синара!B219 -> 900
C20: =C19+1 -> 13 | D20: Состав административной зоны | F20: Холл, ресепшн, офисы
C21: =C20+1 -> 14 | D21: Парковка | E21: кв.м | F21: =Бюджет_Синара!B220 -> 1200
C22: =C21+1 -> 15 | D22: Этажность | E22: этажей | F22: Не более 2
C23: =C22+1 -> 16 | D23: Наличие крытой парковки (количество мест) | E23: кол-во мест | F23: 400 | I23: =F21/F23 -> 3 | J23: кв.м/м-место
C24: =C23+1 -> 17 | D24: Особые требования к компоновке объекта | F24: Крытая или подземная парковка в 2 уровня

Sheet Шале
A1: 1
C2: Вводные технико-экономические показатели | E2: Шале | F2: =F8 -> Не брендируется (номерной фонд отеля 5*)
E3: Ед. измерения | F3: Значение
C4: 1 | D4: Предварительная общая площадь | E4: кв.м | F4: =G4*F6*1.2 -> 2340 | G4: =I24 -> 150
C5: =C4+1 -> 2 | D5: Класс объекта по стандартам РФ | F5: Апартаменты в соответствии с СП 118.13330.2012
C6: =C5+1 -> 3 | D6: Количество зданий всего | E6: здания / номера | F6: 13
C7: =C6+1 -> 4 | D7: Количество мест для проживающих (человек) | E7: мест | F7: 78 | G7: =F7/F6 -> 6
C8: =C7+1 -> 5 | D8: Бренд | F8: Не брендируется (номерной фонд отеля 5*)
C9: =C8+1 -> 6 | D9: Этажность | E9: этажей | F9: Не более 2
C10: =C9+1 -> 7 | D10: Детализация требований к технологии | F10: =_Toc95402285 -> Детализация объекта
C12: Детализация объекта
D13: Наименование помещения | E13: Кол-во | F13: Удельная площадь, кв.м/ед. | I13: ИТОГО площадь, кв.м
C14: 1 | D14: Гостиная совмещенная с кухней | E14: 1 | F14: 40 | G14: Корректировка CW | I14: =F14*E14 -> 40
C15: =C14+1 -> 2 | D15: Тамбур | E15: 1 | F15: 6 | I15: =F15*E15 -> 6
C16: =C15+1 -> 3 | D16: Су на первом этаже | E16: 1 | F16: 5 | G16: Корректировка CW | I16: =F16*E16 -> 5
C17: =C16+1 -> 4 | D17: Спальня на первом этаже | E17: 1 | F17: 16 | G17: Корректировка CW | I17: =F17*E17 -> 16
C18: =C17+1 -> 5 | D18: Спальня на втором этаже (2 шт) | E18: 2 | F18: 16 | G18: Корректировка CW | I18: =F18*E18 -> 32
C19: =C18+1 -> 6 | D19: Спальня на втором этаже (1 шт) | E19: 1 | F19: 15 | I19: =F19*E19 -> 15
C20: =C19+1 -> 7 | D20: Санузел на втором этаже (2 шт) | E20: 2 | F20: 6 | G20: Корректировка CW | I20: =F20*E20 -> 12
C21: =C20+1 -> 8 | D21: Лыжехранилище | E21: 1 | F21: 6 | G21: Корректировка CW | I21: =F21*E21 -> 6
C22: =C21+1 -> 9 | D22: Котельная (техническое помещение) | E22: 1 | F22: 8 | I22: =F22*E22 -> 8
C23: =C22+1 -> 10 | D23: Сауна | E23: 1 | F23: 10 | G23: Корректировка CW | I23: =F23*E23 -> 10
D24: ИТОГО | I24: =SUM(I14:I23) -> 150 | J24: Общая площадь объекта без изменений

Sheet Бюджет_Синара
A1: Источник: | B1: Расчет площадей 24.02.2022 с капексами
B2: Гостиница 5*
A4: Помещения департамента | B4: ПЛОЩАДЬ. КВ.М | C4: Стоимость 1 м2 отделка | D4: Итоговая стоимость отделки B*C | E4: Стоимость 1 м2 мебели и оборудования | F4: Итоговая стоимость мебели и оборудования B*E | G4: Стоимость 1 м2 стройка | H4: Итоговая стоимость стройки B*G | I4: Стоимость 1 м2 инж системы | J4: Итоговая стоимость инж системы B*I | K4: Итого D+F+G+J | L4: Capex за м.кв.
A5: A | B5: B | C5: C | D5: D | E5: E | F5: F | G5: G | H5: H | I5: I | J5: J | K5: K
A6: Служба размещения
A7: Номерной фонд (min/max) | B7: 4750 | C7: 37000 | D7: =B7*C7 -> 175750000 | E7: 65000 | F7: =B7*E7 -> 308750000 | G7: 52500 | H7: =B7*G7 -> 249375000 | I7: 25000 | J7: =B7*I7 -> 118750000 | K7: =D7+H7+J7+F7 -> 852625000 | L7: =K7/B7 -> 179500 | M7: =K7 -> 852625000
C8: 50000 | D8: =B7*C8 -> 237500000 | E8: 70000 | F8: =B7*E8 -> 332500000 | K8: =D8+H7+J7+F8 -> 938125000 | L8: 197500 | M8: средняя цена
A9: Циркуляция (лестницы. коридоры. холлы. лифты) | B9: 990 | C9: 35000 | D9: =B9*C9 -> 34650000 | E9: 0 | F9: =B9*E9 -> 0 | H9: =B9*G7 -> 51975000 | J9: =B9*I7 -> 24750000 | K9: =D9+H9+J9+F9 -> 111375000 | L9: =K9/B9 -> 112500 | M9: =K9 -> 111375000
A10: Служебные помещения на этаже | B10: 56 | C10: 11000 | D10: =B10*C10 -> 616000 | E10: 2000 | F10: =B10*E10 -> 112000 | H10: =B10*G7 -> 2940000 | J10: =B10*I7 -> 1400000 | K10: =D10+H10+J10+F10 -> 5068000 | L10: =K10/B10 -> 90500 | M10: =K10 -> 5068000
A11: B.O.H. служба размещения | B11: 49 | C11: 11000 | D11: =B11*C11 -> 539000 | E11: 2000 | F11: =B11*E11 -> 98000 | H11: =B11*G7 -> 2572500 | J11: =B11*I7 -> 1225000 | K11: =D11+H11+J11+F11 -> 4434500 | L11: =K11/B11 -> 90500 | M11: =K11 -> 4434500
A12: Рестораны и бары
A13: Рестораны и бары | B13: 327 | C13: 40000 | D13: =B13*C13 -> 13080000 | E13: 45000 | F13: =B13*E13 -> 14715000 | G13: 52500 | H13: =B13*G13 -> 17167500 | I13: 30000 | J13: =B13*I13 -> 9810000 | K13: =D13+H13+J13+F13 -> 54772500 | L13: =K13/B13 -> 167500 | M13: =K13 -> 54772500
A15: Кухня, рестораны и бары ( в т.ч. service areas), без циркуляции | B15: 330 | C15: 25000 | D15: =B15*C15 -> 8250000 | E15: 12000 | F15: =B15*E15 -> 3960000 | H15: =B15*G13 -> 17325000 | J15: =B15*I13 -> 9900000 | K15: =D15+H15+J15+F15 -> 39435000 | L15: =K15/B15 -> 119500 | M15: =K15 -> 39435000
A16: Циркуляция (лестницы. вход. лифтовые холлы. лифты) | B16: 111.16888 | C16: 15000 | D16: =B16*C16 -> 1667533.2 | E16: 2000 | F16: =B16*E16 -> 222337.76 | H16: =B16*G13 -> 5836366.1 | J16: =B16*I13 -> 3335066.3 | K16: =D16+H16+J16+F16 -> 11061303 | L16: =K16/B16 -> 99500 | M16: =K16 -> 11061303
A17: Прочие помещения | B17: 105.15 | C17: 11000 | D17: =B17*C17 -> 1156650 | E17: 2000 | F17: =B17*E17 -> 210300 | H17: =B17*G13 -> 5520375 | J17: =B17*I13 -> 3154500 | K17: =D17+H17+J17+F17 -> 10041825 | L17: =K17/B17 -> 95500 | M17: =K17 -> 10041825
A18: Оздоровительный центр/ СПА / фитнес
A19: СПА | B19: 1943 | C19: 55000 | D19: =B19*C19 -> 106865000 | E19: 30000 | F19: =B19*E19 -> 58290000 | G19: 52500 | H19: =B19*G19 -> 102007500 | I19: 75000 | J19: =B19*I19 -> 145725000 | K19: =D19+H19+J19+F19 -> 412887500 | L19: =K19/B19 -> 212500 | M19: =K19 -> 412887500
A20: Конференц-центр
A21: Залы и переговорные (min/max) | B21: 175 | C21: 37000 | D21: =B21*C21 -> 6475000 | E21: 15000 | F21: =B21*E21 -> 2625000 | G21: 52500 | H21: =B21*G21 -> 9187500 | I21: 25000 | J21: =B21*I21 -> 4375000 | K21: =D21+H21+J21+F21 -> 22662500 | L21: =K21/B21 -> 129500 | M21: =K21 -> 22662500
C22: 80000 | D22: =B21*C22 -> 14000000 | E22: 30000 | F22: =B21*E22 -> 5250000 | K22: =D22+H21+J21+F22 -> 32812500 | L22: =K22/B21 -> 187500 | M22: средняя цена
A23: Фойе (min/max) | B23: 135 | C23: 65000 | D23: =B23*C23 -> 8775000 | E23: 5000 | F23: =B23*E23 -> 675000 | H23: =B23*G21 -> 7087500 | J23: =B23*I21 -> 3375000 | K23: =D23+H23+J23+F23 -> 19912500 | L23: =K23/B23 -> 147500 | M23: =K23 -> 19912500
C24: 70000 | D24: =B23*C24 -> 9450000 | E24: 10000 | F24: =B23*E24 -> 1350000 | K24: =D24+H23+J23+F24 -> 21262500 | L24: =K24/B23 -> 157500 | M24: средняя цена
A25: Другие помещения | B25: 138 | C25: 11000 | D25: =B25*C25 -> 1518000 | E25: 1000 | F25: =B25*E25 -> 138000 | H25: =B25*G21 -> 7245000 | J25: =B25*I21 -> 3450000 | K25: =D25+H25+J25+F25 -> 12351000 | L25: =K25/B25 -> 89500 | M25: =K25 -> 12351000
A26: Лобби и общественные зоны
A27: Лобби и общественные зоны(min/max) | B27: 385 | C27: 42000 | D27: =B27*C27 -> 16170000 | E27: 65000 | F27: =B27*E27 -> 25025000 | G27: 52500 | H27: =B27*G27 -> 20212500 | I27: 25000 | J27: =B27*I27 -> 9625000 | K27: =D27+H27+J27+F27 -> 71032500 | L27: =K27/B27 -> 184500 | M27: =K27 -> 71032500
C28: 80000 | D28: =B27*C28 -> 30800000 | E28: 70000 | F28: =B27*E28 -> 26950000 | K28: =D28+H27+J27+F28 -> 87587500 | L28: =K28/B27 -> 227500 | M28: средняя цена
A29: Циркуляция (лестницы, вход, лифтовые холлы, лифты) | B29: 42 | C29: 35000 | D29: =B29*C29 -> 1470000 | E29: 2000 | F29: =B29*E29 -> 84000 | H29: =B29*G27 -> 2205000 | J29: =B29*I27 -> 1050000 | K29: =D29+H29+J29+F29 -> 4809000 | L29: =K29/B29 -> 114500 | M29: =K29 -> 4809000
A30: Административные помещения
A31: Административные помещения | B31: 7 | C31: 11000 | D31: =B31*C31 -> 77000 | E31: 2000 | F31: =B31*E31 -> 14000 | G31: 52500 | H31: =B31*G31 -> 367500 | I31: 25000 | J31: =B31*I31 -> 175000 | K31: =D31+H31+J31+F31 -> 633500 | L31: =K31/B31 -> 90500 | M31: =K31 -> 633500
A32: Циркуляция (лестницы, вход, лифтовые холлы, лифты) | B32: 20 | C32: 15000 | D32: =B32*C32 -> 300000 | E32: 1000 | F32: =B32*E32 -> 20000 | H32: =B32*G31 -> 1050000 | J32: =B32*I31 -> 500000 | K32: =D32+H32+J32+F32 -> 1870000 | L32: =K32/B32 -> 93500 | M32: =K32 -> 1870000
A33: Помещения персонала
A34: Помещения персонала | B34: 183 | C34: 11000 | D34: =B34*C34 -> 2013000 | E34: 1000 | F34: =B34*E34 -> 183000 | G34: 52500 | H34: =B34*G34 -> 9607500 | I34: 25000 | J34: =B34*I34 -> 4575000 | K34: =D34+H34+J34+F34 -> 16378500 | L34: =K34/B34 -> 89500 | M34: =K34 -> 16378500
A35: Циркуляция (лестницы, коридоры, холлы, лифты) | B35: 56.82 | C35: 15000 | D35: =B35*C35 -> 852300 | E35: 0 | F35: =B35*E35 -> 0 | H35: =B35*G34 -> 2983050 | J35: =B35*I34 -> 1420500 | K35: =D35+H35+J35+F35 -> 5255850 | L35: =K35/B35 -> 92500 | M35: =K35 -> 5255850
A36: Служба эксплуатации и ремонта
A37: Служба эксплуатации и ремонта | B37: 168 | C37: 11000 | D37: =B37*C37 -> 1848000 | E37: 1000 | F37: =B37*E37 -> 168000 | G37: 52500 | H37: =B37*G37 -> 8820000 | I37: 25000 | J37: =B37*I37 -> 4200000 | K37: =D37+H37+J37+F37 -> 15036000 | L37: =K37/B37 -> 89500 | M37: =K37 -> 15036000
A38: Циркуляция (лестницы, вход, лифтовые холлы, лифты) | B38: 33.3 | C38: 15000 | D38: =B38*C38 -> 499500 | E38: 0 | F38: =B38*E38 -> 0 | H38: =B38*G37 -> 1748250 | J38: =B38*I37 -> 832500 | K38: =D38+H38+J38+F38 -> 3080250 | L38: =K38/B38 -> 92500 | M38: =K38 -> 3080250
A39: Технические помещения | B39: 800 | C39: 8000 | D39: =B39*C39 -> 6400000 | E39: 0 | F39: =B39*E39 -> 0 | G39: 52500 | H39: =B39*G39 -> 42000000 | I39: 0 | J39: =B39*I39 -> 0 | K39: =D39+F39+H39+J39 -> 48400000 | L39: =K39/B39 -> 60500 | M39: 49948000
A40: Парковка | B40: 1200 | C40: 3000 | D40: =B40*C40 -> 3600000 | E40: 0 | F40: =B40*E40 -> 0 | G40: 33000 | H40: =G40*B40 -> 39600000 | I40: 15000 | J40: =I40*B40 -> 18000000 | K40: =J40+H40+F40+D40 -> 61200000 | L40: =K40/B40 -> 51000 | M40: =K40 -> 61200000
A41: проверочная сумма площадей | B41: =B7+B9+B10+B11+B13+B15+B16+B17+B19+B21+B23+B25+B27+B29+B31+B32+B34+B37+B38+B39+B40 -> 11947.619
A42: Общая площадь по заданию | B42: 11400* | F42: =F7+F9+F10+F11+F13+F15+F16+F17+F19+F21+F23+F25+F27+F29+F31+F34+F37 -> 4.1526964e+08 | N42: смр
A43: Стоимость объекта руб. за кв. м. | L43: =M44/B41*1.2 -> 179369.99 | M43: 150951
A44: всего затрат на здание Гостиница 5 звезд | L44: min | M44: =SUM(M7:M42) -> 1.7858702e+09 | N44: =M44-F42 -> 1.3706006e+09
L45: max | M45: =SUM(K8,K9:K11,K13:K17,K19,K22,K24,K25,K28:K29,K31:K32,K34:K35,K37:K40) -> 1.8978772e+09 | N45: =M45/B41 -> 158849.83
B46: Гостиница 4*
A47: Помещения департамента | B47: ПЛОЩАДЬ. КВ.М | C47: Стоимость 1 м2 отделка | D47: Итоговая стоимость отделки B*C | E47: Стоимость 1 м2 мебели и оборудования | F47: Итоговая стоимость мебели и оборудования B*E | G47: Стоимость 1 м2 стройка | H47: Итоговая стоимость стройки B*G | I47: Стоимость 1 м2 инж системы | J47: Итоговая стоимость инж системы B*I | K47: Итого D+F+G+J | L47: Capex за м.кв.
A48: A | B48: B | C48: C | D48: D | E48: E | F48: F | G48: G | H48: H | I48: I | J48: J | K48: K
A49: Служба размещения
A50: Номерной фонд (min/max) | B50: 3925 | C50: 30000 | D50: =B50*C50 -> 117750000 | E50: 45000 | F50: =B50*E50 -> 176625000 | G50: 37000 | H50: =B50*G50 -> 145225000 | I50: 25000 | J50: =B50*I50 -> 98125000 | K50: =D50+H50+J50+F50 -> 537725000 | L50: =K50/B50 -> 137000 | M50: =K50 -> 537725000
C51: 30000 | D51: =B50*C51 -> 117750000 | E51: 55000 | F51: =B50*E51 -> 215875000 | K51: =D51+H50+J50+F51 -> 576975000 | L51: =K51/B50 -> 147000
A52: Циркуляция (лестницы. коридоры. холлы. лифты) | B52: 702 | C52: 15000 | D52: =B52*C52 -> 10530000 | E52: 0 | F52: =B52*E52 -> 0 | H52: =B52*G50 -> 25974000 | J52: =B52*I50 -> 17550000 | K52: =D52+H52+J52+F52 -> 54054000 | L52: =K52/B52 -> 77000 | M52: =K52 -> 54054000
A53: Служебные помещения на этаже | B53: 56 | C53: 11000 | D53: =B53*C53 -> 616000 | E53: 1000 | F53: =B53*E53 -> 56000 | H53: =B53*G50 -> 2072000 | J53: =B53*I50 -> 1400000 | K53: =D53+H53+J53+F53 -> 4144000 | L53: =K53/B53 -> 74000 | M53: =K53 -> 4144000
A54: B.O.H. служба размещения | B54: 49 | C54: 11000 | D54: =B54*C54 -> 539000 | E54: 1000 | F54: =B54*E54 -> 49000 | H54: =B54*G50 -> 1813000 | J54: =B54*I50 -> 1225000 | K54: =D54+H54+J54+F54 -> 3626000 | L54: =K54/B54 -> 74000 | M54: =K54 -> 3626000
A55: Рестораны и бары
A56: Рестораны и бары (торговая площадь) | B56: 313 | C56: 40000 | D56: =B56*C56 -> 12520000 | E56: 35000 | F56: =B56*E56 -> 10955000 | G56: 37000 | H56: =B56*G56 -> 11581000 | I56: 25000 | J56: =B56*I56 -> 7825000 | K56: =D56+H56+J56+F56 -> 42881000 | L56: =K56/B56 -> 137000 | M56: =K56 -> 42881000
A58: Кухня, рестораны и бары ( в т.ч. service areas), без циркуляции | B58: 300 | C58: 25000 | D58: =B58*C58 -> 7500000 | E58: 12000 | F58: =B58*E58 -> 3600000 | H58: =B58*G56 -> 11100000 | J58: =B58*I56 -> 7500000 | K58: =D58+H58+J58+F58 -> 29700000 | L58: =K58/B58 -> 99000 | M58: =K58 -> 29700000
A59: Циркуляция (лестницы. вход. лифтовые холлы. лифты) | B59: 74 | C59: 15000 | D59: =B59*C59 -> 1110000 | E59: 2000 | F59: =B59*E59 -> 148000 | H59: =B59*G56 -> 2738000 | J59: =B59*I56 -> 1850000 | K59: =D59+H59+J59+F59 -> 5846000 | L59: =K59/B59 -> 79000 | M59: =K59 -> 5846000
A60: Прочие помещения | B60: 59 | C60: 11000 | D60: =B60*C60 -> 649000 | E60: 2000 | F60: =B60*E60 -> 118000 | H60: =B60*G56 -> 2183000 | J60: =B60*I56 -> 1475000 | K60: =D60+H60+J60+F60 -> 4425000 | L60: =K60/B60 -> 75000 | M60: =K60 -> 4425000
A61: Оздоровительный центр/ СПА / фитнес
A62: СПА | B62: 3561 | C62: 55000 | D62: =B62*C62 -> 195855000 | E62: 30000 | F62: =B62*E62 -> 106830000 | G62: 52500 | H62: =B62*G62 -> 186952500 | I62: 75000 | J62: =B62*I62 -> 267075000 | K62: =D62+H62+J62+F62 -> 756712500 | L62: =K62/B62 -> 212500 | M62: =K62 -> 756712500
A63: Конференц-центр
A64: Залы и переговорные (min/max) | B64: 520 | C64: 30000 | D64: =B64*C64 -> 15600000 | E64: 45000 | F64: =B64*E64 -> 23400000 | G64: 37000 | H64: =B64*G64 -> 19240000 | I64: 25000 | J64: =B64*I64 -> 13000000 | K64: =D64+H64+J64+F64 -> 71240000 | L64: =K64/B64 -> 137000 | M64: =K64 -> 71240000
C65: 40000 | D65: =B64*C65 -> 20800000 | E65: 55000 | F65: =B64*E65 -> 28600000 | K65: =D65+H64+J64+F65 -> 81640000 | L65: =K65/B64 -> 157000
A66: Фойе (min/max) | B66: 135 | C66: 30000 | D66: =B66*C66 -> 4050000 | E66: 45000 | F66: =B66*E66 -> 6075000 | H66: =B66*G64 -> 4995000 | J66: =B66*I64 -> 3375000 | K66: =D66+H66+J66+F66 -> 18495000 | L66: =K66/B66 -> 137000 | M66: =K66 -> 18495000
C67: 50000 | D67: =B66*C67 -> 6750000 | E67: 55000 | F67: =B66*E67 -> 7425000 | K67: =D67+H66+J66+F67 -> 22545000 | L67: =K67/B66 -> 167000
A68: Циркуляция и склады | B68: 138 | C68: 11000 | D68: =B68*C68 -> 1518000 | F68: =B68*E68 -> 0 | H68: =B68*G64 -> 5106000 | J68: =B68*I64 -> 3450000 | K68: =D68+H68+J68+F68 -> 10074000 | L68: =K68/B68 -> 73000 | M68: =K68 -> 10074000
A69: Лобби и общественные зоны
A70: Лобби и общественные зоны(min/max) | B70: 385 | C70: 30000 | D70: =B70*C70 -> 11550000 | E70: 45000 | F70: =B70*E70 -> 17325000 | G70: 37000 | H70: =B70*G70 -> 14245000 | I70: 25000 | J70: =B70*I70 -> 9625000 | K70: =D70+H70+J70+F70 -> 52745000 | L70: =K70/$B$70 -> 137000 | M70: =K70 -> 52745000
C71: 50000 | D71: =B70*C71 -> 19250000 | E71: 55000 | F71: =B70*E71 -> 21175000 | K71: =D71+H70+J70+F71 -> 64295000 | L71: =K71/$B$70 -> 167000
A72: Циркуляция (лестницы, вход, лифтовые холлы, лифты) | B72: 33 | C72: 15000 | D72: =B72*C72 -> 495000 | E72: 0 | F72: =B72*E72 -> 0 | H72: =B72*G70 -> 1221000 | J72: =B72*I70 -> 825000 | K72: =D72+H72+J72+F72 -> 2541000 | L72: =K72/B72 -> 77000 | M72: =K72 -> 2541000
A73: Административные помещения
A74: Административные помещения | B74: 7 | C74: 11000 | D74: =B74*C74 -> 77000 | E74: 1000 | F74: =B74*E74 -> 7000 | G74: 37000 | H74: =B74*G74 -> 259000 | I74: 25000 | J74: =B74*I74 -> 175000 | K74: =D74+H74+J74+F74 -> 518000 | L74: =K74/B74 -> 74000 | M74: =K74 -> 518000
A75: Циркуляция (лестницы, вход, лифтовые холлы, лифты) | B75: 22 | C75: 15000 | D75: =B75*C75 -> 330000 | E75: 0 | F75: =B75*E75 -> 0 | H75: =B75*G74 -> 814000 | J75: =B75*I74 -> 550000 | K75: =D75+H75+J75+F75 -> 1694000 | L75: =K75/B75 -> 77000 | M75: =K75 -> 1694000
A76: Помещения персонала
A77: Помещения персонала | B77: 183 | C77: 11000 | D77: 2083400 | E77: 1000 | F77: =B77*E77 -> 183000 | G77: 37000 | H77: =B77*G77 -> 6771000 | I77: 25000 | J77: =B77*I77 -> 4575000 | K77: =D77+H77+J77+F77 -> 13612400 | L77: =K77/B77 -> 74384.699 | M77: =K77 -> 13612400
A78: Циркуляция (лестницы, коридоры, холлы, лифты) | B78: 28 | C78: 15000 | D78: 852300 | E78: 0 | F78: =B78*E78 -> 0 | H78: =B78*G77 -> 1036000 | J78: =B78*I77 -> 700000 | K78: =D78+H78+J78+F78 -> 2588300 | L78: =K78/B78 -> 92439.286 | M78: =K78 -> 2588300
A79: Служба эксплуатации и ремонта
A80: Служба эксплуатации и ремонта | B80: 168 | C80: 11000 | D80: 1221000 | E80: 1000 | F80: =B80*E80 -> 168000 | G80: 37000 | H80: =B80*G80 -> 6216000 | I80: 25000 | J80: =B80*I80 -> 4200000 | K80: =D80+H80+J80+F80 -> 11805000 | L80: =K80/B80 -> 70267.857 | M80: =K80 -> 11805000
A81: Циркуляция (лестницы, вход, лифтовые холлы, лифты) | B81: 17 | C81: 15000 | D81: 499500 | E81: 0 | F81: =B81*E81 -> 0 | H81: =B81*G80 -> 629000 | J81: =B81*I80 -> 425000 | K81: =D81+H81+J81+F81 -> 1553500 | L81: =K81/B81 -> 91382.353 | M81: =K81 -> 1553500 | N81: смр
A82: Технические помещения | B82: 800 | C82: 8000 | D82: =B82*C82 -> 6400000 | E82: 0 | F82: =B82*E82 -> 0 | G82: 37000 | H82: =B82*G82 -> 29600000 | I82: 0 | J82: =B82*I82 -> 0 | K82: =D82+F82+H82+J82 -> 36000000 | L82: =K82/B82 -> 45000 | M82: =K82 -> 36000000 | N82: =M87-F85 -> 1386440700
A83: Торговая зона | B83: 1000 | C83: 8000 | D83: =B83*C83 -> 8000000 | E83: 0 | F83: 0 | G83: 37000 | H83: =G83*B83 -> 37000000 | I83: 25000 | J83: =I83*B83 -> 25000000 | K83: =D83+H83+J83 -> 70000000 | L83: =K83/B83 -> 70000 | M83: =K83 -> 70000000
A84: проверочная сумма площадей | B84: =B50+B52+B53+B54+B56+B58+B59+B60+B62+B64+B66+B68+B70+B72+B74+B75+B77+B78+B80+B81+B82+B83 -> 12475
A85: Общая площадь по заданию | B85: 11000 | F85: =F50+F53+F54+F52+F56+F58+F59+F60+F62+F64+F66+F70+F72+F74+F77+F80 -> 345539000
A86: Стоимость объекта руб. за кв. м. | L86: =M87/B84*1.2 -> 166603.26 | M86: 173296
A87: всего затрат на здание Гостиница 4 звезды | L87: min | M87: =SUM(M50:M85) -> 1731979700
L88: max | M88: =SUM(K51,K52:K54,K56:K60,K62,K65,K67,K68,K71,K72,K74:K75,K77:K78,K80:K83) -> 1797229700 | N88: =M88/B84 -> 144066.51 | Q88: =M88-Бюджет!G6 -> 0
B89: Гостиница 3*
A90: Помещения департамента | B90: ПЛОЩАДЬ. КВ.М | C90: Стоимость 1 м2 отделка | D90: Итоговая стоимость отделки B*C | E90: Стоимость 1 м2 мебели и оборудования | F90: Итоговая стоимость мебели и оборудования B*E | G90: Стоимость 1 м2 стройка | H90: Итоговая стоимость стройки B*G | I90: Стоимость 1 м2 инж системы | J90: Итоговая стоимость инж системы B*I | K90: Итого D+F+G+J
A91: A | B91: B | C91: C | D91: D | E91: E | F91: F | G91: G | H91: H | I91: I | J91: J | K91: K
A92: Служба размещения
A93: Номерной фонд (min/max) | B93: 3780 | C93: 25000 | D93: =B93*C93 -> 94500000 | E93: 32000 | F93: =B93*E93 -> 120960000 | G93: 33000 | H93: =B93*G93 -> 124740000 | I93: 15000 | J93: =B93*I93 -> 56700000 | K93: =D93+H93+J93+F93 -> 396900000 | L93: =K93/B93 -> 105000 | M93: =K93 -> 396900000
C94: 45000 | D94: =B93*C94 -> 170100000 | E94: 37000 | F94: =B93*E94 -> 139860000 | K94: =D94+H93+J93+F94 -> 491400000 | L94: =K94/B93 -> 130000 | M94: средняя цена
A95: Циркуляция (лестницы. коридоры. холлы. лифты) | B95: 800 | C95: 11000 | D95: =B95*C95 -> 8800000 | F95: =B95*E95 -> 0 | H95: =B95*G93 -> 26400000 | J95: =B95*I93 -> 12000000 | K95: =D95+H95+J95+F95 -> 47200000 | L95: =K95/B95 -> 59000 | M95: =K95 -> 47200000
A96: Служебные помещения на этаже | B96: 52 | C96: 11000 | D96: =B96*C96 -> 572000 | F96: =B96*E96 -> 0 | H96: =B96*G93 -> 1716000 | J96: =B96*I93 -> 780000 | K96: =D96+H96+J96+F96 -> 3068000 | L96: =K96/B96 -> 59000 | M96: =K96 -> 3068000
A97: B.O.H. служба размещения | B97: 31 | C97: 11000 | D97: =B97*C97 -> 341000 | F97: =B97*E97 -> 0 | H97: =B97*G93 -> 1023000 | J97: =B97*I93 -> 465000 | K97: =D97+H97+J97+F97 -> 1829000 | L97: =K97/B97 -> 59000 | M97: =K97 -> 1829000
A98: Рестораны и бары
A99: Рестораны и бары | B99: 300 | C99: 40000 | D99: =B99*C99 -> 12000000 | E99: 30000 | F99: =B99*E99 -> 9000000 | G99: 33000 | H99: =B99*G99 -> 9900000 | I99: 25000 | J99: =B99*I99 -> 7500000 | K99: =D99+H99+J99+F99 -> 38400000 | L99: =K99/B99 -> 128000 | M99: =K99 -> 38400000
A101: Кухня, рестораны и бары ( в т.ч. service areas), без циркуляции | B101: 300 | C101: 25000 | D101: =B101*C101 -> 7500000 | E101: 12000 | F101: =B101*E101 -> 3600000 | H101: =B101*G99 -> 9900000 | J101: =B101*I99 -> 7500000 | K101: =D101+H101+J101+F101 -> 28500000 | L101: =K101/B101 -> 95000 | M101: =K101 -> 28500000
A102: Циркуляция (лестницы. вход. лифтовые холлы. лифты) | B102: 234 | C102: 11000 | D102: =B102*C102 -> 2574000 | E102: 2000 | F102: =B102*E102 -> 468000 | H102: =B102*G99 -> 7722000 | J102: =B102*I99 -> 5850000 | K102: =D102+H102+J102+F102 -> 16614000 | L102: =K102/B102 -> 71000 | M102: =K102 -> 16614000
A103: Прочие помещения | B103: 210 | C103: 11000 | D103: =B103*C103 -> 2310000 | E103: 2000 | F103: =B103*E103 -> 420000 | H103: =B103*G99 -> 6930000 | J103: =B103*I99 -> 5250000 | K103: =D103+H103+J103+F103 -> 14910000 | L103: =K103/B103 -> 71000 | M103: =K103 -> 14910000
A104: Конференц-центр
...

Sheet CW --->>

Sheet Вводные
A1: 1
C2: ВВОДНЫЕ ДАННЫЕ
C3: Показатель | D3: Значение
C4: Дата анализа | D4: 44593
C5: Год анализа | D5: =YEAR(D4) -> 2022
C7: Начало строительства | D7: =D4 -> 44593
C9: Даты ввода в эксплуатацию - 1 очередь | D9: =MIN(D10:D16) -> 45839
C10: =Объекты!C5&" - "&Объекты!D5 -> Гостиница 5* - Mövenpick | D10: 46204
C11: =Объекты!C6&" - "&Объекты!D6 -> Гостиница 4* - Mercure | D11: 46204
C12: =Объекты!C7&" - "&Объекты!D7 -> Гостиница 3* - Возможный бренд: Ibis Styles | D12: 45839
C13: =Объекты!C8&" - "&Объекты!D8 -> Гостиница 2* - Ibis Budget
C14: =Объекты!C9&" - "&Объекты!D9 -> Хостел в составе МФЦ - Jo&JOE | D14: 45839
C15: =Объекты!C10 -> Шале | D15: 46204
C16: =Объекты!C13 -> Туристские резиденции | D16: 45839
C18: Курс руб./евро на дату анализа | D18: 86.5032 | E18: EUR
C19: Курс руб./долл. на дату анализа | D19: 77.4702 | E19: USD
C21: Доля собственных средств | D21: 0.2
C22: Доля заемных средств | D22: =1-D21 -> 0.8
C24: Налог на прибыль | D24: федеральн.бюджет | F24: регион.бюджет | H24: ИТОГО
C25: Период | D25: 2017-2024 гг. | E25: с 2025 г. | F25: 2017-2024 гг. | G25: с 2025 г. | H25: 2017-2024 гг. | I25: с 2025 г.
C26: Основная ставка налога на прибыль | D26: 0.03 | E26: 0.02 | F26: 0.17 | G26: 0.18 | H26: =D26+F26 -> 0.2 | I26: =E26+G26 -> 0.2
C27: Резиденты туристско-рекреационных ОЭЗ, объединенных в кластер | D27: 0 | E27: =E26 -> 0.02 | F27: 0.135 | G27: 0.135 | H27: =D27+F27 -> 0.135 | I27: =E27+G27 -> 0.155
D29: 10 лет | E29: с 11 года
C30: Ставка налога на имущество | D30: 0 | E30: 0.022
C31: Срок льготы по налогу на имущество, лет | D31: 10
C32: Премии к ФЗП | D32: =1/12 -> 0.083333333
C33: Страховые взносы с ФОТ | D33: =SUM(D34:D36) -> 0.3
C34: обязательное пенсионное страхование | D34: 0.22 | E34: статья 425 НК РФ с изменениям (Федеральный закон от 3 августа 2018 г. N 303-ФЗ)
C35: обязательное социальное страхование | D35: 0.029 | E35: статья 425 НК РФ
C36: обязательное медицинское страхование | D36: 0.051 | E36: статья 425 НК РФ
C37: Ставка страхования имущества | D37: 0.0025 | E37: от остаточной балансовой стоимости
C40: Условия управления
C41: ВЫБРАТЬ: | D41: 2 | E41: в расчетах утчено -->> | H41: =IF(D41=0,"без учета расходов на бренд",IF(D41=1,"прямое управление","франшиза для отелей 4* и 5*")) -> франшиза для отелей 4* и 5*
D42: 0 - без учета расходов на бренд
D43: 1 - прямое управление
D44: 2 - франшиза для отелей 4* и 5*
D46: NPV FCFE | E46: =KPI!D6 -> 67.805055
D47: IRR FCFE | E47: =KPI!D7 -> 0.14418346
D49: NPV FCFE TV | E49: =KPI!D11 -> 998.27965
D50: IRR FCFE TV | E50: =KPI!D12 -> 0.22612661

Sheet CPI
A1: 1
C2: МАКРОЭКОНОМИЧЕСКИЕ ПОКАЗАТЕЛИ
C3: Годовые показатели | E3: =Вводные!D5 -> 2022 | F3: =E3+1 -> 2023 | G3: =F3+1 -> 2024 | H3: =G3+1 -> 2025 | I3: =H3+1 -> 2026 | J3: =I3+1 -> 2027 | K3: =J3+1 -> 2028 | L3: =K3+1 -> 2029 | M3: =L3+1 -> 2030 | ... AN3: =AM3+1 -> 2057
C4: Инфляция за год | E4: 0.04 | F4: 0.04 | G4: 0.04 | H4: 0.04 | I4: 0.04 | J4: =I4 -> 0.04 | K4: =J4 -> 0.04 | L4: =K4 -> 0.04 | M4: =L4 -> 0.04 | N4: =M4 -> 0.04 | O4: =N4 -> 0.04 | P4: =O4 -> 0.04 | Q4: =P4 -> 0.04 | ... AN4: =AM4 -> 0.04
C5: Инфляция (накопленным итогом) | D5: 1 | E5: =(1+E4)*D5 -> 1.04 | F5: =(1+F4)*E5 -> 1.0816 | G5: =(1+G4)*F5 -> 1.124864 | H5: =(1+H4)*G5 -> 1.1698586 | I5: =(1+I4)*H5 -> 1.2166529 | J5: =(1+J4)*I5 -> 1.265319 | K5: =(1+K4)*J5 -> 1.3159318 | L5: =(1+L4)*K5 -> 1.3685691 | ... AN5: =(1+AN4)*AM5 -> 4.1039326
C6: Динамика земельных платежей | E6: 0 | F6: =E6 -> 0 | G6: =F6 -> 0 | H6: =G6 -> 0 | I6: 0.05 | J6: =E6 -> 0 | K6: =F6 -> 0 | L6: =G6 -> 0 | M6: =H6 -> 0 | N6: =I6 -> 0.05 | O6: =J6 -> 0 | P6: =K6 -> 0 | Q6: =L6 -> 0 | ... AN6: =AI6 -> 0
C7: Динамика земельных платежей (нак. итогом) | E7: 1 | F7: =(1+F6)*E7 -> 1 | G7: =(1+G6)*F7 -> 1 | H7: =(1+H6)*G7 -> 1 | I7: =(1+I6)*H7 -> 1.05 | J7: =(1+J6)*I7 -> 1.05 | K7: =(1+K6)*J7 -> 1.05 | L7: =(1+L6)*K7 -> 1.05 | M7: =(1+M6)*L7 -> 1.05 | ... AN7: =(1+AN6)*AM7 -> 1.4071004
C8: Инфляция заработных плат | E8: =E4 -> 0.04 | F8: =F4 -> 0.04 | G8: =G4 -> 0.04 | H8: =H4 -> 0.04 | I8: =I4 -> 0.04 | J8: =J4 -> 0.04 | K8: =K4 -> 0.04 | L8: =L4 -> 0.04 | ... AN8: =AN4 -> 0.04
C9: Инфляция заработных плат (нак. итогом) | E9: =E5 -> 1.04 | F9: =(1+F8)*E9 -> 1.0816 | G9: =(1+G8)*F9 -> 1.124864 | H9: =(1+H8)*G9 -> 1.1698586 | I9: =(1+I8)*H9 -> 1.2166529 | J9: =(1+J8)*I9 -> 1.265319 | K9: =(1+K8)*J9 -> 1.3159318 | L9: =(1+L8)*K9 -> 1.3685691 | M9: =(1+M8)*L9 -> 1.4233118 | ... AN9: =(1+AN8)*AM9 -> 4.1039326
C10: Руб./Евро | E10: 88.040608 | F10: 84.434627 | G10: 79.241197 | H10: =G10 -> 79.241197 | I10: =H10 -> 79.241197 | J10: =I10 -> 79.241197 | K10: =J10 -> 79.241197 | L10: =K10 -> 79.241197 | M10: =L10 -> 79.241197 | N10: =M10 -> 79.241197 | O10: =N10 -> 79.241197 | ... AN10: =AM10 -> 79.241197
C11: Руб./Долл. | E11: 80 | F11: =E11 -> 80 | G11: =F11 -> 80 | H11: =G11 -> 80 | I11: =H11 -> 80 | J11: =I11 -> 80 | K11: =J11 -> 80 | L11: =K11 -> 80 | M11: =L11 -> 80 | ... AN11: =AM11 -> 80
C12: Квартальные показатели | E12: =YEAR(E16) -> 2022 | F12: =YEAR(F16) -> 2022 | G12: =YEAR(G16) -> 2022 | H12: =YEAR(H16) -> 2022 | I12: =YEAR(I16) -> 2023 | J12: =YEAR(J16) -> 2023 | K12: =YEAR(K16) -> 2023 | L12: =YEAR(L16) -> 2023 | ... BL12: =YEAR(BL16) -> 2036
C13: Номер периода, п/п | E13: 1 | F13: 2 | G13: 3 | H13: 4 | I13: 5 | J13: 6 | K13: 7 | L13: 8 | M13: 9 | N13: 10 | O13: 11 | P13: 12 | Q13: 13 | R13: 14 | S13: 15 | T13: 16 | U13: 17 | V13: 18 | W13: 19 | X13: 20 | Y13: 21 | Z13: 22 | AA13: 23 | AB13: 24 | AC13: 25 | AD13: 26 | AE13: 27 | AF13: 28 | AG13: 29 | AH13: 30 | AI13: 31 | AJ13: 32 | AK13: 33 | AL13: 34 | AM13: 35 | AN13: 36 | AO13: 37 | AP13: 38 | AQ13: 39 | AR13: 40 | AS13: 41 | AT13: 42 | AU13: 43 | AV13: 44 | AW13: 45 | AX13: 46 | AY13: 47 | AZ13: 48 | BA13: 49 | BB13: 50 | BC13: 51 | BD13: 52 | BE13: 53 | BF13: 54 | BG13: 55 | BH13: 56 | BI13: 57 | BJ13: 58 | BK13: 59 | BL13: 60
C14: Квартал | E14: =IF(E15<>"",TRUNC((MONTH(E16)-1)/3, 0)+1,"") -> 1 | F14: =IF(F15<>"",TRUNC((MONTH(F16)-1)/3, 0)+1,"") -> 2 | G14: =IF(G15<>"",TRUNC((MONTH(G16)-1)/3, 0)+1,"") -> 3 | H14: =IF(H15<>"",TRUNC((MONTH(H16)-1)/3, 0)+1,"") -> 4 | I14: =IF(I15<>"",TRUNC((MONTH(I16)-1)/3, 0)+1,"") -> 1 | J14: =IF(J15<>"",TRUNC((MONTH(J16)-1)/3, 0)+1,"") -> 2 | K14: =IF(K15<>"",TRUNC((MONTH(K16)-1)/3, 0)+1,"") -> 3 | L14: =IF(L15<>"",TRUNC((MONTH(L16)-1)/3, 0)+1,"") -> 4 | ... BL14: =IF(BL15<>"",TRUNC((MONTH(BL16)-1)/3, 0)+1,"") -> 4
C15: Начало периода | E15: =Вводные!D4 -> 44593 | F15: =DATE(YEAR(E15),(TRUNC((MONTH(E15)-1)/3,0)+1)*3+1,1) -> 44652 | G15: =DATE(YEAR(F15),(TRUNC((MONTH(F15)-1)/3,0)+1)*3+1,1) -> 44743 | H15: =DATE(YEAR(G15),(TRUNC((MONTH(G15)-1)/3,0)+1)*3+1,1) -> 44835 | I15: =DATE(YEAR(H15),(TRUNC((MONTH(H15)-1)/3,0)+1)*3+1,1) -> 44927 | J15: =DATE(YEAR(I15),(TRUNC((MONTH(I15)-1)/3,0)+1)*3+1,1) -> 45017 | K15: =DATE(YEAR(J15),(TRUNC((MONTH(J15)-1)/3,0)+1)*3+1,1) -> 45108 | L15: =DATE(YEAR(K15),(TRUNC((MONTH(K15)-1)/3,0)+1)*3+1,1) -> 45200 | M15: =DATE(YEAR(L15),(TRUNC((MONTH(L15)-1)/3,0)+1)*3+1,1) -> 45292 | ... BL15: =DATE(YEAR(BK15),(TRUNC((MONTH(BK15)-1)/3,0)+1)*3+1,1) -> 49949
C16: Конец периода | E16: =DATE(YEAR(E15),((TRUNC((MONTH(E15)-1),0)+1)+2),1)-1 -> 44651 | F16: =DATE(YEAR(F15),((TRUNC((MONTH(F15)-1),0)+1)+1)+2,1)-1 -> 44742 | G16: =DATE(YEAR(G15),((TRUNC((MONTH(G15)-1),0)+1)+1)+2,1)-1 -> 44834 | H16: =DATE(YEAR(H15),((TRUNC((MONTH(H15)-1),0)+1)+1)+2,1)-1 -> 44926 | I16: =DATE(YEAR(I15),((TRUNC((MONTH(I15)-1),0)+1)+1)+2,1)-1 -> 45016 | J16: =DATE(YEAR(J15),((TRUNC((MONTH(J15)-1),0)+1)+1)+2,1)-1 -> 45107 | K16: =DATE(YEAR(K15),((TRUNC((MONTH(K15)-1),0)+1)+1)+2,1)-1 -> 45199 | L16: =DATE(YEAR(L15),((TRUNC((MONTH(L15)-1),0)+1)+1)+2,1)-1 -> 45291 | M16: =DATE(YEAR(M15),((TRUNC((MONTH(M15)-1),0)+1)+1)+2,1)-1 -> 45382 | ... BL16: =DATE(YEAR(BL15),((TRUNC((MONTH(BL15)-1),0)+1)+1)+2,1)-1 -> 50040
C17: Квартал | E17: =CONCATENATE(E14," кв. ",H99) -> 1 кв. | F17: =CONCATENATE(F14," кв. ",I99) -> 2 кв. | G17: =CONCATENATE(G14," кв. ",J99) -> 3 кв. | H17: =CONCATENATE(H14," кв. ",K99) -> 4 кв. | I17: =CONCATENATE(I14," кв. ",L99) -> 1 кв. | J17: =CONCATENATE(J14," кв. ",M99) -> 2 кв. | K17: =CONCATENATE(K14," кв. ",N99) -> 3 кв. | L17: =CONCATENATE(L14," кв. ",O99) -> 4 кв. | ... BL17: =CONCATENATE(BL14," кв. ",BO99) -> 4 кв.
C18: Дней в период | E18: =E16-E15+1 -> 59 | F18: =F16-F15+1 -> 91 | G18: =G16-G15+1 -> 92 | H18: =H16-H15+1 -> 92 | I18: =I16-I15+1 -> 90 | J18: =J16-J15+1 -> 91 | K18: =K16-K15+1 -> 92 | L18: =L16-L15+1 -> 92 | ... BL18: =BL16-BL15+1 -> 92
C19: Прогноз роста в период
C20: Инфляция | E20: =(1+SUMIF($E$3:$AN$3,E12,$E$4:$AN$4))^(1/4)-1 -> 0.0098534065 | F20: =(1+SUMIF($E$3:$AN$3,F12,$E$4:$AN$4))^(1/4)-1 -> 0.0098534065 | G20: =(1+SUMIF($E$3:$AN$3,G12,$E$4:$AN$4))^(1/4)-1 -> 0.0098534065 | H20: =(1+SUMIF($E$3:$AN$3,H12,$E$4:$AN$4))^(1/4)-1 -> 0.0098534065 | I20: =(1+SUMIF($E$3:$AN$3,I12,$E$4:$AN$4))^(1/4)-1 -> 0.0098534065 | J20: =(1+SUMIF($E$3:$AN$3,J12,$E$4:$AN$4))^(1/4)-1 -> 0.0098534065 | K20: =(1+SUMIF($E$3:$AN$3,K12,$E$4:$AN$4))^(1/4)-1 -> 0.0098534065 | L20: =(1+SUMIF($E$3:$AN$3,L12,$E$4:$AN$4))^(1/4)-1 -> 0.0098534065 | ... BL20: =(1+SUMIF($E$3:$AN$3,BL12,$E$4:$AN$4))^(1/4)-1 -> 0.0098534065
C21: Земельные платежи | E21: =(1+SUMIF($E$3:$AN$3,E12,$E$6:$AN$6))^(1/4)-1 -> 0 | F21: =(1+SUMIF($E$3:$AN$3,F12,$E$6:$AN$6))^(1/4)-1 -> 0 | G21: =(1+SUMIF($E$3:$AN$3,G12,$E$6:$AN$6))^(1/4)-1 -> 0 | H21: =(1+SUMIF($E$3:$AN$3,H12,$E$6:$AN$6))^(1/4)-1 -> 0 | I21: =(1+SUMIF($E$3:$AN$3,I12,$E$6:$AN$6))^(1/4)-1 -> 0 | J21: =(1+SUMIF($E$3:$AN$3,J12,$E$6:$AN$6))^(1/4)-1 -> 0 | K21: =(1+SUMIF($E$3:$AN$3,K12,$E$6:$AN$6))^(1/4)-1 -> 0 | L21: =(1+SUMIF($E$3:$AN$3,L12,$E$6:$AN$6))^(1/4)-1 -> 0 | ... BL21: =(1+SUMIF($E$3:$AN$3,BL12,$E$6:$AN$6))^(1/4)-1 -> 0.012272234
C22: Заработная плата | E22: =(1+SUMIF($E$3:$AN$3,E12,$E$8:$AN$8))^(1/4)-1 -> 0.0098534065 | F22: =(1+SUMIF($E$3:$AN$3,F12,$E$8:$AN$8))^(1/4)-1 -> 0.0098534065 | G22: =(1+SUMIF($E$3:$AN$3,G12,$E$8:$AN$8))^(1/4)-1 -> 0.0098534065 | H22: =(1+SUMIF($E$3:$AN$3,H12,$E$8:$AN$8))^(1/4)-1 -> 0.0098534065 | I22: =(1+SUMIF($E$3:$AN$3,I12,$E$8:$AN$8))^(1/4)-1 -> 0.0098534065 | J22: =(1+SUMIF($F$3:$AN$3,J12,$F$8:$AN$8))^(1/4)-1 -> 0.0098534065 | K22: =(1+SUMIF($F$3:$AN$3,K12,$F$8:$AN$8))^(1/4)-1 -> 0.0098534065 | L22: =(1+SUMIF($F$3:$AN$3,L12,$F$8:$AN$8))^(1/4)-1 -> 0.0098534065 | M22: =(1+SUMIF($F$3:$AN$3,M12,$F$8:$AN$8))^(1/4)-1 -> 0.0098534065 | N22: =(1+SUMIF($F$3:$AN$3,N12,$F$8:$AN$8))^(1/4)-1 -> 0.0098534065 | O22: =(1+SUMIF($F$3:$AN$3,O12,$F$8:$AN$8))^(1/4)-1 -> 0.0098534065 | P22: =(1+SUMIF($F$3:$AN$3,P12,$F$8:$AN$8))^(1/4)-1 -> 0.0098534065 | Q22: =(1+SUMIF($F$3:$AN$3,Q12,$F$8:$AN$8))^(1/4)-1 -> 0.0098534065 | ... BL22: =(1+SUMIF($F$3:$AN$3,BL12,$F$8:$AN$8))^(1/4)-1 -> 0.0098534065
C23: Накопленный рост (на конец периода)
C24: =C20 -> Инфляция | D24: 1 | E24: =(1+E20)*D24 -> 1.0098534 | F24: =(1+F20)*E24 -> 1.0198039 | G24: =(1+G20)*F24 -> 1.0298524 | H24: =(1+H20)*G24 -> 1.04 | I24: =(1+I20)*H24 -> 1.0502475 | J24: =(1+J20)*I24 -> 1.0605961 | K24: =(1+K20)*J24 -> 1.0710465 | L24: =(1+L20)*K24 -> 1.0816 | ... BL24: =(1+BL20)*BK24 -> 1.8009435
C25: =C21 -> Земельные платежи | D25: 1 | E25: =(1+E21)*D25 -> 1 | F25: =(1+F21)*E25 -> 1 | G25: =(1+G21)*F25 -> 1 | H25: =(1+H21)*G25 -> 1 | I25: =(1+I21)*H25 -> 1 | J25: =(1+J21)*I25 -> 1 | K25: =(1+K21)*J25 -> 1 | L25: =(1+L21)*K25 -> 1 | ... BL25: =(1+BL21)*BK25 -> 1.157625
C26: =C22 -> Заработная плата | D26: 1 | E26: =(1+E22)*D26 -> 1.0098534 | F26: =(1+F22)*E26 -> 1.0198039 | G26: =(1+G22)*F26 -> 1.0298524 | H26: =(1+H22)*G26 -> 1.04 | I26: =(1+I22)*H26 -> 1.0502475 | J26: =(1+J22)*I26 -> 1.0605961 | K26: =(1+K22)*J26 -> 1.0710465 | L26: =(1+L22)*K26 -> 1.0816 | ... BL26: =(1+BL22)*BK26 -> 1.8009435
C27: Проверка | H27: =H24=LOOKUP(H$12,$E$3:$AN$3,$E5:$AN5) -> TRUE | L27: =L24=LOOKUP(L$12,$E$3:$AN$3,$E5:$AN5) -> TRUE | P27: =P24=LOOKUP(P$12,$E$3:$AN$3,$E5:$AN5) -> TRUE | T27: =T24=LOOKUP(T$12,$E$3:$AN$3,$E5:$AN5) -> TRUE | X27: =X24=LOOKUP(X$12,$E$3:$AN$3,$E5:$AN5) -> TRUE | AB27: =AB24=LOOKUP(AB$12,$E$3:$AN$3,$E5:$AN5) -> TRUE
C28: Проверка | H28: =H25=LOOKUP(H$12,$E$3:$AN$3,$E7:$AN7) -> TRUE | L28: =L25=LOOKUP(L$12,$E$3:$AN$3,$E7:$AN7) -> TRUE | P28: =P25=LOOKUP(P$12,$E$3:$AN$3,$E7:$AN7) -> TRUE | T28: =T25=LOOKUP(T$12,$E$3:$AN$3,$E7:$AN7) -> TRUE | X28: =X25=LOOKUP(X$12,$E$3:$AN$3,$E7:$AN7) -> TRUE | AB28: =AB25=LOOKUP(AB$12,$E$3:$AN$3,$E7:$AN7) -> TRUE
C29: Проверка | H29: =H26=LOOKUP(H$12,$E$3:$AN$3,$E9:$AN9) -> TRUE | L29: =L26=LOOKUP(L$12,$E$3:$AN$3,$E9:$AN9) -> TRUE | P29: =P26=LOOKUP(P$12,$E$3:$AN$3,$E9:$AN9) -> TRUE | T29: =T26=LOOKUP(T$12,$E$3:$AN$3,$E9:$AN9) -> TRUE | X29: =X26=LOOKUP(X$12,$E$3:$AN$3,$E9:$AN9) -> TRUE | AB29: =AB26=LOOKUP(AB$12,$E$3:$AN$3,$E9:$AN9) -> TRUE

Sheet Земля
A1: 1
C3: ЗЕМЕЛЬНЫЕ ПЛАТЕЖИ - ВВОДНЫЕ ДАННЫЕ
C4: Кадастровый номер | D4: Площадь, кв.м | E4: Кадастровая стоимость, руб. | F4: Кадастровая стоимость, руб./ кв.м | G4: Вид права | H4: Размер платежа, % от кадастровой стоимости | I4: Размер платежа, руб./год | J4: Размер платежа, руб./кв.м/год | L4: Категория | M4: ВРИ
C5: 09:06:0021401:2308 | D5: 114723 | E5: 30157235 | F5: =E5/D5 -> 262.87 | G5: аренда | H5: 0.015 | I5: =H5*E5 -> 452358.53 | J5: =H5*F5 -> 3.94305 | L5: Земли особо охраняемых территорий и объектов | M5: Для туристско-рекреационной деятельности
C6: 09:06:0000000:16366 | D6: 21600 | E6: 5677992 | F6: =E6/D6 -> 262.87 | G6: аренда | H6: 0.015 | I6: =H6*E6 -> 85169.88 | J6: =H6*F6 -> 3.94305 | L6: Земли особо охраняемых территорий и объектов | M6: Для туристско-рекреационной деятельности
C7: ИТОГО, га | D7: =SUM(D5:D6)/10000 -> 13.6323
C13: Дата ввода в экспл-ю | D13: =Вводные!D9 -> 45839
C14: Год ввода в экспл-ю | D14: =YEAR(D13) -> 2025
B15: Примечание | C15: Доля 1 периода | D15: 1
C17: ПРОГНОЗ ЗЕМЕЛЬНЫХ ПЛАТЕЖЕЙ | E17: руб. | DN17: Мультипликатор | DO17: =10^6 -> 1000000 | DP17: =IF(DO17=1,"руб.",IF(DO17=1000,"тыс. руб.",IF(DO17=1000000,"млн руб.",IF(DO17=1000000000,"млрд руб.","Ошибка")))) -> млн руб.
C18: Показатель | E18: =YEAR(E19) -> 2022 | F18: =YEAR(F19) -> 2022 | G18: =YEAR(G19) -> 2022 | H18: =YEAR(H19) -> 2022 | I18: =YEAR(I19) -> 2023 | J18: =YEAR(J19) -> 2023 | K18: =YEAR(K19) -> 2023 | L18: =YEAR(L19) -> 2023 | ... DK18: =YEAR(DK19) -> 2049 | DM18: ГОД --->> | DN18: =E18 -> 2022 | DO18: =DN18+1 -> 2023 | DP18: =DO18+1 -> 2024 | DQ18: =DP18+1 -> 2025 | DR18: =DQ18+1 -> 2026 | DS18: =DR18+1 -> 2027 | DT18: =DS18+1 -> 2028 | DU18: =DT18+1 -> 2029 | DV18: =DU18+1 -> 2030 | ... EO18: =EN18+1 -> 2049
C19: Начало периода | E19: =Вводные!$D$4 -> 44593 | F19: =DATE(YEAR(E20),(TRUNC((MONTH(E20)-1)/3,0)+1)*3+1,1) -> 44652 | G19: =DATE(YEAR(F20),(TRUNC((MONTH(F20)-1)/3,0)+1)*3+1,1) -> 44743 | H19: =DATE(YEAR(G20),(TRUNC((MONTH(G20)-1)/3,0)+1)*3+1,1) -> 44835 | I19: =DATE(YEAR(H20),(TRUNC((MONTH(H20)-1)/3,0)+1)*3+1,1) -> 44927 | J19: =DATE(YEAR(I20),(TRUNC((MONTH(I20)-1)/3,0)+1)*3+1,1) -> 45017 | K19: =DATE(YEAR(J20),(TRUNC((MONTH(J20)-1)/3,0)+1)*3+1,1) -> 45108 | L19: =DATE(YEAR(K20),(TRUNC((MONTH(K20)-1)/3,0)+1)*3+1,1) -> 45200 | M19: =DATE(YEAR(L20),(TRUNC((MONTH(L20)-1)/3,0)+1)*3+1,1) -> 45292 | ... DK19: =DATE(YEAR(DJ20),(TRUNC((MONTH(DJ20)-1)/3,0)+1)*3+1,1) -> 54605
C20: Конец периода | E20: =DATE(YEAR(E19),((TRUNC((MONTH(E19)-1),0)+1)+2),1)-1 -> 44651 | F20: =DATE(YEAR(F19),((TRUNC((MONTH(F19)-1),0)+1)+1)+2,1)-1 -> 44742 | G20: =DATE(YEAR(G19),((TRUNC((MONTH(G19)-1),0)+1)+1)+2,1)-1 -> 44834 | H20: =DATE(YEAR(H19),((TRUNC((MONTH(H19)-1),0)+1)+1)+2,1)-1 -> 44926 | I20: =DATE(YEAR(I19),((TRUNC((MONTH(I19)-1),0)+1)+1)+2,1)-1 -> 45016 | J20: =DATE(YEAR(J19),((TRUNC((MONTH(J19)-1),0)+1)+1)+2,1)-1 -> 45107 | K20: =DATE(YEAR(K19),((TRUNC((MONTH(K19)-1),0)+1)+1)+2,1)-1 -> 45199 | L20: =DATE(YEAR(L19),((TRUNC((MONTH(L19)-1),0)+1)+1)+2,1)-1 -> 45291 | M20: =DATE(YEAR(M19),((TRUNC((MONTH(M19)-1),0)+1)+1)+2,1)-1 -> 45382 | ... DK20: =DATE(YEAR(DK19),((TRUNC((MONTH(DK19)-1),0)+1)+1)+2,1)-1 -> 54696
C21: Длина периода | E21: =E20-E19+1 -> 59 | F21: =F20-F19+1 -> 91 | G21: =G20-G19+1 -> 92 | H21: =H20-H19+1 -> 92 | I21: =I20-I19+1 -> 90 | J21: =J20-J19+1 -> 91 | K21: =K20-K19+1 -> 92 | L21: =L20-L19+1 -> 92 | ... DK21: =DK20-DK19+1 -> 92
C22: Площадь участка, кв.м | E22: =$D$5 -> 114723 | F22: =E22 -> 114723 | G22: =F22 -> 114723 | H22: =G22 -> 114723 | I22: =H22 -> 114723 | J22: =I22 -> 114723 | K22: =J22 -> 114723 | L22: =K22 -> 114723 | M22: =L22 -> 114723 | ... DK22: =DJ22 -> 114723
C23: Выбытие тур.резиденций ввиду продажи, кв.м | E23: =Резиденции!F29/(Земля!D5+Земля!D6) -> 0.020539454 | F23: =Резиденции!F12 -> 14000 | G23: =LOOKUP(G19,ПРОДАЖА_lease_back!$D$11:$CQ$11,ПРОДАЖА_lease_back!$D$22:$CQ$22) -> 0 | H23: =LOOKUP(H19,ПРОДАЖА_lease_back!$D$11:$CQ$11,ПРОДАЖА_lease_back!$D$22:$CQ$22) -> 0 | I23: =LOOKUP(I19,ПРОДАЖА_lease_back!$D$11:$CQ$11,ПРОДАЖА_lease_back!$D$22:$CQ$22) -> 0 | J23: =LOOKUP(J19,ПРОДАЖА_lease_back!$D$11:$CQ$11,ПРОДАЖА_lease_back!$D$22:$CQ$22) -> 0 | K23: =LOOKUP(K19,ПРОДАЖА_lease_back!$D$11:$CQ$11,ПРОДАЖА_lease_back!$D$22:$CQ$22) -> 0 | L23: =LOOKUP(L19,ПРОДАЖА_lease_back!$D$11:$CQ$11,ПРОДАЖА_lease_back!$D$22:$CQ$22) -> 0 | M23: =LOOKUP(M19,ПРОДАЖА_lease_back!$D$11:$CQ$11,ПРОДАЖА_lease_back!$D$22:$CQ$22) -> 0 | N23: =LOOKUP(N19,ПРОДАЖА_lease_back!$D$11:$CQ$11,ПРОДАЖА_lease_back!$D$22:$CQ$22) -> 0 | ... DK23: =LOOKUP(DK19,ПРОДАЖА_lease_back!$D$11:$CQ$11,ПРОДАЖА_lease_back!$D$22:$CQ$22) -> 0
C24: Выбытие зем./участков ввиду продажи тур.резиденций, кв.м | G24: =-$E$23*G22*(SUM($G$23:G23)/$F$23) -> 0 | H24: =-$E$23*H22*(SUM($G$23:H23)/$F$23) -> 0 | I24: =-$E$23*I22*(SUM($G$23:I23)/$F$23) -> 0 | J24: =-$E$23*J22*(SUM($G$23:J23)/$F$23) -> 0 | K24: =-$E$23*K22*(SUM($G$23:K23)/$F$23) -> 0 | L24: =-$E$23*L22*(SUM($G$23:L23)/$F$23) -> 0 | M24: =-$E$23*M22*(SUM($G$23:M23)/$F$23) -> 0 | N24: =-$E$23*N22*(SUM($G$23:N23)/$F$23) -> 0 | ... DK24: =-$E$23*DK22*(SUM($G$23:DK23)/$F$23) -> -2356.3478
C25: Итого, площадь участка, за который производится оплата земельных платежей, кв.м | E25: =SUM(E22,E24) -> 114723 | F25: =SUM(F22,F24) -> 114723 | G25: =SUM(G22,G24) -> 114723 | H25: =SUM(H22,H24) -> 114723 | I25: =SUM(I22,I24) -> 114723 | J25: =SUM(J22,J24) -> 114723 | K25: =SUM(K22,K24) -> 114723 | L25: =SUM(L22,L24) -> 114723 | ... DK25: =SUM(DK22,DK24) -> 112366.65
C26: Динамика изменения земельных платежей | E26: =F26 -> 1 | F26: =LOOKUP(F19,CPI!$15:$15,CPI!$25:$25) -> 1 | G26: =LOOKUP(G19,CPI!$15:$15,CPI!$25:$25) -> 1 | H26: =LOOKUP(H19,CPI!$15:$15,CPI!$25:$25) -> 1 | I26: =LOOKUP(I19,CPI!$15:$15,CPI!$25:$25) -> 1 | J26: =LOOKUP(J19,CPI!$15:$15,CPI!$25:$25) -> 1 | K26: =LOOKUP(K19,CPI!$15:$15,CPI!$25:$25) -> 1 | L26: =LOOKUP(L19,CPI!$15:$15,CPI!$25:$25) -> 1 | M26: =LOOKUP(M19,CPI!$15:$15,CPI!$25:$25) -> 1 | ... DK26: =LOOKUP(DK19,CPI!$15:$15,CPI!$25:$25) -> 1.157625
C27: Итого, все платежи | E27: =$J$5*E26*E25*E21/365 -> 73120.967 | F27: =$J$5*F26*F25*F21/365 -> 112779.8 | G27: =$J$5*G26*G25*G21/365 -> 114019.14 | H27: =$J$5*H26*H25*H21/365 -> 114019.14 | I27: =$J$5*I26*I25*I21/365 -> 111540.46 | J27: =$J$5*J26*J25*J21/365 -> 112779.8 | K27: =$J$5*K26*K25*K21/365 -> 114019.14 | L27: =$J$5*L26*L25*L21/365 -> 114019.14 | ... DK27: =$J$5*DK26*DK25*DK21/365 -> 129280.37 | DN27: =SUMIF($E$18:$DK$18,DN$18,$E27:$DK27)/$DO$17 -> 0.41393903 | DO27: =SUMIF($E$18:$DK$18,DO$18,$E27:$DK27)/$DO$17 -> 0.45235853 | DP27: =SUMIF($E$18:$DK$18,DP$18,$E27:$DK27)/$DO$17 -> 0.45359786 | DQ27: =SUMIF($E$18:$DK$18,DQ$18,$E27:$DK27)/$DO$17 -> 0.45235853 | DR27: =SUMIF($E$18:$DK$18,DR$18,$E27:$DK27)/$DO$17 -> 0.46508195 | DS27: =SUMIF($E$18:$DK$18,DS$18,$E27:$DK27)/$DO$17 -> 0.47008922 | DT27: =SUMIF($E$18:$DK$18,DT$18,$E27:$DK27)/$DO$17 -> 0.4676403 | DU27: =SUMIF($E$18:$DK$18,DU$18,$E27:$DK27)/$DO$17 -> 0.46522069 | ... EO27: =SUMIF($E$18:$DK$18,EO$18,$E27:$DK27)/$DO$17 -> 0.38362545
C30: ПРОГНОЗ ЗЕМЕЛЬНЫХ ПЛАТЕЖЕЙ - ПО ГОДАМ
C31: Показатель | E31: =E18 -> 2022 | F31: =E31+1 -> 2023 | G31: =F31+1 -> 2024 | H31: =G31+1 -> 2025 | I31: =H31+1 -> 2026 | J31: =I31+1 -> 2027 | K31: =J31+1 -> 2028 | L31: =K31+1 -> 2029 | M31: =L31+1 -> 2030 | ... AB31: =AA31+1 -> 2045
C32: Земельные платежи инвестиционного периода | E32: =IF(E31<$D$14,SUMIF(18:18,E31,27:27),0) -> 413939.45 | F32: =IF(F31<$D$14,SUMIF(18:18,F31,27:27),0) -> 452358.98 | G32: =IF(G31<$D$14,SUMIF(18:18,G31,27:27),0) -> 453598.32 | H32: =IF(H31<$D$14,SUMIF(18:18,H31,27:27),0) -> 0 | I32: =IF(I31<$D$14,SUMIF(18:18,I31,27:27),0) -> 0 | J32: =IF(J31<$D$14,SUMIF(18:18,J31,27:27),0) -> 0 | K32: =IF(K31<$D$14,SUMIF(18:18,K31,27:27),0) -> 0 | L32: =IF(L31<$D$14,SUMIF(18:18,L31,27:27),0) -> 0 | ... AB32: =IF(AB31<$D$14,SUMIF(18:18,AB31,27:27),0) -> 0
C33: Земельные платежи операционного периода | E33: =IF(E31>=$D$14,SUMIF(18:18,E31,27:27),0) -> 0 | F33: =IF(F31>=$D$14,SUMIF(18:18,F31,27:27),0) -> 0 | G33: =IF(G31>=$D$14,SUMIF(18:18,G31,27:27),0) -> 0 | H33: =IF(H31>=$D$14,SUMIF(18:18,H31,27:27),0) -> 452358.98 | I33: =IF(I31>=$D$14,SUMIF(18:18,I31,27:27),0) -> 465082.41 | J33: =IF(J31>=$D$14,SUMIF(18:18,J31,27:27),0) -> 470089.69 | K33: =IF(K31>=$D$14,SUMIF(18:18,K31,27:27),0) -> 467640.77 | L33: =IF(L31>=$D$14,SUMIF(18:18,L31,27:27),0) -> 465221.16 | ... AB33: =IF(AB31>=$D$14,SUMIF(18:18,AB31,27:27),0) -> 512906.33

Sheet Бюджетный эффект
C2: Год ввода 1 очереди | D2: =YEAR(Вводные!D9) -> 2025
H3: =C2 -> Год ввода 1 очереди
E4: =F4-1 -> 2022 | F4: =G4-1 -> 2023 | G4: =H4-1 -> 2024 | H4: =D2 -> 2025 | I4: =H4+1 -> 2026 | J4: =I4+1 -> 2027 | K4: =J4+1 -> 2028 | L4: =K4+1 -> 2029 | M4: =L4+1 -> 2030 | N4: =M4+1 -> 2031 | O4: =N4+1 -> 2032 | P4: =O4+1 -> 2033 | Q4: =P4+1 -> 2034
C5: Выручка, руб. без НДС
C6: Туристический комплекс "Лунная поляна" - Архыз | E6: =IFERROR(LOOKUP(E4,СВОД_PL!$D$3:$T$3,СВОД_PL!$D$32:$T$32),0)+IFERROR(LOOKUP(E4,Ресторан!$F$5:$V$5,Ресторан!$F$62:$V$62),0)+IFERROR(LOOKUP(E4,Retail!$D$21:$V$21,Retail!$D$49:$V$49),0)+IFERROR(LOOKUP(E4,Паркинг_PL!$D$9:$T$9,Паркинг_PL!$D$29:$T$29),0)+SUMIF(ПРОДАЖА_lease_back!$D$8:$CQ$8,E4,ПРОДАЖА_lease_back!$D$32:$CQ$32) -> 0 | F6: =IFERROR(LOOKUP(F4,СВОД_PL!$D$3:$T$3,СВОД_PL!$D$32:$T$32),0)+IFERROR(LOOKUP(F4,Ресторан!$F$5:$V$5,Ресторан!$F$62:$V$62),0)+IFERROR(LOOKUP(F4,Retail!$D$21:$V$21,Retail!$D$49:$V$49),0)+IFERROR(LOOKUP(F4,Паркинг_PL!$D$9:$T$9,Паркинг_PL!$D$29:$T$29),0)+SUMIF(ПРОДАЖА_lease_back!$D$8:$CQ$8,F4,ПРОДАЖА_lease_back!$D$32:$CQ$32) -> 0 | G6: =IFERROR(LOOKUP(G4,СВОД_PL!$D$3:$T$3,СВОД_PL!$D$32:$T$32),0)+IFERROR(LOOKUP(G4,Ресторан!$F$5:$V$5,Ресторан!$F$62:$V$62),0)+IFERROR(LOOKUP(G4,Retail!$D$21:$V$21,Retail!$D$49:$V$49),0)+IFERROR(LOOKUP(G4,Паркинг_PL!$D$9:$T$9,Паркинг_PL!$D$29:$T$29),0)+SUMIF(ПРОДАЖА_lease_back!$D$8:$CQ$8,G4,ПРОДАЖА_lease_back!$D$32:$CQ$32) -> 0 | H6: =IFERROR(LOOKUP(H4,СВОД_PL!$D$3:$T$3,СВОД_PL!$D$32:$T$32),0)+IFERROR(LOOKUP(H4,Ресторан!$F$5:$V$5,Ресторан!$F$62:$V$62),0)+IFERROR(LOOKUP(H4,Retail!$D$21:$V$21,Retail!$D$49:$V$49),0)+IFERROR(LOOKUP(H4,Паркинг_PL!$D$9:$T$9,Паркинг_PL!$D$29:$T$29),0)+SUMIF(ПРОДАЖА_lease_back!$D$8:$CQ$8,H4,ПРОДАЖА_lease_back!$D$32:$CQ$32) -> 4.1149352e+08 | I6: =IFERROR(LOOKUP(I4,СВОД_PL!$D$3:$T$3,СВОД_PL!$D$32:$T$32),0)+IFERROR(LOOKUP(I4,Ресторан!$F$5:$V$5,Ресторан!$F$62:$V$62),0)+IFERROR(LOOKUP(I4,Retail!$D$21:$V$21,Retail!$D$49:$V$49),0)+IFERROR(LOOKUP(I4,Паркинг_PL!$D$9:$T$9,Паркинг_PL!$D$29:$T$29),0)+SUMIF(ПРОДАЖА_lease_back!$D$8:$CQ$8,I4,ПРОДАЖА_lease_back!$D$32:$CQ$32) -> 2.7535099e+09 | J6: =IFERROR(LOOKUP(J4,СВОД_PL!$D$3:$T$3,СВОД_PL!$D$32:$T$32),0)+IFERROR(LOOKUP(J4,Ресторан!$F$5:$V$5,Ресторан!$F$62:$V$62),0)+IFERROR(LOOKUP(J4,Retail!$D$21:$V$21,Retail!$D$49:$V$49),0)+IFERROR(LOOKUP(J4,Паркинг_PL!$D$9:$T$9,Паркинг_PL!$D$29:$T$29),0)+SUMIF(ПРОДАЖА_lease_back!$D$8:$CQ$8,J4,ПРОДАЖА_lease_back!$D$32:$CQ$32) -> 4.2924276e+09 | K6: =IFERROR(LOOKUP(K4,СВОД_PL!$D$3:$T$3,СВОД_PL!$D$32:$T$32),0)+IFERROR(LOOKUP(K4,Ресторан!$F$5:$V$5,Ресторан!$F$62:$V$62),0)+IFERROR(LOOKUP(K4,Retail!$D$21:$V$21,Retail!$D$49:$V$49),0)+IFERROR(LOOKUP(K4,Паркинг_PL!$D$9:$T$9,Паркинг_PL!$D$29:$T$29),0)+SUMIF(ПРОДАЖА_lease_back!$D$8:$CQ$8,K4,ПРОДАЖА_lease_back!$D$32:$CQ$32) -> 4.2009615e+09 | L6: =IFERROR(LOOKUP(L4,СВОД_PL!$D$3:$T$3,СВОД_PL!$D$32:$T$32),0)+IFERROR(LOOKUP(L4,Ресторан!$F$5:$V$5,Ресторан!$F$62:$V$62),0)+IFERROR(LOOKUP(L4,Retail!$D$21:$V$21,Retail!$D$49:$V$49),0)+IFERROR(LOOKUP(L4,Паркинг_PL!$D$9:$T$9,Паркинг_PL!$D$29:$T$29),0)+SUMIF(ПРОДАЖА_lease_back!$D$8:$CQ$8,L4,ПРОДАЖА_lease_back!$D$32:$CQ$32) -> 2.647119e+09 | ... Q6: =IFERROR(LOOKUP(Q4,СВОД_PL!$D$3:$T$3,СВОД_PL!$D$32:$T$32),0)+IFERROR(LOOKUP(Q4,Ресторан!$F$5:$V$5,Ресторан!$F$62:$V$62),0)+IFERROR(LOOKUP(Q4,Retail!$D$21:$V$21,Retail!$D$49:$V$49),0)+IFERROR(LOOKUP(Q4,Паркинг_PL!$D$9:$T$9,Паркинг_PL!$D$29:$T$29),0)+SUMIF(ПРОДАЖА_lease_back!$D$8:$CQ$8,Q4,ПРОДАЖА_lease_back!$D$32:$CQ$32) -> 3.3121542e+09
C8: ЧОП
C9: =C6 -> Туристический комплекс "Лунная поляна" - Архыз | E9: =LOOKUP(E$4,CF_15!$D$5:$T$5,CF_15!$D$24:$T$24) -> 0 | F9: =LOOKUP(F$4,CF_15!$D$5:$T$5,CF_15!$D$24:$T$24) -> 0 | G9: =LOOKUP(G$4,CF_15!$D$5:$T$5,CF_15!$D$24:$T$24) -> 0 | H9: =LOOKUP(H$4,CF_15!$D$5:$T$5,CF_15!$D$24:$T$24) -> 1.0428256e+08 | I9: =LOOKUP(I$4,CF_15!$D$5:$T$5,CF_15!$D$24:$T$24) -> 1.4387461e+09 | J9: =LOOKUP(J$4,CF_15!$D$5:$T$5,CF_15!$D$24:$T$24) -> 2.4141395e+09 | K9: =LOOKUP(K$4,CF_15!$D$5:$T$5,CF_15!$D$24:$T$24) -> 2.2885779e+09 | L9: =LOOKUP(L$4,CF_15!$D$5:$T$5,CF_15!$D$24:$T$24) -> 9.737917e+08 | ... Q9: =LOOKUP(Q$4,CF_15!$D$5:$T$5,CF_15!$D$24:$T$24) -> 1.2404216e+09
C11: Расходы
C12: =C9 -> Туристический комплекс "Лунная поляна" - Архыз | E12: =E6-E9 -> 0 | F12: =F6-F9 -> 0 | G12: =G6-G9 -> 0 | H12: =H6-H9 -> 3.0721096e+08 | I12: =I6-I9 -> 1.3147638e+09 | J12: =J6-J9 -> 1.8782881e+09 | K12: =K6-K9 -> 1.9123836e+09 | L12: =L6-L9 -> 1.6733273e+09 | ... Q12: =Q6-Q9 -> 2.0717327e+09
C14: Доля расходов на персонал в выручке
C15: =C12 -> Туристический комплекс "Лунная поляна" - Архыз | H15: =H20/H6 -> 0.29676723 | I15: =I20/I6 -> 0.14008499 | J15: =J20/J6 -> 0.12526065 | K15: =K20/K6 -> 0.13284752 | L15: =L20/L6 -> 0.22129918 | M15: =M20/M6 -> 0.21682216 | N15: =N20/N6 -> 0.21682216 | O15: =O20/O6 -> 0.21681472 | ... Q15: =Q20/Q6 -> 0.21682216
C16: Доля расходов на персонал в расходах
C17: =C14 -> Доля расходов на персонал в выручке | H17: =H20/H12 -> 0.39750467 | I17: =I20/I12 -> 0.29338 | J17: =J20/J12 -> 0.28625656 | K17: =K20/K12 -> 0.29182813 | L17: =L20/L12 -> 0.35008409 | M17: =M20/M12 -> 0.34783083 | N17: =N20/N12 -> 0.3460461 | O17: =O20/O12 -> 0.34624756 | ... Q17: =Q20/Q12 -> 0.34664145
C19: Расходы на персонал
C20: =C15 -> Туристический комплекс "Лунная поляна" - Архыз | H20: =LOOKUP(H4,СВОД_PL!120:120,СВОД_PL!124:124) -> 1.2211779e+08 | I20: =LOOKUP(I4,СВОД_PL!120:120,СВОД_PL!124:124) -> 3.8572541e+08 | J20: =LOOKUP(J4,СВОД_PL!120:120,СВОД_PL!124:124) -> 5.376723e+08 | K20: =LOOKUP(K4,СВОД_PL!120:120,СВОД_PL!124:124) -> 5.5808732e+08 | L20: =LOOKUP(L4,СВОД_PL!120:120,СВОД_PL!124:124) -> 5.8580527e+08 | M20: =LOOKUP(M4,СВОД_PL!120:120,СВОД_PL!124:124) -> 6.1387628e+08 | N20: =LOOKUP(N4,СВОД_PL!120:120,СВОД_PL!124:124) -> 6.3843133e+08 | O20: =LOOKUP(O4,СВОД_PL!120:120,СВОД_PL!124:124) -> 6.6581461e+08 | ... Q20: =LOOKUP(Q4,СВОД_PL!120:120,СВОД_PL!124:124) -> 7.1814842e+08
C22: НДФЛ
C23: =C20 -> Туристический комплекс "Лунная поляна" - Архыз | H23: =$E$59*H20 -> 12211779 | I23: =$E$59*I20 -> 38572541 | J23: =$E$59*J20 -> 53767230 | K23: =$E$59*K20 -> 55808732 | L23: =$E$59*L20 -> 58580527 | M23: =$E$59*M20 -> 61387628 | N23: =$E$59*N20 -> 63843133 | O23: =$E$59*O20 -> 66581461 | ... Q23: =$E$59*Q20 -> 71814842 | R23: =SUM(H23:Q23) -> 5.516206e+08
C25: Социальные отчисления
C26: =C23 -> Туристический комплекс "Лунная поляна" - Архыз | H26: =$E$62*H20 -> 28181029 | I26: =$E$62*I20 -> 89013555 | J26: =$E$62*J20 -> 1.2407822e+08 | K26: =$E$62*K20 -> 1.2878938e+08 | L26: =$E$62*L20 -> 1.3518583e+08 | M26: =$E$62*M20 -> 1.4166376e+08 | N26: =$E$62*N20 -> 1.4733031e+08 | O26: =$E$62*O20 -> 1.5364953e+08 | ... Q26: =$E$62*Q20 -> 1.6572656e+08 | R26: =SUM(H26:Q26) -> 1.2729706e+09
C28: Налог на прибыль
C29: =C26 -> Туристический комплекс "Лунная поляна" - Архыз | E29: =-LOOKUP(E4,CF_15!5:5,CF_15!34:34) -> 0 | F29: =-LOOKUP(F4,CF_15!5:5,CF_15!34:34) -> 0 | G29: =-LOOKUP(G4,CF_15!5:5,CF_15!34:34) -> 0 | H29: =-LOOKUP(H4,CF_15!5:5,CF_15!34:34) -> 0 | I29: =-LOOKUP(I4,CF_15!5:5,CF_15!34:34) -> 51717310 | J29: =-LOOKUP(J4,CF_15!5:5,CF_15!34:34) -> 1.9663596e+08 | K29: =-LOOKUP(K4,CF_15!5:5,CF_15!34:34) -> 1.9104475e+08 | L29: =-LOOKUP(L4,CF_15!5:5,CF_15!34:34) -> 77573294 | ... Q29: =-LOOKUP(Q4,CF_15!5:5,CF_15!34:34) -> 1.3827964e+08 | R29: =SUM(H29:Q29) -> 1.0946181e+09
C30: в т.ч. в федеральный бюджет | E30: =E29*IF(E4<=$N$55,$N$60,$Q$60) -> 0 | F30: =F29*IF(F4<=$N$55,$N$60,$Q$60) -> 0 | G30: =G29*IF(G4<=$N$55,$N$60,$Q$60) -> 0 | H30: =H29*IF(H4<=$N$55,$N$60,$Q$60) -> 0 | I30: =I29*IF(I4<=$N$55,$N$60,$Q$60) -> 6673201.3 | J30: =J29*IF(J4<=$N$55,$N$60,$Q$60) -> 25372382 | K30: =K29*IF(K4<=$N$55,$N$60,$Q$60) -> 24650935 | L30: =L29*IF(L4<=$N$55,$N$60,$Q$60) -> 10009457 | ... Q30: =Q29*IF(Q4<=$N$55,$N$60,$Q$60) -> 17842535 | R30: =SUM(H30:Q30) -> 1.4124105e+08
C32: Налог на имущество
C33: =C29 -> Туристический комплекс "Лунная поляна" - Архыз | E33: =LOOKUP(E4,Амортизация!295:295,Амортизация!298:298)+LOOKUP(E4,Амортизация!295:295,Амортизация!314:314) -> 0 | F33: =LOOKUP(F4,Амортизация!295:295,Амортизация!298:298)+LOOKUP(F4,Амортизация!295:295,Амортизация!314:314) -> 0 | G33: =LOOKUP(G4,Амортизация!295:295,Амортизация!298:298)+LOOKUP(G4,Амортизация!295:295,Амортизация!314:314) -> 0 | H33: =LOOKUP(H4,Амортизация!295:295,Амортизация!298:298)+LOOKUP(H4,Амортизация!295:295,Амортизация!314:314) -> 0 | I33: =LOOKUP(I4,Амортизация!295:295,Амортизация!298:298)+LOOKUP(I4,Амортизация!295:295,Амортизация!314:314) -> 0 | J33: =LOOKUP(J4,Амортизация!295:295,Амортизация!298:298)+LOOKUP(J4,Амортизация!295:295,Амортизация!314:314) -> 0 | K33: =LOOKUP(K4,Амортизация!295:295,Амортизация!298:298)+LOOKUP(K4,Амортизация!295:295,Амортизация!314:314) -> 0 | L33: =LOOKUP(L4,Амортизация!295:295,Амортизация!298:298)+LOOKUP(L4,Амортизация!295:295,Амортизация!314:314) -> 0 | ... Q33: =LOOKUP(Q4,Амортизация!295:295,Амортизация!298:298)+LOOKUP(Q4,Амортизация!295:295,Амортизация!314:314) -> 0 | R33: =SUM(H33:Q33) -> 0 | S33: 10 лет - льгота по НнИ
C35: Налог на землю / Арендные платежи за землю
C36: =C33 -> Туристический комплекс "Лунная поляна" - Архыз | E36: =LOOKUP(E4,Земля!31:31,Земля!32:32) -> 413939.45 | F36: =LOOKUP(F4,Земля!31:31,Земля!32:32) -> 452358.98 | G36: =LOOKUP(G4,Земля!31:31,Земля!32:32) -> 453598.32 | H36: =LOOKUP(H4,Земля!31:31,Земля!33:33) -> 452358.98 | I36: =LOOKUP(I4,Земля!31:31,Земля!33:33) -> 465082.41 | J36: =LOOKUP(J4,Земля!31:31,Земля!33:33) -> 470089.69 | K36: =LOOKUP(K4,Земля!31:31,Земля!33:33) -> 467640.77 | L36: =LOOKUP(L4,Земля!31:31,Земля!33:33) -> 465221.16 | M36: =LOOKUP(M4,Земля!31:31,Земля!33:33) -> 465221.16 | N36: =LOOKUP(N4,Земля!31:31,Земля!33:33) -> 479726.66 | O36: =LOOKUP(O4,Земля!31:31,Земля!33:33) -> 489820.53 | ... Q36: =LOOKUP(Q4,Земля!31:31,Земля!33:33) -> 488482.22 | R36: =SUM(H36:Q36) -> 4732125.8
C38: НДС
C39: =C36 -> Туристический комплекс "Лунная поляна" - Архыз | H39: =H74 -> 47962420 | I39: =I74 -> 3.7692698e+08 | J39: =J74 -> 6.0391288e+08 | K39: =K74 -> 5.8384711e+08 | L39: =L74 -> 3.2750441e+08 | M39: =M74 -> 3.5276608e+08 | N39: =N74 -> 3.6543027e+08 | O39: =O74 -> 3.8134855e+08 | ... Q39: =Q74 -> 4.1177221e+08 | R39: =SUM(H39:Q39) -> 3.8471902e+09
C41: СВОД
F42: =F4 -> 2023 | G42: =G4 -> 2024 | H42: =H4 -> 2025 | I42: =I4 -> 2026 | J42: =J4 -> 2027 | K42: =K4 -> 2028 | L42: =L4 -> 2029 | M42: =M4 -> 2030 | ... Q42: =Q4 -> 2034 | S42: 2023-2024 гг. | T42: за 10 лет
C43: Федеральные налоги и сборы | F43: =F44+F45+F46+F47 -> 0 | G43: =G44+G45+G46+G47 -> 0 | H43: =H44+H45+H46+H47 -> 88355228 | I43: =I44+I45+I46+I47 -> 5.1118628e+08 | J43: =J44+J45+J46+J47 -> 8.0713071e+08 | K43: =K44+K45+K46+K47 -> 7.9309615e+08 | L43: =L44+L45+L46+L47 -> 5.3128023e+08 | M43: =M44+M45+M46+M47 -> 5.6805863e+08 | ... Q43: =Q44+Q45+Q46+Q47 -> 6.6715614e+08 | S43: =SUM(F43:G43) -> 0 | T43: =SUM(H43:Q43) -> 5.8130224e+09
C44: =C28 -> Налог на прибыль | F44: =F30 -> 0 | G44: =G30 -> 0 | H44: =H30 -> 0 | I44: =I30 -> 6673201.3 | J44: =J30 -> 25372382 | K44: =K30 -> 24650935 | L44: =L30 -> 10009457 | M44: =M30 -> 12241165 | ... Q44: =Q30 -> 17842535 | S44: =SUM(F44:G44) -> 0 | T44: =SUM(H44:Q44) -> 1.4124105e+08
C45: НДС | F45: =F39 -> 0 | G45: =G39 -> 0 | H45: =H39 -> 47962420 | I45: =I39 -> 3.7692698e+08 | J45: =J39 -> 6.0391288e+08 | K45: =K39 -> 5.8384711e+08 | L45: =L39 -> 3.2750441e+08 | M45: =M39 -> 3.5276608e+08 | ... Q45: =Q39 -> 4.1177221e+08 | S45: =SUM(F45:G45) -> 0 | T45: =SUM(H45:Q45) -> 3.8471902e+09
C46: =C22 -> НДФЛ | F46: =F23 -> 0 | G46: =G23 -> 0 | H46: =H23 -> 12211779 | I46: =I23 -> 38572541 | J46: =J23 -> 53767230 | K46: =K23 -> 55808732 | L46: =L23 -> 58580527 | M46: =M23 -> 61387628 | ... Q46: =Q23 -> 71814842 | S46: =SUM(F46:G46) -> 0 | T46: =SUM(H46:Q46) -> 5.516206e+08
C47: =C25 -> Социальные отчисления | F47: =F26 -> 0 | G47: =G26 -> 0 | H47: =H26 -> 28181029 | I47: =I26 -> 89013555 | J47: =J26 -> 1.2407822e+08 | K47: =K26 -> 1.2878938e+08 | L47: =L26 -> 1.3518583e+08 | M47: =M26 -> 1.4166376e+08 | ... Q47: =Q26 -> 1.6572656e+08 | S47: =SUM(F47:G47) -> 0 | T47: =SUM(H47:Q47) -> 1.2729706e+09
C48: Региональные налоги и сборы | F48: =F50+F49 -> 0 | G48: =G50+G49 -> 0 | H48: =H50+H49 -> 0 | I48: =I50+I49 -> 45044109 | J48: =J50+J49 -> 1.7126358e+08 | K48: =K50+K49 -> 1.6639381e+08 | L48: =L50+L49 -> 67563837 | M48: =M50+M49 -> 82627866 | ... Q48: =Q50+Q49 -> 1.2043711e+08 | S48: =SUM(F48:G48) -> 0 | T48: =SUM(H48:Q48) -> 9.5337706e+08
C49: =C44 -> Налог на прибыль | F49: =F29-F30 -> 0 | G49: =G29-G30 -> 0 | H49: =H29-H30 -> 0 | I49: =I29-I30 -> 45044109 | J49: =J29-J30 -> 1.7126358e+08 | K49: =K29-K30 -> 1.6639381e+08 | L49: =L29-L30 -> 67563837 | M49: =M29-M30 -> 82627866 | ... Q49: =Q29-Q30 -> 1.2043711e+08 | S49: =SUM(F49:G49) -> 0 | T49: =SUM(H49:Q49) -> 9.5337706e+08
C50: =C32 -> Налог на имущество | F50: =F33 -> 0 | G50: =G33 -> 0 | H50: =H33 -> 0 | I50: =I33 -> 0 | J50: =J33 -> 0 | K50: =K33 -> 0 | L50: =L33 -> 0 | M50: =M33 -> 0 | ... Q50: =Q33 -> 0 | S50: =SUM(F50:G50) -> 0 | T50: =SUM(H50:Q50) -> 0 | U50: =S33 -> 10 лет - льгота по НнИ
C51: Местные налоги и сборы | F51: =F52 -> 452358.98 | G51: =G52 -> 453598.32 | H51: =H52 -> 452358.98 | I51: =I52 -> 465082.41 | J51: =J52 -> 470089.69 | K51: =K52 -> 467640.77 | L51: =L52 -> 465221.16 | M51: =M52 -> 465221.16 | ... Q51: =Q52 -> 488482.22 | S51: =SUM(F51:G51) -> 905957.29 | T51: =SUM(H51:Q51) -> 4732125.8
C52: =C35 -> Налог на землю / Арендные платежи за землю | F52: =F36 -> 452358.98 | G52: =G36 -> 453598.32 | H52: =H36 -> 452358.98 | I52: =I36 -> 465082.41 | J52: =J36 -> 470089.69 | K52: =K36 -> 467640.77 | L52: =L36 -> 465221.16 | M52: =M36 -> 465221.16 | ... Q52: =Q36 -> 488482.22 | S52: =SUM(F52:G52) -> 905957.29 | T52: =SUM(H52:Q52) -> 4732125.8
C54: ВСПОМОГАТЕЛЬНЫЕ--->
C55: Для расчета НДФЛ и соц. отчислений | I55: Для расчета налога на прибыль | L55: =Вводные!H25 -> 2017-2024 гг. | N55: 2024 | O55: =Вводные!E25 -> с 2025 г. | Q55: 2025
C56: Оклад, руб. | D56: 30000 | E56: для примера | I56: Прибыль, руб. | J56: 100000 | L56: РФ | M56: Субъект РФ | N56: Всего | O56: РФ | P56: Субъект РФ | Q56: Всего
C57: в т.ч. НДФЛ | D57: 0.13 | I57: Ставка по налогу на прибыль | L57: =Вводные!D27 -> 0 | M57: =Вводные!F27 -> 0.135 | N57: =L57+M57 -> 0.135 | O57: =Вводные!E27 -> 0.02 | P57: =Вводные!G27 -> 0.135 | Q57: =O57+P57 -> 0.155
C58: "чистая з.п." | D58: =D56-D57*D56 -> 26100 | I58: Налог на прибыль | N58: =N57*$J$56 -> 13500 | Q58: =Q57*$J$56 -> 15500
C59: НДФЛ | D59: =D56-D58 -> 3900 | E59: =D59/D62 -> 0.1 | F59: доля НДФЛ в расходах на оплату труда | I59: В бюджет РФ | N59: =L57*$J$56 -> 0 | Q59: =O57*$J$56 -> 2000
C60: Налог на ФОТ | D60: =Вводные!D33 -> 0.3 | I60: Доля налога на прибыль, зачисляемая в федеральный бюджет | N60: =N59/$N$58 -> 0 | Q60: =Q59/$Q$58 -> 0.12903226
C61: Налог на ФОТ | D61: =D60*D56 -> 9000 | I61: В бюджет субъекта РФ | N61: =M57*$J$56 -> 13500 | Q61: =P57*$J$56 -> 13500
C62: Итого, платеж | D62: =D61+D56 -> 39000 | E62: =D61/D62 -> 0.23076923 | F62: доля налога на ФОТ в расходах на оплату труда | I62: Доля налога на прибыль, зачисляемая в бюджет субъекта РФ | N62: =N61/$N$58 -> 1 | Q62: =Q61/$Q$58 -> 0.87096774
C65: Для расчета НДС | F65: =F4 -> 2023 | G65: =G4 -> 2024 | H65: =H4 -> 2025 | I65: =I4 -> 2026 | J65: =J4 -> 2027 | K65: =K4 -> 2028 | L65: =L4 -> 2029 | M65: =M4 -> 2030 | ... Q65: =Q4 -> 2034
C66: Прочие расходы (без персонала)
C67: =C33 -> Туристический комплекс "Лунная поляна" - Архыз | F67: =F12-F20 -> 0 | G67: =G12-G20 -> 0 | H67: =H12-H20 -> 1.8509317e+08 | I67: =I12-I20 -> 9.2903842e+08 | J67: =J12-J20 -> 1.3406158e+09 | K67: =K12-K20 -> 1.3542962e+09 | L67: =L12-L20 -> 1.087522e+09 | M67: =M12-M20 -> 1.1509939e+09 | ... Q67: =Q12-Q20 -> 1.3535842e+09
C68: Из них не облагается НДС | H68: =LOOKUP(H42,СВОД_PL!127:127,СВОД_PL!130:130) -> 13411749 | I68: =LOOKUP(I42,СВОД_PL!127:127,СВОД_PL!130:130) -> 60163425 | J68: =LOOKUP(J42,СВОД_PL!127:127,СВОД_PL!130:130) -> 67752619 | K68: =LOOKUP(K42,СВОД_PL!127:127,СВОД_PL!130:130) -> 72570290 | L68: =LOOKUP(L42,СВОД_PL!127:127,СВОД_PL!130:130) -> 77925098 | M68: =LOOKUP(M42,СВОД_PL!127:127,СВОД_PL!130:130) -> 83581014 | N68: =LOOKUP(N42,СВОД_PL!127:127,СВОД_PL!130:130) -> 89158388 | O68: =LOOKUP(O42,СВОД_PL!127:127,СВОД_PL!130:130) -> 92979911 | ... Q68: =LOOKUP(Q42,СВОД_PL!127:127,СВОД_PL!130:130) -> 1.0029106e+08
C69: Из них облагается НДС | F69: =F67-F68 -> 0 | G69: =G67-G68 -> 0 | H69: =H67-H68 -> 1.7168142e+08 | I69: =I67-I68 -> 8.6887499e+08 | J69: =J67-J68 -> 1.2728632e+09 | K69: =K67-K68 -> 1.281726e+09 | L69: =L67-L68 -> 1.0095969e+09 | M69: =M67-M68 -> 1.0674129e+09 | ... Q69: =Q67-Q68 -> 1.2532932e+09
C70: Выручка с НДС всего | F70: =F6*1.2 -> 0 | G70: =G6*1.2 -> 0 | H70: =H6*1.2 -> 4.9379222e+08 | I70: =I6*1.2 -> 3.3042119e+09 | J70: =J6*1.2 -> 5.1509132e+09 | K70: =K6*1.2 -> 5.0411538e+09 | L70: =L6*1.2 -> 3.1765428e+09 | M70: =M6*1.2 -> 3.397492e+09 | ... Q70: =Q6*1.2 -> 3.9745851e+09
C71: НДС входящий | F71: =F70-F6 -> 0 | G71: =G70-G6 -> 0 | H71: =H70-H6 -> 82298704 | I71: =I70-I6 -> 5.5070198e+08 | J71: =J70-J6 -> 8.5848553e+08 | K71: =K70-K6 -> 8.401923e+08 | L71: =L70-L6 -> 5.294238e+08 | M71: =M70-M6 -> 5.6624866e+08 | ... Q71: =Q70-Q6 -> 6.6243084e+08
C72: Расходы с НДС всего | F72: =F69*1.2 -> 0 | G72: =G69*1.2 -> 0 | H72: =H69*1.2 -> 2.0601771e+08 | I72: =I69*1.2 -> 1.04265e+09 | J72: =J69*1.2 -> 1.5274359e+09 | K72: =K69*1.2 -> 1.5380712e+09 | L72: =L69*1.2 -> 1.2115163e+09 | M72: =M69*1.2 -> 1.2808955e+09 | ... Q72: =Q69*1.2 -> 1.5039518e+09
C73: НДС исходящий | F73: =F72-F69 -> 0 | G73: =G72-G69 -> 0 | H73: =H72-H69 -> 34336284 | I73: =I72-I69 -> 1.73775e+08 | J73: =J72-J69 -> 2.5457264e+08 | K73: =K72-K69 -> 2.5634519e+08 | L73: =L72-L69 -> 2.0191939e+08 | M73: =M72-M69 -> 2.1348258e+08 | ... Q73: =Q72-Q69 -> 2.5065863e+08
C74: Сальдо | F74: =F71-F73 -> 0 | G74: =G71-G73 -> 0 | H74: =H71-H73 -> 47962420 | I74: =I71-I73 -> 3.7692698e+08 | J74: =J71-J73 -> 6.0391288e+08 | K74: =K71-K73 -> 5.8384711e+08 | L74: =L71-L73 -> 3.2750441e+08 | M74: =M71-M73 -> 3.5276608e+08 | ... Q74: =Q71-Q73 -> 4.1177221e+08 | R74: =SUM(H74:Q74) -> 3.8471902e+09

Sheet Турпоток
D3: Количество гостей = (Продано номеров в периоде*К двойной загрузки)/ср. продолжительность пребывания
B5: Номеров | D5: Прогноз турпотока (кол-во размещенных лиц в КСР) | F5: =YEAR(Вводные!D9) -> 2025 | G5: =F5+1 -> 2026 | H5: =G5+1 -> 2027 | I5: =H5+1 -> 2028 | J5: =I5+1 -> 2029 | K5: =J5+1 -> 2030 | L5: =K5+1 -> 2031 | M5: =L5+1 -> 2032 | N5: =M5+1 -> 2033 | ... U5: =T5+1 -> 2040
D6: Продано номеров в периоде
B7: =Объекты!F5 -> 125 | D7: =Объекты!C5 -> Гостиница 5* | F7: =IFERROR(LOOKUP(F$5,Отель5_PL!$D$3:$T$3,Отель5_PL!$D$9:$T$9),0) -> 0 | G7: =IFERROR(LOOKUP(G$5,Отель5_PL!$D$3:$T$3,Отель5_PL!$D$9:$T$9),0) -> 10964.481 | H7: =IFERROR(LOOKUP(H$5,Отель5_PL!$D$3:$T$3,Отель5_PL!$D$9:$T$9),0) -> 23203.13 | I7: =IFERROR(LOOKUP(I$5,Отель5_PL!$D$3:$T$3,Отель5_PL!$D$9:$T$9),0) -> 24635.33 | J7: =IFERROR(LOOKUP(J$5,Отель5_PL!$D$3:$T$3,Отель5_PL!$D$9:$T$9),0) -> 25932.91 | K7: =IFERROR(LOOKUP(K$5,Отель5_PL!$D$3:$T$3,Отель5_PL!$D$9:$T$9),0) -> 27297.8 | L7: =IFERROR(LOOKUP(L$5,Отель5_PL!$D$3:$T$3,Отель5_PL!$D$9:$T$9),0) -> 27297.8 | M7: =IFERROR(LOOKUP(M$5,Отель5_PL!$D$3:$T$3,Отель5_PL!$D$9:$T$9),0) -> 27372.589 | ... U7: =IFERROR(LOOKUP(U$5,Отель5_PL!$D$3:$T$3,Отель5_PL!$D$9:$T$9),0) -> 27372.589
B8: =Объекты!F6 -> 160 | D8: =Объекты!C6 -> Гостиница 4* | F8: =IFERROR(LOOKUP(F$5,Отель4_PL!$D$3:$T$3,Отель4_PL!$D$9:$T$9),0) -> 0 | G8: =IFERROR(LOOKUP(G$5,Отель4_PL!$D$3:$T$3,Отель4_PL!$D$9:$T$9),0) -> 13407.671 | H8: =IFERROR(LOOKUP(H$5,Отель4_PL!$D$3:$T$3,Отель4_PL!$D$9:$T$9),0) -> 29955.381 | I8: =IFERROR(LOOKUP(I$5,Отель4_PL!$D$3:$T$3,Отель4_PL!$D$9:$T$9),0) -> 31804.36 | J8: =IFERROR(LOOKUP(J$5,Отель4_PL!$D$3:$T$3,Отель4_PL!$D$9:$T$9),0) -> 33479.544 | K8: =IFERROR(LOOKUP(K$5,Отель4_PL!$D$3:$T$3,Отель4_PL!$D$9:$T$9),0) -> 35241.625 | L8: =IFERROR(LOOKUP(L$5,Отель4_PL!$D$3:$T$3,Отель4_PL!$D$9:$T$9),0) -> 35241.625 | M8: =IFERROR(LOOKUP(M$5,Отель4_PL!$D$3:$T$3,Отель4_PL!$D$9:$T$9),0) -> 35338.177 | ... U8: =IFERROR(LOOKUP(U$5,Отель4_PL!$D$3:$T$3,Отель4_PL!$D$9:$T$9),0) -> 35338.177
B9: =Объекты!F7 -> 160 | D9: =Объекты!C7 -> Гостиница 3* | F9: =IFERROR(LOOKUP(F$5,Отель3_PL!$D$3:$T$3,Отель3_PL!$D$9:$T$9),0) -> 13056.22 | G9: =IFERROR(LOOKUP(G$5,Отель3_PL!$D$3:$T$3,Отель3_PL!$D$9:$T$9),0) -> 33329.757 | H9: =IFERROR(LOOKUP(H$5,Отель3_PL!$D$3:$T$3,Отель3_PL!$D$9:$T$9),0) -> 35290.33 | I9: =IFERROR(LOOKUP(I$5,Отель3_PL!$D$3:$T$3,Отель3_PL!$D$9:$T$9),0) -> 37352.962 | J9: =IFERROR(LOOKUP(J$5,Отель3_PL!$D$3:$T$3,Отель3_PL!$D$9:$T$9),0) -> 39211.478 | K9: =IFERROR(LOOKUP(K$5,Отель3_PL!$D$3:$T$3,Отель3_PL!$D$9:$T$9),0) -> 39211.478 | L9: =IFERROR(LOOKUP(L$5,Отель3_PL!$D$3:$T$3,Отель3_PL!$D$9:$T$9),0) -> 39211.478 | M9: =IFERROR(LOOKUP(M$5,Отель3_PL!$D$3:$T$3,Отель3_PL!$D$9:$T$9),0) -> 39318.907 | ... U9: =IFERROR(LOOKUP(U$5,Отель3_PL!$D$3:$T$3,Отель3_PL!$D$9:$T$9),0) -> 39318.907
B10: =Объекты!F8 -> 0 | D10: =Объекты!C8 -> Гостиница 2* | F10: =IFERROR(LOOKUP(F$5,Отель2_PL!$D$3:$T$3,Отель2_PL!$D$9:$T$9),0) -> 0 | G10: =IFERROR(LOOKUP(G$5,Отель2_PL!$D$3:$T$3,Отель2_PL!$D$9:$T$9),0) -> 0 | H10: =IFERROR(LOOKUP(H$5,Отель2_PL!$D$3:$T$3,Отель2_PL!$D$9:$T$9),0) -> 0 | I10: =IFERROR(LOOKUP(I$5,Отель2_PL!$D$3:$T$3,Отель2_PL!$D$9:$T$9),0) -> 0 | J10: =IFERROR(LOOKUP(J$5,Отель2_PL!$D$3:$T$3,Отель2_PL!$D$9:$T$9),0) -> 0 | K10: =IFERROR(LOOKUP(K$5,Отель2_PL!$D$3:$T$3,Отель2_PL!$D$9:$T$9),0) -> 0 | L10: =IFERROR(LOOKUP(L$5,Отель2_PL!$D$3:$T$3,Отель2_PL!$D$9:$T$9),0) -> 0 | M10: =IFERROR(LOOKUP(M$5,Отель2_PL!$D$3:$T$3,Отель2_PL!$D$9:$T$9),0) -> 0 | ... U10: =IFERROR(LOOKUP(U$5,Отель2_PL!$D$3:$T$3,Отель2_PL!$D$9:$T$9),0) -> 0
B11: =Объекты!F9 -> 101 | D11: =Объекты!C9 -> Хостел в составе МФЦ | F11: =IFERROR(LOOKUP(F$5,Хостел_PL!$D$3:$T$3,Хостел_PL!$D$9:$T$9),0) -> 7209.0561 | G11: =IFERROR(LOOKUP(G$5,Хостел_PL!$D$3:$T$3,Хостел_PL!$D$9:$T$9),0) -> 21039.409 | H11: =IFERROR(LOOKUP(H$5,Хостел_PL!$D$3:$T$3,Хостел_PL!$D$9:$T$9),0) -> 22277.021 | I11: =IFERROR(LOOKUP(I$5,Хостел_PL!$D$3:$T$3,Хостел_PL!$D$9:$T$9),0) -> 23579.057 | J11: =IFERROR(LOOKUP(J$5,Хостел_PL!$D$3:$T$3,Хостел_PL!$D$9:$T$9),0) -> 24752.246 | K11: =IFERROR(LOOKUP(K$5,Хостел_PL!$D$3:$T$3,Хостел_PL!$D$9:$T$9),0) -> 24752.246 | L11: =IFERROR(LOOKUP(L$5,Хостел_PL!$D$3:$T$3,Хостел_PL!$D$9:$T$9),0) -> 24752.246 | M11: =IFERROR(LOOKUP(M$5,Хостел_PL!$D$3:$T$3,Хостел_PL!$D$9:$T$9),0) -> 24820.06 | ... U11: =IFERROR(LOOKUP(U$5,Хостел_PL!$D$3:$T$3,Хостел_PL!$D$9:$T$9),0) -> 24820.06
B12: =Объекты!F10 -> 13 | D12: =Объекты!C10 -> Шале | F12: =IFERROR(LOOKUP(F$5,Шале_PL!$D$3:$T$3,Шале_PL!$D$9:$T$9),0) -> 0 | G12: =IFERROR(LOOKUP(G$5,Шале_PL!$D$3:$T$3,Шале_PL!$D$9:$T$9),0) -> 393.19458 | H12: =IFERROR(LOOKUP(H$5,Шале_PL!$D$3:$T$3,Шале_PL!$D$9:$T$9),0) -> 1681.358 | I12: =IFERROR(LOOKUP(I$5,Шале_PL!$D$3:$T$3,Шале_PL!$D$9:$T$9),0) -> 1785.1388 | J12: =IFERROR(LOOKUP(J$5,Шале_PL!$D$3:$T$3,Шале_PL!$D$9:$T$9),0) -> 1879.1648 | K12: =IFERROR(LOOKUP(K$5,Шале_PL!$D$3:$T$3,Шале_PL!$D$9:$T$9),0) -> 1978.0682 | L12: =IFERROR(LOOKUP(L$5,Шале_PL!$D$3:$T$3,Шале_PL!$D$9:$T$9),0) -> 1978.0682 | M12: =IFERROR(LOOKUP(M$5,Шале_PL!$D$3:$T$3,Шале_PL!$D$9:$T$9),0) -> 1983.4875 | ... U12: =IFERROR(LOOKUP(U$5,Шале_PL!$D$3:$T$3,Шале_PL!$D$9:$T$9),0) -> 1983.4875
B13: =Объекты!F13 -> 385 | D13: =Объекты!C13 -> Туристские резиденции | F13: =IFERROR(LOOKUP(F$5,Резиденции_PL!$D$3:$V$3,Резиденции_PL!$D$9:$V$9),0) -> 31416.53 | G13: =IFERROR(LOOKUP(G$5,Резиденции_PL!$D$3:$V$3,Резиденции_PL!$D$9:$V$9),0) -> 80199.727 | H13: =IFERROR(LOOKUP(H$5,Резиденции_PL!$D$3:$V$3,Резиденции_PL!$D$9:$V$9),0) -> 84917.358 | I13: =IFERROR(LOOKUP(I$5,Резиденции_PL!$D$3:$V$3,Резиденции_PL!$D$9:$V$9),0) -> 89880.564 | J13: =IFERROR(LOOKUP(J$5,Резиденции_PL!$D$3:$V$3,Резиденции_PL!$D$9:$V$9),0) -> 94352.62 | K13: =IFERROR(LOOKUP(K$5,Резиденции_PL!$D$3:$V$3,Резиденции_PL!$D$9:$V$9),0) -> 94352.62 | L13: =IFERROR(LOOKUP(L$5,Резиденции_PL!$D$3:$V$3,Резиденции_PL!$D$9:$V$9),0) -> 94352.62 | M13: =IFERROR(LOOKUP(M$5,Резиденции_PL!$D$3:$V$3,Резиденции_PL!$D$9:$V$9),0) -> 94611.12 | ... U13: =IFERROR(LOOKUP(U$5,Резиденции_PL!$D$3:$V$3,Резиденции_PL!$D$9:$V$9),0) -> 94611.12
D14: Коэффициент двойной загрузки
D15: =D7 -> Гостиница 5* | F15: ='К дв.загр'!G7 -> 2.168 | G15: =F15 -> 2.168 | H15: =G15 -> 2.168 | I15: =H15 -> 2.168 | J15: =I15 -> 2.168 | K15: =J15 -> 2.168 | L15: =K15 -> 2.168 | M15: =L15 -> 2.168 | N15: =M15 -> 2.168 | ... U15: =T15 -> 2.168
D16: =D8 -> Гостиница 4* | F16: ='К дв.загр'!G8 -> 2.203 | G16: =F16 -> 2.203 | H16: =G16 -> 2.203 | I16: =H16 -> 2.203 | J16: =I16 -> 2.203 | K16: =J16 -> 2.203 | L16: =K16 -> 2.203 | M16: =L16 -> 2.203 | N16: =M16 -> 2.203 | ... U16: =T16 -> 2.203
D17: =D9 -> Гостиница 3* | F17: ='К дв.загр'!G9 -> 2.462 | G17: =F17 -> 2.462 | H17: =G17 -> 2.462 | I17: =H17 -> 2.462 | J17: =I17 -> 2.462 | K17: =J17 -> 2.462 | L17: =K17 -> 2.462 | M17: =L17 -> 2.462 | N17: =M17 -> 2.462 | ... U17: =T17 -> 2.462
D18: =D10 -> Гостиница 2* | F18: ='К дв.загр'!G10 -> 2.628 | G18: =F18 -> 2.628 | H18: =G18 -> 2.628 | I18: =H18 -> 2.628 | J18: =I18 -> 2.628 | K18: =J18 -> 2.628 | L18: =K18 -> 2.628 | M18: =L18 -> 2.628 | N18: =M18 -> 2.628 | ... U18: =T18 -> 2.628
D19: =D11 -> Хостел в составе МФЦ | F19: ='К дв.загр'!G11 -> 4.25 | G19: =F19 -> 4.25 | H19: =G19 -> 4.25 | I19: =H19 -> 4.25 | J19: =I19 -> 4.25 | K19: =J19 -> 4.25 | L19: =K19 -> 4.25 | M19: =L19 -> 4.25 | N19: =M19 -> 4.25 | ... U19: =T19 -> 4.25
D20: =D12 -> Шале | F20: ='К дв.загр'!G12 -> 4.8 | G20: =F20 -> 4.8 | H20: =G20 -> 4.8 | I20: =H20 -> 4.8 | J20: =I20 -> 4.8 | K20: =J20 -> 4.8 | L20: =K20 -> 4.8 | M20: =L20 -> 4.8 | N20: =M20 -> 4.8 | ... U20: =T20 -> 4.8
D21: =D13 -> Туристские резиденции | F21: ='К дв.загр'!G13 -> 2.462 | G21: =F21 -> 2.462 | H21: =G21 -> 2.462 | I21: =H21 -> 2.462 | J21: =I21 -> 2.462 | K21: =J21 -> 2.462 | L21: =K21 -> 2.462 | M21: =L21 -> 2.462 | N21: =M21 -> 2.462 | ... U21: =T21 -> 2.462
D22: Средняя продолжительность пребывания, дни
D23: =D15 -> Гостиница 5* | F23: ='К дв.загр'!O7 -> 3.25 | G23: =F23 -> 3.25 | H23: =G23 -> 3.25 | I23: =H23 -> 3.25 | J23: =I23 -> 3.25 | K23: =J23 -> 3.25 | L23: =K23 -> 3.25 | M23: =L23 -> 3.25 | N23: =M23 -> 3.25 | ... U23: =T23 -> 3.25
D24: =D16 -> Гостиница 4* | F24: ='К дв.загр'!O8 -> 3.25 | G24: =F24 -> 3.25 | H24: =G24 -> 3.25 | I24: =H24 -> 3.25 | J24: =I24 -> 3.25 | K24: =J24 -> 3.25 | L24: =K24 -> 3.25 | M24: =L24 -> 3.25 | N24: =M24 -> 3.25 | ... U24: =T24 -> 3.25
D25: =D17 -> Гостиница 3* | F25: ='К дв.загр'!O9 -> 3.25 | G25: =F25 -> 3.25 | H25: =G25 -> 3.25 | I25: =H25 -> 3.25 | J25: =I25 -> 3.25 | K25: =J25 -> 3.25 | L25: =K25 -> 3.25 | M25: =L25 -> 3.25 | N25: =M25 -> 3.25 | ... U25: =T25 -> 3.25
D26: =D18 -> Гостиница 2* | F26: ='К дв.загр'!O10 -> 3.5 | G26: =F26 -> 3.5 | H26: =G26 -> 3.5 | I26: =H26 -> 3.5 | J26: =I26 -> 3.5 | K26: =J26 -> 3.5 | L26: =K26 -> 3.5 | M26: =L26 -> 3.5 | N26: =M26 -> 3.5 | ... U26: =T26 -> 3.5
D27: =D19 -> Хостел в составе МФЦ | F27: ='К дв.загр'!O11 -> 4 | G27: =F27 -> 4 | H27: =G27 -> 4 | I27: =H27 -> 4 | J27: =I27 -> 4 | K27: =J27 -> 4 | L27: =K27 -> 4 | M27: =L27 -> 4 | N27: =M27 -> 4 | ... U27: =T27 -> 4
D28: =D20 -> Шале | F28: ='К дв.загр'!O12 -> 3 | G28: =F28 -> 3 | H28: =G28 -> 3 | I28: =H28 -> 3 | J28: =I28 -> 3 | K28: =J28 -> 3 | L28: =K28 -> 3 | M28: =L28 -> 3 | N28: =M28 -> 3 | ... U28: =T28 -> 3
D29: =D21 -> Туристские резиденции | F29: ='К дв.загр'!O13 -> 3 | G29: =F29 -> 3 | H29: =G29 -> 3 | I29: =H29 -> 3 | J29: =I29 -> 3 | K29: =J29 -> 3 | L29: =K29 -> 3 | M29: =L29 -> 3 | N29: =M29 -> 3 | ... U29: =T29 -> 3
D30: Кол-во размещенных лиц на курорте
D31: =D23 -> Гостиница 5* | F31: =F7*F15/F23 -> 0 | G31: =G7*G15/G23 -> 7314.1525 | H31: =H7*H15/H23 -> 15478.273 | I31: =I7*I15/I23 -> 16433.66 | J31: =J7*J15/J23 -> 17299.246 | K31: =K7*K15/K23 -> 18209.733 | L31: =L7*L15/L23 -> 18209.733 | M31: =M7*M15/M23 -> 18259.622 | ... U31: =U7*U15/U23 -> 18259.622
D32: =D24 -> Гостиница 4* | F32: =F8*F16/F24 -> 0 | G32: =G8*G16/G24 -> 9088.3383 | H32: =H8*H16/H24 -> 20305.14 | I32: =I8*I16/I24 -> 21558.463 | J32: =J8*J16/J24 -> 22693.98 | K32: =K8*K16/K24 -> 23888.4 | L32: =L8*L16/L24 -> 23888.4 | M32: =M8*M16/M24 -> 23953.848 | ... U32: =U8*U16/U24 -> 23953.848
D33: =D25 -> Гостиница 3* | F33: =F9*F17/F25 -> 9890.589 | G33: =G9*G17/G25 -> 25248.572 | H33: =H9*H17/H25 -> 26733.783 | I33: =I9*I17/I25 -> 28296.305 | J33: =J9*J17/J25 -> 29704.203 | K33: =K9*K17/K25 -> 29704.203 | L33: =L9*L17/L25 -> 29704.203 | M33: =M9*M17/M25 -> 29785.584 | ... U33: =U9*U17/U25 -> 29785.584
D34: =D26 -> Гостиница 2* | F34: =F10*F18/F26 -> 0 | G34: =G10*G18/G26 -> 0 | H34: =H10*H18/H26 -> 0 | I34: =I10*I18/I26 -> 0 | J34: =J10*J18/J26 -> 0 | K34: =K10*K18/K26 -> 0 | L34: =L10*L18/L26 -> 0 | M34: =M10*M18/M26 -> 0 | ... U34: =U10*U18/U26 -> 0
D35: =D27 -> Хостел в составе МФЦ | F35: =F11*F19/F27 -> 7659.6221 | G35: =G11*G19/G27 -> 22354.372 | H35: =H11*H19/H27 -> 23669.335 | I35: =I11*I19/I27 -> 25052.748 | J35: =J11*J19/J27 -> 26299.261 | K35: =K11*K19/K27 -> 26299.261 | L35: =L11*L19/L27 -> 26299.261 | M35: =M11*M19/M27 -> 26371.314 | ... U35: =U11*U19/U27 -> 26371.314
D36: =D28 -> Шале | F36: =F12*F20/F28 -> 0 | G36: =G12*G20/G28 -> 629.11133 | H36: =H12*H20/H28 -> 2690.1727 | I36: =I12*I20/I28 -> 2856.2221 | J36: =J12*J20/J28 -> 3006.6636 | K36: =K12*K20/K28 -> 3164.9091 | L36: =L12*L20/L28 -> 3164.9091 | M36: =M12*M20/M28 -> 3173.5801 | ... U36: =U12*U20/U28 -> 3173.5801
D37: =D29 -> Туристские резиденции | F37: =F13*F21/F29 -> 25782.499 | G37: =G13*G21/G29 -> 65817.242 | H37: =H13*H21/H29 -> 69688.845 | I37: =I13*I21/I29 -> 73761.983 | J37: =J13*J21/J29 -> 77432.05 | K37: =K13*K21/K29 -> 77432.05 | L37: =L13*L21/L29 -> 77432.05 | M37: =M13*M21/M29 -> 77644.192 | ... U37: =U13*U21/U29 -> 77644.192
B38: =SUM(B7:B13) -> 944 | D38: Итого, кол-во размещенных лиц на курорте | F38: =SUM(F31:F37) -> 43332.71 | G38: =SUM(G31:G37) -> 130451.79 | H38: =SUM(H31:H37) -> 158565.55 | I38: =SUM(I31:I37) -> 167959.38 | J38: =SUM(J31:J37) -> 176435.4 | K38: =SUM(K31:K37) -> 178698.56 | L38: =SUM(L31:L37) -> 178698.56 | M38: =SUM(M31:M37) -> 179188.14 | ... U38: =SUM(U31:U37) -> 179188.14
F39: =F38/$B$38 -> 45.903295 | G39: =G38/$B$38 -> 138.19045 | H39: =H38/$B$38 -> 167.97198 | I39: =I38/$B$38 -> 177.92307 | J39: =J38/$B$38 -> 186.90191 | K39: =K38/$B$38 -> 189.29932 | L39: =L38/$B$38 -> 189.29932 | M39: =M38/$B$38 -> 189.81795 | ... U39: =U38/$B$38 -> 189.81795
B41: Сравнение с расчетом в 2021 году:
B42: Номеров | E42: =F42-1 -> 2024 | F42: =F5 -> 2025 | G42: =G5 -> 2026 | H42: =H5 -> 2027 | I42: =I5 -> 2028 | J42: =J5 -> 2029 | K42: =K5 -> 2030 | L42: =L5 -> 2031 | M42: =M5 -> 2032 | ... U42: =U5 -> 2040
B43: 3050 | D43: =D38 -> Итого, кол-во размещенных лиц на курорте | E43: 42651.667 | F43: 134659.76 | G43: 233343.69 | H43: 326253.82 | I43: 363521.71 | J43: 375114.28 | K43: 377504.07 | L43: 377504.07 | M43: 380771.17 | N43: 379454.72 | O43: 379454.72 | P43: 379454.72 | Q43: 380771.17 | R43: 379454.72 | S43: 379454.72 | T43: 379454.72 | U43: 380771.17
E44: =E43/$B$43 -> 13.984153 | F44: =F43/$B$43 -> 44.150741 | G44: =G43/$B$43 -> 76.506129 | H44: =H43/$B$43 -> 106.96847 | I44: =I43/$B$43 -> 119.18744 | J44: =J43/$B$43 -> 122.98829 | K44: =K43/$B$43 -> 123.77183 | L44: =L43/$B$43 -> 123.77183 | ... U44: =U43/$B$43 -> 124.84301

Sheet ШР
E2: =YEAR(E3) -> 2025 | F2: =E2+1 -> 2026 | G2: =F2+1 -> 2027 | H2: =G2+1 -> 2028 | I2: =H2+1 -> 2029 | J2: =I2+1 -> 2030 | K2: =J2+1 -> 2031 | M2: Примечание / Комментарий
C3: Начало периода | E3: =Вводные!D9 -> 45839 | F3: =E4+1 -> 46023 | G3: =F4+1 -> 46388 | H3: =G4+1 -> 46753 | I3: =H4+1 -> 47119 | J3: =I4+1 -> 47484 | K3: =J4+1 -> 47849
C4: Конец периода | E4: =DATE(E2,12,31) -> 46022 | F4: =DATE(F2,12,31) -> 46387 | G4: =DATE(G2,12,31) -> 46752 | H4: =DATE(H2,12,31) -> 47118 | I4: =DATE(I2,12,31) -> 47483 | J4: =DATE(J2,12,31) -> 47848 | K4: =DATE(K2,12,31) -> 48213
C5: Длина периода, дней | E5: =E4-E3+1 -> 184 | F5: =F4-F3+1 -> 365 | G5: =G4-G3+1 -> 365 | H5: =H4-H3+1 -> 366 | I5: =I4-I3+1 -> 365 | J5: =J4-J3+1 -> 365 | K5: =K4-K3+1 -> 365
C6: Длина периода, месяцев | E6: 12 | F6: 12 | G6: 12 | H6: 12 | I6: 12 | J6: 12 | K6: 12
C7: Инфляция | E7: =LOOKUP(E2,CPI!3:3,CPI!5:5) -> 1.1698586 | F7: =LOOKUP(F2,CPI!3:3,CPI!5:5) -> 1.2166529 | G7: =LOOKUP(G2,CPI!3:3,CPI!5:5) -> 1.265319 | H7: =LOOKUP(H2,CPI!3:3,CPI!5:5) -> 1.3159318 | I7: =LOOKUP(I2,CPI!3:3,CPI!5:5) -> 1.3685691 | J7: =LOOKUP(J2,CPI!3:3,CPI!5:5) -> 1.4233118 | K7: =LOOKUP(K2,CPI!3:3,CPI!5:5) -> 1.4802443
B9: =Объекты!$C$31 -> Гостиница 5* - Mövenpick | D9: =YEAR(Объекты!$K$5) -> 2026
C10: Номеров в наличии | E10: =Объекты!$F$5 -> 125 | F10: =E10 -> 125 | G10: =F10 -> 125 | H10: =G10 -> 125 | I10: =H10 -> 125 | J10: =I10 -> 125 | K10: =J10 -> 125
C11: Загрузка | E11: =IFERROR(LOOKUP(E2,Отель5_PL!$D$3:$T$3,Отель5_PL!$D$10:$T$10),"не введён") -> не введён | F11: =IFERROR(LOOKUP(F2,Отель5_PL!$D$3:$T$3,Отель5_PL!$D$10:$T$10),"не введён") -> 0.47671658 | G11: =IFERROR(LOOKUP(G2,Отель5_PL!$D$3:$T$3,Отель5_PL!$D$10:$T$10),"не введён") -> 0.50856176 | H11: =IFERROR(LOOKUP(H2,Отель5_PL!$D$3:$T$3,Отель5_PL!$D$10:$T$10),"не введён") -> 0.53847716 | I11: =IFERROR(LOOKUP(I2,Отель5_PL!$D$3:$T$3,Отель5_PL!$D$10:$T$10),"не введён") -> 0.56839255 | J11: =IFERROR(LOOKUP(J2,Отель5_PL!$D$3:$T$3,Отель5_PL!$D$10:$T$10),"не введён") -> 0.59830795 | K11: =IFERROR(LOOKUP(K2,Отель5_PL!$D$3:$T$3,Отель5_PL!$D$10:$T$10),"не введён") -> 0.59830795
C12: Номеров на горничную | E12: =IFERROR(E10/E68,"не введён") -> не введён | F12: =IFERROR(F10/F68,"не введён") -> 17.857143 | G12: =IFERROR(G10/G68,"не введён") -> 17.857143 | H12: =IFERROR(H10/H68,"не введён") -> 17.857143 | I12: =IFERROR(I10/I68,"не введён") -> 17.857143 | J12: =IFERROR(J10/J68,"не введён") -> 17.857143 | K12: =IFERROR(K10/K68,"не введён") -> 17.857143
A13: A&G_5 | B13: Администрация | C13: Генеральный менеджер | D13: 250000 | F13: 1 | G13: 1 | H13: 1 | I13: 1 | J13: =I13 -> 1 | K13: =J13 -> 1
A14: A&G_5 | C14: Операционный менеджер | D14: 120000 | F14: 1 | G14: 1 | H14: 1 | I14: 1 | J14: =I14 -> 1 | K14: =J14 -> 1
A15: A&G_5 | C15: Инженер по охране труда и пожарной безопасности | D15: 55000 | F15: 1 | G15: 1 | H15: 1 | I15: 1 | J15: =I15 -> 1 | K15: =J15 -> 1
A16: A&G_5 | C16: Юрисконсульт | D16: 55000 | F16: 1 | G16: 1 | H16: 1 | I16: 1 | J16: =I16 -> 1 | K16: =J16 -> 1
A17: A&G_5 | C17: Ассистент генерального менеджера | D17: 35000 | F17: 1 | G17: 1 | H17: 1 | I17: 1 | J17: =I17 -> 1 | K17: =J17 -> 1
A18: A&G_5 | C18: Водитель | D18: 30000 | F18: 1 | G18: 1 | H18: 1 | I18: 1 | J18: =I18 -> 1 | K18: =J18 -> 1
A19: A&G_5 | C19: Начальник службы охраны | D19: 70000 | F19: 1 | G19: 1 | H19: 1 | I19: 1 | J19: =I19 -> 1 | K19: =J19 -> 1
A20: A&G_5 | C20: Санитарный врач | D20: 45000 | F20: 1 | G20: 1 | H20: 1 | I20: 1 | J20: =I20 -> 1 | K20: =J20 -> 1
A21: A&G_5 | B21: Бухгалтерия | C21: Главный бухгалтер | D21: 80000 | F21: 1 | G21: 1 | H21: 1 | I21: 1 | J21: =I21 -> 1 | K21: =J21 -> 1
A22: A&G_5 | C22: Заместитель главного бухгалтера | D22: 60000 | F22: 1 | G22: 1 | H22: 1 | I22: 1 | J22: =I22 -> 1 | K22: =J22 -> 1
A23: A&G_5 | C23: Финансовый директор | D23: 115000 | F23: 1 | G23: 1 | H23: 1 | I23: 1 | J23: =I23 -> 1 | K23: =J23 -> 1
A24: A&G_5 | C24: Бухгалтер по заработной плате | D24: 38000 | F24: 1 | G24: 1 | H24: 1 | I24: 1 | J24: =I24 -> 1 | K24: =J24 -> 1
A25: A&G_5 | C25: Бухгалтер по расчетам с поставщиками | D25: 38000 | F25: 1 | G25: 1 | H25: 1 | I25: 1 | J25: =I25 -> 1 | K25: =J25 -> 1
A26: A&G_5 | C26: Бухгалтер по реализации | D26: 38000 | F26: 1 | G26: 1 | H26: 1 | I26: 1 | J26: =I26 -> 1 | K26: =J26 -> 1
A27: A&G_5 | C27: Бухгалтер по учету ТМЦ и ОС | D27: 38000 | F27: 1 | G27: 1 | H27: 1 | I27: 1 | J27: =I27 -> 1 | K27: =J27 -> 1
A28: A&G_5 | C28: Бухгалтер калькулятор | D28: 35000 | F28: 1 | G28: 1 | H28: 1 | I28: 1 | J28: =I28 -> 1 | K28: =J28 -> 1
A29: A&G_5 | C29: Бухгалтер-кассир | D29: 35000 | F29: 1 | G29: 1 | H29: 1 | I29: 1 | J29: =I29 -> 1 | K29: =J29 -> 1
A30: A&G_5 | C30: Бухгалтер по учету банковских операций | D30: 35000 | F30: 1 | G30: 1 | H30: 1 | I30: 1 | J30: =I30 -> 1 | K30: =J30 -> 1
A31: A&G_5 | C31: Внутренний аудитор | D31: 38000 | F31: 1 | G31: 1 | H31: 1 | I31: 1 | J31: =I31 -> 1 | K31: =J31 -> 1
A32: A&G_5 | D32: 0 | J32: =I32 -> 0 | K32: =J32 -> 0
A33: A&G_5 | B33: HR | C33: Начальник отдела управления персоналом | D33: 65000 | F33: 1 | G33: 1 | H33: 1 | I33: 1 | J33: =I33 -> 1 | K33: =J33 -> 1
A34: A&G_5 | C34: Тренинг-менеджер | D34: 50000 | F34: 1 | G34: 1 | H34: 1 | I34: 1 | J34: =I34 -> 1 | K34: =J34 -> 1
A35: A&G_5 | C35: Специалист по кадрам /персоналу | D35: 38000 | F35: 2 | G35: 2 | H35: 2 | I35: 2 | J35: =I35 -> 2 | K35: =J35 -> 2
A36: A&G_5 | D36: 0 | J36: =I36 -> 0 | K36: =J36 -> 0
A37: A&G_5 | B37: Служба снабжения | C37: Кладовщик материально-технического склада | D37: 38000 | F37: 1 | G37: 1 | H37: 1 | I37: 1 | J37: =I37 -> 1 | K37: =J37 -> 1
A38: A&G_5 | C38: Заведующий складом | D38: 38000 | F38: 1 | G38: 1 | H38: 1 | I38: 1 | J38: =I38 -> 1 | K38: =J38 -> 1
A39: A&G_5 | C39: Руководитель отдела закупок | D39: 65000 | F39: 1 | G39: 1 | H39: 1 | I39: 1 | J39: =I39 -> 1 | K39: =J39 -> 1
A40: A&G_5 | C40: Менеджер по закупкам | D40: 38000 | F40: 1 | G40: 1 | H40: 1 | I40: 1 | J40: =I40 -> 1 | K40: =J40 -> 1
A41: A&G_5 | D41: 0 | J41: =I41 -> 0 | K41: =J41 -> 0
A42: A&G_5 | B42: IT | C42: Руководитель службы IT | D42: 65000 | F42: 1 | G42: 1 | H42: 1 | I42: 1 | J42: =I42 -> 1 | K42: =J42 -> 1
A43: A&G_5 | C43: IT специалист | D43: 40000 | F43: 1 | G43: 1 | H43: 1 | I43: 1 | J43: =I43 -> 1 | K43: =J43 -> 1
A44: A&G_5 | D44: 0 | J44: =I44 -> 0 | K44: =J44 -> 0
A45: S&M_5 | B45: Отдел продаж | C45: Начальник отдела продаж | D45: 110000 | F45: 1 | G45: 1 | H45: 1 | I45: 1 | J45: =I45 -> 1 | K45: =J45 -> 1
A46: S&M_5 | C46: Менеджер по работе с клиентами (физлица) | D46: 45000 | F46: 1 | G46: 1 | H46: 1 | I46: 1 | J46: =I46 -> 1 | K46: =J46 -> 1
A47: S&M_5 | C47: Менеджер по работе с корпоративными клиентами | D47: 45000 | F47: 1 | G47: 1 | H47: 1 | I47: 1 | J47: =I47 -> 1 | K47: =J47 -> 1
A48: S&M_5 | C48: Менеджер по продажам MICE | D48: 45000 | F48: 1 | G48: 1 | H48: 1 | I48: 1 | J48: =I48 -> 1 | K48: =J48 -> 1
A49: S&M_5 | C49: Специалисты по бронированию | D49: 35000 | F49: 2 | G49: 2 | H49: 2 | I49: 2 | J49: =I49 -> 2 | K49: =J49 -> 2
A50: S&M_5 | C50: Менеджер по управлению доходами | D50: 65000 | F50: 1 | G50: 1 | H50: 1 | I50: 1 | J50: =I50 -> 1 | K50: =J50 -> 1
A51: S&M_5 | C51: Специалист по е-коммерции | D51: 42000 | F51: 1 | G51: 1 | H51: 1 | I51: 1 | J51: =I51 -> 1 | K51: =J51 -> 1
A52: S&M_5 | C52: Менеджер по маркетингу и PR | D52: 45000 | F52: 1 | G52: 1 | H52: 1 | I52: 1 | J52: =I52 -> 1 | K52: =J52 -> 1
A53: S&M_5 | C53: Маркетолог | D53: 38000 | F53: 1 | G53: 1 | H53: 1 | I53: 1 | J53: =I53 -> 1 | K53: =J53 -> 1
A54: S&M_5 | D54: 0 | J54: =I54 -> 0 | K54: =J54 -> 0
A55: FM_5 | B55: Инженерная служба | C55: Начальник службы - главный инженер | D55: 100000 | F55: 1 | G55: 1 | H55: 1 | I55: 1 | J55: =I55 -> 1 | K55: =J55 -> 1
A56: FM_5 | C56: Инженер по эксплуатации зданий | D56: 50000 | F56: 1 | G56: 1 | H56: 1 | I56: 1 | J56: =I56 -> 1 | K56: =J56 -> 1
A57: FM_5 | C57: Инженер по слаботочным системам и автоматике | D57: 38000 | F57: 1 | G57: 1 | H57: 1 | I57: 1 | J57: =I57 -> 1 | K57: =J57 -> 1
A58: FM_5 | C58: Инженер-энергетик | D58: 35000 | F58: 3 | G58: 3 | H58: 3 | I58: 3 | J58: =I58 -> 3 | K58: =J58 -> 3
A59: FM_5 | C59: Инженер ОВиК | D59: 38000 | F59: 1 | G59: 1 | H59: 1 | I59: 1 | J59: =I59 -> 1 | K59: =J59 -> 1
A60: FM_5 | C60: Дежурный инженер | D60: 35000 | F60: 5 | G60: 5 | H60: 5 | I60: 5 | J60: =I60 -> 5 | K60: =J60 -> 5
A61: FM_5 | C61: Столяр | D61: 32000 | F61: 2 | G61: 2 | H61: 2 | I61: 2 | J61: =I61 -> 2 | K61: =J61 -> 2
A62: FM_5 | C62: Маляр | D62: 32000 | F62: 2 | G62: 2 | H62: 2 | I62: 2 | J62: =I62 -> 2 | K62: =J62 -> 2
A63: FM_5 | C63: Сантехник | D63: 32000 | F63: 1 | G63: 1 | H63: 1 | I63: 1 | J63: =I63 -> 1 | K63: =J63 -> 1
A64: FM_5 | D64: 0 | J64: =I64 -> 0 | K64: =J64 -> 0
A65: Rooms_5 | B65: Хозяйственная служба | C65: Руководитель | D65: 65000 | F65: 1 | G65: 1 | H65: 1 | I65: 1 | J65: =I65 -> 1 | K65: =J65 -> 1
A66: Rooms_5 | C66: Заместитель руководителя | D66: 50000 | F66: 1 | G66: 4 | H66: 4 | I66: 4 | J66: =I66 -> 4 | K66: =J66 -> 4
A67: Rooms_5 | C67: Супервайзер | D67: 38000 | F67: 2 | G67: 2 | H67: 2 | I67: 2 | J67: =I67 -> 2 | K67: =J67 -> 2
A68: Rooms_5 | C68: Горничная | D68: 30000 | F68: 7 | G68: 7 | H68: 7 | I68: 7 | J68: =I68 -> 7 | K68: =J68 -> 7
A69: Rooms_5 | C69: Горничная служебных помещений | D69: 25000 | F69: 5 | G69: 5 | H69: 5 | I69: 5 | J69: =I69 -> 5 | K69: =J69 -> 5
A70: Rooms_5 | C70: Разнорабочий | D70: 27000 | F70: 4 | G70: 4 | H70: 4 | I70: 4 | J70: =I70 -> 4 | K70: =J70 -> 4
A71: Rooms_5 | D71: 0 | J71: =I71 -> 0 | K71: =J71 -> 0
A72: Rooms_5 | B72: СПИР | C72: Начальник службы приема и размещения | D72: 65000 | F72: 1 | G72: 1 | H72: 1 | I72: 1 | J72: =I72 -> 1 | K72: =J72 -> 1
A73: Rooms_5 | C73: Старший администратор | D73: 50000 | F73: 2 | G73: 2 | H73: 2 | I73: 2 | J73: =I73 -> 2 | K73: =J73 -> 2
A74: Rooms_5 | C74: Администратор | D74: 35000 | F74: 3 | G74: 3 | H74: 3 | I74: 3 | J74: =I74 -> 3 | K74: =J74 -> 3
A75: Rooms_5 | C75: Ночной аудитор | D75: 40000 | F75: 2 | G75: 2 | H75: 2 | I75: 2 | J75: =I75 -> 2 | K75: =J75 -> 2
A76: Rooms_5 | C76: Менеджер по работе с гостями | D76: 32000 | F76: 5 | G76: 5 | H76: 5 | I76: 5 | J76: =I76 -> 5 | K76: =J76 -> 5
A77: Rooms_5 | C77: Консьерж | D77: 30000 | F77: 1 | G77: 1 | H77: 2 | I77: 2 | J77: =I77 -> 2 | K77: =J77 -> 2
A78: Rooms_5 | C78: Посыльный | D78: 25000 | F78: 3 | G78: 3 | H78: 4 | I78: 4 | J78: =I78 -> 4 | K78: =J78 -> 4
A79: Rooms_5 | D79: 0 | J79: =I79 -> 0 | K79: =J79 -> 0
A80: Rooms_5 | B80: Прачечная | C80: Руководитель прачечной | D80: 55000 | F80: 1 | G80: 1 | H80: 1 | I80: 1 | J80: =I80 -> 1 | K80: =J80 -> 1
A81: Rooms_5 | C81: Оператор стиральных машин | D81: 33000 | F81: 3 | G81: 3 | H81: 3 | I81: 3 | J81: =I81 -> 3 | K81: =J81 -> 3
A82: Rooms_5 | C82: Кастелянша | D82: 30000 | F82: 1 | G82: 1 | H82: 1 | I82: 1 | J82: =I82 -> 1 | K82: =J82 -> 1
A83: Rooms_5 | D83: 0 | J83: =I83 -> 0 | K83: =J83 -> 0
A84: F&B_5 | B84: Служба питания - адм. | C84: Руководитель службы питания | D84: 65000 | F84: 1 | G84: 1 | H84: 1 | I84: 1 | J84: =I84 -> 1 | K84: =J84 -> 1
A85: F&B_5 | C85: Шеф повар | D85: 150000 | F85: 1 | G85: 1 | H85: 1 | I85: 1 | J85: =I85 -> 1 | K85: =J85 -> 1
A86: F&B_5 | C86: Шеф кондитер | D86: 80000 | F86: 1 | G86: 1 | H86: 1 | I86: 1 | J86: =I86 -> 1 | K86: =J86 -> 1
A87: F&B_5 | C87: Руководитель банкетной службы | D87: 50000 | F87: 1 | G87: 1 | H87: 1 | I87: 1 | J87: =I87 -> 1 | K87: =J87 -> 1
A88: F&B_5 | C88: Инженер-технолог по питанию | D88: 45000 | F88: 1 | G88: 1 | H88: 1 | I88: 1 | J88: =I88 -> 1 | K88: =J88 -> 1
A89: F&B_5 | C89: Руководитель службы стюардинга | D89: 40000 | F89: 1 | G89: 1 | H89: 1 | I89: 1 | J89: =I89 -> 1 | K89: =J89 -> 1
A90: F&B_5 | C90: Уборщик производственных и служебных помещений | D90: 25000 | F90: 3 | G90: 3 | H90: 3 | I90: 3 | J90: =I90 -> 3 | K90: =J90 -> 3
A91: F&B_5 | D91: 0 | J91: =I91 -> 0 | K91: =J91 -> 0
A92: F&B_5 | B92: Шведская линия 5* | C92: Су-шеф повар | D92: 55000 | F92: 1 | G92: 1 | H92: 1 | I92: 1 | J92: =I92 -> 1 | K92: =J92 -> 1
A93: F&B_5 | C93: Старший повар | D93: 42000 | F93: 3 | G93: 3 | H93: 3 | I93: 3 | J93: =I93 -> 3 | K93: =J93 -> 3
A94: F&B_5 | C94: Повар | D94: 35000 | F94: 10 | G94: 10 | H94: 10 | I94: 10 | J94: =I94 -> 10 | K94: =J94 -> 10
A95: F&B_5 | C95: Повар-заготовщик | D95: 32000 | F95: 3 | G95: 3 | H95: 3 | I95: 3 | J95: =I95 -> 3 | K95: =J95 -> 3
A96: F&B_5 | C96: Пекарь-кондитер | D96: 35000 | F96: 2 | G96: 2 | H96: 2 | I96: 2 | J96: =I96 -> 2 | K96: =J96 -> 2
A97: F&B_5 | C97: Менеджер зала | D97: 30000 | F97: 5 | G97: 5 | H97: 5 | I97: 5 | J97: =I97 -> 5 | K97: =J97 -> 5
A98: F&B_5 | C98: Официант | D98: 28000 | F98: 10 | G98: 12 | H98: 12 | I98: 12 | J98: =I98 -> 12 | K98: =J98 -> 12
A99: F&B_5 | C99: Бармен-кассир | D99: 30000 | F99: 5 | G99: 5 | H99: 5 | I99: 5 | J99: =I99 -> 5 | K99: =J99 -> 5
A100: F&B_5 | D100: 0 | J100: =I100 -> 0 | K100: =J100 -> 0
A101: F&B_5 | B101: Ресторан a-la-carte | C101: Су-шеф повар | D101: 55000 | F101: 1 | G101: 1 | H101: 1 | I101: 1 | J101: =I101 -> 1 | K101: =J101 -> 1
A102: F&B_5 | C102: Старший повар | D102: 42000 | F102: 1 | G102: 1 | H102: 1 | I102: 1 | J102: =I102 -> 1 | K102: =J102 -> 1
...

Sheet CF_mln
A1: 0
C2: Мультипликатор
B3: ДЕНЕЖНЫЕ ПОТОКИ ОТ РЕАЛИЗАЦИИ ПРОЕКТА | C3: =10^6 -> 1000000 | D3: млн руб.
T4: Постпрогноз
D5: =YEAR(D6) -> 2022 | E5: =D5+1 -> 2023 | F5: =E5+1 -> 2024 | G5: =F5+1 -> 2025 | H5: =G5+1 -> 2026 | I5: =H5+1 -> 2027 | J5: =I5+1 -> 2028 | K5: =J5+1 -> 2029 | L5: =K5+1 -> 2030 | ... T5: =S5+1 -> 2038
B6: НАЧАЛО ПЕРИОДА | C6: Сумма | D6: =Вводные!D4 -> 44593 | E6: =DATE(E5,1,1) -> 44927 | F6: =DATE(F5,1,1) -> 45292 | G6: =DATE(G5,1,1) -> 45658 | H6: =DATE(H5,1,1) -> 46023 | I6: =DATE(I5,1,1) -> 46388 | J6: =DATE(J5,1,1) -> 46753 | K6: =DATE(K5,1,1) -> 47119 | L6: =DATE(L5,1,1) -> 47484 | ... T6: =DATE(T5,1,1) -> 50406
B7: КОНЕЦ ПЕРИОДА | C7: до термин. | D7: =DATE(D5,12,31) -> 44926 | E7: =DATE(E5,12,31) -> 45291 | F7: =DATE(F5,12,31) -> 45657 | G7: =DATE(G5,12,31) -> 46022 | H7: =DATE(H5,12,31) -> 46387 | I7: =DATE(I5,12,31) -> 46752 | J7: =DATE(J5,12,31) -> 47118 | K7: =DATE(K5,12,31) -> 47483 | ... T7: =DATE(T5,12,31) -> 50770
B8: ДНЕЙ В ПЕРИОД | C8: года | D8: =D7-D6+1 -> 334 | E8: =E7-E6+1 -> 365 | F8: =F7-F6+1 -> 366 | G8: =G7-G6+1 -> 365 | H8: =H7-H6+1 -> 365 | I8: =I7-I6+1 -> 365 | J8: =J7-J6+1 -> 366 | K8: =K7-K6+1 -> 365 | ... T8: =T7-T6+1 -> 365
B9: Операционная прибыль (без НДС)
B10: Гостиничная составляющая | C10: =SUM(D10:S10) -> 13393.23 | D10: =CF_15!D10/$C$3 -> 0 | E10: =CF_15!E10/$C$3 -> 0 | F10: =CF_15!F10/$C$3 -> 0 | G10: =CF_15!G10/$C$3 -> 158.21053 | H10: =CF_15!H10/$C$3 -> 552.55702 | I10: =CF_15!I10/$C$3 -> 870.88409 | J10: =CF_15!J10/$C$3 -> 883.58985 | K10: =CF_15!K10/$C$3 -> 1007.6994 | ... T10: =CF_15!T10/$C$3 -> 1425.3589
B11: Ресторан | C11: =SUM(D11:S11) -> 450.63302 | D11: =CF_15!D11/$C$3 -> 0 | E11: =CF_15!E11/$C$3 -> 0 | F11: =CF_15!F11/$C$3 -> 0 | G11: =CF_15!G11/$C$3 -> 3.2458159 | H11: =CF_15!H11/$C$3 -> 23.501215 | I11: =CF_15!I11/$C$3 -> 28.570795 | J11: =CF_15!J11/$C$3 -> 31.519834 | K11: =CF_15!K11/$C$3 -> 33.982989 | ... T11: =CF_15!T11/$C$3 -> 48.927163
B12: Многофункциональный центр и торговые площади (аренда) | C12: =SUM(D12:S12) -> 681.55314 | D12: =CF_15!D12/$C$3 -> 0 | E12: =CF_15!E12/$C$3 -> 0 | F12: =CF_15!F12/$C$3 -> 0 | G12: =CF_15!G12/$C$3 -> 12.893463 | H12: =CF_15!H12/$C$3 -> 34.263066 | I12: =CF_15!I12/$C$3 -> 40.583045 | J12: =CF_15!J12/$C$3 -> 49.459292 | K12: =CF_15!K12/$C$3 -> 51.437664 | ... T12: =CF_15!T12/$C$3 -> 73.211835
B13: Платная парковка | C13: =SUM(D13:S13) -> 54.351311 | D13: =CF_15!D13/$C$3 -> 0 | E13: =CF_15!E13/$C$3 -> 0 | F13: =CF_15!F13/$C$3 -> 0 | G13: =CF_15!G13/$C$3 -> 0.06135533 | H13: =CF_15!H13/$C$3 -> 1.8171203 | I13: =CF_15!I13/$C$3 -> 2.7448239 | J13: =CF_15!J13/$C$3 -> 3.7116449 | K13: =CF_15!K13/$C$3 -> 4.2938553 | ... T13: =CF_15!T13/$C$3 -> 5.9045776
B14: Продажа резиденций | C14: =SUM(D14:S14) -> 3945.4946 | D14: =CF_15!D14/$C$3 -> 0 | E14: =CF_15!E14/$C$3 -> 0 | F14: =CF_15!F14/$C$3 -> 0 | G14: =CF_15!G14/$C$3 -> 0 | H14: =CF_15!H14/$C$3 -> 923.23553 | I14: =CF_15!I14/$C$3 -> 1585.7869 | J14: =CF_15!J14/$C$3 -> 1436.4722 | K14: =CF_15!K14/$C$3 -> 0 | ... T14: =CF_15!T14/$C$3 -> 0
B15: ВСЕГО, операционная прибыль | C15: =SUM(D15:S15) -> 18525.262 | D15: =SUM(D10:D14) -> 0 | E15: =SUM(E10:E14) -> 0 | F15: =SUM(F10:F14) -> 0 | G15: =SUM(G10:G14) -> 174.41116 | H15: =SUM(H10:H14) -> 1535.3739 | I15: =SUM(I10:I14) -> 2528.5696 | J15: =SUM(J10:J14) -> 2404.7529 | K15: =SUM(K10:K14) -> 1097.4139 | ... T15: =SUM(T10:T14) -> 1553.4025
B16: Расходы общекурортные
B17: Расходы на администрацию и управление | D17: =CF_15!D17/$C$3 -> 0 | E17: =CF_15!E17/$C$3 -> 0 | F17: =CF_15!F17/$C$3 -> 0 | G17: =CF_15!G17/$C$3 -> -29.183266 | H17: =CF_15!H17/$C$3 -> -35.884077 | I17: =CF_15!I17/$C$3 -> -39.7463 | J17: =CF_15!J17/$C$3 -> -40.076614 | K17: =CF_15!K17/$C$3 -> -42.181946 | ... T17: =CF_15!T17/$C$3 -> -60.519303
B18: Расходы на продажи и маркетинг | D18: =CF_15!D18/$C$3 -> 0 | E18: =CF_15!E18/$C$3 -> 0 | F18: =CF_15!F18/$C$3 -> 0 | G18: =CF_15!G18/$C$3 -> -16.414222 | H18: =CF_15!H18/$C$3 -> -23.176155 | I18: =CF_15!I18/$C$3 -> -32.34112 | J18: =CF_15!J18/$C$3 -> -33.547511 | K18: =CF_15!K18/$C$3 -> -36.005562 | ... T18: =CF_15!T18/$C$3 -> -52.316564
B19: Расходы на текущий ремонт и эксплуатацию | D19: =CF_15!D19/$C$3 -> 0 | E19: =CF_15!E19/$C$3 -> 0 | F19: =CF_15!F19/$C$3 -> 0 | G19: =CF_15!G19/$C$3 -> -20.222372 | H19: =CF_15!H19/$C$3 -> -27.252648 | I19: =CF_15!I19/$C$3 -> -28.505889 | J19: =CF_15!J19/$C$3 -> -28.364772 | K19: =CF_15!K19/$C$3 -> -30.280669 | ... T19: =CF_15!T19/$C$3 -> -43.847429
B20: Коммунальные расходы по курорту | D20: =CF_15!D20/$C$3 -> 0 | E20: =CF_15!E20/$C$3 -> 0 | F20: =CF_15!F20/$C$3 -> 0 | G20: =CF_15!G20/$C$3 -> -2.0523547 | H20: =CF_15!H20/$C$3 -> -8.135089 | I20: =CF_15!I20/$C$3 -> -11.733403 | J20: =CF_15!J20/$C$3 -> -12.159112 | K20: =CF_15!K20/$C$3 -> -13.203551 | ... T20: =CF_15!T20/$C$3 -> -19.327482
B21: Налог на имущество - курорт | D21: =CF_15!D21/$C$3 -> 0 | E21: =CF_15!E21/$C$3 -> 0 | F21: =CF_15!F21/$C$3 -> 0 | G21: =CF_15!G21/$C$3 -> 0 | H21: =CF_15!H21/$C$3 -> 0 | I21: =CF_15!I21/$C$3 -> 0 | J21: =CF_15!J21/$C$3 -> 0 | K21: =CF_15!K21/$C$3 -> 0 | ... T21: =CF_15!T21/$C$3 -> -11.44258
B22: Расходы на страхование - курорт | D22: =CF_15!D22/$C$3 -> 0 | E22: =CF_15!E22/$C$3 -> 0 | F22: =CF_15!F22/$C$3 -> 0 | G22: =CF_15!G22/$C$3 -> -2.256391 | H22: =CF_15!H22/$C$3 -> -2.1799032 | I22: =CF_15!I22/$C$3 -> -2.1034154 | J22: =CF_15!J22/$C$3 -> -2.0269275 | K22: =CF_15!K22/$C$3 -> -1.9504397 | ... T22: =CF_15!T22/$C$3 -> -1.2620492
B23: ВСЕГО, расходы | C23: =SUM(D23:S23) -> -1757.7301 | D23: =SUM(D17:D22) -> 0 | E23: =SUM(E17:E22) -> 0 | F23: =SUM(F17:F22) -> 0 | G23: =SUM(G17:G22) -> -70.128605 | H23: =SUM(H17:H22) -> -96.627872 | I23: =SUM(I17:I22) -> -114.43013 | J23: =SUM(J17:J22) -> -116.17494 | K23: =SUM(K17:K22) -> -123.62217 | ... T23: =SUM(T17:T22) -> -188.71541
B24: ИТОГО, Чистая операционная прибыль/убыток | C24: =SUM(D24:S24) -> 16767.532 | D24: =D15+D23 -> 0 | E24: =E15+E23 -> 0 | F24: =F15+F23 -> 0 | G24: =G15+G23 -> 104.28256 | H24: =H15+H23 -> 1438.7461 | I24: =I15+I23 -> 2414.1395 | J24: =J15+J23 -> 2288.5779 | K24: =K15+K23 -> 973.7917 | ... T24: =T15+T23 -> 1364.6871
B25: Минус: проценты про кредиту начисленные | C25: =SUM(D25:S25) -> -2338.6574 | D25: =-D184 -> 0 | E25: =-E184 -> -4 | F25: =-F184 -> -89.844143 | G25: =-G184 -> -208.16635 | H25: =-H184 -> -296.39888 | I25: =-I184 -> -261.668 | J25: =-J184 -> -253.444 | K25: =-K184 -> -239.588 | ... T25: =-T184 -> 0
B26: Минус: амортизация | C26: =SUM(D26:S26) -> -2775.6724 | D26: =-LOOKUP(D$5,Амортизация!$252:$252,Амортизация!$255:$255)/$C$3 -> 0 | E26: =-LOOKUP(E$5,Амортизация!$252:$252,Амортизация!$255:$255)/$C$3 -> 0 | F26: =-LOOKUP(F$5,Амортизация!$252:$252,Амортизация!$255:$255)/$C$3 -> 0 | G26: =-LOOKUP(G$5,Амортизация!$252:$252,Амортизация!$255:$255)/$C$3 -> -43.883903 | H26: =-LOOKUP(H$5,Амортизация!$252:$252,Амортизация!$255:$255)/$C$3 -> -160.74932 | I26: =-LOOKUP(I$5,Амортизация!$252:$252,Амортизация!$255:$255)/$C$3 -> -233.73084 | J26: =-LOOKUP(J$5,Амортизация!$252:$252,Амортизация!$255:$255)/$C$3 -> -233.73084 | K26: =-LOOKUP(K$5,Амортизация!$252:$252,Амортизация!$255:$255)/$C$3 -> -233.73084 | ... T26: =-LOOKUP(T$5,Амортизация!$252:$252,Амортизация!$255:$255)/$C$3 -> -233.73084
B27: Минус: себестоимость резиденций | C27: =SUM(D27:S27) -> -1625.3038 | D27: =SUMIF(ПРОДАЖА_lease_back!8:8,D5,ПРОДАЖА_lease_back!33:33)/$C$3 -> 0 | E27: =SUMIF(ПРОДАЖА_lease_back!8:8,E5,ПРОДАЖА_lease_back!33:33)/$C$3 -> 0 | F27: =SUMIF(ПРОДАЖА_lease_back!8:8,F5,ПРОДАЖА_lease_back!33:33)/$C$3 -> 0 | G27: =SUMIF(ПРОДАЖА_lease_back!8:8,G5,ПРОДАЖА_lease_back!33:33)/$C$3 -> 0 | H27: =SUMIF(ПРОДАЖА_lease_back!8:8,H5,ПРОДАЖА_lease_back!33:33)/$C$3 -> -406.32596 | I27: =SUMIF(ПРОДАЖА_lease_back!8:8,I5,ПРОДАЖА_lease_back!33:33)/$C$3 -> -650.12153 | J27: =SUMIF(ПРОДАЖА_lease_back!8:8,J5,ПРОДАЖА_lease_back!33:33)/$C$3 -> -568.85634 | K27: =SUMIF(ПРОДАЖА_lease_back!8:8,K5,ПРОДАЖА_lease_back!33:33)/$C$3 -> 0 | ... T27: =SUMIF(ПРОДАЖА_lease_back!8:8,T5,ПРОДАЖА_lease_back!33:33)/$C$3 -> 0
B28: Равно: прибыль / убыток за период | D28: =SUM(D24:D27) -> 0 | E28: =SUM(E24:E27) -> -4 | F28: =SUM(F24:F27) -> -89.844143 | G28: =SUM(G24:G27) -> -147.7677 | H28: =SUM(H24:H27) -> 575.27191 | I28: =SUM(I24:I27) -> 1268.6191 | J28: =SUM(J24:J27) -> 1232.5467 | K28: =SUM(K24:K27) -> 500.47287 | ... T28: =SUM(T24:T27) -> 1130.9563
B29: Итого: накопленный убыток | D29: =D28 -> 0 | E29: =IF(E28<0,E28,0)+D31 -> -4 | F29: =IF(F28<0,F28,0)+E31 -> -93.844143 | G29: =IF(G28<0,G28,0)+F31 -> -241.61184 | H29: =IF(H28<0,H28,0)+G31 -> -241.61184 | I29: =IF(I28<0,I28,0)+H31 -> 0 | J29: =IF(J28<0,J28,0)+I31 -> 0 | K29: =IF(K28<0,K28,0)+J31 -> 0 | L29: =IF(L28<0,L28,0)+K31 -> 0 | ... T29: =IF(T28<0,T28,0)+S31 -> 0
B30: Накопленный убыток к зачету | E30: =IF(E29<0,(IF(E28>0,MIN(-E29,E28),0)),0) -> 0 | F30: =IF(F29<0,(IF(F28>0,MIN(-F29,F28),0)),0) -> 0 | G30: =IF(G29<0,(IF(G28>0,MIN(-G29,G28),0)),0) -> 0 | H30: =IF(H29<0,(IF(H28>0,MIN(-H29,H28),0)),0) -> 241.61184 | I30: =IF(I29<0,(IF(I28>0,MIN(-I29,I28),0)),0) -> 0 | J30: =IF(J29<0,(IF(J28>0,MIN(-J29,J28),0)),0) -> 0 | K30: =IF(K29<0,(IF(K28>0,MIN(-K29,K28),0)),0) -> 0 | L30: =IF(L29<0,(IF(L28>0,MIN(-L29,L28),0)),0) -> 0 | ... T30: =IF(T29<0,(IF(T28>0,MIN(-T29,T28),0)),0) -> 0
B31: Итого: накопленный убыток к переносу | E31: =IF((E29+E30)<0,(E29+E30),0) -> -4 | F31: =IF((F29+F30)<0,(F29+F30),0) -> -93.844143 | G31: =IF((G29+G30)<0,(G29+G30),0) -> -241.61184 | H31: =IF((H29+H30)<0,(H29+H30),0) -> 0 | I31: =IF((I29+I30)<0,(I29+I30),0) -> 0 | J31: =IF((J29+J30)<0,(J29+J30),0) -> 0 | K31: =IF((K29+K30)<0,(K29+K30),0) -> 0 | L31: =IF((L29+L30)<0,(L29+L30),0) -> 0 | ... T31: =IF((T29+T30)<0,(T29+T30),0) -> 0
B32: Итого: налоговая база | E32: =IF((E28-E30)<0,0,(E28-E30)) -> 0 | F32: =IF((F28-F30)<0,0,(F28-F30)) -> 0 | G32: =IF((G28-G30)<0,0,(G28-G30)) -> 0 | H32: =IF((H28-H30)<0,0,(H28-H30)) -> 333.66006 | I32: =IF((I28-I30)<0,0,(I28-I30)) -> 1268.6191 | J32: =IF((J28-J30)<0,0,(J28-J30)) -> 1232.5467 | K32: =IF((K28-K30)<0,0,(K28-K30)) -> 500.47287 | L32: =IF((L28-L30)<0,0,(L28-L30)) -> 612.05826 | ... T32: =IF((T28-T30)<0,0,(T28-T30)) -> 1130.9563
B33: Ставка налога на прибыль | D33: =CF_15!D33 -> 0.135 | E33: =CF_15!E33 -> 0.135 | F33: =CF_15!F33 -> 0.135 | G33: =CF_15!G33 -> 0.155 | H33: =CF_15!H33 -> 0.155 | I33: =CF_15!I33 -> 0.155 | J33: =CF_15!J33 -> 0.155 | K33: =CF_15!K33 -> 0.155 | ... T33: =CF_15!T33 -> 0.155
B34: Налог на прибыль | D34: =-D33*D32 -> 0 | E34: =-E33*E32 -> 0 | F34: =-F33*F32 -> 0 | G34: =-G33*G32 -> 0 | H34: =-H33*H32 -> -51.71731 | I34: =-I33*I32 -> -196.63596 | J34: =-J33*J32 -> -191.04475 | K34: =-K33*K32 -> -77.573294 | ... T34: =-T33*T32 -> -175.29822
B35: ИТОГО, Чистая операционная прибыль после налога | C35: =SUM(D35:S35) -> 15213.208 | D35: =D24+D34 -> 0 | E35: =E24+E34 -> 0 | F35: =F24+F34 -> 0 | G35: =G24+G34 -> 104.28256 | H35: =H24+H34 -> 1387.0288 | I35: =I24+I34 -> 2217.5035 | J35: =J24+J34 -> 2097.5332 | K35: =K24+K34 -> 896.21841 | ... T35: =T24+T34 -> 1189.3889
B36: Инвестиционная деятельность
B37: Минус: затраты на строительство | C37: =SUM(D37:S37) -> -11472.203 | D37: =CF_15!D37/$C$3 -> -160.31818 | E37: =CF_15!E37/$C$3 -> -3048.2053 | F37: =CF_15!F37/$C$3 -> -4225.7933 | G37: =CF_15!G37/$C$3 -> -3151.1617 | H37: =CF_15!H37/$C$3 -> -886.72478 | I37: =CF_15!I37/$C$3 -> 0 | J37: =CF_15!J37/$C$3 -> 0 | K37: =CF_15!K37/$C$3 -> 0 | ... S37: =CF_15!S37/$C$3 -> 0
B38: Минус: земельные платежи инвестиционного периода | C38: =SUM(D38:S38) -> -1.3198967 | D38: =CF_15!D38/$C$3 -> -0.41393945 | E38: =CF_15!E38/$C$3 -> -0.45235898 | F38: =CF_15!F38/$C$3 -> -0.45359832 | G38: =CF_15!G38/$C$3 -> 0 | H38: =CF_15!H38/$C$3 -> 0 | I38: =CF_15!I38/$C$3 -> 0 | J38: =CF_15!J38/$C$3 -> 0 | K38: =CF_15!K38/$C$3 -> 0 | ... S38: =CF_15!S38/$C$3 -> 0
B39: Плюс: возмещение строительного НДС | C39: =SUM(D39:S39) -> 1912.0339 | D39: =CF_15!D39/$C$3 -> 0 | E39: =CF_15!E39/$C$3 -> 26.719697 | F39: =CF_15!F39/$C$3 -> 508.03422 | G39: =CF_15!G39/$C$3 -> 704.29888 | H39: =CF_15!H39/$C$3 -> 525.19362 | I39: =CF_15!I39/$C$3 -> 147.78746 | J39: =CF_15!J39/$C$3 -> 0 | K39: =CF_15!K39/$C$3 -> 0 | ... S39: =CF_15!S39/$C$3 -> 0
B40: FCFF | C40: =SUM(D40:S40) -> 5651.7186 | D40: =SUM(D35:D39) -> -160.73212 | E40: =SUM(E35:E39) -> -3021.938 | F40: =SUM(F35:F39) -> -3718.2127 | G40: =SUM(G35:G39) -> -2342.5803 | H40: =SUM(H35:H39) -> 1025.4976 | I40: =SUM(I35:I39) -> 2365.291 | J40: =SUM(J35:J39) -> 2097.5332 | K40: =SUM(K35:K39) -> 896.21841 | ... S40: =SUM(S35:S39) -> 1137.1024
B41: Финансовая деятельность
B42: Собственные средства | C42: =SUM(D42:S42) -> 2274.6748 | D42: =IF(SUM(C48,D40,D44,D45,D43)<0,-SUM(C48,D40,D44,D45,D43),0) -> 60.732124 | E42: =IF(SUM(D48,E40,E44,E45,E43)<0,-SUM(D48,E40,E44,E45,E43),0) -> 879.83437 | F42: =IF(SUM(E48,F40,F44,F45,F43)<0,-SUM(E48,F40,F44,F45,F43),0) -> 850.00151 | G42: =IF(SUM(F48,G40,G44,G45,G43)<0,-SUM(F48,G40,G44,G45,G43),0) -> 344.93343 | H42: =IF(SUM(G48,H40,H44,H45,H43)<0,-SUM(G48,H40,H44,H45,H43),0) -> 139.17336 | I42: =IF(SUM(H48,I40,I44,I45,I43)<0,-SUM(H48,I40,I44,I45,I43),0) -> 0 | J42: =IF(SUM(I48,J40,J44,J45,J43)<0,-SUM(I48,J40,J44,J45,J43),0) -> 0 | K42: =IF(SUM(J48,K40,K44,K45,K43)<0,-SUM(J48,K40,K44,K45,K43),0) -> 0 | ... S42: =IF(SUM(R48,S40,S44,S45,S43)<0,-SUM(R48,S40,S44,S45,S43),0) -> 0
A43: =C43=C181 -> TRUE | B43: Плюс: кредит | C43: =SUM(D43:S43) -> 8028 | D43: =D181 -> 100 | E43: =E181 -> 2146.1036 | F43: =F181 -> 2958.0553 | G43: =G181 -> 2205.8132 | H43: =H181 -> 618.02792 | I43: =I181 -> 0 | J43: =J181 -> 0 | K43: =K181 -> 0 | ... R43: =R181 -> 0
A44: =-C44=C184 -> TRUE | B44: Минус: проценты по кредиту | C44: =SUM(D44:S44) -> -2338.6574 | D44: =D25 -> 0 | E44: =E25 -> -4 | F44: =F25 -> -89.844143 | G44: =G25 -> -208.16635 | H44: =H25 -> -296.39888 | I44: =I25 -> -261.668 | J44: =J25 -> -253.444 | K44: =K25 -> -239.588 | ... S44: =S25 -> 0
A45: =-ROUND(C45,2)=ROUND(C43,2) -> TRUE | B45: Минус: тело долга | C45: =SUM(D45:S45) -> -8028 | D45: =-D185 -> 0 | E45: =-E185 -> 0 | F45: =-F185 -> 0 | G45: =-G185 -> 0 | H45: =-H185 -> -1486.3 | I45: =-I185 -> -205.6 | J45: =-J185 -> -346.4 | K45: =-K185 -> -475.1 | ... S45: =-S185 -> -505
B46: FCFE | C46: =SUM(D46:S46) -> 3313.0612 | D46: =SUM(D40:D45)-D42 -> -60.732124 | E46: =SUM(E40:E45)-E42 -> -879.83437 | F46: =SUM(F40:F45)-F42 -> -850.00151 | G46: =SUM(G40:G45)-G42 -> -344.93343 | H46: =SUM(H40:H45)-H42 -> -139.17336 | I46: =SUM(I40:I45)-I42 -> 1898.023 | J46: =SUM(J40:J45)-J42 -> 1497.6892 | K46: =SUM(K40:K45)-K42 -> 181.53041 | ... S46: =SUM(S40:S45)-S42 -> 632.10241
B47: Оборот за год | D47: =SUM(D40:D45) -> 0 | E47: =SUM(E40:E45) -> -6.8389738e-14 | F47: =SUM(F40:F45) -> -1.7053026e-13 | G47: =SUM(G40:G45) -> 3.126388e-13 | H47: =SUM(H40:H45) -> 0 | I47: =SUM(I40:I45) -> 1898.023 | J47: =SUM(J40:J45) -> 1497.6892 | K47: =SUM(K40:K45) -> 181.53041 | ... S47: =SUM(S40:S45) -> 632.10241
B48: Остаток на счете | D48: =C48+D47 -> 0 | E48: =D48+E47 -> -6.8389738e-14 | F48: =E48+F47 -> -2.3891999e-13 | G48: =F48+G47 -> 7.3718809e-14 | H48: =G48+H47 -> 7.3718809e-14 | I48: =H48+I47 -> 1898.023 | J48: =I48+J47 -> 3395.7122 | K48: =J48+K47 -> 3577.2426 | ... S48: =R48+S47 -> 5587.736
B50: Показатели проекта на собственный капитал | D50: =D5 -> 2022 | E50: =E5 -> 2023 | F50: =F5 -> 2024 | G50: =G5 -> 2025 | H50: =H5 -> 2026 | I50: =I5 -> 2027 | J50: =J5 -> 2028 | K50: =K5 -> 2029 | ... N50: =N5 -> 2032 | T50: =T4 -> Постпрогноз
B51: Терминальная стоимость
B52: Терминальная ставка капитализации | T52: 0.1
B53: Терминальная стоимость | T53: =T35/T52 -> 11893.889
B54: Комиссия брокеру, расходы при продаже % | T54: 0.01
B55: Комиссия брокеру | T55: =-T54*T53 -> -118.93889
B56: Остаточная балансовая стоимость
B57: Налогооблагаемая база | T57: =T53+T55-T56 -> 11774.95
B58: Налог на прибыль, % | U58: Продажа бизнеса
B59: Налог на прибыль | T59: =-T57*T58 -> 0
B60: Остатки по кредиту | T60: 0
B61: Доход от продажи | T61: =T53+T55+T59-T60 -> 11774.95
B62: Движение средств по Проекту
B63: =B46 -> FCFE | D63: =D46+D61 -> -60.732124 | E63: =E46+E61 -> -879.83437 | F63: =F46+F61 -> -850.00151 | G63: =G46+G61 -> -344.93343 | H63: =H46+H61 -> -139.17336 | I63: =I46+I61 -> 1898.023 | J63: =J46+J61 -> 1497.6892 | K63: =K46+K61 -> 181.53041 | ... S63: =S46+S61 -> 632.10241
B64: FCFE + TV | D64: =D63+D61 -> -60.732124 | E64: =E63+E61 -> -879.83437 | F64: =F63+F61 -> -850.00151 | G64: =G63+G61 -> -344.93343 | H64: =H63+H61 -> -139.17336 | I64: =I63+I61 -> 1898.023 | J64: =J63+J61 -> 1497.6892 | K64: =K63+K61 -> 181.53041 | ... T64: =T63+T61 -> 11774.95
B65: Ставка дисконтирования | D65: =WACC!D20 -> 0.17289342 | E65: =D65 -> 0.17289342 | F65: =E65 -> 0.17289342 | G65: =F65 -> 0.17289342 | H65: =G65 -> 0.17289342 | I65: =H65 -> 0.17289342 | J65: =I65 -> 0.17289342 | K65: =J65 -> 0.17289342 | L65: =K65 -> 0.17289342 | ... S65: =R65 -> 0.17289342 | T65: =N65 -> 0.17289342
B66: Период дисконтирования | D66: =D$8/365/2 -> 0.45753425 | E66: =D66*2+0.5 -> 1.4150685 | F66: =E66+1 -> 2.4150685 | G66: =F66+1 -> 3.4150685 | H66: =G66+1 -> 4.4150685 | I66: =H66+1 -> 5.4150685 | J66: =I66+1 -> 6.4150685 | K66: =J66+1 -> 7.4150685 | L66: =K66+1 -> 8.4150685 | M66: =L66+1 -> 9.4150685 | ... S66: =R66+1 -> 15.415068 | T66: =S66+0.5 -> 15.915068
B67: Фактор дисконтирования (с середины года) | D67: =1/(1+D65)^D66 -> 0.92963366 | E67: =1/(1+E65)^E66 -> 0.79798442 | F67: =1/(1+F65)^F66 -> 0.68035544 | G67: =1/(1+G65)^G66 -> 0.58006587 | H67: =1/(1+H65)^H66 -> 0.49455974 | I67: =1/(1+I65)^I66 -> 0.42165787 | J67: =1/(1+J65)^J66 -> 0.35950229 | K67: =1/(1+K65)^K66 -> 0.30650892 | ... T67: =1/(1+T65)^T66 -> 0.079021533
B68: Дисконтированный денежный поток - без TV | D68: =D67*D63 -> -56.458627 | E68: =E67*E63 -> -702.09412 | F68: =F67*F63 -> -578.30315 | G68: =G67*G63 -> -200.08411 | H68: =H67*H63 -> -68.829543 | I68: =I67*I63 -> 800.31634 | J68: =J67*J63 -> 538.4227 | K68: =K67*K63 -> 55.64069 | ... T68: =T67*T63 -> 0
B69: Дисконтированный денежный поток - с TV | D69: =D67*D64 -> -56.458627 | E69: =E67*E64 -> -702.09412 | F69: =F67*F64 -> -578.30315 | G69: =G67*G64 -> -200.08411 | H69: =H67*H64 -> -68.829543 | I69: =I67*I64 -> 800.31634 | J69: =J67*J64 -> 538.4227 | K69: =K67*K64 -> 55.64069 | ... T69: =T67*T64 -> 930.4746
B70: Чистая текущая ст-ть проекта на дату анализа
B71: Чистая текущая ст-ть проекта на дату анализа - без TV | D71: =SUM(D68:S68) -> 67.805055
B72: Чистая текущая ст-ть проекта на дату анализа - с TV | D72: =SUM(D69:T69) -> 998.27965
B73: Денежный поток накопленным итогом - без TV | D73: =SUM($D$63:D63) -> -60.732124 | E73: =SUM($D$63:E63) -> -940.5665 | F73: =SUM($D$63:F63) -> -1790.568 | G73: =SUM($D$63:G63) -> -2135.5014 | H73: =SUM($D$63:H63) -> -2274.6748 | I73: =SUM($D$63:I63) -> -376.65181 | J73: =SUM($D$63:J63) -> 1121.0374 | K73: =SUM($D$63:K63) -> 1302.5678 | ... R73: =SUM($D$63:R63) -> 2680.9588 | S73: =SUM($D$63:T63) -> 3313.0612
B74: Денежный поток накопленным итогом - c TV | D74: =SUM($D$64:D64) -> -60.732124 | E74: =SUM($D$64:E64) -> -940.5665 | F74: =SUM($D$64:F64) -> -1790.568 | G74: =SUM($D$64:G64) -> -2135.5014 | H74: =SUM($D$64:H64) -> -2274.6748 | I74: =SUM($D$64:I64) -> -376.65181 | J74: =SUM($D$64:J64) -> 1121.0374 | K74: =SUM($D$64:K64) -> 1302.5678 | ... R74: =SUM($D$64:R64) -> 2680.9588 | S74: =SUM($D$64:T64) -> 15088.011
B75: PBP (срок окупаемости) - без TV | D75: =IF(AND(S73>0,(COUNTIF(D73:S73,"<0"))=COUNT(D73:S73)-1),"окупается с продажи",IF(OR(S73<0,(COUNTIF(D73:S73,"<0"))=COUNT(D73:S73)),"не окупается",(COUNTIF(D73:S73,"<0")))) -> 6
B76: PBP (срок окупаемости) - c TV | D76: =IF(AND(S74>0,(COUNTIF(D74:S74,"<0"))=COUNT(D74:S74)-1),"окупается с продажи",IF(OR(S74<0,(COUNTIF(D74:S74,"<0"))=COUNT(D74:S74)),"не окупается",(COUNTIF(D74:S74,"<0")))) -> 6
B77: Дисконтированный денежный поток накопленным итогом - без TV | D77: =SUM($D$68:D68) -> -56.458627 | E77: =SUM($D$68:E68) -> -758.55275 | F77: =SUM($D$68:F68) -> -1336.8559 | G77: =SUM($D$68:G68) -> -1536.94 | H77: =SUM($D$68:H68) -> -1605.7695 | I77: =SUM($D$68:I68) -> -805.45321 | J77: =SUM($D$68:J68) -> -267.03052 | K77: =SUM($D$68:K68) -> -211.38983 | ... R77: =SUM($D$68:R68) -> 13.709427 | S77: =SUM($D$68:T68) -> 67.805055
B78: Дисконтированный денежный поток накопленным итогом - c TV | D78: =SUM($D$69:D69) -> -56.458627 | E78: =SUM($D$69:E69) -> -758.55275 | F78: =SUM($D$69:F69) -> -1336.8559 | G78: =SUM($D$69:G69) -> -1536.94 | H78: =SUM($D$69:H69) -> -1605.7695 | I78: =SUM($D$69:I69) -> -805.45321 | J78: =SUM($D$69:J69) -> -267.03052 | K78: =SUM($D$69:K69) -> -211.38983 | ... R78: =SUM($D$69:R69) -> 13.709427 | S78: =SUM($D$69:T69) -> 998.27965
B79: DPBP (дисконтированный срок окупаемости) - без TV | D79: =IF(AND(S77>0,(COUNTIF(D77:S77,"<0"))=COUNT(D77:S77)-1),"окупается с продажи",IF(OR(S77<0,(COUNTIF(D77:S77,"<0"))=COUNT(D77:S77)),"не окупается",(COUNTIF(D77:S77,"<0")))) -> 14
B80: DPBP (дисконтированный срок окупаемости) - c TV | D80: =IF(AND(S78>0,(COUNTIF(D78:S78,"<0"))=COUNT(D78:S78)-1),"окупается с продажи",IF(OR(S78<0,(COUNTIF(D78:S78,"<0"))=COUNT(D78:S78)),"не окупается",(COUNTIF(D78:S78,"<0")))) -> 14
B81: =B63 -> FCFE | C81: =SUM(D81:S81) -> 3313.0612 | D81: =D63 -> -60.732124 | E81: =E63 -> -879.83437 | F81: =F63 -> -850.00151 | G81: =G63 -> -344.93343 | H81: =H63 -> -139.17336 | I81: =I63 -> 1898.023 | J81: =J63 -> 1497.6892 | K81: =K63 -> 181.53041 | ... R81: =R63 -> 258.21579 | S81: =S63+T63 -> 632.10241
A82: =IF(AND(D72<0,D85>=D65),"Error","") | B82: FCFE + TV | C82: =SUM(D82:S82) -> 15088.011 | D82: =D64 -> -60.732124 | E82: =E64 -> -879.83437 | F82: =F64 -> -850.00151 | G82: =G64 -> -344.93343 | H82: =H64 -> -139.17336 | I82: =I64 -> 1898.023 | J82: =J64 -> 1497.6892 | K82: =K64 -> 181.53041 | ... R82: =R64 -> 258.21579 | S82: =S64+T64 -> 12407.052
A83: ВНИМАНИЕ | B83: =B81&" без кассовых разрывов" -> FCFE без кассовых разрывов | C83: =SUM(D83:S83) -> 3313.0612 | D83: =D81 -> -60.732124 | E83: =E81 -> -879.83437 | F83: =MIN(F81,-0.001) -> -850.00151 | G83: =MIN(G81,-0.001) -> -344.93343 | H83: =MIN(H81,-0.001) -> -139.17336 | I83: =MIN(I81,-0.001) -> -0.001 | J83: =MIN(J81,-0.001) -> -0.001 | K83: =SUM($D$81:K81)-SUM($D$83:J83) -> 3577.2446 | L83: =SUM($D$81:L81)-SUM($D$83:K83) -> 183.72007 | M83: =SUM($D$81:M81)-SUM($D$83:L83) -> 168.63573 | N83: =SUM($D$81:N81)-SUM($D$83:M83) -> 161.6995 | O83: =SUM($D$81:O81)-SUM($D$83:N83) -> 165.62767 | P83: =SUM($D$81:P81)-SUM($D$83:O83) -> 206.07793 | Q83: =SUM($D$81:Q81)-SUM($D$83:P83) -> 234.41429 | R83: =SUM($D$81:R81)-SUM($D$83:Q83) -> 258.21579 | S83: =SUM($D$81:S81)-SUM($D$83:R83) -> 632.10241
A84: ВНИМАНИЕ | B84: =B82&" без кассовых разрывов" -> FCFE + TV без кассовых разрывов | C84: =SUM(D84:S84) -> 15088.011 | D84: =D82 -> -60.732124 | E84: =E82 -> -879.83437 | F84: =MIN(F82,-0.001) -> -850.00151 | G84: =MIN(G82,-0.001) -> -344.93343 | H84: =MIN(H82,-0.001) -> -139.17336 | I84: =MIN(I82,-0.001) -> -0.001 | J84: =MIN(J82,-0.001) -> -0.001 | K84: =SUM($D$82:K82)-SUM($D$84:J84) -> 3577.2446 | L84: =SUM($D$82:L82)-SUM($D$84:K84) -> 183.72007 | M84: =SUM($D$82:M82)-SUM($D$84:L84) -> 168.63573 | N84: =SUM($D$82:N82)-SUM($D$84:M84) -> 161.6995 | O84: =SUM($D$82:O82)-SUM($D$84:N84) -> 165.62767 | P84: =SUM($D$82:P82)-SUM($D$84:O84) -> 206.07793 | Q84: =SUM($D$82:Q82)-SUM($D$84:P84) -> 234.41429 | R84: =SUM($D$82:R82)-SUM($D$84:Q84) -> 258.21579 | S84: =SUM($D$82:S82)-SUM($D$84:R84) -> 12407.052
A85: =IF(AND(D71<0,D85>=D65),"Error","") | B85: IRR - без TV | D85: =IF(IRR(D83:S83)<0,"не применимо",IRR(D83:S83)) -> 0.14418346 | E85: =IFERROR(ROUND(D85,5),"-")=IFERROR(ROUND(CF_15!D85,5),"-") -> TRUE
A86: =IF(AND(D72<0,D86>=D65),"Error","") | B86: IRR - c TV | D86: =IF(IRR(D84:S84)<0,"Неприменимо",IRR(D84:S84)) -> 0.22612661 | E86: =IFERROR(ROUND(D86,5),"-")=IFERROR(ROUND(CF_15!D86,5),"-") -> TRUE
B89: Показатели проекта на собственный капитал (FCFE)
B90: Без учета терминальной стоимости
B91: NPV | D91: =D71 -> 67.805055
B92: IRR | D92: =D85 -> 0.14418346
B93: PBP | D93: =D75 -> 6
B94: DPBP | D94: =D79 -> 14
B95: С учетом терминальной стоимости
B96: NPV | D96: =D72 -> 998.27965
B97: IRR | D97: =D86 -> 0.22612661
B98: PBP | D98: =D76 -> 6
B99: DPBP | D99: =D80 -> 14
B102: Показатели проекта для компании (FCFF) | D102: =D5 -> 2022 | E102: =E5 -> 2023 | F102: =F5 -> 2024 | G102: =G5 -> 2025 | H102: =H5 -> 2026 | I102: =I5 -> 2027 | J102: =J5 -> 2028 | K102: =K5 -> 2029 | ... T102: =T5 -> 2038
B103: ИТОГО, Чистая операционная прибыль/убыток | D103: =D24 -> 0 | E103: =E24 -> 0 | F103: =F24 -> 0 | G103: =G24 -> 104.28256 | H103: =H24 -> 1438.7461 | I103: =I24 -> 2414.1395 | J103: =J24 -> 2288.5779 | K103: =K24 -> 973.7917 | ... T103: =T24 -> 1364.6871
B104: Минус: амортизация | D104: =D26 -> 0 | E104: =E26 -> 0 | F104: =F26 -> 0 | G104: =G26 -> -43.883903 | H104: =H26 -> -160.74932 | I104: =I26 -> -233.73084 | J104: =J26 -> -233.73084 | K104: =K26 -> -233.73084 | ... T104: =T26 -> -233.73084
B105: Минус: себестоимость резиденций | D105: =D27 -> 0 | E105: =E27 -> 0 | F105: =F27 -> 0 | G105: =G27 -> 0 | H105: =H27 -> -406.32596 | I105: =I27 -> -650.12153 | J105: =J27 -> -568.85634 | K105: =K27 -> 0 | ... T105: =T27 -> 0
...

Sheet CF_15
A1: 1
B3: ДЕНЕЖНЫЕ ПОТОКИ ОТ РЕАЛИЗАЦИИ ПРОЕКТА
T4: Постпрогноз
D5: =YEAR(D6) -> 2022 | E5: =D5+1 -> 2023 | F5: =E5+1 -> 2024 | G5: =F5+1 -> 2025 | H5: =G5+1 -> 2026 | I5: =H5+1 -> 2027 | J5: =I5+1 -> 2028 | K5: =J5+1 -> 2029 | L5: =K5+1 -> 2030 | ... T5: =S5+1 -> 2038
B6: НАЧАЛО ПЕРИОДА | C6: Сумма | D6: =Вводные!D4 -> 44593 | E6: =DATE(E5,1,1) -> 44927 | F6: =DATE(F5,1,1) -> 45292 | G6: =DATE(G5,1,1) -> 45658 | H6: =DATE(H5,1,1) -> 46023 | I6: =DATE(I5,1,1) -> 46388 | J6: =DATE(J5,1,1) -> 46753 | K6: =DATE(K5,1,1) -> 47119 | L6: =DATE(L5,1,1) -> 47484 | ... T6: =DATE(T5,1,1) -> 50406
B7: КОНЕЦ ПЕРИОДА | C7: до термин. | D7: =DATE(D5,12,31) -> 44926 | E7: =DATE(E5,12,31) -> 45291 | F7: =DATE(F5,12,31) -> 45657 | G7: =DATE(G5,12,31) -> 46022 | H7: =DATE(H5,12,31) -> 46387 | I7: =DATE(I5,12,31) -> 46752 | J7: =DATE(J5,12,31) -> 47118 | K7: =DATE(K5,12,31) -> 47483 | ... T7: =DATE(T5,12,31) -> 50770
A8: Руб./номер | B8: ДНЕЙ В ПЕРИОД | C8: года | D8: =D7-D6+1 -> 334 | E8: =E7-E6+1 -> 365 | F8: =F7-F6+1 -> 366 | G8: =G7-G6+1 -> 365 | H8: =H7-H6+1 -> 365 | I8: =I7-I6+1 -> 365 | J8: =J7-J6+1 -> 366 | K8: =K7-K6+1 -> 365 | ... T8: =T7-T6+1 -> 365
B9: Операционная прибыль (без НДС) | V9: Дисконт
A10: =C10/Объекты!F11 -> 23959267 | B10: Гостиничная составляющая | C10: =SUM(D10:S10) -> 1.339323e+10 | D10: =IFERROR(LOOKUP(D5,СВОД_PL!$D$3:$T$3,СВОД_PL!$D$71:$T$71),0) -> 0 | E10: =IFERROR(LOOKUP(E5,СВОД_PL!$D$3:$T$3,СВОД_PL!$D$71:$T$71),0) -> 0 | F10: =IFERROR(LOOKUP(F5,СВОД_PL!$D$3:$T$3,СВОД_PL!$D$71:$T$71),0) -> 0 | G10: =IFERROR(LOOKUP(G5,СВОД_PL!$D$3:$T$3,СВОД_PL!$D$71:$T$71),0) -> 1.5821053e+08 | H10: =IFERROR(LOOKUP(H5,СВОД_PL!$D$3:$T$3,СВОД_PL!$D$71:$T$71),0) -> 5.5255702e+08 | I10: =IFERROR(LOOKUP(I5,СВОД_PL!$D$3:$T$3,СВОД_PL!$D$71:$T$71),0) -> 8.7088409e+08 | J10: =IFERROR(LOOKUP(J5,СВОД_PL!$D$3:$T$3,СВОД_PL!$D$71:$T$71),0) -> 8.8358985e+08 | K10: =IFERROR(LOOKUP(K5,СВОД_PL!$D$3:$T$3,СВОД_PL!$D$71:$T$71),0) -> 1.0076994e+09 | ... T10: =IFERROR(LOOKUP(T5,СВОД_PL!$D$3:$T$3,СВОД_PL!$D$71:$T$71),0) -> 1.4253589e+09
B11: Ресторан | C11: =SUM(D11:S11) -> 4.5063302e+08 | D11: =IFERROR(LOOKUP(D5,Ресторан!5:5,Ресторан!76:76),0) -> 0 | E11: =IFERROR(LOOKUP(E5,Ресторан!5:5,Ресторан!76:76),0) -> 0 | F11: =IFERROR(LOOKUP(F5,Ресторан!5:5,Ресторан!76:76),0) -> 0 | G11: =IFERROR(LOOKUP(G5,Ресторан!5:5,Ресторан!76:76),0) -> 3245815.9 | H11: =IFERROR(LOOKUP(H5,Ресторан!5:5,Ресторан!76:76),0) -> 23501215 | I11: =IFERROR(LOOKUP(I5,Ресторан!5:5,Ресторан!76:76),0) -> 28570795 | J11: =IFERROR(LOOKUP(J5,Ресторан!5:5,Ресторан!76:76),0) -> 31519834 | K11: =IFERROR(LOOKUP(K5,Ресторан!5:5,Ресторан!76:76),0) -> 33982989 | ... T11: =IFERROR(LOOKUP(T5,Ресторан!5:5,Ресторан!76:76),0) -> 48927163
B12: Многофункциональный центр и торговые площади (аренда) | C12: =SUM(D12:S12) -> 6.8155314e+08 | D12: =IFERROR(LOOKUP(D5,Retail!21:21,Retail!49:49),0) -> 0 | E12: =IFERROR(LOOKUP(E5,Retail!21:21,Retail!49:49),0) -> 0 | F12: =IFERROR(LOOKUP(F5,Retail!21:21,Retail!49:49),0) -> 0 | G12: =IFERROR(LOOKUP(G5,Retail!21:21,Retail!49:49),0) -> 12893463 | H12: =IFERROR(LOOKUP(H5,Retail!21:21,Retail!49:49),0) -> 34263066 | I12: =IFERROR(LOOKUP(I5,Retail!21:21,Retail!49:49),0) -> 40583045 | J12: =IFERROR(LOOKUP(J5,Retail!21:21,Retail!49:49),0) -> 49459292 | K12: =IFERROR(LOOKUP(K5,Retail!21:21,Retail!49:49),0) -> 51437664 | ... T12: =IFERROR(LOOKUP(T5,Retail!21:21,Retail!49:49),0) -> 73211835
B13: Платная парковка | C13: =SUM(D13:S13) -> 54351311 | D13: =IFERROR(LOOKUP(D5,Паркинг_PL!$34:$34,Паркинг_PL!42:42),0) -> 0 | E13: =IFERROR(LOOKUP(E5,Паркинг_PL!$34:$34,Паркинг_PL!42:42),0) -> 0 | F13: =IFERROR(LOOKUP(F5,Паркинг_PL!$34:$34,Паркинг_PL!42:42),0) -> 0 | G13: =IFERROR(LOOKUP(G5,Паркинг_PL!$34:$34,Паркинг_PL!42:42),0) -> 61355.33 | H13: =IFERROR(LOOKUP(H5,Паркинг_PL!$34:$34,Паркинг_PL!42:42),0) -> 1817120.3 | I13: =IFERROR(LOOKUP(I5,Паркинг_PL!$34:$34,Паркинг_PL!42:42),0) -> 2744823.9 | J13: =IFERROR(LOOKUP(J5,Паркинг_PL!$34:$34,Паркинг_PL!42:42),0) -> 3711644.9 | K13: =IFERROR(LOOKUP(K5,Паркинг_PL!$34:$34,Паркинг_PL!42:42),0) -> 4293855.3 | ... T13: =IFERROR(LOOKUP(T5,Паркинг_PL!$34:$34,Паркинг_PL!42:42),0) -> 5904577.6 | V13: =SUMPRODUCT(G12:S12,G67:S67)+SUMPRODUCT(G11:S11,G67:S67)+SUMPRODUCT(G13:S13,G67:S67)+SUMPRODUCT(G10:S10,G67:S67) -> 3.1654041e+09
A14: =C14/Объекты!F13 -> 10248038 | B14: Продажа резиденций | C14: =SUM(D14:S14) -> 3.9454946e+09 | D14: =IFERROR(SUMIF(ПРОДАЖА_lease_back!$8:$8,D5,ПРОДАЖА_lease_back!$41:$41),0) -> 0 | E14: =IFERROR(SUMIF(ПРОДАЖА_lease_back!$8:$8,E5,ПРОДАЖА_lease_back!$41:$41),0) -> 0 | F14: =IFERROR(SUMIF(ПРОДАЖА_lease_back!$8:$8,F5,ПРОДАЖА_lease_back!$41:$41),0) -> 0 | G14: =IFERROR(SUMIF(ПРОДАЖА_lease_back!$8:$8,G5,ПРОДАЖА_lease_back!$41:$41),0) -> 0 | H14: =IFERROR(SUMIF(ПРОДАЖА_lease_back!$8:$8,H5,ПРОДАЖА_lease_back!$41:$41),0) -> 9.2323553e+08 | I14: =IFERROR(SUMIF(ПРОДАЖА_lease_back!$8:$8,I5,ПРОДАЖА_lease_back!$41:$41),0) -> 1.5857869e+09 | J14: =IFERROR(SUMIF(ПРОДАЖА_lease_back!$8:$8,J5,ПРОДАЖА_lease_back!$41:$41),0) -> 1.4364722e+09 | K14: =IFERROR(SUMIF(ПРОДАЖА_lease_back!$8:$8,K5,ПРОДАЖА_lease_back!$41:$41),0) -> 0 | ... T14: =IFERROR(SUMIF(ПРОДАЖА_lease_back!$8:$8,T5,ПРОДАЖА_lease_back!$41:$41),0) -> 0 | V14: =SUMPRODUCT(D14:S14,$D$67:$S$67) -> 1.6416697e+09
B15: ВСЕГО, операционная прибыль | C15: =SUM(D15:S15) -> 1.8525262e+10 | D15: =SUM(D10:D14) -> 0 | E15: =SUM(E10:E14) -> 0 | F15: =SUM(F10:F14) -> 0 | G15: =SUM(G10:G14) -> 1.7441116e+08 | H15: =SUM(H10:H14) -> 1.5353739e+09 | I15: =SUM(I10:I14) -> 2.5285696e+09 | J15: =SUM(J10:J14) -> 2.4047529e+09 | K15: =SUM(K10:K14) -> 1.0974139e+09 | ... T15: =SUM(T10:T14) -> 1.5534025e+09
B16: Расходы общекурортные
B17: Расходы на администрацию и управление | D17: =-LOOKUP(D$5,'Курорт-расходы'!$10:$10,'Курорт-расходы'!21:21) -> 0 | E17: =-LOOKUP(E$5,'Курорт-расходы'!$10:$10,'Курорт-расходы'!21:21) -> 0 | F17: =-LOOKUP(F$5,'Курорт-расходы'!$10:$10,'Курорт-расходы'!21:21) -> 0 | G17: =-LOOKUP(G$5,'Курорт-расходы'!$10:$10,'Курорт-расходы'!21:21) -> -29183266 | H17: =-LOOKUP(H$5,'Курорт-расходы'!$10:$10,'Курорт-расходы'!21:21) -> -35884077 | I17: =-LOOKUP(I$5,'Курорт-расходы'!$10:$10,'Курорт-расходы'!21:21) -> -39746300 | J17: =-LOOKUP(J$5,'Курорт-расходы'!$10:$10,'Курорт-расходы'!21:21) -> -40076614 | K17: =-LOOKUP(K$5,'Курорт-расходы'!$10:$10,'Курорт-расходы'!21:21) -> -42181946 | ... T17: =-LOOKUP(T$5,'Курорт-расходы'!$10:$10,'Курорт-расходы'!21:21) -> -60519303
B18: Расходы на продажи и маркетинг | D18: =-LOOKUP(D$5,'Курорт-расходы'!$10:$10,'Курорт-расходы'!22:22) -> 0 | E18: =-LOOKUP(E$5,'Курорт-расходы'!$10:$10,'Курорт-расходы'!22:22) -> 0 | F18: =-LOOKUP(F$5,'Курорт-расходы'!$10:$10,'Курорт-расходы'!22:22) -> 0 | G18: =-LOOKUP(G$5,'Курорт-расходы'!$10:$10,'Курорт-расходы'!28:28) -> -16414222 | H18: =-LOOKUP(H$5,'Курорт-расходы'!$10:$10,'Курорт-расходы'!28:28) -> -23176155 | I18: =-LOOKUP(I$5,'Курорт-расходы'!$10:$10,'Курорт-расходы'!28:28) -> -32341120 | J18: =-LOOKUP(J$5,'Курорт-расходы'!$10:$10,'Курорт-расходы'!28:28) -> -33547511 | K18: =-LOOKUP(K$5,'Курорт-расходы'!$10:$10,'Курорт-расходы'!28:28) -> -36005562 | L18: =-LOOKUP(L$5,'Курорт-расходы'!$10:$10,'Курорт-расходы'!28:28) -> -38227201 | M18: =-LOOKUP(M$5,'Курорт-расходы'!$10:$10,'Курорт-расходы'!28:28) -> -39756289 | N18: =-LOOKUP(N$5,'Курорт-расходы'!$10:$10,'Курорт-расходы'!28:28) -> -41432533 | ... T18: =-LOOKUP(T$5,'Курорт-расходы'!$10:$10,'Курорт-расходы'!28:28) -> -52316564
B19: Расходы на текущий ремонт и эксплуатацию | D19: =-LOOKUP(D$5,'Курорт-расходы'!$10:$10,'Курорт-расходы'!23:23) -> 0 | E19: =-LOOKUP(E$5,'Курорт-расходы'!$10:$10,'Курорт-расходы'!23:23) -> 0 | F19: =-LOOKUP(F$5,'Курорт-расходы'!$10:$10,'Курорт-расходы'!23:23) -> 0 | G19: =-LOOKUP(G$5,'Курорт-расходы'!$10:$10,'Курорт-расходы'!35:35) -> -20222372 | H19: =-LOOKUP(H$5,'Курорт-расходы'!$10:$10,'Курорт-расходы'!35:35) -> -27252648 | I19: =-LOOKUP(I$5,'Курорт-расходы'!$10:$10,'Курорт-расходы'!35:35) -> -28505889 | J19: =-LOOKUP(J$5,'Курорт-расходы'!$10:$10,'Курорт-расходы'!35:35) -> -28364772 | K19: =-LOOKUP(K$5,'Курорт-расходы'!$10:$10,'Курорт-расходы'!35:35) -> -30280669 | L19: =-LOOKUP(L$5,'Курорт-расходы'!$10:$10,'Курорт-расходы'!35:35) -> -32038887 | M19: =-LOOKUP(M$5,'Курорт-расходы'!$10:$10,'Курорт-расходы'!35:35) -> -33320442 | N19: =-LOOKUP(N$5,'Курорт-расходы'!$10:$10,'Курорт-расходы'!35:35) -> -34713455 | ... T19: =-LOOKUP(T$5,'Курорт-расходы'!$10:$10,'Курорт-расходы'!35:35) -> -43847429
B20: Коммунальные расходы по курорту | D20: =-LOOKUP(D$5,'Курорт-расходы'!$10:$10,'Курорт-расходы'!24:24) -> 0 | E20: =-LOOKUP(E$5,'Курорт-расходы'!$10:$10,'Курорт-расходы'!24:24) -> 0 | F20: =-LOOKUP(F$5,'Курорт-расходы'!$10:$10,'Курорт-расходы'!24:24) -> 0 | G20: =-LOOKUP(G$5,'Курорт-расходы'!$10:$10,'Курорт-расходы'!42:42) -> -2052354.7 | H20: =-LOOKUP(H$5,'Курорт-расходы'!$10:$10,'Курорт-расходы'!42:42) -> -8135089 | I20: =-LOOKUP(I$5,'Курорт-расходы'!$10:$10,'Курорт-расходы'!42:42) -> -11733403 | J20: =-LOOKUP(J$5,'Курорт-расходы'!$10:$10,'Курорт-расходы'!42:42) -> -12159112 | K20: =-LOOKUP(K$5,'Курорт-расходы'!$10:$10,'Курорт-расходы'!42:42) -> -13203551 | L20: =-LOOKUP(L$5,'Курорт-расходы'!$10:$10,'Курорт-расходы'!42:42) -> -14122402 | M20: =-LOOKUP(M$5,'Курорт-расходы'!$10:$10,'Курорт-расходы'!42:42) -> -14687298 | N20: =-LOOKUP(N$5,'Курорт-расходы'!$10:$10,'Курорт-расходы'!42:42) -> -15317786 | ... T20: =-LOOKUP(T$5,'Курорт-расходы'!$10:$10,'Курорт-расходы'!42:42) -> -19327482
B21: Налог на имущество - курорт | D21: =-IFERROR(LOOKUP(D$5,Амортизация!$295:$295,Амортизация!314:314),0) -> 0 | E21: =-IFERROR(LOOKUP(E$5,Амортизация!$295:$295,Амортизация!314:314),0) -> 0 | F21: =-IFERROR(LOOKUP(F$5,Амортизация!$295:$295,Амортизация!314:314),0) -> 0 | G21: =-IFERROR(LOOKUP(G$5,Амортизация!$295:$295,Амортизация!314:314),0) -> 0 | H21: =-IFERROR(LOOKUP(H$5,Амортизация!$295:$295,Амортизация!314:314),0) -> 0 | I21: =-IFERROR(LOOKUP(I5,Амортизация!295:295,Амортизация!314:314),0) -> 0 | J21: =-IFERROR(LOOKUP(J5,Амортизация!295:295,Амортизация!314:314),0) -> 0 | K21: =-IFERROR(LOOKUP(K5,Амортизация!295:295,Амортизация!314:314),0) -> 0 | L21: =-IFERROR(LOOKUP(L5,Амортизация!295:295,Амортизация!314:314),0) -> 0 | M21: =-IFERROR(LOOKUP(M5,Амортизация!295:295,Амортизация!314:314),0) -> 0 | N21: =-IFERROR(LOOKUP(N5,Амортизация!295:295,Амортизация!314:314),0) -> 0 | O21: =-IFERROR(LOOKUP(O5,Амортизация!295:295,Амортизация!314:314),0) -> 0 | P21: =-IFERROR(LOOKUP(P5,Амортизация!295:295,Амортизация!314:314),0) -> 0 | ... T21: =-IFERROR(LOOKUP(T5,Амортизация!295:295,Амортизация!314:314),0) -> -11442580
B22: Расходы на страхование - курорт | D22: =-IFERROR(LOOKUP(D$5,Амортизация!$295:$295,Амортизация!336:336),0) -> 0 | E22: =-IFERROR(LOOKUP(E$5,Амортизация!$295:$295,Амортизация!336:336),0) -> 0 | F22: =-IFERROR(LOOKUP(F$5,Амортизация!$295:$295,Амортизация!336:336),0) -> 0 | G22: =-IFERROR(LOOKUP(G$5,Амортизация!$295:$295,Амортизация!336:336),0) -> -2256391 | H22: =-IFERROR(LOOKUP(H$5,Амортизация!$295:$295,Амортизация!336:336),0) -> -2179903.2 | I22: =-IFERROR(LOOKUP(I$5,Амортизация!$295:$295,Амортизация!336:336),0) -> -2103415.4 | J22: =-IFERROR(LOOKUP(J$5,Амортизация!$295:$295,Амортизация!336:336),0) -> -2026927.5 | K22: =-IFERROR(LOOKUP(K$5,Амортизация!$295:$295,Амортизация!336:336),0) -> -1950439.7 | ... T22: =-IFERROR(LOOKUP(T$5,Амортизация!$295:$295,Амортизация!336:336),0) -> -1262049.2
A23: =C23/Объекты!$F$14 -> -1862002.2 | B23: ВСЕГО, расходы | C23: =SUM(D23:S23) -> -1.7577301e+09 | D23: =SUM(D17:D22) -> 0 | E23: =SUM(E17:E22) -> 0 | F23: =SUM(F17:F22) -> 0 | G23: =SUM(G17:G22) -> -70128605 | H23: =SUM(H17:H22) -> -96627872 | I23: =SUM(I17:I22) -> -1.1443013e+08 | J23: =SUM(J17:J22) -> -1.1617494e+08 | K23: =SUM(K17:K22) -> -1.2362217e+08 | ... T23: =SUM(T17:T22) -> -1.8871541e+08 | V23: =SUMPRODUCT(D23:S23,$D$67:$S$67) -> -4.0576285e+08
A24: =C24/Объекты!$F$14 -> 17762216 | B24: ИТОГО, Чистая операционная прибыль/убыток | C24: =SUM(D24:S24) -> 1.6767532e+10 | D24: =D15+D23 -> 0 | E24: =E15+E23 -> 0 | F24: =F15+F23 -> 0 | G24: =G15+G23 -> 1.0428256e+08 | H24: =H15+H23 -> 1.4387461e+09 | I24: =I15+I23 -> 2.4141395e+09 | J24: =J15+J23 -> 2.2885779e+09 | K24: =K15+K23 -> 9.737917e+08 | ... T24: =T15+T23 -> 1.3646871e+09 | V24: =SUMPRODUCT(D24:S24,$D$67:$S$67) -> 4.401311e+09
B25: Минус: проценты про кредиту начисленные | C25: =SUM(D25:S25) -> -2.3386574e+09 | D25: =-D183 -> 0 | E25: =-E183 -> -4000000 | F25: =-F183 -> -89844143 | G25: =-G183 -> -2.0816635e+08 | H25: =-H183 -> -2.9639888e+08 | I25: =-I183 -> -2.61668e+08 | J25: =-J183 -> -2.53444e+08 | K25: =-K183 -> -2.39588e+08 | ... T25: =-T183 -> 0
B26: Минус: амортизация | C26: =SUM(D26:S26) -> -2.7756724e+09 | D26: =-LOOKUP(D$5,Амортизация!$252:$252,Амортизация!$255:$255) -> 0 | E26: =-LOOKUP(E$5,Амортизация!$252:$252,Амортизация!$255:$255) -> 0 | F26: =-LOOKUP(F$5,Амортизация!$252:$252,Амортизация!$255:$255) -> 0 | G26: =-LOOKUP(G$5,Амортизация!$252:$252,Амортизация!$255:$255) -> -43883903 | H26: =-LOOKUP(H$5,Амортизация!$252:$252,Амортизация!$255:$255) -> -1.6074932e+08 | I26: =-LOOKUP(I$5,Амортизация!$252:$252,Амортизация!$255:$255) -> -2.3373084e+08 | J26: =-LOOKUP(J$5,Амортизация!$252:$252,Амортизация!$255:$255) -> -2.3373084e+08 | K26: =-LOOKUP(K$5,Амортизация!$252:$252,Амортизация!$255:$255) -> -2.3373084e+08 | ... T26: =-LOOKUP(T$5,Амортизация!$252:$252,Амортизация!$255:$255) -> -2.3373084e+08
B27: Минус: себестоимость резиденций | C27: =SUM(D27:S27) -> -1.6253038e+09 | D27: =SUMIF(ПРОДАЖА_lease_back!8:8,D5,ПРОДАЖА_lease_back!33:33) -> 0 | E27: =SUMIF(ПРОДАЖА_lease_back!8:8,E5,ПРОДАЖА_lease_back!33:33) -> 0 | F27: =SUMIF(ПРОДАЖА_lease_back!8:8,F5,ПРОДАЖА_lease_back!33:33) -> 0 | G27: =SUMIF(ПРОДАЖА_lease_back!8:8,G5,ПРОДАЖА_lease_back!33:33) -> 0 | H27: =SUMIF(ПРОДАЖА_lease_back!8:8,H5,ПРОДАЖА_lease_back!33:33) -> -4.0632596e+08 | I27: =SUMIF(ПРОДАЖА_lease_back!8:8,I5,ПРОДАЖА_lease_back!33:33) -> -6.5012153e+08 | J27: =SUMIF(ПРОДАЖА_lease_back!8:8,J5,ПРОДАЖА_lease_back!33:33) -> -5.6885634e+08 | K27: =SUMIF(ПРОДАЖА_lease_back!8:8,K5,ПРОДАЖА_lease_back!33:33) -> 0 | ... T27: =SUMIF(ПРОДАЖА_lease_back!8:8,T5,ПРОДАЖА_lease_back!33:33) -> 0
B28: Равно: прибыль / убыток за период | D28: =SUM(D24:D27) -> 0 | E28: =SUM(E24:E27) -> -4000000 | F28: =SUM(F24:F27) -> -89844143 | G28: =SUM(G24:G27) -> -1.477677e+08 | H28: =SUM(H24:H27) -> 5.7527191e+08 | I28: =SUM(I24:I27) -> 1.2686191e+09 | J28: =SUM(J24:J27) -> 1.2325467e+09 | K28: =SUM(K24:K27) -> 5.0047287e+08 | ... T28: =SUM(T24:T27) -> 1.1309563e+09
B29: Итого: накопленный убыток | D29: =D28 -> 0 | E29: =IF(E28<0,E28,0)+D31 -> -4000000 | F29: =IF(F28<0,F28,0)+E31 -> -93844143 | G29: =IF(G28<0,G28,0)+F31 -> -2.4161184e+08 | H29: =IF(H28<0,H28,0)+G31 -> -2.4161184e+08 | I29: =IF(I28<0,I28,0)+H31 -> 0 | J29: =IF(J28<0,J28,0)+I31 -> 0 | K29: =IF(K28<0,K28,0)+J31 -> 0 | L29: =IF(L28<0,L28,0)+K31 -> 0 | ... T29: =IF(T28<0,T28,0)+S31 -> 0
B30: Накопленный убыток к зачету | E30: =IF(E29<0,(IF(E28>0,MIN(-E29,E28),0)),0) -> 0 | F30: =IF(F29<0,(IF(F28>0,MIN(-F29,F28),0)),0) -> 0 | G30: =IF(G29<0,(IF(G28>0,MIN(-G29,G28),0)),0) -> 0 | H30: =IF(H29<0,(IF(H28>0,MIN(-H29,H28),0)),0) -> 2.4161184e+08 | I30: =IF(I29<0,(IF(I28>0,MIN(-I29,I28),0)),0) -> 0 | J30: =IF(J29<0,(IF(J28>0,MIN(-J29,J28),0)),0) -> 0 | K30: =IF(K29<0,(IF(K28>0,MIN(-K29,K28),0)),0) -> 0 | L30: =IF(L29<0,(IF(L28>0,MIN(-L29,L28),0)),0) -> 0 | ... T30: =IF(T29<0,(IF(T28>0,MIN(-T29,T28),0)),0) -> 0
B31: Итого: накопленный убыток к переносу | E31: =IF((E29+E30)<0,(E29+E30),0) -> -4000000 | F31: =IF((F29+F30)<0,(F29+F30),0) -> -93844143 | G31: =IF((G29+G30)<0,(G29+G30),0) -> -2.4161184e+08 | H31: =IF((H29+H30)<0,(H29+H30),0) -> 0 | I31: =IF((I29+I30)<0,(I29+I30),0) -> 0 | J31: =IF((J29+J30)<0,(J29+J30),0) -> 0 | K31: =IF((K29+K30)<0,(K29+K30),0) -> 0 | L31: =IF((L29+L30)<0,(L29+L30),0) -> 0 | ... T31: =IF((T29+T30)<0,(T29+T30),0) -> 0
B32: Итого: налоговая база | E32: =IF((E28-E30)<0,0,(E28-E30)) -> 0 | F32: =IF((F28-F30)<0,0,(F28-F30)) -> 0 | G32: =IF((G28-G30)<0,0,(G28-G30)) -> 0 | H32: =IF((H28-H30)<0,0,(H28-H30)) -> 3.3366006e+08 | I32: =IF((I28-I30)<0,0,(I28-I30)) -> 1.2686191e+09 | J32: =IF((J28-J30)<0,0,(J28-J30)) -> 1.2325467e+09 | K32: =IF((K28-K30)<0,0,(K28-K30)) -> 5.0047287e+08 | L32: =IF((L28-L30)<0,0,(L28-L30)) -> 6.1205826e+08 | ... T32: =IF((T28-T30)<0,0,(T28-T30)) -> 1.1309563e+09
B33: Ставка налога на прибыль | D33: =IF(D5<=2024,Вводные!$H$27,Вводные!$I$27) -> 0.135 | E33: =IF(E5<=2024,Вводные!$H$27,Вводные!$I$27) -> 0.135 | F33: =IF(F5<=2024,Вводные!$H$27,Вводные!$I$27) -> 0.135 | G33: =IF(G5<=2024,Вводные!$H$27,Вводные!$I$27) -> 0.155 | H33: =IF(H5<=2024,Вводные!$H$27,Вводные!$I$27) -> 0.155 | I33: =IF(I5<=2024,Вводные!$H$27,Вводные!$I$27) -> 0.155 | J33: =IF(J5<=2024,Вводные!$H$27,Вводные!$I$27) -> 0.155 | K33: =IF(K5<=2024,Вводные!$H$27,Вводные!$I$27) -> 0.155 | ... T33: =IF(T5<=2024,Вводные!$H$27,Вводные!$I$27) -> 0.155
B34: Налог на прибыль | C34: =SUM(D34:S34) -> -1.5543243e+09 | D34: =-D33*D32 -> 0 | E34: =-E33*E32 -> 0 | F34: =-F33*F32 -> 0 | G34: =-G33*G32 -> 0 | H34: =-H33*H32 -> -51717310 | I34: =-I33*I32 -> -1.9663596e+08 | J34: =-J33*J32 -> -1.9104475e+08 | K34: =-K33*K32 -> -77573294 | ... T34: =-T33*T32 -> -1.7529822e+08 | V34: =SUMPRODUCT(D34:S34,$D$67:$S$67) -> -3.5635576e+08
A35: =C35/Объекты!$F$14 -> 16115686 | B35: ИТОГО, Чистая операционная прибыль после налога | C35: =SUM(D35:S35) -> 1.5213208e+10 | D35: =D24+D34 -> 0 | E35: =E24+E34 -> 0 | F35: =F24+F34 -> 0 | G35: =G24+G34 -> 1.0428256e+08 | H35: =H24+H34 -> 1.3870288e+09 | I35: =I24+I34 -> 2.2175035e+09 | J35: =J24+J34 -> 2.0975332e+09 | K35: =K24+K34 -> 8.9621841e+08 | ... T35: =T24+T34 -> 1.1893889e+09 | V35: =SUMPRODUCT(D35:S35,$D$67:$S$67) -> 4.0449552e+09
B36: Инвестиционная деятельность
B37: Минус: затраты на строительство | C37: =SUM(D37:S37) -> -1.1472203e+10 | D37: =-Строительство!G53 -> -1.6031818e+08 | E37: =-Строительство!H53 -> -3.0482053e+09 | F37: =-Строительство!I53 -> -4.2257933e+09 | G37: =-Строительство!J53 -> -3.1511617e+09 | H37: =-Строительство!K53 -> -8.8672478e+08 | I37: =-Строительство!L53 -> 0 | J37: =-Строительство!M53 -> 0 | K37: =-Строительство!N53 -> 0 | ... S37: =-Строительство!V53 -> 0 | V37: =SUMPRODUCT(D37:S37,$D$67:$S$67) -> -7.7229187e+09
B38: Минус: земельные платежи инвестиционного периода | C38: =SUM(D38:S38) -> -1319896.7 | D38: =-LOOKUP(D5,Земля!31:31,Земля!32:32) -> -413939.45 | E38: =-LOOKUP(E5,Земля!31:31,Земля!32:32) -> -452358.98 | F38: =-LOOKUP(F5,Земля!31:31,Земля!32:32) -> -453598.32 | G38: =-LOOKUP(G5,Земля!31:31,Земля!32:32) -> 0 | H38: =-LOOKUP(H5,Земля!31:31,Земля!32:32) -> 0 | I38: =-LOOKUP(I5,Земля!31:31,Земля!32:32) -> 0 | J38: =-LOOKUP(J5,Земля!31:31,Земля!32:32) -> 0 | K38: =-LOOKUP(K5,Земля!31:31,Земля!32:32) -> 0 | ... S38: =-LOOKUP(S5,Земля!31:31,Земля!32:32) -> 0 | V38: =SUMPRODUCT(D38:S38,$D$67:$S$67) -> -1054395.5
B39: Плюс: возмещение строительного НДС | C39: =SUM(D39:S39) -> 1.9120339e+09 | D39: =Строительство!G54 -> 0 | E39: =Строительство!H54 -> 26719697 | F39: =Строительство!I54 -> 5.0803422e+08 | G39: =Строительство!J54 -> 7.0429888e+08 | H39: =Строительство!K54 -> 5.2519362e+08 | I39: =Строительство!L54 -> 1.4778746e+08 | J39: =Строительство!M54 -> 0 | K39: =Строительство!N54 -> 0 | ... S39: =Строительство!V54 -> 0 | V39: =SUMPRODUCT(D39:S39,$D$67:$S$67) -> 1.0975609e+09
B40: FCFF | C40: =SUM(D40:S40) -> 5.6517186e+09 | D40: =SUM(D35:D39) -> -1.6073212e+08 | E40: =SUM(E35:E39) -> -3.021938e+09 | F40: =SUM(F35:F39) -> -3.7182127e+09 | G40: =SUM(G35:G39) -> -2.3425803e+09 | H40: =SUM(H35:H39) -> 1.0254976e+09 | I40: =SUM(I35:I39) -> 2.365291e+09 | J40: =SUM(J35:J39) -> 2.0975332e+09 | K40: =SUM(K35:K39) -> 8.9621841e+08 | ... S40: =SUM(S35:S39) -> 1.1371024e+09 | V40: =SUMPRODUCT(D40:S40,$D$67:$S$67) -> -2.581457e+09
B41: Финансовая деятельность
B42: Собственные средства | C42: =SUM(D42:S42) -> 2.2746748e+09 | D42: =IF(SUM(C48,D40,D44,D45,D43)<0,-SUM(C48,D40,D44,D45,D43),0) -> 60732124 | E42: =IF(SUM(D48,E40,E44,E45,E43)<0,-SUM(D48,E40,E44,E45,E43),0) -> 8.7983437e+08 | F42: =IF(SUM(E48,F40,F44,F45,F43)<0,-SUM(E48,F40,F44,F45,F43),0) -> 8.5000151e+08 | G42: =IF(SUM(F48,G40,G44,G45,G43)<0,-SUM(F48,G40,G44,G45,G43),0) -> 3.4493343e+08 | H42: =IF(SUM(G48,H40,H44,H45,H43)<0,-SUM(G48,H40,H44,H45,H43),0) -> 1.3917336e+08 | I42: =IF(SUM(H48,I40,I44,I45,I43)<0,-SUM(H48,I40,I44,I45,I43),0) -> 0 | J42: =IF(SUM(I48,J40,J44,J45,J43)<0,-SUM(I48,J40,J44,J45,J43),0) -> 0 | K42: =IF(SUM(J48,K40,K44,K45,K43)<0,-SUM(J48,K40,K44,K45,K43),0) -> 0 | ... S42: =IF(SUM(R48,S40,S44,S45,S43)<0,-SUM(R48,S40,S44,S45,S43),0) -> 0
A43: =C43=C180 -> TRUE | B43: Плюс: кредит | C43: =SUM(D43:S43) -> 8.028e+09 | D43: =D180 -> 1e+08 | E43: =E180 -> 2.1461036e+09 | F43: =F180 -> 2.9580553e+09 | G43: =G180 -> 2.2058132e+09 | H43: =H180 -> 6.1802792e+08 | I43: =I180 -> 0 | J43: =J180 -> 0 | K43: =K180 -> 0 | ... R43: =R180 -> 0 | V43: =SUMPRODUCT(D43:S43,$D$67:$S$67) -> 5.4032183e+09
A44: =-C44=C183 -> TRUE | B44: Минус: проценты по кредиту | C44: =SUM(D44:S44) -> -2.3386574e+09 | D44: =D25 -> 0 | E44: =E25 -> -4000000 | F44: =F25 -> -89844143 | G44: =G25 -> -2.0816635e+08 | H44: =H25 -> -2.9639888e+08 | I44: =I25 -> -2.61668e+08 | J44: =J25 -> -2.53444e+08 | K44: =K25 -> -2.39588e+08 | ... S44: =S25 -> 0 | V44: =SUMPRODUCT(D44:S44,$D$67:$S$67) -> -7.9535064e+08
A45: =-C45=C43 -> FALSE | B45: Минус: тело долга | C45: =SUM(D45:S45) -> -8028000000 | D45: =-D184 -> 0 | E45: =-E184 -> 0 | F45: =-F184 -> 0 | G45: =-G184 -> 0 | H45: =-H184 -> -1486300000 | I45: =-I184 -> -205600000 | J45: =-J184 -> -346400000 | K45: =-K184 -> -475100000 | ... S45: =-S184 -> -505000000 | V45: =SUMPRODUCT(D45:S45,$D$67:$S$67) -> -1.9586056e+09
A46: =A186 -> ВНИМАНИЕ | B46: FCFE | C46: =SUM(D46:S46) -> 3.3130612e+09 | D46: =SUM(D40:D45)-D42 -> -60732124 | E46: =SUM(E40:E45)-E42 -> -8.7983437e+08 | F46: =SUM(F40:F45)-F42 -> -8.5000151e+08 | G46: =SUM(G40:G45)-G42 -> -3.4493343e+08 | H46: =SUM(H40:H45)-H42 -> -1.3917336e+08 | I46: =SUM(I40:I45)-I42 -> 1.898023e+09 | J46: =SUM(J40:J45)-J42 -> 1.4976892e+09 | K46: =SUM(K40:K45)-K42 -> 1.8153041e+08 | ... S46: =SUM(S40:S45)-S42 -> 6.3210241e+08 | V46: =SUMPRODUCT(D46:S46,$D$67:$S$67) -> 67805055 | X46: =V46=D71 -> TRUE
B47: Оборот за год | D47: =SUM(D40:D45) -> 0 | E47: =SUM(E40:E45) -> 2.4214387e-08 | F47: =SUM(F40:F45) -> 2.0861626e-07 | G47: =SUM(G40:G45) -> 0 | H47: =SUM(H40:H45) -> 0 | I47: =SUM(I40:I45) -> 1.898023e+09 | J47: =SUM(J40:J45) -> 1.4976892e+09 | K47: =SUM(K40:K45) -> 1.8153041e+08 | ... S47: =SUM(S40:S45) -> 6.3210241e+08
B48: Остаток на счете | D48: =C48+D47 -> 0 | E48: =D48+E47 -> 2.4214387e-08 | F48: =E48+F47 -> 2.3283064e-07 | G48: =F48+G47 -> 2.3283064e-07 | H48: =G48+H47 -> 2.3283064e-07 | I48: =H48+I47 -> 1.898023e+09 | J48: =I48+J47 -> 3.3957122e+09 | K48: =J48+K47 -> 3.5772426e+09 | ... S48: =R48+S47 -> 5.587736e+09
B50: Показатели проекта на собственный капитал | D50: =D5 -> 2022 | E50: =E5 -> 2023 | F50: =F5 -> 2024 | G50: =G5 -> 2025 | H50: =H5 -> 2026 | I50: =I5 -> 2027 | J50: =J5 -> 2028 | K50: =K5 -> 2029 | ... N50: =N5 -> 2032 | T50: =T4 -> Постпрогноз
B51: Терминальная стоимость
B52: Терминальная ставка капитализации | T52: 0.1
B53: Терминальная стоимость | T53: =T35/T52 -> 1.1893889e+10
B54: Комиссия брокеру, расходы при продаже % | T54: 0.01
B55: Комиссия брокеру | T55: =-T54*T53 -> -1.1893889e+08
B56: Остаточная балансовая стоимость
B57: Налогооблагаемая база | T57: =T53+T55-T56 -> 1.177495e+10
B58: Налог на прибыль, % | U58: Продажа бизнеса
B59: Налог на прибыль | T59: =-T57*T58 -> 0
B60: Остатки по кредиту | T60: 0
B61: Доход от продажи | T61: =T53+T55+T59-T60 -> 1.177495e+10
B62: Движение средств по Проекту
B63: =B46 -> FCFE | D63: =D46 -> -60732124 | E63: =E46 -> -8.7983437e+08 | F63: =F46 -> -8.5000151e+08 | G63: =G46 -> -3.4493343e+08 | H63: =H46 -> -1.3917336e+08 | I63: =I46 -> 1.898023e+09 | J63: =J46 -> 1.4976892e+09 | K63: =K46 -> 1.8153041e+08 | ... S63: =S46 -> 6.3210241e+08
B64: FCFE + TV | D64: =D63+D61 -> -60732124 | E64: =E63+E61 -> -8.7983437e+08 | F64: =F63+F61 -> -8.5000151e+08 | G64: =G63+G61 -> -3.4493343e+08 | H64: =H63+H61 -> -1.3917336e+08 | I64: =I63+I61 -> 1.898023e+09 | J64: =J63+J61 -> 1.4976892e+09 | K64: =K63+K61 -> 1.8153041e+08 | ... T64: =T63+T61 -> 1.177495e+10
B65: Ставка дисконтирования | D65: =WACC!D20 -> 0.17289342 | E65: =D65 -> 0.17289342 | F65: =E65 -> 0.17289342 | G65: =F65 -> 0.17289342 | H65: =G65 -> 0.17289342 | I65: =H65 -> 0.17289342 | J65: =I65 -> 0.17289342 | K65: =J65 -> 0.17289342 | L65: =K65 -> 0.17289342 | ... S65: =R65 -> 0.17289342 | T65: =N65 -> 0.17289342
B66: Период дисконтирования | D66: =D$8/365/2 -> 0.45753425 | E66: =D66*2+0.5 -> 1.4150685 | F66: =E66+1 -> 2.4150685 | G66: =F66+1 -> 3.4150685 | H66: =G66+1 -> 4.4150685 | I66: =H66+1 -> 5.4150685 | J66: =I66+1 -> 6.4150685 | K66: =J66+1 -> 7.4150685 | L66: =K66+1 -> 8.4150685 | M66: =L66+1 -> 9.4150685 | ... S66: =R66+1 -> 15.415068 | T66: =S66+0.5 -> 15.915068
B67: Фактор дисконтирования (с середины года) | D67: =1/(1+D65)^D66 -> 0.92963366 | E67: =1/(1+E65)^E66 -> 0.79798442 | F67: =1/(1+F65)^F66 -> 0.68035544 | G67: =1/(1+G65)^G66 -> 0.58006587 | H67: =1/(1+H65)^H66 -> 0.49455974 | I67: =1/(1+I65)^I66 -> 0.42165787 | J67: =1/(1+J65)^J66 -> 0.35950229 | K67: =1/(1+K65)^K66 -> 0.30650892 | ... T67: =1/(1+T65)^T66 -> 0.079021533
B68: Дисконтированный денежный поток - без TV | D68: =D67*D63 -> -56458627 | E68: =E67*E63 -> -7.0209412e+08 | F68: =F67*F63 -> -5.7830315e+08 | G68: =G67*G63 -> -2.0008411e+08 | H68: =H67*H63 -> -68829543 | I68: =I67*I63 -> 8.0031634e+08 | J68: =J67*J63 -> 5.384227e+08 | K68: =K67*K63 -> 55640690 | ... T68: =T67*T63 -> 0
B69: Дисконтированный денежный поток - с TV | D69: =D64*D67 -> -56458627 | E69: =E64*E67 -> -7.0209412e+08 | F69: =F64*F67 -> -5.7830315e+08 | G69: =G64*G67 -> -2.0008411e+08 | H69: =H64*H67 -> -68829543 | I69: =I64*I67 -> 8.0031634e+08 | J69: =J64*J67 -> 5.384227e+08 | K69: =K64*K67 -> 55640690 | ... T69: =T64*T67 -> 9.304746e+08
B70: Чистая текущая ст-ть проекта на дату анализа
B71: Чистая текущая ст-ть проекта на дату анализа - без TV | D71: =SUM(D68:S68) -> 67805055
B72: Чистая текущая ст-ть проекта на дату анализа - с TV | D72: =SUM(D69:T69) -> 9.9827965e+08
B73: Денежный поток накопленным итогом - без TV | D73: =SUM($D$63:D63) -> -60732124 | E73: =SUM($D$63:E63) -> -9.405665e+08 | F73: =SUM($D$63:F63) -> -1.790568e+09 | G73: =SUM($D$63:G63) -> -2.1355014e+09 | H73: =SUM($D$63:H63) -> -2.2746748e+09 | I73: =SUM($D$63:I63) -> -3.7665181e+08 | J73: =SUM($D$63:J63) -> 1.1210374e+09 | K73: =SUM($D$63:K63) -> 1.3025678e+09 | ... R73: =SUM($D$63:R63) -> 2.6809588e+09 | S73: =SUM($D$63:T63) -> 3.3130612e+09
B74: Денежный поток накопленным итогом - c TV | D74: =SUM($D$64:D64) -> -60732124 | E74: =SUM($D$64:E64) -> -9.405665e+08 | F74: =SUM($D$64:F64) -> -1.790568e+09 | G74: =SUM($D$64:G64) -> -2.1355014e+09 | H74: =SUM($D$64:H64) -> -2.2746748e+09 | I74: =SUM($D$64:I64) -> -3.7665181e+08 | J74: =SUM($D$64:J64) -> 1.1210374e+09 | K74: =SUM($D$64:K64) -> 1.3025678e+09 | ... R74: =SUM($D$64:R64) -> 2.6809588e+09 | S74: =SUM($D$64:T64) -> 1.5088011e+10
B75: PBP (срок окупаемости) - без TV | D75: =IF(AND(S73>0,(COUNTIF(D73:S73,"<0"))=COUNT(D73:S73)-1),"окупается с продажи",IF(OR(S73<0,(COUNTIF(D73:S73,"<0"))=COUNT(D73:S73)),"не окупается",(COUNTIF(D73:S73,"<0")))) -> 6
B76: PBP (срок окупаемости) - c TV | D76: =IF(AND(S74>0,(COUNTIF(D74:S74,"<0"))=COUNT(D74:S74)-1),"окупается с продажи",IF(OR(S74<0,(COUNTIF(D74:S74,"<0"))=COUNT(D74:S74)),"не окупается",(COUNTIF(D74:S74,"<0")))) -> 6
B77: Дисконтированный денежный поток накопленным итогом - без TV | D77: =SUM($D$68:D68) -> -56458627 | E77: =SUM($D$68:E68) -> -7.5855275e+08 | F77: =SUM($D$68:F68) -> -1.3368559e+09 | G77: =SUM($D$68:G68) -> -1.53694e+09 | H77: =SUM($D$68:H68) -> -1.6057695e+09 | I77: =SUM($D$68:I68) -> -8.0545321e+08 | J77: =SUM($D$68:J68) -> -2.6703052e+08 | K77: =SUM($D$68:K68) -> -2.1138983e+08 | ... R77: =SUM($D$68:R68) -> 13709427 | S77: =SUM($D$68:T68) -> 67805055
B78: Дисконтированный денежный поток накопленным итогом - c TV | D78: =SUM($D$69:D69) -> -56458627 | E78: =SUM($D$69:E69) -> -7.5855275e+08 | F78: =SUM($D$69:F69) -> -1.3368559e+09 | G78: =SUM($D$69:G69) -> -1.53694e+09 | H78: =SUM($D$69:H69) -> -1.6057695e+09 | I78: =SUM($D$69:I69) -> -8.0545321e+08 | J78: =SUM($D$69:J69) -> -2.6703052e+08 | K78: =SUM($D$69:K69) -> -2.1138983e+08 | ... R78: =SUM($D$69:R69) -> 13709427 | S78: =SUM($D$69:T69) -> 9.9827965e+08
B79: DPBP (дисконтированный срок окупаемости) - без TV | D79: =IF(AND(S77>0,(COUNTIF(D77:S77,"<0"))=COUNT(D77:S77)-1),"окупается с продажи",IF(OR(S77<0,(COUNTIF(D77:S77,"<0"))=COUNT(D77:S77)),"не окупается",(COUNTIF(D77:S77,"<0")))) -> 14
B80: DPBP (дисконтированный срок окупаемости) - c TV | D80: =IF(AND(S78>0,(COUNTIF(D78:S78,"<0"))=COUNT(D78:S78)-1),"окупается с продажи",IF(OR(S78<0,(COUNTIF(D78:S78,"<0"))=COUNT(D78:S78)),"не окупается",(COUNTIF(D78:S78,"<0")))) -> 14
B81: =B63 -> FCFE | C81: =SUM(D81:S81) -> 3.3130612e+09 | D81: =D63 -> -60732124 | E81: =E63 -> -8.7983437e+08 | F81: =F63 -> -8.5000151e+08 | G81: =G63 -> -3.4493343e+08 | H81: =H63 -> -1.3917336e+08 | I81: =I63 -> 1.898023e+09 | J81: =J63 -> 1.4976892e+09 | K81: =K63 -> 1.8153041e+08 | ... R81: =R63 -> 2.5821579e+08 | S81: =S63+T63 -> 6.3210241e+08
B82: FCFE + TV | C82: =SUM(D82:S82) -> 1.5088011e+10 | D82: =D64 -> -60732124 | E82: =E64 -> -8.7983437e+08 | F82: =F64 -> -8.5000151e+08 | G82: =G64 -> -3.4493343e+08 | H82: =H64 -> -1.3917336e+08 | I82: =I64 -> 1.898023e+09 | J82: =J64 -> 1.4976892e+09 | K82: =K64 -> 1.8153041e+08 | ... R82: =R64 -> 2.5821579e+08 | S82: =S64+T64 -> 1.2407052e+10
A83: ВНИМАНИЕ | B83: =B81&" без кассовых разрывов" -> FCFE без кассовых разрывов | C83: =SUM(D83:S83) -> 3.3130612e+09 | D83: =D81 -> -60732124 | E83: =E81 -> -8.7983437e+08 | F83: =MIN(F81,-1000) -> -8.5000151e+08 | G83: =MIN(G81,-1000) -> -3.4493343e+08 | H83: =MIN(H81,-1000) -> -1.3917336e+08 | I83: =MIN(I81,-1000) -> -1000 | J83: =MIN(J81,-1000) -> -1000 | K83: =SUM($D$81:K81)-SUM($D$83:J83) -> 3.5772446e+09 | L83: =SUM($D$81:L81)-SUM($D$83:K83) -> 1.8372007e+08 | M83: =SUM($D$81:M81)-SUM($D$83:L83) -> 1.6863573e+08 | N83: =SUM($D$81:N81)-SUM($D$83:M83) -> 1.616995e+08 | O83: =SUM($D$81:O81)-SUM($D$83:N83) -> 1.6562767e+08 | P83: =SUM($D$81:P81)-SUM($D$83:O83) -> 2.0607793e+08 | Q83: =SUM($D$81:Q81)-SUM($D$83:P83) -> 2.3441429e+08 | R83: =SUM($D$81:R81)-SUM($D$83:Q83) -> 2.5821579e+08 | S83: =SUM($D$81:S81)-SUM($D$83:R83) -> 6.3210241e+08
A84: ВНИМАНИЕ | B84: =B82&" без кассовых разрывов" -> FCFE + TV без кассовых разрывов | C84: =SUM(D84:S84) -> 1.5088011e+10 | D84: =D82 -> -60732124 | E84: =E82 -> -8.7983437e+08 | F84: =MIN(F82,-1000) -> -8.5000151e+08 | G84: =MIN(G82,-1000) -> -3.4493343e+08 | H84: =MIN(H82,-1000) -> -1.3917336e+08 | I84: =MIN(I82,-1000) -> -1000 | J84: =MIN(J82,-1000) -> -1000 | K84: =SUM($D$82:K82)-SUM($D$84:J84) -> 3.5772446e+09 | L84: =SUM($D$82:L82)-SUM($D$84:K84) -> 1.8372007e+08 | M84: =SUM($D$82:M82)-SUM($D$84:L84) -> 1.6863573e+08 | N84: =SUM($D$82:N82)-SUM($D$84:M84) -> 1.616995e+08 | O84: =SUM($D$82:O82)-SUM($D$84:N84) -> 1.6562767e+08 | P84: =SUM($D$82:P82)-SUM($D$84:O84) -> 2.0607793e+08 | Q84: =SUM($D$82:Q82)-SUM($D$84:P84) -> 2.3441429e+08 | R84: =SUM($D$82:R82)-SUM($D$84:Q84) -> 2.5821579e+08 | S84: =SUM($D$82:S82)-SUM($D$84:R84) -> 1.2407052e+10
A85: =IF(AND(D71<0,D85>=D65),"Error","") | B85: IRR - без TV | D85: =IF(IRR(D83:S83)<0,"не применимо",IRR(D83:S83)) -> 0.14418346
A86: =IF(AND(D72<0,D86>=D65),"Error","") | B86: IRR - c TV | D86: =IF(IRR(D84:S84)<0,"Неприменимо",IRR(D84:S84)) -> 0.22612661
B89: Показатели проекта на собственный капитал (FCFE)
B90: Без учета терминальной стоимости
B91: NPV | D91: =D71 -> 67805055
B92: IRR | D92: =D85 -> 0.14418346
B93: PBP | D93: =D75 -> 6
B94: DPBP | D94: =D79 -> 14
B95: С учетом терминальной стоимости
B96: NPV | D96: =D72 -> 9.9827965e+08
B97: IRR | D97: =D86 -> 0.22612661
B98: PBP | D98: =D76 -> 6
B99: DPBP | D99: =D80 -> 14
B102: Показатели проекта для компании (FCFF) | D102: =D5 -> 2022 | E102: =E5 -> 2023 | F102: =F5 -> 2024 | G102: =G5 -> 2025 | H102: =H5 -> 2026 | I102: =I5 -> 2027 | J102: =J5 -> 2028 | K102: =K5 -> 2029 | ... T102: =T5 -> 2038
B103: ИТОГО, Чистая операционная прибыль/убыток | D103: =D24 -> 0 | E103: =E24 -> 0 | F103: =F24 -> 0 | G103: =G24 -> 1.0428256e+08 | H103: =H24 -> 1.4387461e+09 | I103: =I24 -> 2.4141395e+09 | J103: =J24 -> 2.2885779e+09 | K103: =K24 -> 9.737917e+08 | ... T103: =T24 -> 1.3646871e+09
B104: Минус: амортизация | D104: =D26 -> 0 | E104: =E26 -> 0 | F104: =F26 -> 0 | G104: =G26 -> -43883903 | H104: =H26 -> -1.6074932e+08 | I104: =I26 -> -2.3373084e+08 | J104: =J26 -> -2.3373084e+08 | K104: =K26 -> -2.3373084e+08 | ... T104: =T26 -> -2.3373084e+08
B105: Минус: себестоимость резиденций | D105: =D27 -> 0 | E105: =E27 -> 0 | F105: =F27 -> 0 | G105: =G27 -> 0 | H105: =H27 -> -4.0632596e+08 | I105: =I27 -> -6.5012153e+08 | J105: =J27 -> -5.6885634e+08 | K105: =K27 -> 0 | ... T105: =T27 -> 0
B106: Равно: прибыль / убыток за период | D106: =SUM(D103:D105) -> 0 | E106: =SUM(E103:E105) -> 0 | F106: =SUM(F103:F105) -> 0 | G106: =SUM(G103:G105) -> 60398656 | H106: =SUM(H103:H105) -> 8.7167079e+08 | I106: =SUM(I103:I105) -> 1.5302871e+09 | J106: =SUM(J103:J105) -> 1.4859907e+09 | K106: =SUM(K103:K105) -> 7.4006087e+08 | ... T106: =SUM(T103:T105) -> 1.1309563e+09
...

Sheet WACC
A1: 0
C4: Показатель | D4: Значение | E4: Комментарий | F4: Источник
C5: Доля заемного капитала | D5: =I5/(1+I5) -> 0.35913868 | E5: Среднеотраслевой показатель для проектов коммерческой недвиимости в сфере услуг (Real Estate (Operations & Services)) - emerging markets | F5: http://www.stern.nyu.edu/~adamodar/New_Home_Page/data.html | H5: D/E Ratio | I5: 0.5604 | J5: столбец D | K5: Real Estate (Operations & Services)
C6: Доля собственного капитала | D6: =100%-D5 -> 0.64086132 | E6: Расчетное значение 100%-ЗК
C7: Безрисковая ставка в долларах США | D7: 0.0226 | E7: UST 30Y
C8: Безрисковая ставка для Россия в долларах США | D8: 0.0399515 | E8: Россия-2035 (в обращении) | F8: https://www.moex.com/ru/issue.aspx?code=XS0088543193
C9: Безрисковая ставка для России в рублях | D9: 0.0841 | E9: ОФЗ-26230-ПД (в обращении) | F9: https://rusbonds.ru/bonds/153478/
C10: Beta (unlevered) | D10: 0.59 | E10: =I10 -> Real Estate (Operations & Services) | F10: http://www.stern.nyu.edu/~adamodar/pc/datasets/betaemerg.xls | H10: Cтолбец H | I10: =K5 -> Real Estate (Operations & Services)
C11: Соотношение долга к собственному капиталу | D11: =D5/D6 -> 0.5604 | E11: Расчетное значение
C12: Эффективная ставка налога | D12: 0.2
C13: Beta (relevered) | D13: =D10*(1+(1-D12)*D11) -> 0.8545088 | E13: Beta с учетом ставки налога
C14: Среднерыночная премия | D14: 0.0541 | E14: arithmetiс average 1972-2021 | F14: http://www.stern.nyu.edu/~adamodar/pc/datasets/histretSP.xls
C15: Премия за страновой риск | D15: 0.0288 | E15: Разница доходности безрисковых бумаг в рублях и долларах США | F15: http://pages.stern.nyu.edu/~adamodar/New_Home_Page/datafile/ctryprem.html
C16: Премия за размер компании | D16: 0.0175 | E16: По оценкам Ibbotson | F16: принтскрин ниже | G16: https://edisciplinas.usp.br/pluginfile.php/3787205/mod_resource/content/1/SIZE%20PREMIUM%20IBOTTSON.pdf
C17: Премия за специфический риск | D17: 0.01 | E17: Оценочное суждение
C18: Стоимость собственного капитала (САРМ) в долл | D18: =(D7+D13*D14+D15+D16+D17) -> 0.12512893
C19: Валютная корректировка | D19: =(1+D9)/(1+D8) -> 1.0424525
C20: Стоимость собственного капитала (САРМ) в рублях | D20: =(1+D18)*D19-1 -> 0.17289342
C21: Стоимость заемных средств | D21: =CF_15!D158 -> 0.04
C22: Посленалоговая стоимость заемного капитала | D22: =D21*(1-D12) -> 0.032
C23: Средневзвешенная стоимость капитала (WACC) | D23: =(D6*D20+D5*D22) -> 0.12229314

Sheet Sensitivity
B2: ПОКАЗАТЕЛИ ПРОЕКТА БЕЗ УЧЕТА ПРОДАЖИ В ТЕРМИНАЛЬНОМ ГОДУ | L2: ПОКАЗАТЕЛИ ПРОЕКТА С УЧЕТОМ ПРОДАЖИ В ТЕРМИНАЛЬНОМ ГОДУ
B4: =KPI!B3 -> Показатели проекта на собственный капитал | E4: =KPI!D3 -> FCFE | H4: =KPI!G3 -> Показатели проекта | K4: =KPI!I3 -> FCFF | L4: =KPI!B3 -> Показатели проекта на собственный капитал | N4: =KPI!D3 -> FCFE | P4: =KPI!G3 -> Показатели проекта | S4: =KPI!I3 -> FCFF
B5: Ставка дисконтирования | E5: =KPI!D4 -> 0.17289342 | H5: Ставка дисконтирования | K5: =KPI!I4 -> 0.12229314 | L5: Ставка дисконтирования | N5: =KPI!D4 -> 0.17289342 | P5: Ставка дисконтирования | S5: =KPI!I4 -> 0.12229314
B6: =KPI!B6 -> NPV | C6: Чистая текущая стоимость | D6: млн руб. | E6: =KPI!D6 -> 67.805055 | H6: =B6 -> NPV | J6: млн руб. | K6: =KPI!I6 -> -1808.2418 | L6: =KPI!B11 -> NPV | M6: млн руб. | N6: =KPI!D11 -> 998.27965 | P6: =L6 -> NPV | R6: млн руб. | S6: =KPI!I11 -> 68.971955
B7: =KPI!B7 -> IRR | C7: Внутрення норма доходности | E7: =KPI!D7 -> 0.14418346 | H7: =B7 -> IRR | K7: =KPI!I7 -> 0.069552783 | L7: =KPI!B12 -> IRR | N7: =KPI!D12 -> 0.22612661 | P7: =L7 -> IRR | S7: =KPI!I12 -> 0.12587749
B8: =KPI!B8 -> PBP | C8: Срок окупаемости | D8: лет | E8: =KPI!D8 -> 6 | H8: =B8 -> PBP | J8: лет | K8: =KPI!I8 -> 11 | L8: =KPI!B13 -> PBP | M8: лет | N8: =KPI!D13 -> 6 | P8: =L8 -> PBP | R8: лет | S8: =KPI!I13 -> 11
B9: =KPI!B9 -> DPBP | C9: Дисконтированный срок окупаемости | D9: лет | E9: =KPI!D9 -> 14 | H9: =B9 -> DPBP | J9: лет | K9: =KPI!I9 -> не окупается | L9: =KPI!B14 -> DPBP | M9: лет | N9: =KPI!D14 -> 14 | P9: =L9 -> DPBP | R9: лет | S9: =KPI!I14 -> окупается с продажи
B13: АНАЛИЗ ЧУВСТВИТЕЛЬНОСТИ К РАЗМЕРУ СТРОИТЕЛЬНОГО БЮДЖЕТА
D15: =B2 -> ПОКАЗАТЕЛИ ПРОЕКТА БЕЗ УЧЕТА ПРОДАЖИ В ТЕРМИНАЛЬНОМ ГОДУ | L15: =L2 -> ПОКАЗАТЕЛИ ПРОЕКТА С УЧЕТОМ ПРОДАЖИ В ТЕРМИНАЛЬНОМ ГОДУ
D16: =B4 -> Показатели проекта на собственный капитал | G16: =E4 -> FCFE | H16: =H4 -> Показатели проекта | K16: =K4 -> FCFF | L16: =L4 -> Показатели проекта на собственный капитал | O16: =N4 -> FCFE | P16: =P4 -> Показатели проекта | S16: =S4 -> FCFF
B17: 1 | C17: Размер инвестиций, млн руб. | D17: NPV, млн руб. | E17: =B8 -> PBP | F17: =B9 -> DPBP | G17: =B7 -> IRR | H17: =D17 -> NPV, млн руб. | I17: =E17 -> PBP | J17: =F17 -> DPBP | K17: =G17 -> IRR | L17: NPV, млн руб. | M17: =L8 -> PBP | N17: =L9 -> DPBP | O17: =L7 -> IRR | P17: =L17 -> NPV, млн руб. | Q17: =M17 -> PBP | R17: =N17 -> DPBP | S17: =O17 -> IRR
C18: =Строительство!F53/10^6 -> 11472.203 | D18: =E6 -> 67.805055 | E18: =E8 -> 6 | F18: =E9 -> 14 | G18: =E7 -> 0.14418346 | H18: =K6 -> -1808.2418 | I18: =K8 -> 11 | J18: =K9 -> не окупается | K18: =K7 -> 0.069552783 | L18: =N6 -> 998.27965 | M18: =N8 -> 6 | N18: =N9 -> 14 | O18: =N7 -> 0.22612661 | P18: =S6 -> 68.971955 | Q18: =S8 -> 11 | R18: =S9 -> окупается с продажи | S18: =S7 -> 0.12587749
B19: 0.8 | C19: 9177.7626 | D19: 440.04381 | E19: 5 | F19: 6 | G19: 0.19268666 | H19: -411.38379 | I19: 9 | J19: не окупается | K19: 0.10812641 | L19: 1378.1548 | M19: 5 | N19: 6 | O19: 0.26230139 | P19: 1481.2363 | Q19: 9 | R19: окупается с продажи | S19: 0.15940959
B20: =B19+0.025 -> 0.825 | C20: 9464.5677 | D20: 393.51396 | E20: 6 | F20: 7 | G20: 0.18605456 | H20: -585.99105 | I20: 9 | J20: не окупается | K20: 0.10257401 | L20: 1330.6704 | M20: 6 | N20: 7 | O20: 0.25723631 | P20: 1304.7032 | Q20: 9 | R20: окупается с продажи | S20: 0.15459318
B21: =B20+0.025 -> 0.85 | C21: 9751.3728 | D21: 346.98412 | E21: 6 | F21: 7 | G21: 0.179608 | H21: -760.5983 | I21: 9 | J21: не окупается | K21: 0.097261454 | L21: 1283.186 | M21: 6 | N21: 7 | O21: 0.25234696 | P21: 1128.1702 | Q21: 9 | R21: окупается с продажи | S21: 0.14998238
B22: =B21+0.025 -> 0.875 | C22: 10038.178 | D22: 300.45427 | E22: 6 | F22: 8 | G22: 0.1733343 | H22: -935.20556 | I22: 10 | J22: не окупается | K22: 0.092171232 | L22: 1235.7016 | M22: 6 | N22: 8 | O22: 0.24762187 | P22: 951.63714 | Q22: 10 | R22: окупается с продажи | S22: 0.1455619
B23: =B22+0.025 -> 0.9 | C23: 10324.983 | D23: 253.92443 | E23: 6 | F23: 9 | G23: 0.16722182 | H23: -1109.8128 | I23: 10 | J23: не окупается | K23: 0.087287568 | L23: 1188.2172 | M23: 6 | N23: 9 | O23: 0.24305067 | P23: 775.1041 | Q23: 10 | R23: окупается с продажи | S23: 0.14131798
B24: =B23+0.025 -> 0.925 | C24: 10611.788 | D24: 207.39459 | E24: 6 | F24: 10 | G24: 0.16125992 | H24: -1284.4201 | I24: 10 | J24: не окупается | K24: 0.082596216 | L24: 1140.7328 | M24: 6 | N24: 10 | O24: 0.23862385 | P24: 598.57107 | Q24: 10 | R24: окупается с продажи | S24: 0.13723825
B25: =B24+0.025 -> 0.95 | C25: 10898.593 | D25: 160.86474 | E25: 6 | F25: 11 | G25: 0.15543881 | H25: -1459.0273 | I25: 10 | J25: не окупается | K25: 0.078084272 | L25: 1093.2484 | M25: 6 | N25: 11 | O25: 0.23433275 | P25: 422.03803 | Q25: 10 | R25: окупается с продажи | S25: 0.13331153
B26: =B25+0.025 -> 0.975 | C26: 11185.398 | D26: 114.3349 | E26: 6 | F26: 12 | G26: 0.14974944 | H26: -1633.6346 | I26: 10 | J26: не окупается | K26: 0.073740017 | L26: 1045.764 | M26: 6 | N26: 12 | O26: 0.23016943 | P26: 245.50499 | Q26: 10 | R26: окупается с продажи | S26: 0.12952767
B27: =B26+0.025 -> 1 | C27: 11472.203 | D27: 67.805055 | E27: 6 | F27: 14 | G27: 0.14418346 | H27: -1808.2418 | I27: 11 | J27: не окупается | K27: 0.069552783 | L27: 998.27965 | M27: 6 | N27: 14 | O27: 0.22612661 | P27: 68.971955 | Q27: 11 | R27: окупается с продажи | S27: 0.12587749
B28: =B27+0.025 -> 1.025 | C28: 11759.008 | D28: 21.275212 | E28: 6 | F28: окупается с продажи | G28: 0.13873312 | H28: -1982.8491 | I28: 11 | J28: не окупается | K28: 0.065512832 | L28: 950.79526 | M28: 6 | N28: окупается с продажи | O28: 0.22219756 | P28: -107.56108 | Q28: 11 | R28: не окупается | S28: 0.1223526
B29: =B28+0.025 -> 1.05 | C29: 12045.813 | D29: -25.254632 | E29: 6 | F29: не окупается | G29: 0.13339122 | H29: -2157.4563 | I29: 11 | J29: не окупается | K29: 0.061611255 | L29: 903.31087 | M29: 6 | N29: окупается с продажи | O29: 0.21837611 | P29: -284.09412 | Q29: 11 | R29: не окупается | S29: 0.11894533
B30: =B29+0.025 -> 1.075 | C30: 12332.619 | D30: -71.784476 | E30: 6 | F30: не окупается | G30: 0.12815103 | H30: -2332.0636 | I30: 11 | J30: не окупается | K30: 0.057839885 | L30: 855.82648 | M30: 6 | N30: окупается с продажи | O30: 0.21465653 | P30: -460.62716 | Q30: 11 | R30: не окупается | S30: 0.1156487
B31: =B30+0.025 -> 1.1 | C31: 12619.424 | D31: -118.31432 | E31: 6 | F31: не окупается | G31: 0.12300629 | H31: -2506.6709 | I31: 12 | J31: не окупается | K31: 0.054191219 | L31: 808.34209 | M31: 6 | N31: окупается с продажи | O31: 0.21103355 | P31: -637.16019 | Q31: 12 | R31: не окупается | S31: 0.11245627
C34: АНАЛИЗ ЧУВСТВИТЕЛЬНОСТИ К СТАБИЛИЗИРОВАННОМУ УРОВНЮ ЗАГРУЗКИ
D36: =D15 -> ПОКАЗАТЕЛИ ПРОЕКТА БЕЗ УЧЕТА ПРОДАЖИ В ТЕРМИНАЛЬНОМ ГОДУ | L36: =L15 -> ПОКАЗАТЕЛИ ПРОЕКТА С УЧЕТОМ ПРОДАЖИ В ТЕРМИНАЛЬНОМ ГОДУ
D37: =D16 -> Показатели проекта на собственный капитал | H37: =H16 -> Показатели проекта | L37: =L16 -> Показатели проекта на собственный капитал | P37: =P16 -> Показатели проекта
B38: 1 | C38: Стабилизированный уровень загрузки по всем средствам размещения | D38: NPV, млн руб. | E38: =E17 -> PBP | F38: =F17 -> DPBP | G38: =G17 -> IRR | H38: =D38 -> NPV, млн руб. | I38: =E38 -> PBP | J38: =F38 -> DPBP | K38: =G38 -> IRR | L38: NPV, млн руб. | M38: =M17 -> PBP | N38: =N17 -> DPBP | O38: =O17 -> IRR | P38: =L38 -> NPV, млн руб. | Q38: =M38 -> PBP | R38: =N38 -> DPBP | S38: =O38 -> IRR
C39: =СВОД_PL!$I$31 -> 0.64671998 | D39: =D18 -> 67.805055 | E39: =E18 -> 6 | F39: =F18 -> 14 | G39: =G18 -> 0.14418346 | H39: =H18 -> -1808.2418 | I39: =I18 -> 11 | J39: =J18 -> не окупается | K39: =K18 -> 0.069552783 | ... S39: =S18 -> 0.12587749
B40: 0.8 | C40: 0.51737599 | D40: -796.89338 | E40: не окупается | F40: не окупается | G40: не применимо | H40: -3035.9698 | I40: 13 | J40: не окупается | K40: 0.026896485 | L40: -109.03666 | M40: окупается с продажи | N40: не окупается | O40: 0.15118038 | P40: -1648.2327 | Q40: 13 | R40: не окупается | S40: 0.08809238
B41: =B40+0.025 -> 0.825 | C41: 0.53354398 | D41: -688.60267 | E41: 10 | F41: не окупается | G41: 0.020372071 | H41: -2882.5038 | I41: 13 | J41: не окупается | K41: 0.032660278 | L41: 29.581282 | M41: 10 | N41: окупается с продажи | O41: 0.16167093 | P41: -1433.5821 | Q41: 13 | R41: не окупается | S41: 0.093231843
B42: =B41+0.025 -> 0.85 | C42: 0.54971198 | D42: -580.54443 | E42: 6 | F42: не окупается | G42: 0.044430065 | H42: -2729.0378 | I42: 12 | J42: не окупается | K42: 0.038283381 | L42: 167.96676 | M42: 6 | N42: окупается с продажи | O42: 0.17175154 | P42: -1218.9315 | Q42: 12 | R42: не окупается | S42: 0.098234436
B43: =B42+0.025 -> 0.875 | C43: 0.56587998 | D43: -472.48618 | E43: 6 | F43: не окупается | G43: 0.065274257 | H43: -2575.5718 | I43: 12 | J43: не окупается | K43: 0.04377563 | L43: 306.35225 | M43: 6 | N43: окупается с продажи | O43: 0.1814967 | P43: -1004.2809 | Q43: 12 | R43: не окупается | S43: 0.10311037
B44: =B43+0.025 -> 0.9 | C44: 0.58204798 | D44: -364.42793 | E44: 6 | F44: не окупается | G44: 0.083840991 | H44: -2422.1058 | I44: 12 | J44: не окупается | K44: 0.049145819 | L44: 444.73773 | M44: 6 | N44: окупается с продажи | O44: 0.1909368 | P44: -789.63036 | Q44: 12 | R44: не окупается | S44: 0.10786874
B45: =B44+0.025 -> 0.925 | C45: 0.59821598 | D45: -256.36969 | E45: 6 | F45: не окупается | G45: 0.10069672 | H45: -2268.6398 | I45: 11 | J45: не окупается | K45: 0.054401844 | L45: 583.12321 | M45: 6 | N45: окупается с продажи | O45: 0.20009821 | P45: -574.97978 | Q45: 11 | R45: не окупается | S45: 0.11251768
B46: =B45+0.025 -> 0.95 | C46: 0.61438398 | D46: -148.31144 | E46: 6 | F46: не окупается | G46: 0.11621252 | H46: -2115.1738 | I46: 11 | J46: не окупается | K46: 0.059550821 | L46: 721.50869 | M46: 6 | N46: окупается с продажи | O46: 0.20900391 | P46: -360.3292 | Q46: 11 | R46: не окупается | S46: 0.11706449
B47: =B46+0.025 -> 0.975 | C47: 0.63055198 | D47: -40.253191 | E47: 6 | F47: не окупается | G47: 0.13064588 | H47: -1961.7078 | I47: 11 | J47: не окупается | K47: 0.064599186 | L47: 859.89417 | M47: 6 | N47: окупается с продажи | O47: 0.2176741 | P47: -145.67862 | Q47: 11 | R47: не окупается | S47: 0.12151578
B48: =B47+0.025 -> 1 | C48: 0.64671998 | D48: 67.805055 | E48: 6 | F48: 14 | G48: 0.14418346 | H48: -1808.2418 | I48: 11 | J48: не окупается | K48: 0.069552783 | L48: 998.27965 | M48: 6 | N48: 14 | O48: 0.22612661 | P48: 68.971955 | Q48: 11 | R48: окупается с продажи | S48: 0.12587749
B49: =B48+0.025 -> 1.025 | C49: 0.66288798 | D49: 175.8633 | E49: 6 | F49: 11 | G49: 0.15696531 | H49: -1654.7758 | I49: 10 | J49: не окупается | K49: 0.074416934 | L49: 1136.6651 | M49: 6 | N49: 11 | O49: 0.23437721 | P49: 283.62253 | Q49: 10 | R49: окупается с продажи | S49: 0.13015505
B50: =B49+0.025 -> 1.05 | C50: 0.67905598 | D50: 283.92155 | E50: 6 | F50: 9 | G50: 0.16909943 | H50: -1501.3098 | I50: 10 | J50: не окупается | K50: 0.0791965 | L50: 1275.0506 | M50: 6 | N50: 9 | O50: 0.24244 | P50: 498.27311 | Q50: 10 | R50: окупается с продажи | S50: 0.13435339
B51: =B50+0.025 -> 1.075 | C51: 0.69522398 | D51: 391.9798 | E51: 6 | F51: 8 | G51: 0.18067107 | H51: -1347.8439 | I51: 10 | J51: не окупается | K51: 0.083895931 | L51: 1413.4361 | M51: 6 | N51: 8 | O51: 0.25032754 | P51: 712.92369 | Q51: 10 | R51: окупается с продажи | S51: 0.13847701
B52: =B51+0.025 -> 1.1 | C52: 0.71139198 | D52: 500.03804 | E52: 6 | F52: 7 | G52: 0.19174878 | H52: -1194.3779 | I52: 10 | J52: не окупается | K52: 0.088519315 | L52: 1551.8216 | M52: 6 | N52: 7 | O52: 0.25805113 | P52: 927.57427 | Q52: 10 | R52: окупается с продажи | S52: 0.14253004
B53: =B52+0.025 -> 1.125 | C53: 0.72755998 | D53: 608.09629 | E53: 5 | F53: 6 | G53: 0.20180066 | H53: -1040.9119 | I53: 10 | J53: не окупается | K53: 0.093070418 | L53: 1690.2071 | M53: 5 | N53: 6 | O53: 0.26511278 | P53: 1142.2249 | Q53: 10 | R53: окупается с продажи | S53: 0.14651626
B54: =B53+0.025 -> 1.15 | C54: 0.74372798 | D54: 716.15454 | E54: 5 | F54: 6 | G54: 0.21122101 | H54: -887.44588 | I54: 9 | J54: не окупается | K54: 0.097552711 | L54: 1828.5925 | M54: 5 | N54: 6 | O54: 0.27182739 | P54: 1356.8754 | Q54: 9 | R54: окупается с продажи | S54: 0.15043917
B55: =B54+0.025 -> 1.175 | C55: 0.75989598 | D55: 824.21278 | E55: 5 | F55: 6 | G55: 0.22025283 | H55: -733.97988 | I55: 9 | J55: не окупается | K55: 0.10196941 | L55: 1966.978 | M55: 5 | N55: 6 | O55: 0.27837807 | P55: 1571.526 | Q55: 9 | R55: окупается с продажи | S55: 0.15430197
B56: =B55+0.025 -> 1.2 | C56: 0.77606398 | D56: 932.27103 | E56: 5 | F56: 6 | G56: 0.22893337 | H56: -580.51389 | I56: 9 | J56: не окупается | K56: 0.10632348 | L56: 2105.3635 | M56: 5 | N56: 6 | O56: 0.28477402 | P56: 1786.1766 | Q56: 9 | R56: окупается с продажи | S56: 0.15810764
C59: АНАЛИЗ ЧУВСТВИТЕЛЬНОСТИ К УРОВНЮ ADR
D61: =D36 -> ПОКАЗАТЕЛИ ПРОЕКТА БЕЗ УЧЕТА ПРОДАЖИ В ТЕРМИНАЛЬНОМ ГОДУ | L61: =L36 -> ПОКАЗАТЕЛИ ПРОЕКТА С УЧЕТОМ ПРОДАЖИ В ТЕРМИНАЛЬНОМ ГОДУ
D62: =D37 -> Показатели проекта на собственный капитал | H62: =H37 -> Показатели проекта | L62: =L37 -> Показатели проекта на собственный капитал | P62: =P37 -> Показатели проекта
B63: 1 | C63: Стабилизированный уровень ADR, по всем средствам размещения - в текущих ценах | D63: NPV, млн руб. | E63: =E38 -> PBP | F63: =F38 -> DPBP | G63: =G38 -> IRR | H63: =D63 -> NPV, млн руб. | I63: =E63 -> PBP | J63: =F63 -> DPBP | K63: =G63 -> IRR | L63: NPV, млн руб. | M63: =M38 -> PBP | N63: =N38 -> DPBP | O63: =O38 -> IRR | P63: =L63 -> NPV, млн руб. | Q63: =M63 -> PBP | R63: =N63 -> DPBP | S63: =O63 -> IRR
C64: =СВОД_PL!$I$147 -> 8401.9927 | D64: =D39 -> 67.805055 | E64: =E39 -> 6 | F64: =F39 -> 14 | G64: =G39 -> 0.14418346 | H64: =H39 -> -1808.2418 | I64: =I39 -> 11 | J64: =J39 -> не окупается | K64: =K39 -> 0.069552783 | ... S64: =S39 -> 0.12587749
B65: 0.8 | C65: 6721.5941 | D65: -955.82579 | E65: не окупается | F65: не окупается | G65: не применимо | H65: -3257.6023 | I65: 14 | J65: не окупается | K65: 0.018540638 | L65: -307.85113 | M65: окупается с продажи | N65: не окупается | O65: 0.13564091 | P65: -1950.3265 | Q65: 14 | R65: не окупается | S65: 0.080708514
B66: =B65+0.025 -> 0.825 | C66: 6931.6439 | D66: -827.40065 | E66: не окупается | F66: не окупается | G66: не применимо | H66: -3076.4323 | I66: 13 | J66: не окупается | K66: 0.025540925 | L66: -144.11349 | M66: окупается с продажи | N66: не окупается | O66: 0.14861662 | P66: -1697.9142 | Q66: 13 | R66: не окупается | S66: 0.086957915
B67: =B66+0.025 -> 0.85 | C67: 7141.6938 | D67: -699.09791 | E67: 10 | F67: не окупается | G67: 0.018976969 | H67: -2895.2622 | I67: 13 | J67: не окупается | K67: 0.032332604 | L67: 19.501739 | M67: 10 | N67: окупается с продажи | O67: 0.1610228 | P67: -1445.5019 | Q67: 13 | R67: не окупается | S67: 0.093003438
B68: =B67+0.025 -> 0.875 | C68: 7351.7436 | D68: -571.28075 | E68: 6 | F68: не окупается | G68: 0.046998207 | H68: -2714.0922 | I68: 12 | J68: не окупается | K68: 0.038933345 | L68: 182.63139 | M68: 6 | N68: окупается с продажи | O68: 0.17284898 | P68: -1193.0896 | Q68: 12 | R68: не окупается | S68: 0.098863489
B69: =B68+0.025 -> 0.9 | C69: 7561.7934 | D69: -443.46359 | E69: 6 | F69: не окупается | G69: 0.070842801 | H69: -2532.9221 | I69: 12 | J69: не окупается | K69: 0.045358567 | L69: 345.76104 | M69: 6 | N69: окупается с продажи | O69: 0.18423004 | P69: -940.67727 | Q69: 12 | R69: не окупается | S69: 0.10455406
B70: =B69+0.025 -> 0.925 | C70: 7771.8432 | D70: -315.64643 | E70: 6 | F70: не окупается | G70: 0.091847775 | H70: -2351.752 | I70: 12 | J70: не окупается | K70: 0.051621813 | L70: 508.8907 | M70: 6 | N70: окупается с продажи | O70: 0.19521197 | P70: -688.26496 | Q70: 12 | R70: не окупается | S70: 0.11008913
B71: =B70+0.025 -> 0.95 | C71: 7981.893 | D71: -187.82927 | E71: 6 | F71: не окупается | G71: 0.11077775 | H71: -2170.582 | I71: 11 | J71: не окупается | K71: 0.057735042 | L71: 672.02035 | M71: 6 | N71: окупается с продажи | O71: 0.20583384 | P71: -435.85266 | Q71: 11 | R71: не окупается | S71: 0.11548101
B72: =B71+0.025 -> 0.975 | C72: 8191.9428 | D72: -60.012106 | E72: 6 | F72: не окупается | G72: 0.12811462 | H72: -1989.4119 | I72: 11 | J72: не окупается | K72: 0.063708875 | L72: 835.15 | M72: 6 | N72: окупается с продажи | O72: 0.2161291 | P72: -183.44035 | Q72: 11 | R72: не окупается | S72: 0.12074057
B73: =B72+0.025 -> 1 | C73: 8401.9927 | D73: 67.805055 | E73: 6 | F73: 14 | G73: 0.14418346 | H73: -1808.2418 | I73: 11 | J73: не окупается | K73: 0.069552783 | L73: 998.27965 | M73: 6 | N73: 14 | O73: 0.22612661 | P73: 68.971955 | Q73: 11 | R73: окупается с продажи | S73: 0.12587749
B74: =B73+0.025 -> 1.025 | C74: 8612.0425 | D74: 195.62222 | E74: 6 | F74: 10 | G74: 0.1592149 | H74: -1627.0718 | I74: 10 | J74: не окупается | K74: 0.075275255 | L74: 1161.4093 | M74: 6 | N74: 10 | O74: 0.23585142 | P74: 321.38426 | Q74: 10 | R74: окупается с продажи | S74: 0.1309004
B75: =B74+0.025 -> 1.05 | C75: 8822.0923 | D75: 323.43938 | E75: 6 | F75: 8 | G75: 0.17337902 | H75: -1445.9017 | I75: 10 | J75: не окупается | K75: 0.080883926 | L75: 1324.539 | M75: 6 | N75: 8 | O75: 0.24532544 | P75: 573.79657 | Q75: 10 | R75: окупается с продажи | S75: 0.13581705
B76: =B75+0.025 -> 1.075 | C76: 9032.1421 | D76: 451.25654 | E76: 6 | F76: 7 | G76: 0.18680526 | H76: -1264.7316 | I76: 10 | J76: не окупается | K76: 0.086385692 | L76: 1487.6686 | M76: 6 | N76: 7 | O76: 0.2545679 | P76: 826.20887 | Q76: 10 | R76: окупается с продажи | S76: 0.14063441
B77: =B76+0.025 -> 1.1 | C77: 9242.1919 | D77: 579.0737 | E77: 5 | F77: 6 | G77: 0.19915309 | H77: -1083.5616 | I77: 10 | J77: не окупается | K77: 0.091786803 | L77: 1650.7983 | M77: 5 | N77: 6 | O77: 0.26321379 | P77: 1078.6212 | Q77: 10 | R77: окупается с продажи | S77: 0.14535877
B78: =B77+0.025 -> 1.125 | C78: 9452.2417 | D78: 706.89086 | E78: 5 | F78: 6 | G78: 0.21039284 | H78: -902.39151 | I78: 9 | J78: не окупается | K78: 0.097092941 | L78: 1813.9279 | M78: 5 | N78: 6 | O78: 0.27118943 | P78: 1331.0335 | Q78: 9 | R78: окупается с продажи | S78: 0.14999586
B79: =B78+0.025 -> 1.15 | C79: 9662.2915 | D79: 834.70802 | E79: 5 | F79: 6 | G79: 0.22108866 | H79: -721.22145 | I79: 9 | J79: не окупается | K79: 0.10230929 | L79: 1977.0576 | M79: 5 | N79: 6 | O79: 0.27893874 | P79: 1583.4458 | Q79: 9 | R79: окупается с продажи | S79: 0.15455085
B80: =B79+0.025 -> 1.175 | C80: 9872.3414 | D80: 962.52518 | E80: 5 | F80: 6 | G80: 0.23130129 | H80: -540.05138 | I80: 9 | J80: не окупается | K80: 0.10744058 | L80: 2140.1872 | M80: 5 | N80: 6 | O80: 0.28647647 | P80: 1835.8581 | Q80: 9 | R80: окупается с продажи | S80: 0.15902849
B81: =B80+0.025 -> 1.2 | C81: 10082.391 | D81: 1090.3423 | E81: 5 | F81: 6 | G81: 0.24108131 | H81: -358.88132 | I81: 9 | J81: не окупается | K81: 0.11249118 | L81: 2303.3169 | M81: 5 | N81: 6 | O81: 0.29381591 | P81: 2088.2704 | Q81: 9 | R81: окупается с продажи | S81: 0.16343311

Sheet KPI
B3: Показатели проекта на собственный капитал | D3: FCFE | G3: Показатели проекта | I3: FCFF
B4: Ставка дисконтирования | D4: =CF_mln!D65 -> 0.17289342 | G4: Ставка дисконтирования | I4: =CF_mln!D121 -> 0.12229314
B5: Без учета терминальной стоимости | G5: Без учета терминальной стоимости
B6: NPV | D6: =CF_mln!D91 -> 67.805055 | E6: млн руб. | G6: NPV | I6: =CF_mln!D144 -> -1808.2418 | J6: млн руб.
B7: IRR | D7: =CF_mln!D92 -> 0.14418346 | G7: IRR | I7: =CF_mln!D145 -> 0.069552783
B8: PBP | D8: =CF_mln!D93 -> 6 | E8: =IF(OR(D8="окупается с продажи",D8="не окупается"),"","лет") -> лет | G8: PBP | I8: =CF_mln!D146 -> 11 | J8: =IF(OR(I8="окупается с продажи",I8="не окупается"),"","лет") -> лет
B9: DPBP | D9: =CF_mln!D94 -> 14 | E9: =IF(OR(D9="окупается с продажи",D9="не окупается"),"","лет") -> лет | G9: DPBP | I9: =CF_mln!D147 -> не окупается | J9: =IF(OR(I9="окупается с продажи",I9="не окупается"),"","лет")
B10: С учетом терминальной стоимости | G10: С учетом терминальной стоимости
B11: NPV | D11: =CF_mln!D96 -> 998.27965 | E11: млн руб. | G11: NPV | I11: =CF_mln!D149 -> 68.971955 | J11: млн руб.
B12: IRR | D12: =CF_mln!D97 -> 0.22612661 | G12: IRR | I12: =CF_mln!D150 -> 0.12587749
B13: PBP | D13: =CF_mln!D98 -> 6 | E13: =IF(OR(D13="окупается с продажи",D13="не окупается"),"","лет") -> лет | G13: PBP | I13: =CF_mln!D151 -> 11 | J13: =IF(OR(I13="окупается с продажи",I13="не окупается"),"","лет") -> лет
B14: DPBP | D14: =CF_mln!D99 -> 14 | E14: =IF(OR(D14="окупается с продажи",D14="не окупается"),"","лет") -> лет | G14: DPBP | I14: =CF_mln!D152 -> окупается с продажи | J14: =IF(OR(I14="окупается с продажи",I14="не окупается"),"","лет")
B15: Досрочное погашение кредита в 2025-2026 гг. | D15: =CF_mln!C187 -> 0 | E15: млн руб.
B18: Прогнозы 2022 | C18: Доля по кол-ву номерного фонда | D18: Доля по площади номерного фонда | E18: Доля по выручке (2030 год) | G18: Прогнозы 2021 | H18: Доля по кол-ву номерного фонда | I18: Доля по площади номерного фонда | J18: Доля по выручке (2030 год)
B19: =Объекты!C5 -> Гостиница 5* | C19: =Объекты!F5/Объекты!$F$11 -> 0.2236136 | D19: =Объекты!E5/Объекты!$E$11 -> 0.33012115 | E19: =СВОД_PL!I33/(СВОД_PL!$I$32-СВОД_PL!$I$39) -> 0.32454342 | G19: ГОСТИНИЦА 5* - 150 номеров | H19: 0.10344828 | I19: 0.18980609 | J19: 0.23062273
B20: =Объекты!C6 -> Гостиница 4* | C20: =Объекты!F6/Объекты!$F$11 -> 0.2862254 | D20: =Объекты!E6/Объекты!$E$11 -> 0.34469306 | E20: =СВОД_PL!I34/(СВОД_PL!$I$32-СВОД_PL!$I$39) -> 0.26070729 | G20: ГОСТИНИЦЫ 4* - 400 номеров | H20: 0.27586207 | I20: 0.35452493 | J20: 0.29716591
B21: =Объекты!C7 -> Гостиница 3* | C21: =Объекты!F7/Объекты!$F$11 -> 0.2862254 | D21: =Объекты!E7/Объекты!$E$11 -> 0.19145317 | E21: =СВОД_PL!I35/(СВОД_PL!$I$32-СВОД_PL!$I$39) -> 0.2123097 | G21: ГОСТИНИЦЫ 3* - 900 номеров | H21: 0.62068966 | I21: 0.45566899 | J21: 0.47221136
B22: =Объекты!C8 -> Гостиница 2* | C22: =Объекты!F8/Объекты!$F$11 -> 0 | D22: =Объекты!E8/Объекты!$E$11 -> 0 | E22: =СВОД_PL!I36/(СВОД_PL!$I$32-СВОД_PL!$I$39) -> 0
B23: =Объекты!C9 -> Хостел в составе МФЦ | C23: =Объекты!F9/Объекты!$F$11 -> 0.18067979 | D23: =Объекты!E9/Объекты!$E$11 -> 0.069076766 | E23: =СВОД_PL!I37/(СВОД_PL!$I$32-СВОД_PL!$I$39) -> 0.078401992
B24: =Объекты!C10 -> Шале | C24: =Объекты!F10/Объекты!$F$11 -> 0.023255814 | D24: =Объекты!E10/Объекты!$E$11 -> 0.064655853 | E24: =СВОД_PL!I38/(СВОД_PL!$I$32-СВОД_PL!$I$39) -> 0.12403759
B26: =Объекты!C13 -> Туристские резиденции | C26: продажа | D26: продажа | E26: продажа | G26: Апартаменты на продажу | H26: продажа | I26: продажа | J26: продажа
C27: =Объекты!F13 -> 385 | D27: единиц | H27: 1600 | I27: единиц
B29: Гипотетическая продажа гостиниц в 2030 году | G29: Операционный бизнес - с гипотетической продажей в 2037 году | M29: Результаты 2021 года
C30: Баланс потоков с учетом дисконтирования | H30: Баланс потоков с учетом дисконтирования | N30: Баланс потоков с учетом дисконтирования
C31: продажа гостиниц | D31: =СВОД_PL!E79*CF_15!H67 -> 5.8674974e+09 | H31: операционная прибыль гостиницы + инфр-ра | I31: =CF_15!V13 -> 3.1654041e+09 | N31: продажа гостиниц (в 2024, 2025 и 2026) | O31: 1.1986016e+10
C32: продажа резиденций | D32: =CF_15!V14 -> 1.6416697e+09 | H32: продажа резиденций | I32: =D32 -> 1.6416697e+09 | N32: продажа апартаментов в собственность | O32: 3.7084427e+09
C33: TV курорта | D33: =SUM(CF_15!T11:T13)/CF_15!T52*(1-CF_15!T54)*CF_15!T67 -> 1.0017018e+08 | H33: TV курорта | I33: =CF_15!T69 -> 9.304746e+08 | N33: продажа апартов lease-back | O33: 5.3767635e+09
C34: возмещение НДС | D34: =CF_15!V39 -> 1.0975609e+09 | H34: возмещение НДС | I34: =D34 -> 1.0975609e+09 | N34: операционный бизнес | O34: 3.1744635e+09
C35: + кредит | D35: =CF_15!V43 -> 5.4032183e+09 | H35: + кредит | I35: =D35 -> 5.4032183e+09 | N35: TV курорта | O35: 2.3909139e+08
D36: =SUM(D31:D35) -> 1.4110116e+10 | I36: =SUM(I31:I35) -> 1.2238328e+10 | N36: возмещение НДС | O36: 2.0455235e+09
C37: - налог на прибыль | D37: =CF_15!V34 -> -3.5635576e+08 | H37: - налог на прибыль | I37: =D37 -> -3.5635576e+08 | N37: + кредит | O37: 1.4838806e+10
C38: % по кредиту | D38: =CF_15!V44 -> -7.9535064e+08 | H38: % по кредиту | I38: =D38 -> -7.9535064e+08 | O38: =SUM(O31:O37) -> 4.1369107e+10
C39: - выплата кредита | D39: =CF_15!V45 -> -1.9586056e+09 | H39: - выплата кредита | I39: =D39 -> -1.9586056e+09 | N39: минус НДС и земельный налог | O39: -1.5013278e+09
C40: инвестиции | D40: =CF_15!V37+CF_15!V38 -> -7.7239731e+09 | H40: инвестиции | I40: =D40 -> -7.7239731e+09 | N40: минус налог на прибыль | O40: -2.7368729e+09
C41: Общекурортные расходы | D41: =CF_15!V23 -> -4.0576285e+08 | H41: Общекурортные расходы | I41: =D41 -> -4.0576285e+08 | N41: % по кредиту | O41: -1.7286631e+09
D42: =D36+SUM(D37:D41) -> 2.8700685e+09 | I42: =I36+SUM(I37:I41) -> 9.9827965e+08 | N42: - выплата кредита | O42: -9.4267199e+09
N43: инвестиции | O43: -2.1957678e+10
H44: =B6&B10&" - "&D3 -> NPV С учетом терминальной стоимости - FCFE | I44: =D11 -> 998.27965 | N44: общекурортные | O44: -9.160025e+08
N45: баланс | O45: =O38+SUM(O39:O44) -> 3.1018421e+09
N47: =H44 -> NPV С учетом терминальной стоимости - FCFE | O47: 3101.8421
B53: Объект | E53: Площадь, кв.м | G53: CAPEX, млн руб. с НДС | H53: ВОД за 10 лет, млн руб. без НДС | I53: CAPEX, руб. с НДC/ кв.м | J53: ВОД за 10 лет, руб. без НДС/кв.м
B54: =Строительство!C33 -> Гостиница 5* | E54: =Объекты!E5 -> 11947.619 | G54: =Строительство!F33/10^6 -> 2563.5973 | H54: =SUM(Отель5_PL!D47:M47)/10^6 -> 3990.4886 | I54: =G54/$E54*10^6 -> 214569.72 | J54: =H54/$E54*10^6 -> 333998.65
B55: =Строительство!C38 -> Шале | E55: =Объекты!E10 -> 2340 | G55: =Строительство!F38/10^6 -> 263.42638 | H55: =SUM(Шале_PL!D47:M47)/10^6 -> 2017.9771 | I55: =G55/$E55*10^6 -> 112575.38 | J55: =H55/$E55*10^6 -> 862383.36
B56: =Строительство!C34 -> Гостиница 4* | E56: =Объекты!E6 -> 12475 | G56: =Строительство!F34/10^6 -> 2427.6455 | H56: =SUM(Отель4_PL!D47:M47)/10^6 -> 3367.351 | I56: =G56/$E56*10^6 -> 194600.84 | J56: =H56/$E56*10^6 -> 269927.93
B57: =Строительство!C35 -> Гостиница 3* | E57: =Объекты!E7 -> 6929 | G57: =Строительство!F35/10^6 -> 959.71084 | H57: =SUM(Отель3_PL!D47:M47)/10^6-SUM(Отель3_PL!D37:M37)/10^6 -> 2577.3557 | I57: =G57/$E57*10^6 -> 138506.4 | J57: =H57/$E57*10^6 -> 371966.48
B58: =Строительство!C36 -> Гостиница 2* | E58: =Объекты!E8 -> 0 | G58: =Строительство!F36/10^6 -> 0 | H58: =SUM(Отель2_PL!D47:M47)/10^6 -> 0 | I58: =IFERROR(G58/$E58*10^6,) -> 0 | J58: =IFERROR(H58/$E58*10^6,"")
B59: =Строительство!C37 -> МФЦ, в том числе хостел Jo&JOE | E59: =Объекты!E54 -> 10800 | G59: =Строительство!F37/10^6 -> 1098.5054 | H59: =SUM(H60:H63) -> 1539.3365 | I59: =G59/$E59*10^6 -> 101713.46 | J59: =H59/$E59*10^6 -> 142531.16
B60: =Бюджет_Синара!A214 -> Хостел | E60: =Объекты!E9 -> 2500 | H60: =SUM(Хостел_PL!D47:M47)/10^6 -> 1296.5884 | J60: =H60/$E60*10^6 -> 518635.35
B61: =Бюджет_Синара!A215 -> Рестораны | E61: =Объекты!E55 -> 150 | H61: =SUM(Retail!D46:M46)/10^6 -> 36.098291 | J61: =H61/$E61*10^6 -> 240655.27
B62: =Бюджет_Синара!A218 -> Торговая зона | E62: =Объекты!E58 -> 4000 | H62: =SUM(Retail!D45:M45)/10^6 -> 169.46516 | J62: =H62/$E62*10^6 -> 42366.289
B63: =Бюджет_Синара!A220 -> Парковка крытая | E63: =Бюджет_Синара!B220 -> 1200 | H63: =SUM(Паркинг_PL!D42:M42)/10^6 -> 37.1847 | J63: =H63/$E63*10^6 -> 30987.25
B64: =Строительство!C39 -> Туристские резиденции | E64: =Объекты!E13 -> 21950 | G64: =Строительство!F39/10^6 -> 3057.8931 | H64: =SUM(H65:H67) -> 8183.9645 | I64: =G64/$E64*10^6 -> 139311.76 | J64: =H64/$E64*10^6 -> 372845.76
B65: Туристские резиденции (вт.ч. ресторан) | E65: =SUM(Бюджет_Синара!B174:B178) -> 16452 | H65: =SUM(ПРОДАЖА_lease_back!CT40:DP40)+(SUM(Резиденции_PL!D79:M79)+SUM(Резиденции_PL!D87:M87))/10^6 -> 7911.1443 | J65: =H65/$E65*10^6 -> 480862.16
B66: =Объекты!C52 -> Торговая зона тур.резиденций | E66: =Объекты!E52 -> 3400 | H66: =SUM(Retail!D47:M47)/10^6 -> 251.08606 | J66: =H66/$E66*10^6 -> 73848.842
B67: =Объекты!C53 -> Лыжная школа | E67: =Объекты!E53 -> 200 | H67: =SUM(Retail!D48:M48)/10^6 -> 21.734118 | J67: =H67/$E67*10^6 -> 108670.59
B68: =Строительство!C40 -> Ресторан в зоне катания | E68: =Объекты!E60 -> 900 | G68: =Строительство!F40/10^6 -> 217.93674 | H68: =SUM(Ресторан!F76:O76)/10^6 -> 314.64097 | I68: =G68/$E68*10^6 -> 242151.93 | J68: =H68/$E68*10^6 -> 349601.08
B69: =Строительство!C41 -> SPA-комплекс | E69: =Объекты!E47 -> 1900 | G69: =Строительство!F41/10^6 -> 376.83578 | H69: =SUM(Отель3_PL!D37:M37)/10^6 -> 152.52583 | I69: =G69/$E69*10^6 -> 198334.62 | J69: =H69/$E69*10^6 -> 80276.751
B70: =Строительство!C42 -> Решения по генплану. Включают в себя благоустройство, инженерные сети, планировку участка. Не включают в себя создание инженерных сооружений (ТП, ВЗУ, КНС) | G70: =Строительство!F42/10^6 -> 23.139039
B71: =Строительство!C43 -> Наземный паркинг | G71: =Строительство!F43/10^6 -> 16.858443
B72: =Строительство!C44 -> Организация набережных | G72: =Строительство!F44/10^6 -> 158.6677
B73: =Строительство!C45 -> Трансформаторная подстанция | G73: =Строительство!F45/10^6 -> 15.86677
B74: =Строительство!C46 -> Канализационная насосная станция | G74: =Строительство!F46/10^6 -> 6.0293726
B75: =Строительство!C47 -> Стоимость проектных работ - 4% от СМР (мебель и технологическое оборудование не учитываются) | G75: =Строительство!F47/10^6 -> 286.09093
B76: ИТОГО | E76: =SUM(E54:E59)+E64+E68+E69 -> 69241.619 | G76: =SUM(G54:G75) -> 11472.203 | H76: =SUM(H54:H75) -> 31866.941 | I76: =G76/E76*10^6 -> 165683.64 | J76: =H76/E76*10^6 -> 460228.13

Sheet Объекты
A1: 1
C3: Сводные данные по номерному фонду Проекта
C4: Тип объекта | D4: Бренд (при наличии) | E4: Общая площадь, кв.м | F4: Кол-во номеров | G4: Кол-во мест | I4: Мест/ номер | J4: кв.м общей S/ номер | K4: Дата ввода в эксплуатацию | M4: Извлечение прибыли
C5: =Отель5!E2 -> Гостиница 5* | D5: =Отель5!F2 -> Mövenpick | E5: =Отель5!F4 -> 11947.619 | F5: =Отель5!F6 -> 125 | G5: =Отель5!F10 -> 276 | I5: =G5/F5 -> 2.208 | J5: =E5/F5 -> 95.580951 | K5: =Вводные!D10 -> 46204 | M5: Операционный бизнес
C6: =Отель4!E2 -> Гостиница 4* | D6: =Отель4!F2 -> Mercure | E6: =Отель4!F4 -> 12475 | F6: =Отель4!F6 -> 160 | G6: =Отель4!F9 -> 346 | I6: =G6/F6 -> 2.1625 | J6: =E6/F6 -> 77.96875 | K6: =Вводные!D11 -> 46204 | M6: Операционный бизнес
C7: =Отель3!E2 -> Гостиница 3* | D7: Возможный бренд: Ibis Styles | E7: =Отель3!F4 -> 6929 | F7: =Отель3!F6 -> 160 | G7: =Отель3!F9 -> 380 | I7: =G7/F7 -> 2.375 | J7: =E7/F7 -> 43.30625 | K7: =Вводные!D12 -> 45839 | M7: Операционный бизнес
C8: =Отель2!E2 -> Гостиница 2* | D8: =Отель2!F2 -> Ibis Budget | E8: 0 | F8: 0 | G8: 0 | M8: Операционный бизнес
C9: =Хостел!E2 -> Хостел в составе МФЦ | D9: =Хостел!F12 -> Jo&JOE | E9: =Хостел!F6 -> 2500 | F9: =Хостел!F7 -> 101 | G9: =Хостел!J12 -> 412 | I9: =G9/F9 -> 4.0792079 | J9: =E9/F9 -> 24.752475 | K9: =Вводные!D14 -> 45839 | M9: Операционный бизнес
C10: =Шале!E2 -> Шале | D10: =Шале!F2 -> Не брендируется (номерной фонд отеля 5*) | E10: =Шале!F4 -> 2340 | F10: =Шале!F6 -> 13 | G10: =Шале!F7 -> 78 | I10: =G10/F10 -> 6 | J10: =E10/F10 -> 180 | K10: =Вводные!D15 -> 46204 | M10: Операционный бизнес
C11: Итого по объектам в управлении | E11: =SUM(E5:E10) -> 36191.619 | F11: =SUM(F5:F10) -> 559 | G11: =SUM(G5:G10) -> 1492 | I11: =G11/F11 -> 2.6690519 | J11: =E11/F11 -> 64.743504
C13: =Резиденции!E2 -> Туристские резиденции | D13: =Резиденции!F2 -> Не брендируется | E13: =Резиденции!F4 -> 21950 | F13: =Резиденции!F6 -> 385 | G13: =Резиденции!F11 -> 980 | I13: =G13/F13 -> 2.5454545 | J13: =E13/F13 -> 57.012987 | K13: =Вводные!D16 -> 45839 | M13: Продажа по схеме lease-back
C14: ВСЕГО | E14: =E13+E11 -> 58141.619 | F14: =F13+F11 -> 944 | G14: =G13+G11 -> 2472 | I14: =G14/F14 -> 2.6186441 | J14: =E14/F14 -> 61.590698
C16: =C30 -> Функциональная составляющая | M16: =M4 -> Извлечение прибыли
C17: =C54 -> Многофункциональный центр
C18: =C55 -> Ресторан МФЦ | E18: =E55 -> 150 | F18: =F55 -> 70 | K18: =$K$13 -> 45839 | M18: Арендатор | O18: Расчет на листе Retail
C19: =C57 -> Общежитие служебное | E19: =E57 -> 1800 | F19: =F57 -> 300 | K19: =$K$13 -> 45839 | M19: Производственная необходимость
C20: =C58 -> Торговая зона МФЦ | E20: =E58 -> 4000 | K20: =$K$13 -> 45839 | M20: Арендаторы | O20: Расчет на листе Retail
C21: Торговые зоны
C22: =C52 -> Торговая зона тур.резиденций | D22: территория тур.резиденций | E22: =E52 -> 3400 | K22: =K13 -> 45839 | M22: Арендаторы | O22: Расчет на листе Retail
C23: =Резиденции!D21 -> Лыжная школа | D23: =D22 -> территория тур.резиденций | E23: =Резиденции!F21 -> 200 | K23: =K22 -> 45839 | M23: Арендатор | O23: Расчет на листе Retail
C24: =C42 -> Торговая зона отеля 4* | D24: =D42 -> с южной стороны отеля 4* | E24: =E42 -> 1000 | K24: =K6 -> 46204 | M24: Арендаторы | O24: Учет в составе PL отеля 4*
C25: =C60 -> Ресторан в зоне катания | E25: =E60 -> 900 | F25: =F60 -> 350 | M25: Операционный бизнес
C26: =C47 -> SPA-комплекс (отдельно стоящий) | E26: =E47 -> 1900 | M26: Операционный бизнес в составе PL Отеля 3*
M28: =Строительство!F53 -> 1.1472203e+10
C29: Данные по ЦФО | D29: дополнительно к номерному фонду
C30: Функциональная составляющая | D30: Комментарий | E30: Общая площадь, кв.м | F30: Кол-во посадочных мест (при наличии) | I30: Коэфф-т
C31: =C5&" - "&D5 -> Гостиница 5* - Mövenpick | E31: =Бюджет_Синара!B41 -> 11947.619
C32: Ресторан | E32: =Бюджет_Синара!B13 -> 327 | F32: =Отель5!F15 -> 100 | I32: =E32/F32 -> 3.27
C33: =Отель5!D17 -> Залы и переговорные | E33: =Отель5!F17 -> 175
C34: =Отель5!D18 -> Фойе | E34: =Отель5!F18 -> 135
C35: =Бюджет_Синара!A18 -> Оздоровительный центр/ СПА / фитнес | E35: =Отель5!F13 -> 1943
C36: =C10 -> Шале | E36: =E10 -> 2340
C37: =C6&" - "&D6 -> Гостиница 4* - Mercure | E37: =Бюджет_Синара!B84 -> 12475
C38: Ресторан | E38: =Отель4!F16 -> 313 | F38: =Отель4!F15 -> 150 | I38: =E38/F38 -> 2.0866667
C39: =Отель4!D17 -> Залы и переговорные | E39: =Отель4!F17 -> 520 | I39: в т.ч. многофункциональный конференц-зал (с мобильной перегородкой) на 300 кв.м
C40: =Отель4!D18 -> Фойе | E40: =Отель4!F18 -> 135
C41: =Бюджет_Синара!A61 -> Оздоровительный центр/ СПА / фитнес | E41: =Бюджет_Синара!B62 -> 3561
C42: Торговая зона отеля 4* | D42: с южной стороны отеля 4* | E42: =Отель4!F22 -> 1000
C43: =C7&" - "&D7 -> Гостиница 3* - Возможный бренд: Ibis Styles | E43: =Бюджет_Синара!B124 -> 6929
C44: Ресторан | E44: =Отель3!F14 -> 300 | F44: =Отель3!F13 -> 160 | I44: =E44/F44 -> 1.875
C45: =Отель3!D15 -> Залы и переговорные | E45: =Отель3!F15 -> 100
C46: =Отель3!D16 -> Фойе | E46: =Отель3!F16 -> 35
C47: SPA-комплекс (отдельно стоящий) | E47: =Бюджет_Синара!B233 -> 1900
C48: =C8&" - "&D8 -> Гостиница 2* - Ibis Budget
C49: Ресторан
C50: =C13 -> Туристские резиденции | E50: =Бюджет_Синара!B206 -> 21950
C51: Ресторан тур.резиденций | E51: =Резиденции!F19 -> 400 | F51: =Резиденции!F18 -> 200 | I51: =E51/F51 -> 2
C52: Торговая зона тур.резиденций | E52: =Резиденции!F20 -> 3400
C53: Лыжная школа | E53: =Резиденции!F21 -> 200
C54: Многофункциональный центр | E54: =Бюджет_Синара!B221 -> 10800
C55: Ресторан МФЦ | E55: =Бюджет_Синара!B215 -> 150 | F55: =Хостел!F13 -> 70 | I55: =E55/F55 -> 2.1428571
C56: Хостел
C57: =Хостел!D15 -> Общежитие служебное | E57: =Хостел!F15 -> 1800 | F57: =Хостел!F16 -> 300
C58: =Хостел!D18 -> Торговая зона МФЦ | D58: ТЦ с обособленными выходами, загрузкой | E58: =Хостел!F18 -> 4000
C59: Дополнительные точки питания на курорте
