Workbook

Sheet Дашборд
A1: ПЛАТО | DEVELOPMENT MODEL
A3: ="Проект: "&ОТЧЕТ!C1 -> Проект: Мишина | I3: Сценарий | L3: =Вводные!C3 -> Базовый
A5: ВЫРУЧКА, МЛН ₽ | D5: EBITDA, МЛН ₽ | G5: ЧИСТАЯ ПРИБЫЛЬ, МЛН ₽ | J5: МАРЖИНАЛЬНОСТЬ | M5: IRR EQUITY
A6: =ОТЧЕТ!C4 -> 21875.892 | D6: =ОТЧЕТ!C21 -> 5232.5088 | G6: =ОТЧЕТ!C24 -> 2849.8068 | J6: =ОТЧЕТ!C27 -> 0.13027157 | M6: =ОТЧЕТ!C29 -> N/A
A10: NPV @20%, МЛН ₽ | D10: LLCR С УЧЕТОМ БРИДЖ | G10: РАСЧЕТНЫЙ БРИДЖ, МЛН ₽ | J10: ФАКТИЧЕСКИЙ БРИДЖ, МЛН ₽ | M10: ПФ, МЛН ₽
A11: =ОТЧЕТ!C28 -> 2680.6691 | D11: =ОТЧЕТ!C30 -> 1.1968375 | G11: =Финансирование!C7 -> 1898.297 | J11: =ОТЧЕТ!C25 -> 1048.6505 | M11: =ОТЧЕТ!C26 -> 14264.843
A15: ЭКОНОМИКА ПРОЕКТА | J15: КЛЮЧЕВЫЕ ПАРАМЕТРЫ
A16: Стоимость покупки, млн ₽ | F16: =Вводные!G6 -> 700 | J16: Стартовая цена квартир, тыс. ₽/м² | M16: =Вводные!G11 -> 675
A17: Стоимость смены ВРИ, млн ₽ | F17: ='Расчет ВРИ (ТЭП)'!D73 -> 2141.838 | J17: Рост цены до РВЭ, %/мес. | M17: =Вводные!G46 -> 0.010991815
A18: Социальный платеж, млн ₽ | F18: ='Расчет ВРИ (ТЭП)'!D83 -> 988.447 | J18: Цена квартир на РВЭ, тыс. ₽/м² | M18: =IFERROR(INDEX(ПОДБОР_КВ.М!H64:DC64,1,MATCH(EDATE(Вводные!G8,Вводные!G9),ПОДБОР_КВ.М!H2:DC2,0)),0) -> 877.5
A19: Проектирование П и РД, млн ₽ | F19: =-ОТЧЕТ!C35 -> 230.055 | J19: Цена последних продаж, тыс. ₽/м² | M19: =IFERROR(LOOKUP(2,1/(ПОДБОР_КВ.М!H61:DC61>0),ПОДБОР_КВ.М!H64:DC64),0) -> 890.56523
J20: Средняя цена квартир, тыс. ₽/м² | M20: =F21 -> 788.59515
A21: Средневзвешенная цена квартир, тыс. ₽/м², NSA | F21: =IFERROR(ОТЧЕТ!C5*1000/ТЭП!G7,0) -> 788.59515 | J21: Расчетный БРИДЖ, млн ₽ | M21: =Финансирование!C7 -> 1898.297
A22: Полная себестоимость, тыс. ₽/м², NSA | F22: =-ОТЧЕТ!D13 -> 585.90477 | J22: Фактический БРИДЖ, млн ₽ | M22: =ОТЧЕТ!C25 -> 1048.6505
A23: Строительная себестоимость, тыс. ₽/м², NSA | F23: =-ОТЧЕТ!D18 -> 330.82291 | J23: Процентные расходы, млн ₽ | M23: =-ОТЧЕТ!C22 -> 1432.7396
A26: СТРУКТУРА ВЫРУЧКИ | I26: СТРУКТУРА ЗАТРАТ
A45: СТАВКИ, БРИДЖ, ПФ, ЭСКРОУ И LLCR
A46: Показатель | E46: Значение | G46: Ед. | H46: Комментарий | J46: БРИДЖ И КЛЮЧЕВЫЕ ДАТЫ
A47: Средневзвешенная ставка ПФ | E47: =Ставки!B4 -> 0.058023046 | G47: % год | H47: По ежемесячному остатку ПФ | J47: Покупка / начало проекта | N47: =Вводные!G7 -> 46266
A48: Средняя ставка БРИДЖ | E48: =Ставки!B5 -> 0.18924731 | G48: % год | H48: За период действия БРИДЖ | J48: Срок ИРД | N48: =Вводные!G48 -> 18
A49: Средневзвешенная совокупная ставка | E49: =Ставки!B6 -> 0.06810413 | G49: % год | H49: БРИДЖ + ПФ | J49: Дата РнС | N49: =Вводные!G8 -> 46813
A50: Расчетный лимит БРИДЖ | E50: =Ставки!B7 -> 931.04345 | G50: млн ₽ | H50: Потребность по модели | J50: Погашение БРИДЖ | N50: =EDATE(Вводные!G8,Вводные!G50) -> 46813
A51: Пиковая выборка БРИДЖ | E51: =Ставки!B8 -> 700.84525 | G51: млн ₽ | H51: Максимальный фактический остаток | J51: Срок БРИДЖ | N51: =Ставки!G6 -> 18
A52: Пиковая выборка ПФ | E52: =Ставки!B9 -> 14264.843 | G52: млн ₽ | H52: Максимальный остаток ПФ | J52: Старт продаж | N52: =Вводные!G10 -> 46813
A53: Среднее покрытие ПФ эскроу | E53: =Ставки!B11 -> 1.9901741 | G53: x | H53: Эскроу / ПФ | J53: РВЭ / окончание строительства | N53: =EDATE(Вводные!G8,Вводные!G9) -> 47543
A54: LLCR с учетом БРИДЖ | E54: =LLCR!C18 -> 1.1968375 | G54: x | H54: Без двойного учета перенесенных процентов | J54: Окончание продаж | N54: =EDATE(EDATE(Вводные!G8,Вводные!G9),Вводные!G51) -> 47727
A55: Корректировка процентов БРИДЖ | E55: =LLCR!C16 -> 200.58366 | G55: млн ₽ | H55: Исключается при переносе в ПФ | J55: Срок строительства | N55: =Вводные!G9 -> 24
A77: LLCR рассчитывается на дату окончательного погашения. При капитализации процентов БРИДЖ их отдельная строка исключается из знаменателя, поскольку эти проценты уже перенесены в ПФ. Подробная расшифровка — на листе «LLCR».

Sheet Вводные
A1: ПЛАТО — ВВОДНЫЕ ДАННЫЕ
A3: Активный сценарий | C3: Базовый
A5: Блок | B5: Параметр | C5: Ед. изм. | D5: Консервативный | E5: Базовый | F5: Оптимистичный | G5: Выбрано | H5: Исходная ячейка | I5: До изменения | J5: Комментарий
A6: Сделка | B6: Стоимость покупки / цена входа | C6: млн ₽ | D6: 700 | E6: 700 | F6: 700 | G6: =INDEX($D6:$F6,1,MATCH($C$3,$D$5:$F$5,0)) -> 700 | H6: ОТЧЕТ!C14 | I6: 3500 | J6: Вводится здесь; в ОТЧЕТ C14 передается со знаком минус
A7: Общие | B7: Начало проекта | C7: дата | D7: 46266 | E7: 46266 | F7: 46266 | G7: =INDEX($D7:$F7,1,MATCH($C$3,$D$5:$F$5,0)) -> 46266 | H7: ТЭП!C1 | I7: 46388
A8: Сроки | B8: Дата РнС | C8: дата | D8: =EDATE(D7,D48) -> 46997 | E8: =EDATE(E7,E48) -> 46813 | F8: =EDATE(F7,F48) -> 46692 | G8: =INDEX($D8:$F8,1,MATCH($C$3,$D$5:$F$5,0)) -> 46813 | H8: СРОКИ!C17 | I8: 46631 | J8: Дата рассчитывается автоматически: начало проекта + срок ИРД до РнС (строка 48).
A9: Сроки | B9: Срок строительства | C9: мес. | D9: 26 | E9: 24 | F9: 22 | G9: =INDEX($D9:$F9,1,MATCH($C$3,$D$5:$F$5,0)) -> 24 | H9: СРОКИ!C18 | I9: 24
A10: Сроки | B10: Старт продаж | C10: дата | D10: =EDATE(D8,D49) -> 47027 | E10: =EDATE(E8,E49) -> 46813 | F10: =EDATE(F8,F49) -> 46692 | G10: =INDEX($D10:$F10,1,MATCH($C$3,$D$5:$F$5,0)) -> 46813 | H10: СРОКИ!C16 | I10: 46661 | J10: Дата рассчитывается автоматически: РнС + лаг старта продаж (строка 49).
A11: Продажи | B11: Стартовая цена квартир | C11: тыс. ₽/м² | D11: 650 | E11: 675 | F11: 700 | G11: =INDEX($D11:$F11,1,MATCH($C$3,$D$5:$F$5,0)) -> 675 | H11: ПОДБОР_КВ.М!D33 | I11: 550
A12: Продажи | B12: Стартовая цена коммерции | C12: тыс. ₽/м² | D12: 500 | E12: 650 | F12: 575 | G12: =INDEX($D12:$F12,1,MATCH($C$3,$D$5:$F$5,0)) -> 650 | H12: ПОДБОР_КВ.М!D70 | I12: 500
A13: Продажи | B13: Цена машино-места | C13: тыс. ₽/шт. | D13: 3000 | E13: 4000 | F13: 5000 | G13: =INDEX($D13:$F13,1,MATCH($C$3,$D$5:$F$5,0)) -> 4000 | H13: ПОДБОР_КВ.М!D71 | I13: 5000
A14: Продажи | B14: Цена кладовой | C14: тыс. ₽/шт. | D14: 900 | E14: 1000 | F14: 1100 | G14: =INDEX($D14:$F14,1,MATCH($C$3,$D$5:$F$5,0)) -> 1000 | H14: ПОДБОР_КВ.М!D72 | I14: 1000
A15: Продажи | B15: Доля продаж до РВЭ | C15: % | D15: 0.8 | E15: 0.85 | F15: 0.9 | G15: =INDEX($D15:$F15,1,MATCH($C$3,$D$5:$F$5,0)) -> 0.85 | H15: ПОДБОР_КВ.М!D66 | I15: 6
A16: Продажи | B16: Смещение темпа продаж к поздним месяцам | C16: % | D16: 0.2 | E16: 0.25 | F16: 0.3 | G16: =INDEX($D16:$F16,1,MATCH($C$3,$D$5:$F$5,0)) -> 0.25 | H16: ПОДБОР_КВ.М!D17 | I16: 0.25 | J16: 0% = равномерный профиль (с учётом сезонности). Положительное значение плавно увеличивает вес более поздних месяцев до РВЭ; общий объём продаж не меняется.
A17: Продажи | B17: Инфляция после РВЭ | C17: % год | D17: 0.02 | E17: 0.03 | F17: 0.04 | G17: =INDEX($D17:$F17,1,MATCH($C$3,$D$5:$F$5,0)) -> 0.03 | H17: ПОДБОР_КВ.М!D18 | I17: 0.03
A18: Продажи | B18: Сезонное снижение темпа | C18: % | D18: -0.2 | E18: -0.15 | F18: -0.1 | G18: =INDEX($D18:$F18,1,MATCH($C$3,$D$5:$F$5,0)) -> -0.15 | H18: ПОДБОР_КВ.М!D10:D14 | I18: -0.15 | J18: Применяется к январю и маю–августу
A19: Продажи | B19: Рост цены — этап 1 | C19: % | D19: 0 | E19: 0 | F19: 0 | G19: =INDEX($D19:$F19,1,MATCH($C$3,$D$5:$F$5,0)) -> 0 | H19: ПОДБОР_КВ.М!F25 | I19: 0.15 | J19: Устаревший параметр: новый движок продаж не использует этапные скачки цены по строительной готовности.
A20: Продажи | B20: Рост цены — этап 2 | C20: % | D20: 0 | E20: 0 | F20: 0 | G20: =INDEX($D20:$F20,1,MATCH($C$3,$D$5:$F$5,0)) -> 0 | H20: ПОДБОР_КВ.М!F26 | I20: 0.15 | J20: Устаревший параметр: новый движок продаж не использует этапные скачки цены по строительной готовности.
A21: Продажи | B21: Рост цены — этап 3 | C21: % | D21: 0 | E21: 0 | F21: 0 | G21: =INDEX($D21:$F21,1,MATCH($C$3,$D$5:$F$5,0)) -> 0 | H21: ПОДБОР_КВ.М!F27 | I21: 0.05 | J21: Устаревший параметр: новый движок продаж не использует этапные скачки цены по строительной готовности.
A22: Продажи | B22: Рост цены — этап 4 | C22: % | D22: 0 | E22: 0 | F22: 0 | G22: =INDEX($D22:$F22,1,MATCH($C$3,$D$5:$F$5,0)) -> 0 | H22: ПОДБОР_КВ.М!F28 | I22: 0.05 | J22: Устаревший параметр: новый движок продаж не использует этапные скачки цены по строительной готовности.
A23: Строительство | B23: ИРД и согласования | C23: тыс. ₽/м² GBA | D23: 1.1 | E23: 1 | F23: 0.95 | G23: =INDEX($D23:$F23,1,MATCH($C$3,$D$5:$F$5,0)) -> 1 | H23: СРОКИ!C40 | I23: 1
A24: Строительство | B24: Проектирование стадии П | C24: тыс. ₽/м² GBA | D24: 2.75 | E24: 2.5 | F24: 2.35 | G24: =INDEX($D24:$F24,1,MATCH($C$3,$D$5:$F$5,0)) -> 2.5 | H24: СРОКИ!C41 | I24: 2.5
A25: Строительство | B25: Проектирование стадии РД | C25: тыс. ₽/м² GBA | D25: 2.75 | E25: 2.5 | F25: 2.35 | G25: =INDEX($D25:$F25,1,MATCH($C$3,$D$5:$F$5,0)) -> 2.5 | H25: СРОКИ!C42 | I25: 2.5
A26: Строительство | B26: Подготовительные работы | C26: тыс. ₽/м² GBA | D26: 1.2 | E26: 1 | F26: 0.9 | G26: =INDEX($D26:$F26,1,MATCH($C$3,$D$5:$F$5,0)) -> 1 | H26: СРОКИ!C43 | I26: 1
A27: Строительство | B27: Основное строительство ЖК | C27: тыс. ₽/м² GBA | D27: 225 | E27: 190 | F27: 175 | G27: =INDEX($D27:$F27,1,MATCH($C$3,$D$5:$F$5,0)) -> 190 | H27: СРОКИ!C44 | I27: 165
A28: Строительство | B28: Наружные инженерные сети | C28: тыс. ₽/м² GBA | D28: 8 | E28: 7 | F28: 6 | G28: =INDEX($D28:$F28,1,MATCH($C$3,$D$5:$F$5,0)) -> 7 | H28: СРОКИ!C49 | I28: 7.5
A29: Строительство | B29: Благоустройство | C29: тыс. ₽/м² GBA | D29: 4 | E29: 3.5 | F29: 4 | G29: =INDEX($D29:$F29,1,MATCH($C$3,$D$5:$F$5,0)) -> 3.5 | H29: СРОКИ!C50 | I29: 5
A30: Строительство | B30: Сдача и ввод | C30: тыс. ₽/м² GBA | D30: 1.1 | E30: 1 | F30: 0.9 | G30: =INDEX($D30:$F30,1,MATCH($C$3,$D$5:$F$5,0)) -> 1 | H30: СРОКИ!C51 | I30: 1
A31: Строительство | B31: Содержание стройплощадки | C31: тыс. ₽/м² GBA | D31: 1.2 | E31: 1 | F31: 0.9 | G31: =INDEX($D31:$F31,1,MATCH($C$3,$D$5:$F$5,0)) -> 1 | H31: СРОКИ!C52 | I31: 1
A32: Строительство | B32: Вознаграждение генподрядчика | C32: % СМР | D32: 0.08 | E32: 0.07 | F32: 0.05 | G32: =INDEX($D32:$F32,1,MATCH($C$3,$D$5:$F$5,0)) -> 0.07 | H32: cf_1/cf_2!E129 | I32: 0.035
A33: Строительство | B33: Резерв | C33: % | D33: 0.07 | E33: 0.05 | F33: 0.03 | G33: =INDEX($D33:$F33,1,MATCH($C$3,$D$5:$F$5,0)) -> 0.05 | H33: cf_1/cf_2!E180 | I33: 0.05
A34: Строительство | B34: Управление проектом | C34: % | D34: 0.06 | E34: 0.05 | F34: 0.04 | G34: =INDEX($D34:$F34,1,MATCH($C$3,$D$5:$F$5,0)) -> 0.05 | H34: cf_1/cf_2!E182 | I34: 0.05
... A38: Налоги | B38: НДС | C38: % | D38: 0.22 | E38: 0.22 | F38: 0.22 | G38: =INDEX($D38:$F38,1,MATCH($C$3,$D$5:$F$5,0)) -> 0.22 | H38: cf_1/cf_2!E66 | I38: 0.22
A39: Финансирование | B39: Спред БРИДЖ | C39: п.п. | D39: 0.07 | E39: 0.06 | F39: 0.05 | G39: =INDEX($D39:$F39,1,MATCH($C$3,$D$5:$F$5,0)) -> 0.06 | H39: КРЕДИТЫ!D13 | I39: 0.06 | J39: Размер БРИДЖ не вводится — рассчитывается на листе Финансирование
A40: Финансирование | B40: Спред капитализации БРИДЖ | C40: п.п. | D40: 0.07 | E40: 0.06 | F40: 0.05 | G40: =INDEX($D40:$F40,1,MATCH($C$3,$D$5:$F$5,0)) -> 0.06 | H40: КРЕДИТЫ!D14 | I40: 0.06
A41: Финансирование | B41: Спред ПФ | C41: п.п. | D41: 0.055 | E41: 0.045 | F41: 0.035 | G41: =INDEX($D41:$F41,1,MATCH($C$3,$D$5:$F$5,0)) -> 0.045 | H41: КРЕДИТЫ!D15 | I41: 0.045
A42: Финансирование | B42: Специальная ставка ПФ | C42: % | D42: 0.05 | E42: 0.045 | F42: 0.04 | G42: =INDEX($D42:$F42,1,MATCH($C$3,$D$5:$F$5,0)) -> 0.045 | H42: КРЕДИТЫ!D16 | I42: 0.045
A43: Финансирование | B43: Плата за лимит | C43: % | D43: 0.0075 | E43: 0.005 | F43: 0.0035 | G43: =INDEX($D43:$F43,1,MATCH($C$3,$D$5:$F$5,0)) -> 0.005 | H43: КРЕДИТЫ!D19 | I43: 0.005
A44: Финансирование | B44: Плата за резервирование | C44: % | D44: 0.0075 | E44: 0.005 | F44: 0.0035 | G44: =INDEX($D44:$F44,1,MATCH($C$3,$D$5:$F$5,0)) -> 0.005 | H44: КРЕДИТЫ!D20 | I44: 0.005
A45: Оценка | B45: Ставка дисконтирования | C45: % | D45: 0.25 | E45: 0.2 | F45: 0.18 | G45: =INDEX($D45:$F45,1,MATCH($C$3,$D$5:$F$5,0)) -> 0.2 | H45: CF!I94 | I45: 0.2
A46: Продажи | B46: Ежемесячный рост цены до РВЭ | C46: % в месяц | D46: =IFERROR((1+D52)^(1/MAX(1,12*(YEAR(EDATE(D8,D9))-YEAR(D10))+MONTH(EDATE(D8,D9))-MONTH(D10)))-1,0) -> 0.00731952 | E46: =IFERROR((1+E52)^(1/MAX(1,12*(YEAR(EDATE(E8,E9))-YEAR(E10))+MONTH(EDATE(E8,E9))-MONTH(E10)))-1,0) -> 0.010991815 | F46: =IFERROR((1+F52)^(1/MAX(1,12*(YEAR(EDATE(F8,F9))-YEAR(F10))+MONTH(EDATE(F8,F9))-MONTH(F10)))-1,0) -> 0.015411747 | G46: =INDEX($D46:$F46,1,MATCH($C$3,$D$5:$F$5,0)) -> 0.010991815 | H46: ПОДБОР_КВ.М!H69:DC72 | J46: Расчётный месячный сложный рост, обеспечивающий целевой совокупный рост из строки 52 к РВЭ.
A47: Продажи | B47: Ежемесячный рост цены после РВЭ | C47: % в месяц | D47: =(1+D17)^(1/12)-1 -> 0.0016515813 | E47: =(1+E17)^(1/12)-1 -> 0.0024662698 | F47: =(1+F17)^(1/12)-1 -> 0.0032737398 | G47: =INDEX($D47:$F47,1,MATCH($C$3,$D$5:$F$5,0)) -> 0.0024662698 | H47: ПОДБОР_КВ.М!H69:DC72 | J47: Расчётный месячный темп из годовой инфляции после РВЭ (строка 17).
A48: Сроки | B48: Срок ИРД до РнС | C48: мес. | D48: 24 | E48: 18 | F48: 14 | G48: =INDEX($D48:$F48,1,MATCH($C$3,$D$5:$F$5,0)) -> 18 | H48: расчет даты РнС | J48: Период от начала проекта до РнС. Можно задавать 1 месяц и другие короткие сроки: предпроектные работы не уходят раньше даты начала проекта, а расходы перераспределяются автоматически.
A49: Сроки | B49: Лаг старта продаж после РнС | C49: мес. | D49: 1 | E49: 0 | F49: 0 | G49: =INDEX($D49:$F49,1,MATCH($C$3,$D$5:$F$5,0)) -> 0 | H49: расчет старта продаж | J49: Позволяет отдельно настроить начало продаж после РнС
A50: Финансирование | B50: Лаг погашения БРИДЖ после РнС | C50: мес. | D50: 0 | E50: 0 | F50: 0 | G50: =INDEX($D50:$F50,1,MATCH($C$3,$D$5:$F$5,0)) -> 0 | H50: КРЕДИТЫ!D40 | J50: БРИДЖ действует с даты покупки до РнС плюс указанный лаг
A51: Продажи | B51: Остаточные продажи после РВЭ | C51: мес. | D51: 12 | E51: 6 | F51: 3 | G51: =INDEX($D51:$F51,1,MATCH($C$3,$D$5:$F$5,0)) -> 6 | H51: календарный график | J51: Используется для расчета даты окончания продаж
A52: Продажи | B52: Целевой совокупный рост цены от старта продаж до РВЭ | C52: % | D52: 0.2 | E52: 0.3 | F52: 0.4 | G52: =INDEX($D52:$F52,1,MATCH($C$3,$D$5:$F$5,0)) -> 0.3 | H52: ПОДБОР_КВ.М!H69:DC69 | J52: Основной ценовой ориентир. Месячный темп в строке 46 рассчитывается автоматически из срока от старта продаж до РВЭ.
A53: ПРОГНОЗ КЛЮЧЕВОЙ СТАВКИ
A54: Сценарий ставки | C54: Низкая | D54: Текущая ключевая ставка | E54: 0.1425 | F54: Срок выхода на цель, мес. | G54: 31 | H54: Дата актуальности | I54: =DATE(YEAR(TODAY()),MONTH(TODAY()),1) -> 46204 | J54: https://www.cbr.ru/key-indicators/
A55: Целевая ставка | C55: % год | D55: 0.13 | E55: 0.11 | F55: 0.1 | G55: =INDEX($D$55:$F$55,1,MATCH($C$54,{"Высокая","Базовая","Низкая"},0)) -> 0.1 | H55: Конец финансового горизонта | I55: =MAX(EDATE(EDATE($G$8,$G$9),$G$51),EDATE($G$8,$G$50)) -> 47727 | J55: Целевые ставки сохранены из исходной кривой модели: 10% / 8% / 6%. Все значения редактируются.
A56: Дата | B56: Мес. от старта | C56: Ед. изм. | D56: Высокая | E56: Базовая | F56: Низкая | G56: =INDEX($D56:$F56,1,MATCH($C$54,$D$56:$F$56,0)) -> Низкая | H56: Стадия кривой | I56: Горизонт | J56: Комментарий
A57: =$I$54 -> 46204 | B57: =0 -> 0 | C57: % год | D57: =$E$54 -> 0.1425 | E57: =$E$54 -> 0.1425 | F57: =$E$54 -> 0.1425 | G57: =INDEX($D57:$F57,1,MATCH($C$54,$D$56:$F$56,0)) -> 0.1425 | H57: Старт | I57: =$I$55 -> 47727 | J57: Первая точка = текущая ключевая ставка
A58: =EDATE($I$54,ROUND(1*MAX(0,12*(YEAR($I$55)-YEAR($I$54))+MONTH($I$55)-MONTH($I$54))/20,0)) -> 46296 | B58: =MAX(0,12*(YEAR(A58)-YEAR($I$54))+MONTH(A58)-MONTH($I$54)) -> 3 | C58: % год | D58: =IF($G$54<=0,$D$55,$E$54+($D$55-$E$54)*MIN(1,B58/$G$54)) -> 0.14129032 | E58: =IF($G$54<=0,$E$55,$E$54+($E$55-$E$54)*MIN(1,B58/$G$54)) -> 0.13935484 | F58: =IF($G$54<=0,$F$55,$E$54+($F$55-$E$54)*MIN(1,B58/$G$54)) -> 0.1383871 | G58: =INDEX($D58:$F58,1,MATCH($C$54,$D$56:$F$56,0)) -> 0.1383871 | H58: =IF(B58=0,"Старт",IF(B58<$G$54,"Нормализация","Target")) -> Нормализация | I58: =$I$55 -> 47727 | J58: =IF(B58<$G$54,"Линейный выход к целевой ставке","Целевая ставка до конца проекта") -> Линейный выход к целевой ставке
A59: =EDATE($I$54,ROUND(2*MAX(0,12*(YEAR($I$55)-YEAR($I$54))+MONTH($I$55)-MONTH($I$54))/20,0)) -> 46357 | B59: =MAX(0,12*(YEAR(A59)-YEAR($I$54))+MONTH(A59)-MONTH($I$54)) -> 5 | C59: % год | D59: =IF($G$54<=0,$D$55,$E$54+($D$55-$E$54)*MIN(1,CB6759/$G$54)) -> 0.1425 | E59: =IF($G$54<=0,$E$55,$E$54+($E$55-$E$54)*MIN(1,B59/$G$54)) -> 0.13725806 | F59: =IF($G$54<=0,$F$55,$E$54+($F$55-$E$54)*MIN(1,B59/$G$54)) -> 0.13564516 | G59: =INDEX($D59:$F59,1,MATCH($C$54,$D$56:$F$56,0)) -> 0.13564516 | H59: =IF(B59=0,"Старт",IF(B59<$G$54,"Нормализация","Target")) -> Нормализация | I59: =$I$55 -> 47727 | J59: =IF(B59<$G$54,"Линейный выход к целевой ставке","Целевая ставка до конца проекта") -> Линейный выход к целевой ставке
A60: =EDATE($I$54,ROUND(3*MAX(0,12*(YEAR($I$55)-YEAR($I$54))+MONTH($I$55)-MONTH($I$54))/20,0)) -> 46447 | B60: =MAX(0,12*(YEAR(A60)-YEAR($I$54))+MONTH(A60)-MONTH($I$54)) -> 8 | C60: % год | D60: =IF($G$54<=0,$D$55,$E$54+($D$55-$E$54)*MIN(1,B60/$G$54)) -> 0.13927419 | E60: =IF($G$54<=0,$E$55,$E$54+($E$55-$E$54)*MIN(1,B60/$G$54)) -> 0.1341129 | F60: =IF($G$54<=0,$F$55,$E$54+($F$55-$E$54)*MIN(1,B60/$G$54)) -> 0.13153226 | G60: =INDEX($D60:$F60,1,MATCH($C$54,$D$56:$F$56,0)) -> 0.13153226 | H60: =IF(B60=0,"Старт",IF(B60<$G$54,"Нормализация","Target")) -> Нормализация | I60: =$I$55 -> 47727 | J60: =IF(B60<$G$54,"Линейный выход к целевой ставке","Целевая ставка до конца проекта") -> Линейный выход к целевой ставке
A61: =EDATE($I$54,ROUND(4*MAX(0,12*(YEAR($I$55)-YEAR($I$54))+MONTH($I$55)-MONTH($I$54))/20,0)) -> 46508 | B61: =MAX(0,12*(YEAR(A61)-YEAR($I$54))+MONTH(A61)-MONTH($I$54)) -> 10 | C61: % год | D61: =IF($G$54<=0,$D$55,$E$54+($D$55-$E$54)*MIN(1,B61/$G$54)) -> 0.13846774 | E61: =IF($G$54<=0,$E$55,$E$54+($E$55-$E$54)*MIN(1,B61/$G$54)) -> 0.13201613 | F61: =IF($G$54<=0,$F$55,$E$54+($F$55-$E$54)*MIN(1,B61/$G$54)) -> 0.12879032 | G61: =INDEX($D61:$F61,1,MATCH($C$54,$D$56:$F$56,0)) -> 0.12879032 | H61: =IF(B61=0,"Старт",IF(B61<$G$54,"Нормализация","Target")) -> Нормализация | I61: =$I$55 -> 47727 | J61: =IF(B61<$G$54,"Линейный выход к целевой ставке","Целевая ставка до конца проекта") -> Линейный выход к целевой ставке
A62: =EDATE($I$54,ROUND(5*MAX(0,12*(YEAR($I$55)-YEAR($I$54))+MONTH($I$55)-MONTH($I$54))/20,0)) -> 46600 | B62: =MAX(0,12*(YEAR(A62)-YEAR($I$54))+MONTH(A62)-MONTH($I$54)) -> 13 | C62: % год | D62: =IF($G$54<=0,$D$55,$E$54+($D$55-$E$54)*MIN(1,B62/$G$54)) -> 0.13725806 | E62: =IF($G$54<=0,$E$55,$E$54+($E$55-$E$54)*MIN(1,B62/$G$54)) -> 0.12887097 | F62: =IF($G$54<=0,$F$55,$E$54+($F$55-$E$54)*MIN(1,B62/$G$54)) -> 0.12467742 | G62: =INDEX($D62:$F62,1,MATCH($C$54,$D$56:$F$56,0)) -> 0.12467742 | H62: =IF(B62=0,"Старт",IF(B62<$G$54,"Нормализация","Target")) -> Нормализация | I62: =$I$55 -> 47727 | J62: =IF(B62<$G$54,"Линейный выход к целевой ставке","Целевая ставка до конца проекта") -> Линейный выход к целевой ставке
A63: =EDATE($I$54,ROUND(6*MAX(0,12*(YEAR($I$55)-YEAR($I$54))+MONTH($I$55)-MONTH($I$54))/20,0)) -> 46661 | B63: =MAX(0,12*(YEAR(A63)-YEAR($I$54))+MONTH(A63)-MONTH($I$54)) -> 15 | C63: % год | D63: =IF($G$54<=0,$D$55,$E$54+($D$55-$E$54)*MIN(1,B63/$G$54)) -> 0.13645161 | E63: =IF($G$54<=0,$E$55,$E$54+($E$55-$E$54)*MIN(1,B63/$G$54)) -> 0.12677419 | F63: =IF($G$54<=0,$F$55,$E$54+($F$55-$E$54)*MIN(1,B63/$G$54)) -> 0.12193548 | G63: =INDEX($D63:$F63,1,MATCH($C$54,$D$56:$F$56,0)) -> 0.12193548 | H63: =IF(B63=0,"Старт",IF(B63<$G$54,"Нормализация","Target")) -> Нормализация | I63: =$I$55 -> 47727 | J63: =IF(B63<$G$54,"Линейный выход к целевой ставке","Целевая ставка до конца проекта") -> Линейный выход к целевой ставке
A64: =EDATE($I$54,ROUND(7*MAX(0,12*(YEAR($I$55)-YEAR($I$54))+MONTH($I$55)-MONTH($I$54))/20,0)) -> 46753 | B64: =MAX(0,12*(YEAR(A64)-YEAR($I$54))+MONTH(A64)-MONTH($I$54)) -> 18 | C64: % год | D64: =IF($G$54<=0,$D$55,$E$54+($D$55-$E$54)*MIN(1,B64/$G$54)) -> 0.13524194 | E64: =IF($G$54<=0,$E$55,$E$54+($E$55-$E$54)*MIN(1,B64/$G$54)) -> 0.12362903 | F64: =IF($G$54<=0,$F$55,$E$54+($F$55-$E$54)*MIN(1,B64/$G$54)) -> 0.11782258 | G64: =INDEX($D64:$F64,1,MATCH($C$54,$D$56:$F$56,0)) -> 0.11782258 | H64: =IF(B64=0,"Старт",IF(B64<$G$54,"Нормализация","Target")) -> Нормализация | I64: =$I$55 -> 47727 | J64: =IF(B64<$G$54,"Линейный выход к целевой ставке","Целевая ставка до конца проекта") -> Линейный выход к целевой ставке
A65: =EDATE($I$54,ROUND(8*MAX(0,12*(YEAR($I$55)-YEAR($I$54))+MONTH($I$55)-MONTH($I$54))/20,0)) -> 46813 | B65: =MAX(0,12*(YEAR(A65)-YEAR($I$54))+MONTH(A65)-MONTH($I$54)) -> 20 | C65: % год | D65: =IF($G$54<=0,$D$55,$E$54+($D$55-$E$54)*MIN(1,B65/$G$54)) -> 0.13443548 | E65: =IF($G$54<=0,$E$55,$E$54+($E$55-$E$54)*MIN(1,B65/$G$54)) -> 0.12153226 | F65: =IF($G$54<=0,$F$55,$E$54+($F$55-$E$54)*MIN(1,B65/$G$54)) -> 0.11508065 | G65: =INDEX($D65:$F65,1,MATCH($C$54,$D$56:$F$56,0)) -> 0.11508065 | H65: =IF(B65=0,"Старт",IF(B65<$G$54,"Нормализация","Target")) -> Нормализация | I65: =$I$55 -> 47727 | J65: =IF(B65<$G$54,"Линейный выход к целевой ставке","Целевая ставка до конца проекта") -> Линейный выход к целевой ставке
A66: =EDATE($I$54,ROUND(9*MAX(0,12*(YEAR($I$55)-YEAR($I$54))+MONTH($I$55)-MONTH($I$54))/20,0)) -> 46905 | B66: =MAX(0,12*(YEAR(A66)-YEAR($I$54))+MONTH(A66)-MONTH($I$54)) -> 23 | C66: % год | D66: =IF($G$54<=0,$D$55,$E$54+($D$55-$E$54)*MIN(1,B66/$G$54)) -> 0.13322581 | E66: =IF($G$54<=0,$E$55,$E$54+($E$55-$E$54)*MIN(1,B66/$G$54)) -> 0.1183871 | F66: =IF($G$54<=0,$F$55,$E$54+($F$55-$E$54)*MIN(1,B66/$G$54)) -> 0.11096774 | G66: =INDEX($D66:$F66,1,MATCH($C$54,$D$56:$F$56,0)) -> 0.11096774 | H66: =IF(B66=0,"Старт",IF(B66<$G$54,"Нормализация","Target")) -> Нормализация | I66: =$I$55 -> 47727 | J66: =IF(B66<$G$54,"Линейный выход к целевой ставке","Целевая ставка до конца проекта") -> Линейный выход к целевой ставке
A67: =EDATE($I$54,ROUND(10*MAX(0,12*(YEAR($I$55)-YEAR($I$54))+MONTH($I$55)-MONTH($I$54))/20,0)) -> 46966 | B67: =MAX(0,12*(YEAR(A67)-YEAR($I$54))+MONTH(A67)-MONTH($I$54)) -> 25 | C67: % год | D67: =IF($G$54<=0,$D$55,$E$54+($D$55-$E$54)*MIN(1,B67/$G$54)) -> 0.13241935 | E67: =IF($G$54<=0,$E$55,$E$54+($E$55-$E$54)*MIN(1,B67/$G$54)) -> 0.11629032 | F67: =IF($G$54<=0,$F$55,$E$54+($F$55-$E$54)*MIN(1,B67/$G$54)) -> 0.10822581 | G67: =INDEX($D67:$F67,1,MATCH($C$54,$D$56:$F$56,0)) -> 0.10822581 | H67: =IF(B67=0,"Старт",IF(B67<$G$54,"Нормализация","Target")) -> Нормализация | I67: =$I$55 -> 47727 | J67: =IF(B67<$G$54,"Линейный выход к целевой ставке","Целевая ставка до конца проекта") -> Линейный выход к целевой ставке
A68: =EDATE($I$54,ROUND(11*MAX(0,12*(YEAR($I$55)-YEAR($I$54))+MONTH($I$55)-MONTH($I$54))/20,0)) -> 47058 | B68: =MAX(0,12*(YEAR(A68)-YEAR($I$54))+MONTH(A68)-MONTH($I$54)) -> 28 | C68: % год | D68: =IF($G$54<=0,$D$55,$E$54+($D$55-$E$54)*MIN(1,B68/$G$54)) -> 0.13120968 | E68: =IF($G$54<=0,$E$55,$E$54+($E$55-$E$54)*MIN(1,B68/$G$54)) -> 0.11314516 | F68: =IF($G$54<=0,$F$55,$E$54+($F$55-$E$54)*MIN(1,B68/$G$54)) -> 0.1041129 | G68: =INDEX($D68:$F68,1,MATCH($C$54,$D$56:$F$56,0)) -> 0.1041129 | H68: =IF(B68=0,"Старт",IF(B68<$G$54,"Нормализация","Target")) -> Нормализация | I68: =$I$55 -> 47727 | J68: =IF(B68<$G$54,"Линейный выход к целевой ставке","Целевая ставка до конца проекта") -> Линейный выход к целевой ставке
A69: =EDATE($I$54,ROUND(12*MAX(0,12*(YEAR($I$55)-YEAR($I$54))+MONTH($I$55)-MONTH($I$54))/20,0)) -> 47119 | B69: =MAX(0,12*(YEAR(A69)-YEAR($I$54))+MONTH(A69)-MONTH($I$54)) -> 30 | C69: % год | D69: =IF($G$54<=0,$D$55,$E$54+($D$55-$E$54)*MIN(1,B69/$G$54)) -> 0.13040323 | E69: =IF($G$54<=0,$E$55,$E$54+($E$55-$E$54)*MIN(1,B69/$G$54)) -> 0.11104839 | F69: =IF($G$54<=0,$F$55,$E$54+($F$55-$E$54)*MIN(1,B69/$G$54)) -> 0.10137097 | G69: =INDEX($D69:$F69,1,MATCH($C$54,$D$56:$F$56,0)) -> 0.10137097 | H69: =IF(B69=0,"Старт",IF(B69<$G$54,"Нормализация","Target")) -> Нормализация | I69: =$I$55 -> 47727 | J69: =IF(B69<$G$54,"Линейный выход к целевой ставке","Целевая ставка до конца проекта") -> Линейный выход к целевой ставке
A70: =EDATE($I$54,ROUND(13*MAX(0,12*(YEAR($I$55)-YEAR($I$54))+MONTH($I$55)-MONTH($I$54))/20,0)) -> 47209 | B70: =MAX(0,12*(YEAR(A70)-YEAR($I$54))+MONTH(A70)-MONTH($I$54)) -> 33 | C70: % год | D70: =IF($G$54<=0,$D$55,$E$54+($D$55-$E$54)*MIN(1,B70/$G$54)) -> 0.13 | E70: =IF($G$54<=0,$E$55,$E$54+($E$55-$E$54)*MIN(1,B70/$G$54)) -> 0.11 | F70: =IF($G$54<=0,$F$55,$E$54+($F$55-$E$54)*MIN(1,B70/$G$54)) -> 0.1 | G70: =INDEX($D70:$F70,1,MATCH($C$54,$D$56:$F$56,0)) -> 0.1 | H70: =IF(B70=0,"Старт",IF(B70<$G$54,"Нормализация","Target")) -> Target | I70: =$I$55 -> 47727 | J70: =IF(B70<$G$54,"Линейный выход к целевой ставке","Целевая ставка до конца проекта") -> Целевая ставка до конца проекта
A71: =EDATE($I$54,ROUND(14*MAX(0,12*(YEAR($I$55)-YEAR($I$54))+MONTH($I$55)-MONTH($I$54))/20,0)) -> 47270 | B71: =MAX(0,12*(YEAR(A71)-YEAR($I$54))+MONTH(A71)-MONTH($I$54)) -> 35 | C71: % год | D71: =IF($G$54<=0,$D$55,$E$54+($D$55-$E$54)*MIN(1,B71/$G$54)) -> 0.13 | E71: =IF($G$54<=0,$E$55,$E$54+($E$55-$E$54)*MIN(1,B71/$G$54)) -> 0.11 | F71: =IF($G$54<=0,$F$55,$E$54+($F$55-$E$54)*MIN(1,B71/$G$54)) -> 0.1 | G71: =INDEX($D71:$F71,1,MATCH($C$54,$D$56:$F$56,0)) -> 0.1 | H71: =IF(B71=0,"Старт",IF(B71<$G$54,"Нормализация","Target")) -> Target | I71: =$I$55 -> 47727 | J71: =IF(B71<$G$54,"Линейный выход к целевой ставке","Целевая ставка до конца проекта") -> Целевая ставка до конца проекта
A72: =EDATE($I$54,ROUND(15*MAX(0,12*(YEAR($I$55)-YEAR($I$54))+MONTH($I$55)-MONTH($I$54))/20,0)) -> 47362 | B72: =MAX(0,12*(YEAR(A72)-YEAR($I$54))+MONTH(A72)-MONTH($I$54)) -> 38 | C72: % год | D72: =IF($G$54<=0,$D$55,$E$54+($D$55-$E$54)*MIN(1,B72/$G$54)) -> 0.13 | E72: =IF($G$54<=0,$E$55,$E$54+($E$55-$E$54)*MIN(1,B72/$G$54)) -> 0.11 | F72: =IF($G$54<=0,$F$55,$E$54+($F$55-$E$54)*MIN(1,B72/$G$54)) -> 0.1 | G72: =INDEX($D72:$F72,1,MATCH($C$54,$D$56:$F$56,0)) -> 0.1 | H72: =IF(B72=0,"Старт",IF(B72<$G$54,"Нормализация","Target")) -> Target | I72: =$I$55 -> 47727 | J72: =IF(B72<$G$54,"Линейный выход к целевой ставке","Целевая ставка до конца проекта") -> Целевая ставка до конца проекта
A73: =EDATE($I$54,ROUND(16*MAX(0,12*(YEAR($I$55)-YEAR($I$54))+MONTH($I$55)-MONTH($I$54))/20,0)) -> 47423 | B73: =MAX(0,12*(YEAR(A73)-YEAR($I$54))+MONTH(A73)-MONTH($I$54)) -> 40 | C73: % год | D73: =IF($G$54<=0,$D$55,$E$54+($D$55-$E$54)*MIN(1,B73/$G$54)) -> 0.13 | E73: =IF($G$54<=0,$E$55,$E$54+($E$55-$E$54)*MIN(1,B73/$G$54)) -> 0.11 | F73: =IF($G$54<=0,$F$55,$E$54+($F$55-$E$54)*MIN(1,B73/$G$54)) -> 0.1 | G73: =INDEX($D73:$F73,1,MATCH($C$54,$D$56:$F$56,0)) -> 0.1 | H73: =IF(B73=0,"Старт",IF(B73<$G$54,"Нормализация","Target")) -> Target | I73: =$I$55 -> 47727 | J73: =IF(B73<$G$54,"Линейный выход к целевой ставке","Целевая ставка до конца проекта") -> Целевая ставка до конца проекта
A74: =EDATE($I$54,ROUND(17*MAX(0,12*(YEAR($I$55)-YEAR($I$54))+MONTH($I$55)-MONTH($I$54))/20,0)) -> 47515 | B74: =MAX(0,12*(YEAR(A74)-YEAR($I$54))+MONTH(A74)-MONTH($I$54)) -> 43 | C74: % год | D74: =IF($G$54<=0,$D$55,$E$54+($D$55-$E$54)*MIN(1,B74/$G$54)) -> 0.13 | E74: =IF($G$54<=0,$E$55,$E$54+($E$55-$E$54)*MIN(1,B74/$G$54)) -> 0.11 | F74: =IF($G$54<=0,$F$55,$E$54+($F$55-$E$54)*MIN(1,B74/$G$54)) -> 0.1 | G74: =INDEX($D74:$F74,1,MATCH($C$54,$D$56:$F$56,0)) -> 0.1 | H74: =IF(B74=0,"Старт",IF(B74<$G$54,"Нормализация","Target")) -> Target | I74: =$I$55 -> 47727 | J74: =IF(B74<$G$54,"Линейный выход к целевой ставке","Целевая ставка до конца проекта") -> Целевая ставка до конца проекта
A75: =EDATE($I$54,ROUND(18*MAX(0,12*(YEAR($I$55)-YEAR($I$54))+MONTH($I$55)-MONTH($I$54))/20,0)) -> 47574 | B75: =MAX(0,12*(YEAR(A75)-YEAR($I$54))+MONTH(A75)-MONTH($I$54)) -> 45 | C75: % год | D75: =IF($G$54<=0,$D$55,$E$54+($D$55-$E$54)*MIN(1,B75/$G$54)) -> 0.13 | E75: =IF($G$54<=0,$E$55,$E$54+($E$55-$E$54)*MIN(1,B75/$G$54)) -> 0.11 | F75: =IF($G$54<=0,$F$55,$E$54+($F$55-$E$54)*MIN(1,B75/$G$54)) -> 0.1 | G75: =INDEX($D75:$F75,1,MATCH($C$54,$D$56:$F$56,0)) -> 0.1 | H75: =IF(B75=0,"Старт",IF(B75<$G$54,"Нормализация","Target")) -> Target | I75: =$I$55 -> 47727 | J75: =IF(B75<$G$54,"Линейный выход к целевой ставке","Целевая ставка до конца проекта") -> Целевая ставка до конца проекта
A76: =EDATE($I$54,ROUND(19*MAX(0,12*(YEAR($I$55)-YEAR($I$54))+MONTH($I$55)-MONTH($I$54))/20,0)) -> 47665 | B76: =MAX(0,12*(YEAR(A76)-YEAR($I$54))+MONTH(A76)-MONTH($I$54)) -> 48 | C76: % год | D76: =IF($G$54<=0,$D$55,$E$54+($D$55-$E$54)*MIN(1,B76/$G$54)) -> 0.13 | E76: =IF($G$54<=0,$E$55,$E$54+($E$55-$E$54)*MIN(1,B76/$G$54)) -> 0.11 | F76: =IF($G$54<=0,$F$55,$E$54+($F$55-$E$54)*MIN(1,B76/$G$54)) -> 0.1 | G76: =INDEX($D76:$F76,1,MATCH($C$54,$D$56:$F$56,0)) -> 0.1 | H76: =IF(B76=0,"Старт",IF(B76<$G$54,"Нормализация","Target")) -> Target | I76: =$I$55 -> 47727 | J76: =IF(B76<$G$54,"Линейный выход к целевой ставке","Целевая ставка до конца проекта") -> Целевая ставка до конца проекта
A77: =$I$55 -> 47727 | B77: =MAX(0,12*(YEAR(A77)-YEAR($I$54))+MONTH(A77)-MONTH($I$54)) -> 50 | C77: % год | D77: =IF($G$54<=0,$D$55,$E$54+($D$55-$E$54)*MIN(1,B77/$G$54)) -> 0.13 | E77: =IF($G$54<=0,$E$55,$E$54+($E$55-$E$54)*MIN(1,B77/$G$54)) -> 0.11 | F77: =IF($G$54<=0,$F$55,$E$54+($F$55-$E$54)*MIN(1,B77/$G$54)) -> 0.1 | G77: =INDEX($D77:$F77,1,MATCH($C$54,$D$56:$F$56,0)) -> 0.1 | H77: =IF(B77=0,"Старт",IF(B77<$G$54,"Нормализация","Target")) -> Target | I77: =$I$55 -> 47727 | J77: =IF(B77<$G$54,"Линейный выход к целевой ставке","Целевая ставка до конца проекта") -> Целевая ставка до конца проекта
A80: СОЦИАЛЬНАЯ НАГРУЗКА: КОМПЕНСАЦИЯ ИЛИ РЕАЛЬНОЕ СТРОИТЕЛЬСТВО
A81: Блок | B81: Параметр | C81: Ед. изм. | D81: Консервативный | E81: Базовый | F81: Оптимистичный | G81: Выбрано | H81: Связь с моделью | I81: До изменения | J81: Комментарий
A82: Соцнагрузка | B82: Форма исполнения | C82: режим | G82: Денежная компенсация | H82: ОБЪЕКТЫ КРТ | J82: Компенсация — сумма с листа «Расчет ВРИ (ТЭП)»; строительство — мощность × стоимость единицы
A83: Соцнагрузка | B83: Дата денежной компенсации | C83: дата | D83: =EDATE(D8,-1) -> 46966 | E83: =EDATE(E8,-1) -> 46784 | F83: =EDATE(F8,-1) -> 46661 | G83: =INDEX($D83:$F83,1,MATCH($C$3,$D$81:$F$81,0)) -> 46784 | H83: ОБЪЕКТЫ КРТ / БРИДЖ | J83: По умолчанию — за 1 месяц до РнС. Дату можно изменить отдельно по каждому сценарию.
A84: ДОУ | B84: Количество мест | C84: мест | D84: 250 | E84: 250 | F84: 250 | G84: =INDEX($D84:$F84,1,MATCH($C$3,$D$81:$F$81,0)) -> 250 | H84: Расчет ВРИ (ТЭП)!D30 | J84: Редактируемая мощность
A85: ДОУ | B85: Себестоимость одного места | C85: млн ₽/место | D85: ='Расчет ВРИ (ТЭП)'!$E$84/1000000 -> 0.0096696364 | E85: ='Расчет ВРИ (ТЭП)'!$E$84/1000000 -> 0.0096696364 | F85: ='Расчет ВРИ (ТЭП)'!$E$84/1000000 -> 0.0096696364 | G85: =INDEX($D85:$F85,1,MATCH($C$3,$D$81:$F$81,0)) -> 0.0096696364 | H85: ОБЪЕКТЫ КРТ | J85: All-in стоимость места
A86: ДОУ | B86: Начало строительства | C86: дата | D86: =EDATE(D8,-1) -> 46966 | E86: =EDATE(E8,-1) -> 46784 | F86: =EDATE(F8,-1) -> 46661 | G86: =INDEX($D86:$F86,1,MATCH($C$3,$D$81:$F$81,0)) -> 46784 | H86: ОБЪЕКТЫ КРТ
A87: ДОУ | B87: Срок строительства | C87: мес. | D87: 24 | E87: 24 | F87: 24 | G87: =INDEX($D87:$F87,1,MATCH($C$3,$D$81:$F$81,0)) -> 24 | H87: ОБЪЕКТЫ КРТ | J87: S-профиль 10% / 70% / 20%
A88: ДОУ | B88: Итоговая стоимость | C88: млн ₽ | D88: =D84*D85 -> 2.4174091 | E88: =E84*E85 -> 2.4174091 | F88: =F84*F85 -> 2.4174091 | G88: =G84*G85 -> 2.4174091 | H88: ОБЪЕКТЫ КРТ
A89: СОШ | B89: Количество мест | C89: мест | D89: 0 | E89: 0 | F89: 0 | G89: =INDEX($D89:$F89,1,MATCH($C$3,$D$81:$F$81,0)) -> 0 | H89: Расчет ВРИ (ТЭП)!D31 | J89: Редактируемая мощность
A90: СОШ | B90: Себестоимость одного места | C90: млн ₽/место | D90: ='Расчет ВРИ (ТЭП)'!$E$85/1000000 -> 0.0074936471 | E90: ='Расчет ВРИ (ТЭП)'!$E$85/1000000 -> 0.0074936471 | F90: ='Расчет ВРИ (ТЭП)'!$E$85/1000000 -> 0.0074936471 | G90: =INDEX($D90:$F90,1,MATCH($C$3,$D$81:$F$81,0)) -> 0.0074936471 | H90: ОБЪЕКТЫ КРТ | J90: All-in стоимость места
A91: СОШ | B91: Начало строительства | C91: дата | D91: =EDATE(D8,-1) -> 46966 | E91: =EDATE(E8,-1) -> 46784 | F91: =EDATE(F8,-1) -> 46661 | G91: =INDEX($D91:$F91,1,MATCH($C$3,$D$81:$F$81,0)) -> 46784 | H91: ОБЪЕКТЫ КРТ
A92: СОШ | B92: Срок строительства | C92: мес. | D92: 30 | E92: 30 | F92: 30 | G92: =INDEX($D92:$F92,1,MATCH($C$3,$D$81:$F$81,0)) -> 30 | H92: ОБЪЕКТЫ КРТ | J92: S-профиль 10% / 70% / 20%
A93: СОШ | B93: Итоговая стоимость | C93: млн ₽ | D93: =D89*D90 -> 0 | E93: =E89*E90 -> 0 | F93: =F89*F90 -> 0 | G93: =G89*G90 -> 0 | H93: ОБЪЕКТЫ КРТ
A94: Поликлиника | B94: Мощность | C94: пос./смену | D94: ='Расчет ВРИ (ТЭП)'!$D$54 -> 15 | E94: ='Расчет ВРИ (ТЭП)'!$D$54 -> 15 | F94: ='Расчет ВРИ (ТЭП)'!$D$54 -> 15 | G94: =INDEX($D94:$F94,1,MATCH($C$3,$D$81:$F$81,0)) -> 15 | H94: Расчет ВРИ (ТЭП)!D32 | J94: Редактируемая мощность
A95: Поликлиника | B95: Себестоимость единицы мощности | C95: млн ₽/(пос./смену) | D95: ='Расчет ВРИ (ТЭП)'!$E$86/1000000 -> 0.010652067 | E95: ='Расчет ВРИ (ТЭП)'!$E$86/1000000 -> 0.010652067 | F95: ='Расчет ВРИ (ТЭП)'!$E$86/1000000 -> 0.010652067 | G95: =INDEX($D95:$F95,1,MATCH($C$3,$D$81:$F$81,0)) -> 0.010652067 | H95: ОБЪЕКТЫ КРТ | J95: All-in стоимость единицы
A96: Поликлиника | B96: Начало строительства | C96: дата | D96: =EDATE(D8,-1) -> 46966 | E96: =EDATE(E8,-1) -> 46784 | F96: =EDATE(F8,-1) -> 46661 | G96: =INDEX($D96:$F96,1,MATCH($C$3,$D$81:$F$81,0)) -> 46784 | H96: ОБЪЕКТЫ КРТ
A97: Поликлиника | B97: Срок строительства | C97: мес. | D97: 24 | E97: 24 | F97: 24 | G97: =INDEX($D97:$F97,1,MATCH($C$3,$D$81:$F$81,0)) -> 24 | H97: ОБЪЕКТЫ КРТ | J97: S-профиль 10% / 70% / 20%
A98: Поликлиника | B98: Итоговая стоимость | C98: млн ₽ | D98: =D94*D95 -> 0.159781 | E98: =E94*E95 -> 0.159781 | F98: =F94*F95 -> 0.159781 | G98: =G94*G95 -> 0.159781 | H98: ОБЪЕКТЫ КРТ
A99: Соцнагрузка | B99: ИТОГО строительство соцобъектов | C99: млн ₽ | G99: =SUM(G88,G93,G98) -> 2.5771901 | H99: ОБЪЕКТЫ КРТ
A100: Соцнагрузка | B100: Компенсация по расчету ВРИ | C100: млн ₽ | G100: ='Расчет ВРИ (ТЭП)'!D83 -> 988.447 | H100: Расчет ВРИ (ТЭП)!D83
A101: Соцнагрузка | B101: Отклонение строительства от компенсации | C101: млн ₽ | G101: =G99-G100 -> -985.86981 | H101: ОБЪЕКТЫ КРТ
A104: ОТДЕЛЬНО СТОЯЩИЕ КОММЕРЧЕСКИЕ ОБЪЕКТЫ: СТРОИТЕЛЬСТВО И ПРОДАЖА
A105: Блок | B105: Параметр | C105: Ед. изм. | D105: Консервативный | E105: Базовый | F105: Оптимистичный | G105: Выбрано | H105: Связь с моделью | I105: До изменения | J105: Комментарий
A106: МФОЦ / офисы | B106: Объект включен | C106: Да / Нет | G106: Нет | H106: ОБЪЕКТЫ КРТ | J106: Только строительство и продажа
A107: МФОЦ / офисы | B107: Общая площадь (GBA) | C107: м² | D107: =D108/0.8 -> 26700 | E107: =E108/0.8 -> 26700 | F107: =F108/0.8 -> 26700 | G107: =INDEX($D107:$F107,1,MATCH($C$3,$D$105:$F$105,0)) -> 26700 | H107: ТЭП!C10:D10
A108: МФОЦ / офисы | B108: Продаваемая площадь | C108: м² | D108: 21360 | E108: 21360 | F108: 21360 | G108: =INDEX($D108:$F108,1,MATCH($C$3,$D$105:$F$105,0)) -> 21360 | H108: ТЭП!F10:G10
A109: МФОЦ / офисы | B109: Начало строительства | C109: дата | D109: =D8 -> 46997 | E109: =E8 -> 46813 | F109: =F8 -> 46692 | G109: =INDEX($D109:$F109,1,MATCH($C$3,$D$105:$F$105,0)) -> 46813 | H109: ОБЪЕКТЫ КРТ
...

Sheet ОТЧЕТ
B1: ПРОЕКТ: | C1: Мишина | AZ1: Месяц | BA1: Темп продаж квартир, м²/мес | BB1: Цена квартир, тыс. ₽/м² | BD1: Месяц | BE1: Эскроу, остаток, млн ₽ | BF1: Затраты проекта, нараст., млн ₽ | BG1: Остаток ПФ, млн ₽
B2: ФЭП | G2: ТЭП | AZ2: ='План продаж'!B22 -> 46266 | BA2: =IFERROR('План продаж'!G22,0) -> 0 | BB2: =IFERROR('План продаж'!I22/1000,0) -> 0 | BD2: =INDEX(КРЕДИТЫ!$S$3:$EO$3,1,ROW()-1) -> 46266 | BE2: =(SUM(cf_1!$S$9:INDEX(cf_1!$S$9:$EO$9,1,ROW()-1))+SUM(cf_2!$S$9:INDEX(cf_2!$S$9:$EO$9,1,ROW()-1))-SUM(cf_1!$S$209:INDEX(cf_1!$S$209:$EO$209,1,ROW()-1))-SUM(cf_2!$S$209:INDEX(cf_2!$S$209:$EO$209,1,ROW()-1)))/1000000 -> 0 | BF2: =(SUM(cf_1!$S$183:INDEX(cf_1!$S$183:$EO$183,1,ROW()-1))+SUM(cf_2!$S$183:INDEX(cf_2!$S$183:$EO$183,1,ROW()-1)))/1000000 -> 0 | BG2: =(INDEX(КРЕДИТЫ!$S$52:$EO$52,1,ROW()-1)+INDEX(КРЕДИТЫ!$S$75:$EO$75,1,ROW()-1))/1000000 -> 0
B3: Показатель | C3: ИТОГО млн.р | D3: Тыс. руб/кв.м NSA | E3: Тыс. руб/кв.м GBA | G3: Показатель | H3: ГНС, кв.м | I3: Общая площадь, кв.м | J3: k выхода полезной площади | K3: Полезная площадь, кв.м | L3: Продаваемая площадь, кв.м | M3: Передаваемая площадь, кв.м | N3: Штуки | O3: ср S, кв.м | AZ3: ='План продаж'!B23 -> 46296 | BA3: =IFERROR('План продаж'!G23,0) -> 0 | BB3: =IFERROR('План продаж'!I23/1000,0) -> 0 | BD3: =INDEX(КРЕДИТЫ!$S$3:$EO$3,1,ROW()-1) -> 46296 | BE3: =(SUM(cf_1!$S$9:INDEX(cf_1!$S$9:$EO$9,1,ROW()-1))+SUM(cf_2!$S$9:INDEX(cf_2!$S$9:$EO$9,1,ROW()-1))-SUM(cf_1!$S$209:INDEX(cf_1!$S$209:$EO$209,1,ROW()-1))-SUM(cf_2!$S$209:INDEX(cf_2!$S$209:$EO$209,1,ROW()-1)))/1000000 -> 0 | BF3: =(SUM(cf_1!$S$183:INDEX(cf_1!$S$183:$EO$183,1,ROW()-1))+SUM(cf_2!$S$183:INDEX(cf_2!$S$183:$EO$183,1,ROW()-1)))/1000000 -> 0 | BG3: =(INDEX(КРЕДИТЫ!$S$52:$EO$52,1,ROW()-1)+INDEX(КРЕДИТЫ!$S$75:$EO$75,1,ROW()-1))/1000000 -> 0
B4: Поступления | C4: =SUM(C5:C12) -> 21875.892 | D4: =IFERROR(C4/$L$4*1000,0) -> 673.66404 | E4: =IFERROR(C4/$I$4*1000,0) -> 521.22688 | G4: ИТОГО | H4: =H5+H16+H9+H10+H11 -> 46011 | I4: =I5+I16+I9+I10+I11 -> 41970 | K4: =K5+K16+K9+K10+K11 -> 32473 | L4: =L5+L16+L9+L10+L11 -> 32473 | AZ4: ='План продаж'!B24 -> 46327 | BA4: =IFERROR('План продаж'!G24,0) -> 0 | BB4: =IFERROR('План продаж'!I24/1000,0) -> 0 | BD4: =INDEX(КРЕДИТЫ!$S$3:$EO$3,1,ROW()-1) -> 46327 | BE4: =(SUM(cf_1!$S$9:INDEX(cf_1!$S$9:$EO$9,1,ROW()-1))+SUM(cf_2!$S$9:INDEX(cf_2!$S$9:$EO$9,1,ROW()-1))-SUM(cf_1!$S$209:INDEX(cf_1!$S$209:$EO$209,1,ROW()-1))-SUM(cf_2!$S$209:INDEX(cf_2!$S$209:$EO$209,1,ROW()-1)))/1000000 -> 0 | BF4: =(SUM(cf_1!$S$183:INDEX(cf_1!$S$183:$EO$183,1,ROW()-1))+SUM(cf_2!$S$183:INDEX(cf_2!$S$183:$EO$183,1,ROW()-1)))/1000000 -> 0.84525 | BG4: =(INDEX(КРЕДИТЫ!$S$52:$EO$52,1,ROW()-1)+INDEX(КРЕДИТЫ!$S$75:$EO$75,1,ROW()-1))/1000000 -> 0
B5: Квартиры | C5: =CF!I13 -> 19471.203 | D5: =IFERROR(C5/$L$7*1000,0) -> 788.59515 | E5: =IFERROR(C5/$H$7*1000,0) -> 512.58892 | G5: Основные объекты | H5: =H6+H13 -> 46011 | I5: =I6+I13 -> 41970 | K5: =K6+K13 -> 32473 | L5: =L6+L13 -> 32473 | M5: =M6+M13 -> 0 | AZ5: ='План продаж'!B25 -> 46357 | BA5: =IFERROR('План продаж'!G25,0) -> 0 | BB5: =IFERROR('План продаж'!I25/1000,0) -> 0 | BD5: =INDEX(КРЕДИТЫ!$S$3:$EO$3,1,ROW()-1) -> 46357 | BE5: =(SUM(cf_1!$S$9:INDEX(cf_1!$S$9:$EO$9,1,ROW()-1))+SUM(cf_2!$S$9:INDEX(cf_2!$S$9:$EO$9,1,ROW()-1))-SUM(cf_1!$S$209:INDEX(cf_1!$S$209:$EO$209,1,ROW()-1))-SUM(cf_2!$S$209:INDEX(cf_2!$S$209:$EO$209,1,ROW()-1)))/1000000 -> 0 | BF5: =(SUM(cf_1!$S$183:INDEX(cf_1!$S$183:$EO$183,1,ROW()-1))+SUM(cf_2!$S$183:INDEX(cf_2!$S$183:$EO$183,1,ROW()-1)))/1000000 -> 701.6905 | BG5: =(INDEX(КРЕДИТЫ!$S$52:$EO$52,1,ROW()-1)+INDEX(КРЕДИТЫ!$S$75:$EO$75,1,ROW()-1))/1000000 -> 0
B6: Коммерция 1 эт. | C6: =CF!I14 -> 1656.9844 | D6: =IFERROR(C6/$L$8*1000,0) -> 759.38792 | E6: =IFERROR(C6/$H$8*1000,0) -> 683.29256 | G6: Наземная часть | H6: =SUM(H7:H8) -> 40411 | I6: =SUM(I7:I8) -> 36370 | J6: =IFERROR(K6/I6,0) -> 0.7388782 | K6: =SUM(K7:K8) -> 26873 | L6: =SUM(L7:L8) -> 26873 | M6: =SUM(M7:M8) -> 0 | AZ6: ='План продаж'!B26 -> 46388 | BA6: =IFERROR('План продаж'!G26,0) -> 0 | BB6: =IFERROR('План продаж'!I26/1000,0) -> 0 | BD6: =INDEX(КРЕДИТЫ!$S$3:$EO$3,1,ROW()-1) -> 46388 | BE6: =(SUM(cf_1!$S$9:INDEX(cf_1!$S$9:$EO$9,1,ROW()-1))+SUM(cf_2!$S$9:INDEX(cf_2!$S$9:$EO$9,1,ROW()-1))-SUM(cf_1!$S$209:INDEX(cf_1!$S$209:$EO$209,1,ROW()-1))-SUM(cf_2!$S$209:INDEX(cf_2!$S$209:$EO$209,1,ROW()-1)))/1000000 -> 0 | BF6: =(SUM(cf_1!$S$183:INDEX(cf_1!$S$183:$EO$183,1,ROW()-1))+SUM(cf_2!$S$183:INDEX(cf_2!$S$183:$EO$183,1,ROW()-1)))/1000000 -> 702.53575 | BG6: =(INDEX(КРЕДИТЫ!$S$52:$EO$52,1,ROW()-1)+INDEX(КРЕДИТЫ!$S$75:$EO$75,1,ROW()-1))/1000000 -> 0
B7: Коммерция ОСЗ | C7: =CF!I7 -> 0 | D7: =IFERROR(C7/$L$4*1000,0) -> 0 | E7: =IFERROR(C7/$I$4*1000,0) -> 0 | G7: Квартиры | H7: =ТЭП!C7 -> 37986 | I7: =ТЭП!D7 -> 34188 | J7: =IFERROR(K7/I7,0) -> 0.72221247 | K7: =ТЭП!F7 -> 24691 | L7: =ТЭП!G7 -> 24691 | M7: =ТЭП!H7 -> 0 | N7: =ТЭП!I7 -> 357 | O7: =K7/N7 -> 69.162465 | AZ7: ='План продаж'!B27 -> 46419 | BA7: =IFERROR('План продаж'!G27,0) -> 0 | BB7: =IFERROR('План продаж'!I27/1000,0) -> 0 | BD7: =INDEX(КРЕДИТЫ!$S$3:$EO$3,1,ROW()-1) -> 46419 | BE7: =(SUM(cf_1!$S$9:INDEX(cf_1!$S$9:$EO$9,1,ROW()-1))+SUM(cf_2!$S$9:INDEX(cf_2!$S$9:$EO$9,1,ROW()-1))-SUM(cf_1!$S$209:INDEX(cf_1!$S$209:$EO$209,1,ROW()-1))-SUM(cf_2!$S$209:INDEX(cf_2!$S$209:$EO$209,1,ROW()-1)))/1000000 -> 0 | BF7: =(SUM(cf_1!$S$183:INDEX(cf_1!$S$183:$EO$183,1,ROW()-1))+SUM(cf_2!$S$183:INDEX(cf_2!$S$183:$EO$183,1,ROW()-1)))/1000000 -> 703.381 | BG7: =(INDEX(КРЕДИТЫ!$S$52:$EO$52,1,ROW()-1)+INDEX(КРЕДИТЫ!$S$75:$EO$75,1,ROW()-1))/1000000 -> 0
B8: Офисы | C8: =CF!I6 -> 0 | D8: =IFERROR(C8/$L$10*1000,0) -> 0 | E8: =IFERROR(C8/$H$10*1000,0) -> 0 | G8: Коммерция 1 эт. | H8: =ТЭП!C8 -> 2425 | I8: =ТЭП!D8 -> 2182 | J8: =IFERROR(K8/I8,0) -> 1 | K8: =ТЭП!F8 -> 2182 | L8: =ТЭП!G8 -> 2182 | M8: =ТЭП!H8 -> 0 | N8: =ТЭП!I8 -> 0 | AZ8: ='План продаж'!B28 -> 46447 | BA8: =IFERROR('План продаж'!G28,0) -> 0 | BB8: =IFERROR('План продаж'!I28/1000,0) -> 0 | BD8: =INDEX(КРЕДИТЫ!$S$3:$EO$3,1,ROW()-1) -> 46447 | BE8: =(SUM(cf_1!$S$9:INDEX(cf_1!$S$9:$EO$9,1,ROW()-1))+SUM(cf_2!$S$9:INDEX(cf_2!$S$9:$EO$9,1,ROW()-1))-SUM(cf_1!$S$209:INDEX(cf_1!$S$209:$EO$209,1,ROW()-1))-SUM(cf_2!$S$209:INDEX(cf_2!$S$209:$EO$209,1,ROW()-1)))/1000000 -> 0 | BF8: =(SUM(cf_1!$S$183:INDEX(cf_1!$S$183:$EO$183,1,ROW()-1))+SUM(cf_2!$S$183:INDEX(cf_2!$S$183:$EO$183,1,ROW()-1)))/1000000 -> 704.22625 | BG8: =(INDEX(КРЕДИТЫ!$S$52:$EO$52,1,ROW()-1)+INDEX(КРЕДИТЫ!$S$75:$EO$75,1,ROW()-1))/1000000 -> 0
B9: Подземный паркинг | C9: =CF!I16 -> 747.70503 | D9: =IFERROR(C9/$L$14*1000,0) -> 133.51876 | E9: =IFERROR(C9/$I$14*1000,0) -> 133.51876 | G9: Коммерция ОСЗ | H9: =ТЭП!C9 -> 0 | I9: =ТЭП!D9 -> 0 | J9: =IFERROR(K9/I9,0) -> 0 | K9: =ТЭП!F9 -> 0 | L9: =ТЭП!G9 -> 0 | M9: =ТЭП!H9 -> 0 | N9: =ТЭП!I9 -> 0 | AZ9: ='План продаж'!B29 -> 46478 | BA9: =IFERROR('План продаж'!G29,0) -> 0 | BB9: =IFERROR('План продаж'!I29/1000,0) -> 0 | BD9: =INDEX(КРЕДИТЫ!$S$3:$EO$3,1,ROW()-1) -> 46478 | BE9: =(SUM(cf_1!$S$9:INDEX(cf_1!$S$9:$EO$9,1,ROW()-1))+SUM(cf_2!$S$9:INDEX(cf_2!$S$9:$EO$9,1,ROW()-1))-SUM(cf_1!$S$209:INDEX(cf_1!$S$209:$EO$209,1,ROW()-1))-SUM(cf_2!$S$209:INDEX(cf_2!$S$209:$EO$209,1,ROW()-1)))/1000000 -> 0 | BF9: =(SUM(cf_1!$S$183:INDEX(cf_1!$S$183:$EO$183,1,ROW()-1))+SUM(cf_2!$S$183:INDEX(cf_2!$S$183:$EO$183,1,ROW()-1)))/1000000 -> 705.0715 | BG9: =(INDEX(КРЕДИТЫ!$S$52:$EO$52,1,ROW()-1)+INDEX(КРЕДИТЫ!$S$75:$EO$75,1,ROW()-1))/1000000 -> 0
B10: Наземный паркинг | C10: =CF!I15 -> 0 | D10: =IFERROR(C10/$L$4*1000,0) -> 0 | E10: =IFERROR(C10/$I$4*1000,0) -> 0 | G10: Офисы | H10: =ТЭП!C10 -> 0 | I10: =ТЭП!D10 -> 0 | J10: =IFERROR(K10/I10,0) -> 0 | K10: =ТЭП!F10 -> 0 | L10: =ТЭП!G10 -> 0 | M10: =ТЭП!H10 -> 0 | N10: =ТЭП!I10 -> 0 | AZ10: ='План продаж'!B30 -> 46508 | BA10: =IFERROR('План продаж'!G30,0) -> 0 | BB10: =IFERROR('План продаж'!I30/1000,0) -> 0 | BD10: =INDEX(КРЕДИТЫ!$S$3:$EO$3,1,ROW()-1) -> 46508 | BE10: =(SUM(cf_1!$S$9:INDEX(cf_1!$S$9:$EO$9,1,ROW()-1))+SUM(cf_2!$S$9:INDEX(cf_2!$S$9:$EO$9,1,ROW()-1))-SUM(cf_1!$S$209:INDEX(cf_1!$S$209:$EO$209,1,ROW()-1))-SUM(cf_2!$S$209:INDEX(cf_2!$S$209:$EO$209,1,ROW()-1)))/1000000 -> 0 | BF10: =(SUM(cf_1!$S$183:INDEX(cf_1!$S$183:$EO$183,1,ROW()-1))+SUM(cf_2!$S$183:INDEX(cf_2!$S$183:$EO$183,1,ROW()-1)))/1000000 -> 705.91675 | BG10: =(INDEX(КРЕДИТЫ!$S$52:$EO$52,1,ROW()-1)+INDEX(КРЕДИТЫ!$S$75:$EO$75,1,ROW()-1))/1000000 -> 0
B11: Кладовки | C11: =CF!I17 -> 0 | D11: =IFERROR(C11/$L$4*1000,0) -> 0 | E11: =IFERROR(C11/$I$4*1000,0) -> 0 | G11: Наземный паркинг | H11: =ТЭП!C11 -> 0 | I11: =ТЭП!D11 -> 0 | J11: =IFERROR(K11/I11,0) -> 0 | K11: =ТЭП!F11 -> 0 | L11: =ТЭП!G11 -> 0 | M11: =ТЭП!H11 -> 0 | N11: =ТЭП!I11 -> 0 | AZ11: ='План продаж'!B31 -> 46539 | BA11: =IFERROR('План продаж'!G31,0) -> 0 | BB11: =IFERROR('План продаж'!I31/1000,0) -> 0 | BD11: =INDEX(КРЕДИТЫ!$S$3:$EO$3,1,ROW()-1) -> 46539 | BE11: =(SUM(cf_1!$S$9:INDEX(cf_1!$S$9:$EO$9,1,ROW()-1))+SUM(cf_2!$S$9:INDEX(cf_2!$S$9:$EO$9,1,ROW()-1))-SUM(cf_1!$S$209:INDEX(cf_1!$S$209:$EO$209,1,ROW()-1))-SUM(cf_2!$S$209:INDEX(cf_2!$S$209:$EO$209,1,ROW()-1)))/1000000 -> 0 | BF11: =(SUM(cf_1!$S$183:INDEX(cf_1!$S$183:$EO$183,1,ROW()-1))+SUM(cf_2!$S$183:INDEX(cf_2!$S$183:$EO$183,1,ROW()-1)))/1000000 -> 706.762 | BG11: =(INDEX(КРЕДИТЫ!$S$52:$EO$52,1,ROW()-1)+INDEX(КРЕДИТЫ!$S$75:$EO$75,1,ROW()-1))/1000000 -> 0
B12: Прочие | C12: =SUM(CF!I8:I10) -> 0 | D12: =IFERROR(C12/$L$4*1000,0) -> 0 | E12: =IFERROR(C12/$I$4*1000,0) -> 0 | G12: Прочие | H12: =ТЭП!C12 -> 0 | I12: =ТЭП!D12 -> 0 | J12: =IFERROR(K12/I12,0) -> 0 | K12: =ТЭП!F12 -> 0 | L12: =ТЭП!G12 -> 0 | M12: =ТЭП!H12 -> 0 | N12: =ТЭП!I12 -> 0 | AZ12: ='План продаж'!B32 -> 46569 | BA12: =IFERROR('План продаж'!G32,0) -> 0 | BB12: =IFERROR('План продаж'!I32/1000,0) -> 0 | BD12: =INDEX(КРЕДИТЫ!$S$3:$EO$3,1,ROW()-1) -> 46569 | BE12: =(SUM(cf_1!$S$9:INDEX(cf_1!$S$9:$EO$9,1,ROW()-1))+SUM(cf_2!$S$9:INDEX(cf_2!$S$9:$EO$9,1,ROW()-1))-SUM(cf_1!$S$209:INDEX(cf_1!$S$209:$EO$209,1,ROW()-1))-SUM(cf_2!$S$209:INDEX(cf_2!$S$209:$EO$209,1,ROW()-1)))/1000000 -> 0 | BF12: =(SUM(cf_1!$S$183:INDEX(cf_1!$S$183:$EO$183,1,ROW()-1))+SUM(cf_2!$S$183:INDEX(cf_2!$S$183:$EO$183,1,ROW()-1)))/1000000 -> 707.60725 | BG12: =(INDEX(КРЕДИТЫ!$S$52:$EO$52,1,ROW()-1)+INDEX(КРЕДИТЫ!$S$75:$EO$75,1,ROW()-1))/1000000 -> 0
B13: Расходы | C13: =SUM(C14:C20)+SUM(C22:C23) -> -19026.086 | D13: =IFERROR(C13/$L$4*1000,0) -> -585.90477 | E13: =IFERROR(C13/$I$4*1000,0) -> -453.32584 | G13: Подземная часть | H13: =SUM(H14:H15) -> 5600 | I13: =SUM(I14:I15) -> 5600 | K13: =SUM(K14:K15) -> 5600 | L13: =SUM(L14:L15) -> 5600 | M13: =SUM(M14:M15) -> 0 | AZ13: ='План продаж'!B33 -> 46600 | BA13: =IFERROR('План продаж'!G33,0) -> 0 | BB13: =IFERROR('План продаж'!I33/1000,0) -> 0 | BD13: =INDEX(КРЕДИТЫ!$S$3:$EO$3,1,ROW()-1) -> 46600 | BE13: =(SUM(cf_1!$S$9:INDEX(cf_1!$S$9:$EO$9,1,ROW()-1))+SUM(cf_2!$S$9:INDEX(cf_2!$S$9:$EO$9,1,ROW()-1))-SUM(cf_1!$S$209:INDEX(cf_1!$S$209:$EO$209,1,ROW()-1))-SUM(cf_2!$S$209:INDEX(cf_2!$S$209:$EO$209,1,ROW()-1)))/1000000 -> 0 | BF13: =(SUM(cf_1!$S$183:INDEX(cf_1!$S$183:$EO$183,1,ROW()-1))+SUM(cf_2!$S$183:INDEX(cf_2!$S$183:$EO$183,1,ROW()-1)))/1000000 -> 708.4525 | BG13: =(INDEX(КРЕДИТЫ!$S$52:$EO$52,1,ROW()-1)+INDEX(КРЕДИТЫ!$S$75:$EO$75,1,ROW()-1))/1000000 -> 0
B14: Вход | C14: =-Вводные!G6 -> -700 | D14: =IFERROR(C14/$L$4*1000,0) -> -21.55637 | E14: =IFERROR(C14/$I$4*1000,0) -> -16.67858 | G14: Подземный паркинг | H14: =ТЭП!C14 -> 5600 | I14: =ТЭП!D14 -> 5600 | K14: =ТЭП!F14 -> 5600 | L14: =ТЭП!G14 -> 5600 | M14: =ТЭП!H14 -> 0 | N14: =ТЭП!I14 -> 160 | AZ14: ='План продаж'!B34 -> 46631 | BA14: =IFERROR('План продаж'!G34,0) -> 0 | BB14: =IFERROR('План продаж'!I34/1000,0) -> 0 | BD14: =INDEX(КРЕДИТЫ!$S$3:$EO$3,1,ROW()-1) -> 46631 | BE14: =(SUM(cf_1!$S$9:INDEX(cf_1!$S$9:$EO$9,1,ROW()-1))+SUM(cf_2!$S$9:INDEX(cf_2!$S$9:$EO$9,1,ROW()-1))-SUM(cf_1!$S$209:INDEX(cf_1!$S$209:$EO$209,1,ROW()-1))-SUM(cf_2!$S$209:INDEX(cf_2!$S$209:$EO$209,1,ROW()-1)))/1000000 -> 0 | BF14: =(SUM(cf_1!$S$183:INDEX(cf_1!$S$183:$EO$183,1,ROW()-1))+SUM(cf_2!$S$183:INDEX(cf_2!$S$183:$EO$183,1,ROW()-1)))/1000000 -> 764.65473 | BG14: =(INDEX(КРЕДИТЫ!$S$52:$EO$52,1,ROW()-1)+INDEX(КРЕДИТЫ!$S$75:$EO$75,1,ROW()-1))/1000000 -> 0
B15: Обременения / денежная компенсация | C15: =IF(Вводные!G82="Денежная компенсация",-Вводные!G100,0) -> -988.447 | D15: =IFERROR(C15/$L$4*1000,0) -> -30.439042 | E15: =IFERROR(C15/$I$4*1000,0) -> -23.551275 | G15: Кладовки | H15: =ТЭП!C15 -> 0 | I15: =ТЭП!D15 -> 0 | K15: =ТЭП!F15 -> 0 | L15: =ТЭП!G15 -> 0 | M15: =ТЭП!H15 -> 0 | N15: =ТЭП!I15 -> 0 | AZ15: ='План продаж'!B35 -> 46661 | BA15: =IFERROR('План продаж'!G35,0) -> 0 | BB15: =IFERROR('План продаж'!I35/1000,0) -> 0 | BD15: =INDEX(КРЕДИТЫ!$S$3:$EO$3,1,ROW()-1) -> 46661 | BE15: =(SUM(cf_1!$S$9:INDEX(cf_1!$S$9:$EO$9,1,ROW()-1))+SUM(cf_2!$S$9:INDEX(cf_2!$S$9:$EO$9,1,ROW()-1))-SUM(cf_1!$S$209:INDEX(cf_1!$S$209:$EO$209,1,ROW()-1))-SUM(cf_2!$S$209:INDEX(cf_2!$S$209:$EO$209,1,ROW()-1)))/1000000 -> 0 | BF15: =(SUM(cf_1!$S$183:INDEX(cf_1!$S$183:$EO$183,1,ROW()-1))+SUM(cf_2!$S$183:INDEX(cf_2!$S$183:$EO$183,1,ROW()-1)))/1000000 -> 795.49341 | BG15: =(INDEX(КРЕДИТЫ!$S$52:$EO$52,1,ROW()-1)+INDEX(КРЕДИТЫ!$S$75:$EO$75,1,ROW()-1))/1000000 -> 0
B16: Расходы на ЗУ | C16: =CF!I27+CF!I29 -> -2169.2493 | D16: =IFERROR(C16/$L$4*1000,0) -> -66.80163 | E16: =IFERROR(C16/$I$4*1000,0) -> -51.685712 | G16: Социальные объекты | H16: =SUM(H17:H19) -> 0 | I16: =SUM(I17:I19) -> 0 | K16: =SUM(K17:K19) -> 0 | L16: =SUM(L17:L19) -> 0 | M16: =SUM(M17:M19) -> 0 | N16: =SUM(N17:N19) -> 0 | AZ16: ='План продаж'!B36 -> 46692 | BA16: =IFERROR('План продаж'!G36,0) -> 0 | BB16: =IFERROR('План продаж'!I36/1000,0) -> 0 | BD16: =INDEX(КРЕДИТЫ!$S$3:$EO$3,1,ROW()-1) -> 46692 | BE16: =(SUM(cf_1!$S$9:INDEX(cf_1!$S$9:$EO$9,1,ROW()-1))+SUM(cf_2!$S$9:INDEX(cf_2!$S$9:$EO$9,1,ROW()-1))-SUM(cf_1!$S$209:INDEX(cf_1!$S$209:$EO$209,1,ROW()-1))-SUM(cf_2!$S$209:INDEX(cf_2!$S$209:$EO$209,1,ROW()-1)))/1000000 -> 0 | BF16: =(SUM(cf_1!$S$183:INDEX(cf_1!$S$183:$EO$183,1,ROW()-1))+SUM(cf_2!$S$183:INDEX(cf_2!$S$183:$EO$183,1,ROW()-1)))/1000000 -> 826.33208 | BG16: =(INDEX(КРЕДИТЫ!$S$52:$EO$52,1,ROW()-1)+INDEX(КРЕДИТЫ!$S$75:$EO$75,1,ROW()-1))/1000000 -> 0
B17: Строительство соцобъектов | C17: =IF(Вводные!G82="Строительство",SUM(CF!I36:I38),0) -> 0 | D17: =IFERROR(C17/$L$4*1000,0) -> 0 | E17: =IFERROR(C17/$I$4*1000,0) -> 0 | G17: ДОУ | H17: =ТЭП!C17 -> 0 | I17: =ТЭП!D17 -> 0 | K17: =ТЭП!F17 -> 0 | L17: =ТЭП!G17 -> 0 | M17: =ТЭП!H17 -> 0 | N17: =ТЭП!I17 -> 0 | AZ17: ='План продаж'!B37 -> 46722 | BA17: =IFERROR('План продаж'!G37,0) -> 0 | BB17: =IFERROR('План продаж'!I37/1000,0) -> 0 | BD17: =INDEX(КРЕДИТЫ!$S$3:$EO$3,1,ROW()-1) -> 46722 | BE17: =(SUM(cf_1!$S$9:INDEX(cf_1!$S$9:$EO$9,1,ROW()-1))+SUM(cf_2!$S$9:INDEX(cf_2!$S$9:$EO$9,1,ROW()-1))-SUM(cf_1!$S$209:INDEX(cf_1!$S$209:$EO$209,1,ROW()-1))-SUM(cf_2!$S$209:INDEX(cf_2!$S$209:$EO$209,1,ROW()-1)))/1000000 -> 0 | BF17: =(SUM(cf_1!$S$183:INDEX(cf_1!$S$183:$EO$183,1,ROW()-1))+SUM(cf_2!$S$183:INDEX(cf_2!$S$183:$EO$183,1,ROW()-1)))/1000000 -> 957.6069 | BG17: =(INDEX(КРЕДИТЫ!$S$52:$EO$52,1,ROW()-1)+INDEX(КРЕДИТЫ!$S$75:$EO$75,1,ROW()-1))/1000000 -> 0
B18: Расходы на строительство (+расшифровка) | C18: =C33 -> -10742.812 | D18: =IFERROR(C18/$L$4*1000,0) -> -330.82291 | E18: =IFERROR(C18/$I$4*1000,0) -> -255.96408 | G18: СОШ | H18: =ТЭП!C18 -> 0 | I18: =ТЭП!D18 -> 0 | K18: =ТЭП!F18 -> 0 | L18: =ТЭП!G18 -> 0 | M18: =ТЭП!H18 -> 0 | N18: =ТЭП!I18 -> 0 | AZ18: ='План продаж'!B38 -> 46753 | BA18: =IFERROR('План продаж'!G38,0) -> 0 | BB18: =IFERROR('План продаж'!I38/1000,0) -> 0 | BD18: =INDEX(КРЕДИТЫ!$S$3:$EO$3,1,ROW()-1) -> 46753 | BE18: =(SUM(cf_1!$S$9:INDEX(cf_1!$S$9:$EO$9,1,ROW()-1))+SUM(cf_2!$S$9:INDEX(cf_2!$S$9:$EO$9,1,ROW()-1))-SUM(cf_1!$S$209:INDEX(cf_1!$S$209:$EO$209,1,ROW()-1))-SUM(cf_2!$S$209:INDEX(cf_2!$S$209:$EO$209,1,ROW()-1)))/1000000 -> 0 | BF18: =(SUM(cf_1!$S$183:INDEX(cf_1!$S$183:$EO$183,1,ROW()-1))+SUM(cf_2!$S$183:INDEX(cf_2!$S$183:$EO$183,1,ROW()-1)))/1000000 -> 1003.1287 | BG18: =(INDEX(КРЕДИТЫ!$S$52:$EO$52,1,ROW()-1)+INDEX(КРЕДИТЫ!$S$75:$EO$75,1,ROW()-1))/1000000 -> 0
B19: Управление проектом (+расшифровка) | C19: =C46 -> -511.56249 | D19: =IFERROR(C19/$L$4*1000,0) -> -15.753472 | E19: =IFERROR(C19/$I$4*1000,0) -> -12.188766 | G19: Поликлиника | H19: =ТЭП!C19 -> 0 | I19: =ТЭП!D19 -> 0 | K19: =ТЭП!F19 -> 0 | L19: =ТЭП!G19 -> 0 | M19: =ТЭП!H19 -> 0 | N19: =ТЭП!I19 -> 0 | AZ19: ='План продаж'!B39 -> 46784 | BA19: =IFERROR('План продаж'!G39,0) -> 0 | BB19: =IFERROR('План продаж'!I39/1000,0) -> 0 | BD19: =INDEX(КРЕДИТЫ!$S$3:$EO$3,1,ROW()-1) -> 46784 | BE19: =(SUM(cf_1!$S$9:INDEX(cf_1!$S$9:$EO$9,1,ROW()-1))+SUM(cf_2!$S$9:INDEX(cf_2!$S$9:$EO$9,1,ROW()-1))-SUM(cf_1!$S$209:INDEX(cf_1!$S$209:$EO$209,1,ROW()-1))-SUM(cf_2!$S$209:INDEX(cf_2!$S$209:$EO$209,1,ROW()-1)))/1000000 -> 0 | BF19: =(SUM(cf_1!$S$183:INDEX(cf_1!$S$183:$EO$183,1,ROW()-1))+SUM(cf_2!$S$183:INDEX(cf_2!$S$183:$EO$183,1,ROW()-1)))/1000000 -> 1048.6505 | BG19: =(INDEX(КРЕДИТЫ!$S$52:$EO$52,1,ROW()-1)+INDEX(КРЕДИТЫ!$S$75:$EO$75,1,ROW()-1))/1000000 -> 0
B20: Коммерческие | C20: =CF!I22 -> -1531.3125 | D20: =IFERROR(C20/$L$4*1000,0) -> -47.156483 | E20: =IFERROR(C20/$I$4*1000,0) -> -36.485882 | AZ20: ='План продаж'!B40 -> 46813 | BA20: =IFERROR('План продаж'!G40,0) -> 832.62485 | BB20: =IFERROR('План продаж'!I40/1000,0) -> 675 | BD20: =INDEX(КРЕДИТЫ!$S$3:$EO$3,1,ROW()-1) -> 46813 | BE20: =(SUM(cf_1!$S$9:INDEX(cf_1!$S$9:$EO$9,1,ROW()-1))+SUM(cf_2!$S$9:INDEX(cf_2!$S$9:$EO$9,1,ROW()-1))-SUM(cf_1!$S$209:INDEX(cf_1!$S$209:$EO$209,1,ROW()-1))-SUM(cf_2!$S$209:INDEX(cf_2!$S$209:$EO$209,1,ROW()-1)))/1000000 -> 541.50786 | BF20: =(SUM(cf_1!$S$183:INDEX(cf_1!$S$183:$EO$183,1,ROW()-1))+SUM(cf_2!$S$183:INDEX(cf_2!$S$183:$EO$183,1,ROW()-1)))/1000000 -> 2372.4516 | BG20: =(INDEX(КРЕДИТЫ!$S$52:$EO$52,1,ROW()-1)+INDEX(КРЕДИТЫ!$S$75:$EO$75,1,ROW()-1))/1000000 -> 2573.0352
B21: EBITDA | C21: =C4+SUM(C14:C20) -> 5232.5088 | D21: =IFERROR(C21/$L$4*1000,0) -> 161.13413 | E21: =IFERROR(C21/$I$4*1000,0) -> 124.67259 | AZ21: ='План продаж'!B41 -> 46844 | BA21: =IFERROR('План продаж'!G41,0) -> 841.29802 | BB21: =IFERROR('План продаж'!I41/1000,0) -> 682.41948 | BD21: =INDEX(КРЕДИТЫ!$S$3:$EO$3,1,ROW()-1) -> 46844 | BE21: =(SUM(cf_1!$S$9:INDEX(cf_1!$S$9:$EO$9,1,ROW()-1))+SUM(cf_2!$S$9:INDEX(cf_2!$S$9:$EO$9,1,ROW()-1))-SUM(cf_1!$S$209:INDEX(cf_1!$S$209:$EO$209,1,ROW()-1))-SUM(cf_2!$S$209:INDEX(cf_2!$S$209:$EO$209,1,ROW()-1)))/1000000 -> 1095.5698 | BF21: =(SUM(cf_1!$S$183:INDEX(cf_1!$S$183:$EO$183,1,ROW()-1))+SUM(cf_2!$S$183:INDEX(cf_2!$S$183:$EO$183,1,ROW()-1)))/1000000 -> 3785.525 | BG21: =(INDEX(КРЕДИТЫ!$S$52:$EO$52,1,ROW()-1)+INDEX(КРЕДИТЫ!$S$75:$EO$75,1,ROW()-1))/1000000 -> 3986.1086
B22: %% по кредитам | C22: =CF!I52 -> -1432.7396 | D22: =IFERROR(C22/$L$4*1000,0) -> -44.120948 | E22: =IFERROR(C22/$I$4*1000,0) -> -34.13723 | G22: Темп продаж | K22: Цены продаж | AZ22: ='План продаж'!B42 -> 46874 | BA22: =IFERROR('План продаж'!G42,0) -> 722.47552 | BB22: =IFERROR('План продаж'!I42/1000,0) -> 689.9205 | BD22: =INDEX(КРЕДИТЫ!$S$3:$EO$3,1,ROW()-1) -> 46874 | BE22: =(SUM(cf_1!$S$9:INDEX(cf_1!$S$9:$EO$9,1,ROW()-1))+SUM(cf_2!$S$9:INDEX(cf_2!$S$9:$EO$9,1,ROW()-1))-SUM(cf_1!$S$209:INDEX(cf_1!$S$209:$EO$209,1,ROW()-1))-SUM(cf_2!$S$209:INDEX(cf_2!$S$209:$EO$209,1,ROW()-1)))/1000000 -> 1577.6448 | BF22: =(SUM(cf_1!$S$183:INDEX(cf_1!$S$183:$EO$183,1,ROW()-1))+SUM(cf_2!$S$183:INDEX(cf_2!$S$183:$EO$183,1,ROW()-1)))/1000000 -> 4204.1124 | BG22: =(INDEX(КРЕДИТЫ!$S$52:$EO$52,1,ROW()-1)+INDEX(КРЕДИТЫ!$S$75:$EO$75,1,ROW()-1))/1000000 -> 4404.6961
B23: Налог на прибыль / прочие налоги | C23: =CF!I24 -> -949.96238 | D23: =IFERROR(C23/$L$4*1000,0) -> -29.253915 | E23: =IFERROR(C23/$I$4*1000,0) -> -22.634319 | G23: Объект недвижимости | H23: кв.м./мес | I23: шт/мес | J23: % до РНВ | K23: Объект недвижимости | L23: Цена, тыс. руб./кв.м. | AZ23: ='План продаж'!B43 -> 46905 | BA23: =IFERROR('План продаж'!G43,0) -> 729.84772 | BB23: =IFERROR('План продаж'!I43/1000,0) -> 697.50398 | BD23: =INDEX(КРЕДИТЫ!$S$3:$EO$3,1,ROW()-1) -> 46905 | BE23: =(SUM(cf_1!$S$9:INDEX(cf_1!$S$9:$EO$9,1,ROW()-1))+SUM(cf_2!$S$9:INDEX(cf_2!$S$9:$EO$9,1,ROW()-1))-SUM(cf_1!$S$209:INDEX(cf_1!$S$209:$EO$209,1,ROW()-1))-SUM(cf_2!$S$209:INDEX(cf_2!$S$209:$EO$209,1,ROW()-1)))/1000000 -> 2070.7506 | BF23: =(SUM(cf_1!$S$183:INDEX(cf_1!$S$183:$EO$183,1,ROW()-1))+SUM(cf_2!$S$183:INDEX(cf_2!$S$183:$EO$183,1,ROW()-1)))/1000000 -> 4622.6999 | BG23: =(INDEX(КРЕДИТЫ!$S$52:$EO$52,1,ROW()-1)+INDEX(КРЕДИТЫ!$S$75:$EO$75,1,ROW()-1))/1000000 -> 4823.2835
B24: Чистая прибыль | C24: =C4+C13 -> 2849.8068 | D24: =IFERROR(C24/$L$4*1000,0) -> 87.759272 | E24: =IFERROR(C24/$I$4*1000,0) -> 67.901044 | L24: Старт | M24: Финиш | O24: Средняя | AZ24: ='План продаж'!B44 -> 46935 | BA24: =IFERROR('План продаж'!G44,0) -> 737.21991 | BB24: =IFERROR('План продаж'!I44/1000,0) -> 705.17082 | BD24: =INDEX(КРЕДИТЫ!$S$3:$EO$3,1,ROW()-1) -> 46935 | BE24: =(SUM(cf_1!$S$9:INDEX(cf_1!$S$9:$EO$9,1,ROW()-1))+SUM(cf_2!$S$9:INDEX(cf_2!$S$9:$EO$9,1,ROW()-1))-SUM(cf_1!$S$209:INDEX(cf_1!$S$209:$EO$209,1,ROW()-1))-SUM(cf_2!$S$209:INDEX(cf_2!$S$209:$EO$209,1,ROW()-1)))/1000000 -> 2575.0712 | BF24: =(SUM(cf_1!$S$183:INDEX(cf_1!$S$183:$EO$183,1,ROW()-1))+SUM(cf_2!$S$183:INDEX(cf_2!$S$183:$EO$183,1,ROW()-1)))/1000000 -> 5041.2873 | BG24: =(INDEX(КРЕДИТЫ!$S$52:$EO$52,1,ROW()-1)+INDEX(КРЕДИТЫ!$S$75:$EO$75,1,ROW()-1))/1000000 -> 5241.871
B25: Получение кредитов БРИДЖ | C25: =CF!I65 -> 1048.6505 | G25: Квартиры | H25: =cf_0!D23 -> 796.48387 | I25: =H25/O7 -> 11.516129 | J25: =cf_0!E23 -> 0 | K25: Квартиры | L25: =cf_0!E29/1000 -> 675 | M25: =cf_0!F29/1000 -> 890.56523 | O25: =C5/K7*1000 -> 788.59515 | AZ25: ='План продаж'!B45 -> 46966 | BA25: =IFERROR('План продаж'!G45,0) -> 744.59211 | BB25: =IFERROR('План продаж'!I45/1000,0) -> 712.92193 | BD25: =INDEX(КРЕДИТЫ!$S$3:$EO$3,1,ROW()-1) -> 46966 | BE25: =(SUM(cf_1!$S$9:INDEX(cf_1!$S$9:$EO$9,1,ROW()-1))+SUM(cf_2!$S$9:INDEX(cf_2!$S$9:$EO$9,1,ROW()-1))-SUM(cf_1!$S$209:INDEX(cf_1!$S$209:$EO$209,1,ROW()-1))-SUM(cf_2!$S$209:INDEX(cf_2!$S$209:$EO$209,1,ROW()-1)))/1000000 -> 3090.7932 | BF25: =(SUM(cf_1!$S$183:INDEX(cf_1!$S$183:$EO$183,1,ROW()-1))+SUM(cf_2!$S$183:INDEX(cf_2!$S$183:$EO$183,1,ROW()-1)))/1000000 -> 5459.8748 | BG25: =(INDEX(КРЕДИТЫ!$S$52:$EO$52,1,ROW()-1)+INDEX(КРЕДИТЫ!$S$75:$EO$75,1,ROW()-1))/1000000 -> 5660.4584
B26: Получение кредитов ПФ | C26: =CF!I66 -> 14264.843 | G26: Коммерция 1 эт. | H26: =cf_0!D24 -> 70.387097 | J26: =cf_0!E24 -> 0 | K26: Коммерция 1 эт. | L26: =cf_0!E30/1000 -> 650 | M26: =cf_0!F30/1000 -> 857.58134 | O26: =C6/K8*1000 -> 759.38792 | AZ26: ='План продаж'!B46 -> 46997 | BA26: =IFERROR('План продаж'!G46,0) -> 884.6639 | BB26: =IFERROR('План продаж'!I46/1000,0) -> 720.75823 | BD26: =INDEX(КРЕДИТЫ!$S$3:$EO$3,1,ROW()-1) -> 46997 | BE26: =(SUM(cf_1!$S$9:INDEX(cf_1!$S$9:$EO$9,1,ROW()-1))+SUM(cf_2!$S$9:INDEX(cf_2!$S$9:$EO$9,1,ROW()-1))-SUM(cf_1!$S$209:INDEX(cf_1!$S$209:$EO$209,1,ROW()-1))-SUM(cf_2!$S$209:INDEX(cf_2!$S$209:$EO$209,1,ROW()-1)))/1000000 -> 3710.2594 | BF26: =(SUM(cf_1!$S$183:INDEX(cf_1!$S$183:$EO$183,1,ROW()-1))+SUM(cf_2!$S$183:INDEX(cf_2!$S$183:$EO$183,1,ROW()-1)))/1000000 -> 5878.4622 | BG26: =(INDEX(КРЕДИТЫ!$S$52:$EO$52,1,ROW()-1)+INDEX(КРЕДИТЫ!$S$75:$EO$75,1,ROW()-1))/1000000 -> 6079.0459
B27: Маржинальность | C27: =IFERROR(C24/C4,0) -> 0.13027157 | G27: Коммерция ОСЗ | K27: Коммерция ОСЗ | AZ27: ='План продаж'!B47 -> 47027 | BA27: =IFERROR('План продаж'!G47,0) -> 893.33707 | BB27: =IFERROR('План продаж'!I47/1000,0) -> 728.68067 | BD27: =INDEX(КРЕДИТЫ!$S$3:$EO$3,1,ROW()-1) -> 47027 | BE27: =(SUM(cf_1!$S$9:INDEX(cf_1!$S$9:$EO$9,1,ROW()-1))+SUM(cf_2!$S$9:INDEX(cf_2!$S$9:$EO$9,1,ROW()-1))-SUM(cf_1!$S$209:INDEX(cf_1!$S$209:$EO$209,1,ROW()-1))-SUM(cf_2!$S$209:INDEX(cf_2!$S$209:$EO$209,1,ROW()-1)))/1000000 -> 4343.588 | BF27: =(SUM(cf_1!$S$183:INDEX(cf_1!$S$183:$EO$183,1,ROW()-1))+SUM(cf_2!$S$183:INDEX(cf_2!$S$183:$EO$183,1,ROW()-1)))/1000000 -> 6297.0497 | BG27: =(INDEX(КРЕДИТЫ!$S$52:$EO$52,1,ROW()-1)+INDEX(КРЕДИТЫ!$S$75:$EO$75,1,ROW()-1))/1000000 -> 6497.6333
B28: NPV @20% | C28: =CF!I95 -> 2680.6691 | G28: Офисы | K28: Офисы | AZ28: ='План продаж'!B48 -> 47058 | BA28: =IFERROR('План продаж'!G48,0) -> 902.01025 | BB28: =IFERROR('План продаж'!I48/1000,0) -> 736.6902 | BD28: =INDEX(КРЕДИТЫ!$S$3:$EO$3,1,ROW()-1) -> 47058 | BE28: =(SUM(cf_1!$S$9:INDEX(cf_1!$S$9:$EO$9,1,ROW()-1))+SUM(cf_2!$S$9:INDEX(cf_2!$S$9:$EO$9,1,ROW()-1))-SUM(cf_1!$S$209:INDEX(cf_1!$S$209:$EO$209,1,ROW()-1))-SUM(cf_2!$S$209:INDEX(cf_2!$S$209:$EO$209,1,ROW()-1)))/1000000 -> 4991.0084 | BF28: =(SUM(cf_1!$S$183:INDEX(cf_1!$S$183:$EO$183,1,ROW()-1))+SUM(cf_2!$S$183:INDEX(cf_2!$S$183:$EO$183,1,ROW()-1)))/1000000 -> 6715.6371 | BG28: =(INDEX(КРЕДИТЫ!$S$52:$EO$52,1,ROW()-1)+INDEX(КРЕДИТЫ!$S$75:$EO$75,1,ROW()-1))/1000000 -> 6916.2208
B29: IRR (акц) | C29: =CF!I96 -> N/A | G29: Наземный паркинг | K29: Наземный паркинг | AZ29: ='План продаж'!B49 -> 47088 | BA29: =IFERROR('План продаж'!G49,0) -> 910.68342 | BB29: =IFERROR('План продаж'!I49/1000,0) -> 744.78776 | BD29: =INDEX(КРЕДИТЫ!$S$3:$EO$3,1,ROW()-1) -> 47088 | BE29: =(SUM(cf_1!$S$9:INDEX(cf_1!$S$9:$EO$9,1,ROW()-1))+SUM(cf_2!$S$9:INDEX(cf_2!$S$9:$EO$9,1,ROW()-1))-SUM(cf_1!$S$209:INDEX(cf_1!$S$209:$EO$209,1,ROW()-1))-SUM(cf_2!$S$209:INDEX(cf_2!$S$209:$EO$209,1,ROW()-1)))/1000000 -> 5652.7533 | BF29: =(SUM(cf_1!$S$183:INDEX(cf_1!$S$183:$EO$183,1,ROW()-1))+SUM(cf_2!$S$183:INDEX(cf_2!$S$183:$EO$183,1,ROW()-1)))/1000000 -> 7134.2246 | BG29: =(INDEX(КРЕДИТЫ!$S$52:$EO$52,1,ROW()-1)+INDEX(КРЕДИТЫ!$S$75:$EO$75,1,ROW()-1))/1000000 -> 7334.8083
B30: LLCR | C30: =LLCR!C18 -> 1.1968375 | G30: Подземный паркинг | I30: =cf_0!D25 -> 5.1612903 | J30: =cf_0!E25 -> 0 | K30: Подземный паркинг | L30: =cf_0!E31/1000 -> 4000 | M30: =cf_0!F31/1000 -> 5277.4236 | O30: =C9/N14*1000 -> 4673.1564 | AZ30: ='План продаж'!B50 -> 47119 | BA30: =IFERROR('План продаж'!G50,0) -> 781.45311 | BB30: =IFERROR('План продаж'!I50/1000,0) -> 752.97433 | BD30: =INDEX(КРЕДИТЫ!$S$3:$EO$3,1,ROW()-1) -> 47119 | BE30: =(SUM(cf_1!$S$9:INDEX(cf_1!$S$9:$EO$9,1,ROW()-1))+SUM(cf_2!$S$9:INDEX(cf_2!$S$9:$EO$9,1,ROW()-1))-SUM(cf_1!$S$209:INDEX(cf_1!$S$209:$EO$209,1,ROW()-1))-SUM(cf_2!$S$209:INDEX(cf_2!$S$209:$EO$209,1,ROW()-1)))/1000000 -> 6229.0113 | BF30: =(SUM(cf_1!$S$183:INDEX(cf_1!$S$183:$EO$183,1,ROW()-1))+SUM(cf_2!$S$183:INDEX(cf_2!$S$183:$EO$183,1,ROW()-1)))/1000000 -> 7552.812 | BG30: =(INDEX(КРЕДИТЫ!$S$52:$EO$52,1,ROW()-1)+INDEX(КРЕДИТЫ!$S$75:$EO$75,1,ROW()-1))/1000000 -> 7753.3957
AZ31: ='План продаж'!B51 -> 47150 | BA31: =IFERROR('План продаж'!G51,0) -> 928.02978 | BB31: =IFERROR('План продаж'!I51/1000,0) -> 761.25088 | BD31: =INDEX(КРЕДИТЫ!$S$3:$EO$3,1,ROW()-1) -> 47150 | BE31: =(SUM(cf_1!$S$9:INDEX(cf_1!$S$9:$EO$9,1,ROW()-1))+SUM(cf_2!$S$9:INDEX(cf_2!$S$9:$EO$9,1,ROW()-1))-SUM(cf_1!$S$209:INDEX(cf_1!$S$209:$EO$209,1,ROW()-1))-SUM(cf_2!$S$209:INDEX(cf_2!$S$209:$EO$209,1,ROW()-1)))/1000000 -> 6919.9514 | BF31: =(SUM(cf_1!$S$183:INDEX(cf_1!$S$183:$EO$183,1,ROW()-1))+SUM(cf_2!$S$183:INDEX(cf_2!$S$183:$EO$183,1,ROW()-1)))/1000000 -> 7971.3995 | BG31: =(INDEX(КРЕДИТЫ!$S$52:$EO$52,1,ROW()-1)+INDEX(КРЕДИТЫ!$S$75:$EO$75,1,ROW()-1))/1000000 -> 8171.9832
B32: Расшифровка статей | C32: ИТОГО млн.р | D32: т. руб/кв.м NSA | E32: т. руб/кв.м GBA | G32: Себестоимость строительства | AZ32: ='План продаж'!B52 -> 47178 | BA32: =IFERROR('План продаж'!G52,0) -> 936.70295 | BB32: =IFERROR('План продаж'!I52/1000,0) -> 769.61841 | BD32: =INDEX(КРЕДИТЫ!$S$3:$EO$3,1,ROW()-1) -> 47178 | BE32: =(SUM(cf_1!$S$9:INDEX(cf_1!$S$9:$EO$9,1,ROW()-1))+SUM(cf_2!$S$9:INDEX(cf_2!$S$9:$EO$9,1,ROW()-1))-SUM(cf_1!$S$209:INDEX(cf_1!$S$209:$EO$209,1,ROW()-1))-SUM(cf_2!$S$209:INDEX(cf_2!$S$209:$EO$209,1,ROW()-1)))/1000000 -> 7625.935 | BF32: =(SUM(cf_1!$S$183:INDEX(cf_1!$S$183:$EO$183,1,ROW()-1))+SUM(cf_2!$S$183:INDEX(cf_2!$S$183:$EO$183,1,ROW()-1)))/1000000 -> 8389.987 | BG32: =(INDEX(КРЕДИТЫ!$S$52:$EO$52,1,ROW()-1)+INDEX(КРЕДИТЫ!$S$75:$EO$75,1,ROW()-1))/1000000 -> 8590.5706
B33: Расходы на строительство | C33: =SUM(C34:C45) -> -10742.812 | D33: =IFERROR(C33/$L$4*1000,0) -> -330.82291 | E33: =IFERROR(C33/$I$4*1000,0) -> -255.96408 | G33: Показатель | J33: Ед. | K33: Выбрано | AZ33: ='План продаж'!B53 -> 47209 | BA33: =IFERROR('План продаж'!G53,0) -> 945.37613 | BB33: =IFERROR('План продаж'!I53/1000,0) -> 778.07792 | BD33: =INDEX(КРЕДИТЫ!$S$3:$EO$3,1,ROW()-1) -> 47209 | BE33: =(SUM(cf_1!$S$9:INDEX(cf_1!$S$9:$EO$9,1,ROW()-1))+SUM(cf_2!$S$9:INDEX(cf_2!$S$9:$EO$9,1,ROW()-1))-SUM(cf_1!$S$209:INDEX(cf_1!$S$209:$EO$209,1,ROW()-1))-SUM(cf_2!$S$209:INDEX(cf_2!$S$209:$EO$209,1,ROW()-1)))/1000000 -> 8347.209 | BF33: =(SUM(cf_1!$S$183:INDEX(cf_1!$S$183:$EO$183,1,ROW()-1))+SUM(cf_2!$S$183:INDEX(cf_2!$S$183:$EO$183,1,ROW()-1)))/1000000 -> 8808.5744 | BG33: =(INDEX(КРЕДИТЫ!$S$52:$EO$52,1,ROW()-1)+INDEX(КРЕДИТЫ!$S$75:$EO$75,1,ROW()-1))/1000000 -> 9009.1581
B34: Получение ИРД и согласования | C34: =CF!I30+CF!I32+CF!I33 -> -65.561 | D34: =IFERROR(C34/$L$4*1000,0) -> -2.0189388 | E34: =IFERROR(C34/$I$4*1000,0) -> -1.562092 | G34: ИРД и согласования | J34: =Вводные!C23 -> тыс. ₽/м² GBA | K34: =Вводные!G23 -> 1 | AZ34: ='План продаж'!B54 -> 47239 | BA34: =IFERROR('План продаж'!G54,0) -> 810.94191 | BB34: =IFERROR('План продаж'!I54/1000,0) -> 786.6304 | BD34: =INDEX(КРЕДИТЫ!$S$3:$EO$3,1,ROW()-1) -> 47239 | BE34: =(SUM(cf_1!$S$9:INDEX(cf_1!$S$9:$EO$9,1,ROW()-1))+SUM(cf_2!$S$9:INDEX(cf_2!$S$9:$EO$9,1,ROW()-1))-SUM(cf_1!$S$209:INDEX(cf_1!$S$209:$EO$209,1,ROW()-1))-SUM(cf_2!$S$209:INDEX(cf_2!$S$209:$EO$209,1,ROW()-1)))/1000000 -> 8975.56 | BF34: =(SUM(cf_1!$S$183:INDEX(cf_1!$S$183:$EO$183,1,ROW()-1))+SUM(cf_2!$S$183:INDEX(cf_2!$S$183:$EO$183,1,ROW()-1)))/1000000 -> 9227.1619 | BG34: =(INDEX(КРЕДИТЫ!$S$52:$EO$52,1,ROW()-1)+INDEX(КРЕДИТЫ!$S$75:$EO$75,1,ROW()-1))/1000000 -> 9427.7455
B35: Разработка проекта стадии "П" и "РД" | C35: =CF!I31 -> -230.055 | D35: =IFERROR(C35/$L$4*1000,0) -> -7.084501 | E35: =IFERROR(C35/$I$4*1000,0) -> -5.4814153 | G35: Проектирование стадии "П" | J35: =Вводные!C24 -> тыс. ₽/м² GBA | K35: =Вводные!G24 -> 2.5 | AZ35: ='План продаж'!B55 -> 47270 | BA35: =IFERROR('План продаж'!G55,0) -> 818.31411 | BB35: =IFERROR('План продаж'!I55/1000,0) -> 795.2769 | BD35: =INDEX(КРЕДИТЫ!$S$3:$EO$3,1,ROW()-1) -> 47270 | BE35: =(SUM(cf_1!$S$9:INDEX(cf_1!$S$9:$EO$9,1,ROW()-1))+SUM(cf_2!$S$9:INDEX(cf_2!$S$9:$EO$9,1,ROW()-1))-SUM(cf_1!$S$209:INDEX(cf_1!$S$209:$EO$209,1,ROW()-1))-SUM(cf_2!$S$209:INDEX(cf_2!$S$209:$EO$209,1,ROW()-1)))/1000000 -> 9617.3364 | BF35: =(SUM(cf_1!$S$183:INDEX(cf_1!$S$183:$EO$183,1,ROW()-1))+SUM(cf_2!$S$183:INDEX(cf_2!$S$183:$EO$183,1,ROW()-1)))/1000000 -> 9645.7493 | BG35: =(INDEX(КРЕДИТЫ!$S$52:$EO$52,1,ROW()-1)+INDEX(КРЕДИТЫ!$S$75:$EO$75,1,ROW()-1))/1000000 -> 9846.333
B36: Подготовительный период | C36: =CF!I34 -> -46.011 | D36: =IFERROR(C36/$L$4*1000,0) -> -1.4169002 | E36: =IFERROR(C36/$I$4*1000,0) -> -1.0962831 | G36: Проектирование стадии "РД" | J36: =Вводные!C25 -> тыс. ₽/м² GBA | K36: =Вводные!G25 -> 2.5 | AZ36: ='План продаж'!B56 -> 47300 | BA36: =IFERROR('План продаж'!G56,0) -> 825.6863 | BB36: =IFERROR('План продаж'!I56/1000,0) -> 804.01844 | BD36: =INDEX(КРЕДИТЫ!$S$3:$EO$3,1,ROW()-1) -> 47300 | BE36: =(SUM(cf_1!$S$9:INDEX(cf_1!$S$9:$EO$9,1,ROW()-1))+SUM(cf_2!$S$9:INDEX(cf_2!$S$9:$EO$9,1,ROW()-1))-SUM(cf_1!$S$209:INDEX(cf_1!$S$209:$EO$209,1,ROW()-1))-SUM(cf_2!$S$209:INDEX(cf_2!$S$209:$EO$209,1,ROW()-1)))/1000000 -> 10272.757 | BF36: =(SUM(cf_1!$S$183:INDEX(cf_1!$S$183:$EO$183,1,ROW()-1))+SUM(cf_2!$S$183:INDEX(cf_2!$S$183:$EO$183,1,ROW()-1)))/1000000 -> 10064.337 | BG36: =(INDEX(КРЕДИТЫ!$S$52:$EO$52,1,ROW()-1)+INDEX(КРЕДИТЫ!$S$75:$EO$75,1,ROW()-1))/1000000 -> 10264.92
B37: Строительство основных объектов | C37: =CF!I35 -> -8742.09 | D37: =IFERROR(C37/$L$4*1000,0) -> -269.21104 | E37: =IFERROR(C37/$I$4*1000,0) -> -208.29378 | G37: Подготовительные работы | J37: =Вводные!C26 -> тыс. ₽/м² GBA | K37: =Вводные!G26 -> 1 | AZ37: ='План продаж'!B57 -> 47331 | BA37: =IFERROR('План продаж'!G57,0) -> 833.0585 | BB37: =IFERROR('План продаж'!I57/1000,0) -> 812.85606 | BD37: =INDEX(КРЕДИТЫ!$S$3:$EO$3,1,ROW()-1) -> 47331 | BE37: =(SUM(cf_1!$S$9:INDEX(cf_1!$S$9:$EO$9,1,ROW()-1))+SUM(cf_2!$S$9:INDEX(cf_2!$S$9:$EO$9,1,ROW()-1))-SUM(cf_1!$S$209:INDEX(cf_1!$S$209:$EO$209,1,ROW()-1))-SUM(cf_2!$S$209:INDEX(cf_2!$S$209:$EO$209,1,ROW()-1)))/1000000 -> 10942.045 | BF37: =(SUM(cf_1!$S$183:INDEX(cf_1!$S$183:$EO$183,1,ROW()-1))+SUM(cf_2!$S$183:INDEX(cf_2!$S$183:$EO$183,1,ROW()-1)))/1000000 -> 10482.924 | BG37: =(INDEX(КРЕДИТЫ!$S$52:$EO$52,1,ROW()-1)+INDEX(КРЕДИТЫ!$S$75:$EO$75,1,ROW()-1))/1000000 -> 10683.508
B38: Строительство отдельных коммерческих объектов | C38: =CF!I40 -> 0 | D38: =IFERROR(C38/$L$10*1000,0) -> 0 | E38: =IFERROR(C38/$I$10*1000,0) -> 0 | G38: Основное строительство ЖК | J38: =Вводные!C27 -> тыс. ₽/м² GBA | K38: =Вводные!G27 -> 190 | AZ38: ='План продаж'!B58 -> 47362 | BA38: =IFERROR('План продаж'!G58,0) -> 988.742 | BB38: =IFERROR('План продаж'!I58/1000,0) -> 821.79082 | BD38: =INDEX(КРЕДИТЫ!$S$3:$EO$3,1,ROW()-1) -> 47362 | BE38: =(SUM(cf_1!$S$9:INDEX(cf_1!$S$9:$EO$9,1,ROW()-1))+SUM(cf_2!$S$9:INDEX(cf_2!$S$9:$EO$9,1,ROW()-1))-SUM(cf_1!$S$209:INDEX(cf_1!$S$209:$EO$209,1,ROW()-1))-SUM(cf_2!$S$209:INDEX(cf_2!$S$209:$EO$209,1,ROW()-1)))/1000000 -> 11742.857 | BF38: =(SUM(cf_1!$S$183:INDEX(cf_1!$S$183:$EO$183,1,ROW()-1))+SUM(cf_2!$S$183:INDEX(cf_2!$S$183:$EO$183,1,ROW()-1)))/1000000 -> 10901.512 | BG38: =(INDEX(КРЕДИТЫ!$S$52:$EO$52,1,ROW()-1)+INDEX(КРЕДИТЫ!$S$75:$EO$75,1,ROW()-1))/1000000 -> 11102.095
B39: Вознаграждение Генподрядчика | C39: =CF!I39 -> -611.9463 | D39: =IFERROR(C39/$L$4*1000,0) -> -18.844773 | E39: =IFERROR(C39/$I$4*1000,0) -> -14.580565 | G39: Наружные инженерные сети | J39: =Вводные!C28 -> тыс. ₽/м² GBA | K39: =Вводные!G28 -> 7 | AZ39: ='План продаж'!B59 -> 47392 | BA39: =IFERROR('План продаж'!G59,0) -> 997.41518 | BB39: =IFERROR('План продаж'!I59/1000,0) -> 830.8238 | BD39: =INDEX(КРЕДИТЫ!$S$3:$EO$3,1,ROW()-1) -> 47392 | BE39: =(SUM(cf_1!$S$9:INDEX(cf_1!$S$9:$EO$9,1,ROW()-1))+SUM(cf_2!$S$9:INDEX(cf_2!$S$9:$EO$9,1,ROW()-1))-SUM(cf_1!$S$209:INDEX(cf_1!$S$209:$EO$209,1,ROW()-1))-SUM(cf_2!$S$209:INDEX(cf_2!$S$209:$EO$209,1,ROW()-1)))/1000000 -> 12693.106 | BF39: =(SUM(cf_1!$S$183:INDEX(cf_1!$S$183:$EO$183,1,ROW()-1))+SUM(cf_2!$S$183:INDEX(cf_2!$S$183:$EO$183,1,ROW()-1)))/1000000 -> 11320.099 | BG39: =(INDEX(КРЕДИТЫ!$S$52:$EO$52,1,ROW()-1)+INDEX(КРЕДИТЫ!$S$75:$EO$75,1,ROW()-1))/1000000 -> 11520.683
B40: Вынос инженерных сетей | C40: =CF!I42 -> 0 | D40: =IFERROR(C40/$L$4*1000,0) -> 0 | E40: =IFERROR(C40/$I$4*1000,0) -> 0 | G40: Благоустройство | J40: =Вводные!C29 -> тыс. ₽/м² GBA | K40: =Вводные!G29 -> 3.5 | AZ40: ='План продаж'!B60 -> 47423 | BA40: =IFERROR('План продаж'!G60,0) -> 1006.0884 | BB40: =IFERROR('План продаж'!I60/1000,0) -> 839.95606 | BD40: =INDEX(КРЕДИТЫ!$S$3:$EO$3,1,ROW()-1) -> 47423 | BE40: =(SUM(cf_1!$S$9:INDEX(cf_1!$S$9:$EO$9,1,ROW()-1))+SUM(cf_2!$S$9:INDEX(cf_2!$S$9:$EO$9,1,ROW()-1))-SUM(cf_1!$S$209:INDEX(cf_1!$S$209:$EO$209,1,ROW()-1))-SUM(cf_2!$S$209:INDEX(cf_2!$S$209:$EO$209,1,ROW()-1)))/1000000 -> 13661.773 | BF40: =(SUM(cf_1!$S$183:INDEX(cf_1!$S$183:$EO$183,1,ROW()-1))+SUM(cf_2!$S$183:INDEX(cf_2!$S$183:$EO$183,1,ROW()-1)))/1000000 -> 11738.687 | BG40: =(INDEX(КРЕДИТЫ!$S$52:$EO$52,1,ROW()-1)+INDEX(КРЕДИТЫ!$S$75:$EO$75,1,ROW()-1))/1000000 -> 11939.27
B41: Наружные инженерные сети | C41: =CF!I43+CF!I44 -> -322.077 | D41: =IFERROR(C41/$L$4*1000,0) -> -9.9183014 | E41: =IFERROR(C41/$I$4*1000,0) -> -7.6739814 | G41: Сдача и ввод | J41: =Вводные!C30 -> тыс. ₽/м² GBA | K41: =Вводные!G30 -> 1 | AZ41: ='План продаж'!B61 -> 47453 | BA41: =IFERROR('План продаж'!G61,0) -> 1014.7615 | BB41: =IFERROR('План продаж'!I61/1000,0) -> 849.1887 | BD41: =INDEX(КРЕДИТЫ!$S$3:$EO$3,1,ROW()-1) -> 47453 | BE41: =(SUM(cf_1!$S$9:INDEX(cf_1!$S$9:$EO$9,1,ROW()-1))+SUM(cf_2!$S$9:INDEX(cf_2!$S$9:$EO$9,1,ROW()-1))-SUM(cf_1!$S$209:INDEX(cf_1!$S$209:$EO$209,1,ROW()-1))-SUM(cf_2!$S$209:INDEX(cf_2!$S$209:$EO$209,1,ROW()-1)))/1000000 -> 14649.15 | BF41: =(SUM(cf_1!$S$183:INDEX(cf_1!$S$183:$EO$183,1,ROW()-1))+SUM(cf_2!$S$183:INDEX(cf_2!$S$183:$EO$183,1,ROW()-1)))/1000000 -> 12211.373 | BG41: =(INDEX(КРЕДИТЫ!$S$52:$EO$52,1,ROW()-1)+INDEX(КРЕДИТЫ!$S$75:$EO$75,1,ROW()-1))/1000000 -> 12411.957
B42: Благоустройство территории | C42: =CF!I45 -> -161.0385 | D42: =IFERROR(C42/$L$4*1000,0) -> -4.9591507 | E42: =IFERROR(C42/$I$4*1000,0) -> -3.8369907 | G42: Содержание стройплощадки | J42: =Вводные!C31 -> тыс. ₽/м² GBA | K42: =Вводные!G31 -> 1 | AZ42: ='План продаж'!B62 -> 47484 | BA42: =IFERROR('План продаж'!G62,0) -> 869.9195 | BB42: =IFERROR('План продаж'!I62/1000,0) -> 858.52282 | BD42: =INDEX(КРЕДИТЫ!$S$3:$EO$3,1,ROW()-1) -> 47484 | BE42: =(SUM(cf_1!$S$9:INDEX(cf_1!$S$9:$EO$9,1,ROW()-1))+SUM(cf_2!$S$9:INDEX(cf_2!$S$9:$EO$9,1,ROW()-1))-SUM(cf_1!$S$209:INDEX(cf_1!$S$209:$EO$209,1,ROW()-1))-SUM(cf_2!$S$209:INDEX(cf_2!$S$209:$EO$209,1,ROW()-1)))/1000000 -> 15507.462 | BF42: =(SUM(cf_1!$S$183:INDEX(cf_1!$S$183:$EO$183,1,ROW()-1))+SUM(cf_2!$S$183:INDEX(cf_2!$S$183:$EO$183,1,ROW()-1)))/1000000 -> 12684.059 | BG42: =(INDEX(КРЕДИТЫ!$S$52:$EO$52,1,ROW()-1)+INDEX(КРЕДИТЫ!$S$75:$EO$75,1,ROW()-1))/1000000 -> 12884.643
B43: Расходы по сдаче + содержание | C43: =CF!I47+CF!I48 -> -52.471 | D43: =IFERROR(C43/$L$4*1000,0) -> -1.6158347 | E43: =IFERROR(C43/$I$4*1000,0) -> -1.2502025 | G43: Вознаграждение генподрядчика | J43: =Вводные!C32 -> % СМР | K43: =Вводные!G32 -> 0.07 | AZ43: ='План продаж'!B63 -> 47515 | BA43: =IFERROR('План продаж'!G63,0) -> 1032.1079 | BB43: =IFERROR('План продаж'!I63/1000,0) -> 867.95955 | BD43: =INDEX(КРЕДИТЫ!$S$3:$EO$3,1,ROW()-1) -> 47515 | BE43: =(SUM(cf_1!$S$9:INDEX(cf_1!$S$9:$EO$9,1,ROW()-1))+SUM(cf_2!$S$9:INDEX(cf_2!$S$9:$EO$9,1,ROW()-1))-SUM(cf_1!$S$209:INDEX(cf_1!$S$209:$EO$209,1,ROW()-1))-SUM(cf_2!$S$209:INDEX(cf_2!$S$209:$EO$209,1,ROW()-1)))/1000000 -> 16533.156 | BF43: =(SUM(cf_1!$S$183:INDEX(cf_1!$S$183:$EO$183,1,ROW()-1))+SUM(cf_2!$S$183:INDEX(cf_2!$S$183:$EO$183,1,ROW()-1)))/1000000 -> 14064.259 | BG43: =(INDEX(КРЕДИТЫ!$S$52:$EO$52,1,ROW()-1)+INDEX(КРЕДИТЫ!$S$75:$EO$75,1,ROW()-1))/1000000 -> 14264.843
B44: Дорожные работы (внеплощадочные дороги) | C44: =CF!I46 -> 0 | D44: =IFERROR(C44/$L$4*1000,0) -> 0 | E44: =IFERROR(C44/$I$4*1000,0) -> 0 | G44: Резерв | J44: =Вводные!C33 -> % | K44: =Вводные!G33 -> 0.05 | AZ44: ='План продаж'!B64 -> 47543 | BA44: =IFERROR('План продаж'!G64,0) -> 578.69531 | BB44: =IFERROR('План продаж'!I64/1000,0) -> 877.5 | BD44: =INDEX(КРЕДИТЫ!$S$3:$EO$3,1,ROW()-1) -> 47543 | BE44: =(SUM(cf_1!$S$9:INDEX(cf_1!$S$9:$EO$9,1,ROW()-1))+SUM(cf_2!$S$9:INDEX(cf_2!$S$9:$EO$9,1,ROW()-1))-SUM(cf_1!$S$209:INDEX(cf_1!$S$209:$EO$209,1,ROW()-1))-SUM(cf_2!$S$209:INDEX(cf_2!$S$209:$EO$209,1,ROW()-1)))/1000000 -> 0 | BF44: =(SUM(cf_1!$S$183:INDEX(cf_1!$S$183:$EO$183,1,ROW()-1))+SUM(cf_2!$S$183:INDEX(cf_2!$S$183:$EO$183,1,ROW()-1)))/1000000 -> 14877.381 | BG44: =(INDEX(КРЕДИТЫ!$S$52:$EO$52,1,ROW()-1)+INDEX(КРЕДИТЫ!$S$75:$EO$75,1,ROW()-1))/1000000 -> 0
B45: Резервы | C45: =CF!I49 -> -511.56249 | D45: =IFERROR(C45/$L$4*1000,0) -> -15.753472 | E45: =IFERROR(C45/$I$4*1000,0) -> -12.188766 | G45: Управление проектом | J45: =Вводные!C34 -> % | K45: =Вводные!G34 -> 0.05 | AZ45: ='План продаж'!B65 -> 47574 | BA45: =IFERROR('План продаж'!G65,0) -> 578.69531 | BB45: =IFERROR('План продаж'!I65/1000,0) -> 879.66415 | BD45: =INDEX(КРЕДИТЫ!$S$3:$EO$3,1,ROW()-1) -> 47574 | BE45: =(SUM(cf_1!$S$9:INDEX(cf_1!$S$9:$EO$9,1,ROW()-1))+SUM(cf_2!$S$9:INDEX(cf_2!$S$9:$EO$9,1,ROW()-1))-SUM(cf_1!$S$209:INDEX(cf_1!$S$209:$EO$209,1,ROW()-1))-SUM(cf_2!$S$209:INDEX(cf_2!$S$209:$EO$209,1,ROW()-1)))/1000000 -> 0 | BF45: =(SUM(cf_1!$S$183:INDEX(cf_1!$S$183:$EO$183,1,ROW()-1))+SUM(cf_2!$S$183:INDEX(cf_2!$S$183:$EO$183,1,ROW()-1)))/1000000 -> 14972.686 | BG45: =(INDEX(КРЕДИТЫ!$S$52:$EO$52,1,ROW()-1)+INDEX(КРЕДИТЫ!$S$75:$EO$75,1,ROW()-1))/1000000 -> 0
B46: Управление проектом | C46: =SUM(C47:C49) -> -511.56249 | D46: =IFERROR(C46/$L$4*1000,0) -> -15.753472 | E46: =IFERROR(D46/$L$4*1000,0) -> -0.48512524 | G46: Маркетинг | J46: =Вводные!C35 -> % выручки | K46: =Вводные!G35 -> 0.03 | AZ46: ='План продаж'!B66 -> 47604 | BA46: =IFERROR('План продаж'!G66,0) -> 491.89102 | BB46: =IFERROR('План продаж'!I66/1000,0) -> 881.83364 | BD46: =INDEX(КРЕДИТЫ!$S$3:$EO$3,1,ROW()-1) -> 47604 | BE46: =(SUM(cf_1!$S$9:INDEX(cf_1!$S$9:$EO$9,1,ROW()-1))+SUM(cf_2!$S$9:INDEX(cf_2!$S$9:$EO$9,1,ROW()-1))-SUM(cf_1!$S$209:INDEX(cf_1!$S$209:$EO$209,1,ROW()-1))-SUM(cf_2!$S$209:INDEX(cf_2!$S$209:$EO$209,1,ROW()-1)))/1000000 -> 0 | BF46: =(SUM(cf_1!$S$183:INDEX(cf_1!$S$183:$EO$183,1,ROW()-1))+SUM(cf_2!$S$183:INDEX(cf_2!$S$183:$EO$183,1,ROW()-1)))/1000000 -> 15061.472 | BG46: =(INDEX(КРЕДИТЫ!$S$52:$EO$52,1,ROW()-1)+INDEX(КРЕДИТЫ!$S$75:$EO$75,1,ROW()-1))/1000000 -> 0
C47: =CF!I21 -> 0 | D47: =IFERROR(C47/$L$4*1000,0) -> 0 | E47: =IFERROR(C47/$I$4*1000,0) -> 0 | G47: Расходы на продажи | J47: =Вводные!C36 -> % выручки | K47: =Вводные!G36 -> 0.04 | AZ47: ='План продаж'!B67 -> 47635 | BA47: =IFERROR('План продаж'!G67,0) -> 491.89102 | BB47: =IFERROR('План продаж'!I67/1000,0) -> 884.00848 | BD47: =INDEX(КРЕДИТЫ!$S$3:$EO$3,1,ROW()-1) -> 47635 | BE47: =(SUM(cf_1!$S$9:INDEX(cf_1!$S$9:$EO$9,1,ROW()-1))+SUM(cf_2!$S$9:INDEX(cf_2!$S$9:$EO$9,1,ROW()-1))-SUM(cf_1!$S$209:INDEX(cf_1!$S$209:$EO$209,1,ROW()-1))-SUM(cf_2!$S$209:INDEX(cf_2!$S$209:$EO$209,1,ROW()-1)))/1000000 -> 0 | BF47: =(SUM(cf_1!$S$183:INDEX(cf_1!$S$183:$EO$183,1,ROW()-1))+SUM(cf_2!$S$183:INDEX(cf_2!$S$183:$EO$183,1,ROW()-1)))/1000000 -> 15150.559 | BG47: =(INDEX(КРЕДИТЫ!$S$52:$EO$52,1,ROW()-1)+INDEX(КРЕДИТЫ!$S$75:$EO$75,1,ROW()-1))/1000000 -> 0
C48: =CF!I23 -> 0 | D48: =IFERROR(C48/$L$4*1000,0) -> 0 | E48: =IFERROR(C48/$I$4*1000,0) -> 0 | AZ48: ='План продаж'!B68 -> 47665 | BA48: =IFERROR('План продаж'!G68,0) -> 491.89102 | BB48: =IFERROR('План продаж'!I68/1000,0) -> 886.18868 | BD48: =INDEX(КРЕДИТЫ!$S$3:$EO$3,1,ROW()-1) -> 47665 | BE48: =(SUM(cf_1!$S$9:INDEX(cf_1!$S$9:$EO$9,1,ROW()-1))+SUM(cf_2!$S$9:INDEX(cf_2!$S$9:$EO$9,1,ROW()-1))-SUM(cf_1!$S$209:INDEX(cf_1!$S$209:$EO$209,1,ROW()-1))-SUM(cf_2!$S$209:INDEX(cf_2!$S$209:$EO$209,1,ROW()-1)))/1000000 -> 0 | BF48: =(SUM(cf_1!$S$183:INDEX(cf_1!$S$183:$EO$183,1,ROW()-1))+SUM(cf_2!$S$183:INDEX(cf_2!$S$183:$EO$183,1,ROW()-1)))/1000000 -> 15239.946 | BG48: =(INDEX(КРЕДИТЫ!$S$52:$EO$52,1,ROW()-1)+INDEX(КРЕДИТЫ!$S$75:$EO$75,1,ROW()-1))/1000000 -> 0
B49: Услуги ФТЗ / управление проектом | C49: =CF!I50 -> -511.56249 | D49: =IFERROR(C49/$L$4*1000,0) -> -15.753472 | E49: =IFERROR(C49/$I$4*1000,0) -> -12.188766 | AZ49: ='План продаж'!B69 -> 47696 | BA49: =IFERROR('План продаж'!G69,0) -> 491.89102 | BB49: =IFERROR('План продаж'!I69/1000,0) -> 888.37426 | BD49: =INDEX(КРЕДИТЫ!$S$3:$EO$3,1,ROW()-1) -> 47696 | BE49: =(SUM(cf_1!$S$9:INDEX(cf_1!$S$9:$EO$9,1,ROW()-1))+SUM(cf_2!$S$9:INDEX(cf_2!$S$9:$EO$9,1,ROW()-1))-SUM(cf_1!$S$209:INDEX(cf_1!$S$209:$EO$209,1,ROW()-1))-SUM(cf_2!$S$209:INDEX(cf_2!$S$209:$EO$209,1,ROW()-1)))/1000000 -> 0 | BF49: =(SUM(cf_1!$S$183:INDEX(cf_1!$S$183:$EO$183,1,ROW()-1))+SUM(cf_2!$S$183:INDEX(cf_2!$S$183:$EO$183,1,ROW()-1)))/1000000 -> 15329.636 | BG49: =(INDEX(КРЕДИТЫ!$S$52:$EO$52,1,ROW()-1)+INDEX(КРЕДИТЫ!$S$75:$EO$75,1,ROW()-1))/1000000 -> 0
AZ50: ='План продаж'!B70 -> 47727 | BA50: =IFERROR('План продаж'!G70,0) -> 578.69531 | BB50: =IFERROR('План продаж'!I70/1000,0) -> 890.56523 | BD50: =INDEX(КРЕДИТЫ!$S$3:$EO$3,1,ROW()-1) -> 47727 | BE50: =(SUM(cf_1!$S$9:INDEX(cf_1!$S$9:$EO$9,1,ROW()-1))+SUM(cf_2!$S$9:INDEX(cf_2!$S$9:$EO$9,1,ROW()-1))-SUM(cf_1!$S$209:INDEX(cf_1!$S$209:$EO$209,1,ROW()-1))-SUM(cf_2!$S$209:INDEX(cf_2!$S$209:$EO$209,1,ROW()-1)))/1000000 -> 0 | BF50: =(SUM(cf_1!$S$183:INDEX(cf_1!$S$183:$EO$183,1,ROW()-1))+SUM(cf_2!$S$183:INDEX(cf_2!$S$183:$EO$183,1,ROW()-1)))/1000000 -> 15426.267 | BG50: =(INDEX(КРЕДИТЫ!$S$52:$EO$52,1,ROW()-1)+INDEX(КРЕДИТЫ!$S$75:$EO$75,1,ROW()-1))/1000000 -> 0
AZ51: ='План продаж'!B71 -> 47757 | BA51: =IFERROR('План продаж'!G71,0) -> 0 | BB51: =IFERROR('План продаж'!I71/1000,0) -> 0 | BD51: =INDEX(КРЕДИТЫ!$S$3:$EO$3,1,ROW()-1) -> 47757 | BE51: =(SUM(cf_1!$S$9:INDEX(cf_1!$S$9:$EO$9,1,ROW()-1))+SUM(cf_2!$S$9:INDEX(cf_2!$S$9:$EO$9,1,ROW()-1))-SUM(cf_1!$S$209:INDEX(cf_1!$S$209:$EO$209,1,ROW()-1))-SUM(cf_2!$S$209:INDEX(cf_2!$S$209:$EO$209,1,ROW()-1)))/1000000 -> 0 | BF51: =(SUM(cf_1!$S$183:INDEX(cf_1!$S$183:$EO$183,1,ROW()-1))+SUM(cf_2!$S$183:INDEX(cf_2!$S$183:$EO$183,1,ROW()-1)))/1000000 -> 15426.267 | BG51: =(INDEX(КРЕДИТЫ!$S$52:$EO$52,1,ROW()-1)+INDEX(КРЕДИТЫ!$S$75:$EO$75,1,ROW()-1))/1000000 -> 0
AZ52: ='План продаж'!B72 -> 47788 | BA52: =IFERROR('План продаж'!G72,0) -> 0 | BB52: =IFERROR('План продаж'!I72/1000,0) -> 0 | BD52: =INDEX(КРЕДИТЫ!$S$3:$EO$3,1,ROW()-1) -> 47788 | BE52: =(SUM(cf_1!$S$9:INDEX(cf_1!$S$9:$EO$9,1,ROW()-1))+SUM(cf_2!$S$9:INDEX(cf_2!$S$9:$EO$9,1,ROW()-1))-SUM(cf_1!$S$209:INDEX(cf_1!$S$209:$EO$209,1,ROW()-1))-SUM(cf_2!$S$209:INDEX(cf_2!$S$209:$EO$209,1,ROW()-1)))/1000000 -> 0 | BF52: =(SUM(cf_1!$S$183:INDEX(cf_1!$S$183:$EO$183,1,ROW()-1))+SUM(cf_2!$S$183:INDEX(cf_2!$S$183:$EO$183,1,ROW()-1)))/1000000 -> 15426.267 | BG52: =(INDEX(КРЕДИТЫ!$S$52:$EO$52,1,ROW()-1)+INDEX(КРЕДИТЫ!$S$75:$EO$75,1,ROW()-1))/1000000 -> 0
AZ53: ='План продаж'!B73 -> 47818 | BA53: =IFERROR('План продаж'!G73,0) -> 0 | BB53: =IFERROR('План продаж'!I73/1000,0) -> 0 | BD53: =INDEX(КРЕДИТЫ!$S$3:$EO$3,1,ROW()-1) -> 47818 | BE53: =(SUM(cf_1!$S$9:INDEX(cf_1!$S$9:$EO$9,1,ROW()-1))+SUM(cf_2!$S$9:INDEX(cf_2!$S$9:$EO$9,1,ROW()-1))-SUM(cf_1!$S$209:INDEX(cf_1!$S$209:$EO$209,1,ROW()-1))-SUM(cf_2!$S$209:INDEX(cf_2!$S$209:$EO$209,1,ROW()-1)))/1000000 -> 0 | BF53: =(SUM(cf_1!$S$183:INDEX(cf_1!$S$183:$EO$183,1,ROW()-1))+SUM(cf_2!$S$183:INDEX(cf_2!$S$183:$EO$183,1,ROW()-1)))/1000000 -> 15426.267 | BG53: =(INDEX(КРЕДИТЫ!$S$52:$EO$52,1,ROW()-1)+INDEX(КРЕДИТЫ!$S$75:$EO$75,1,ROW()-1))/1000000 -> 0
AZ54: ='План продаж'!B74 -> 47849 | BA54: =IFERROR('План продаж'!G74,0) -> 0 | BB54: =IFERROR('План продаж'!I74/1000,0) -> 0 | BD54: =INDEX(КРЕДИТЫ!$S$3:$EO$3,1,ROW()-1) -> 47849 | BE54: =(SUM(cf_1!$S$9:INDEX(cf_1!$S$9:$EO$9,1,ROW()-1))+SUM(cf_2!$S$9:INDEX(cf_2!$S$9:$EO$9,1,ROW()-1))-SUM(cf_1!$S$209:INDEX(cf_1!$S$209:$EO$209,1,ROW()-1))-SUM(cf_2!$S$209:INDEX(cf_2!$S$209:$EO$209,1,ROW()-1)))/1000000 -> 0 | BF54: =(SUM(cf_1!$S$183:INDEX(cf_1!$S$183:$EO$183,1,ROW()-1))+SUM(cf_2!$S$183:INDEX(cf_2!$S$183:$EO$183,1,ROW()-1)))/1000000 -> 15426.267 | BG54: =(INDEX(КРЕДИТЫ!$S$52:$EO$52,1,ROW()-1)+INDEX(КРЕДИТЫ!$S$75:$EO$75,1,ROW()-1))/1000000 -> 0
AZ55: ='План продаж'!B75 -> 47880 | BA55: =IFERROR('План продаж'!G75,0) -> 0 | BB55: =IFERROR('План продаж'!I75/1000,0) -> 0 | BD55: =INDEX(КРЕДИТЫ!$S$3:$EO$3,1,ROW()-1) -> 47880 | BE55: =(SUM(cf_1!$S$9:INDEX(cf_1!$S$9:$EO$9,1,ROW()-1))+SUM(cf_2!$S$9:INDEX(cf_2!$S$9:$EO$9,1,ROW()-1))-SUM(cf_1!$S$209:INDEX(cf_1!$S$209:$EO$209,1,ROW()-1))-SUM(cf_2!$S$209:INDEX(cf_2!$S$209:$EO$209,1,ROW()-1)))/1000000 -> 0 | BF55: =(SUM(cf_1!$S$183:INDEX(cf_1!$S$183:$EO$183,1,ROW()-1))+SUM(cf_2!$S$183:INDEX(cf_2!$S$183:$EO$183,1,ROW()-1)))/1000000 -> 15426.267 | BG55: =(INDEX(КРЕДИТЫ!$S$52:$EO$52,1,ROW()-1)+INDEX(КРЕДИТЫ!$S$75:$EO$75,1,ROW()-1))/1000000 -> 0
AZ56: ='План продаж'!B76 -> 47908 | BA56: =IFERROR('План продаж'!G76,0) -> 0 | BB56: =IFERROR('План продаж'!I76/1000,0) -> 0 | BD56: =INDEX(КРЕДИТЫ!$S$3:$EO$3,1,ROW()-1) -> 47908 | BE56: =(SUM(cf_1!$S$9:INDEX(cf_1!$S$9:$EO$9,1,ROW()-1))+SUM(cf_2!$S$9:INDEX(cf_2!$S$9:$EO$9,1,ROW()-1))-SUM(cf_1!$S$209:INDEX(cf_1!$S$209:$EO$209,1,ROW()-1))-SUM(cf_2!$S$209:INDEX(cf_2!$S$209:$EO$209,1,ROW()-1)))/1000000 -> 0 | BF56: =(SUM(cf_1!$S$183:INDEX(cf_1!$S$183:$EO$183,1,ROW()-1))+SUM(cf_2!$S$183:INDEX(cf_2!$S$183:$EO$183,1,ROW()-1)))/1000000 -> 15426.267 | BG56: =(INDEX(КРЕДИТЫ!$S$52:$EO$52,1,ROW()-1)+INDEX(КРЕДИТЫ!$S$75:$EO$75,1,ROW()-1))/1000000 -> 0
AZ57: ='План продаж'!B77 -> 47939 | BA57: =IFERROR('План продаж'!G77,0) -> 0 | BB57: =IFERROR('План продаж'!I77/1000,0) -> 0 | BD57: =INDEX(КРЕДИТЫ!$S$3:$EO$3,1,ROW()-1) -> 47939 | BE57: =(SUM(cf_1!$S$9:INDEX(cf_1!$S$9:$EO$9,1,ROW()-1))+SUM(cf_2!$S$9:INDEX(cf_2!$S$9:$EO$9,1,ROW()-1))-SUM(cf_1!$S$209:INDEX(cf_1!$S$209:$EO$209,1,ROW()-1))-SUM(cf_2!$S$209:INDEX(cf_2!$S$209:$EO$209,1,ROW()-1)))/1000000 -> 0 | BF57: =(SUM(cf_1!$S$183:INDEX(cf_1!$S$183:$EO$183,1,ROW()-1))+SUM(cf_2!$S$183:INDEX(cf_2!$S$183:$EO$183,1,ROW()-1)))/1000000 -> 15426.267 | BG57: =(INDEX(КРЕДИТЫ!$S$52:$EO$52,1,ROW()-1)+INDEX(КРЕДИТЫ!$S$75:$EO$75,1,ROW()-1))/1000000 -> 0
AZ58: ='План продаж'!B78 -> 47969 | BA58: =IFERROR('План продаж'!G78,0) -> 0 | BB58: =IFERROR('План продаж'!I78/1000,0) -> 0 | BD58: =INDEX(КРЕДИТЫ!$S$3:$EO$3,1,ROW()-1) -> 47969 | BE58: =(SUM(cf_1!$S$9:INDEX(cf_1!$S$9:$EO$9,1,ROW()-1))+SUM(cf_2!$S$9:INDEX(cf_2!$S$9:$EO$9,1,ROW()-1))-SUM(cf_1!$S$209:INDEX(cf_1!$S$209:$EO$209,1,ROW()-1))-SUM(cf_2!$S$209:INDEX(cf_2!$S$209:$EO$209,1,ROW()-1)))/1000000 -> 0 | BF58: =(SUM(cf_1!$S$183:INDEX(cf_1!$S$183:$EO$183,1,ROW()-1))+SUM(cf_2!$S$183:INDEX(cf_2!$S$183:$EO$183,1,ROW()-1)))/1000000 -> 15426.267 | BG58: =(INDEX(КРЕДИТЫ!$S$52:$EO$52,1,ROW()-1)+INDEX(КРЕДИТЫ!$S$75:$EO$75,1,ROW()-1))/1000000 -> 0
AZ59: ='План продаж'!B79 -> 48000 | BA59: =IFERROR('План продаж'!G79,0) -> 0 | BB59: =IFERROR('План продаж'!I79/1000,0) -> 0 | BD59: =INDEX(КРЕДИТЫ!$S$3:$EO$3,1,ROW()-1) -> 48000 | BE59: =(SUM(cf_1!$S$9:INDEX(cf_1!$S$9:$EO$9,1,ROW()-1))+SUM(cf_2!$S$9:INDEX(cf_2!$S$9:$EO$9,1,ROW()-1))-SUM(cf_1!$S$209:INDEX(cf_1!$S$209:$EO$209,1,ROW()-1))-SUM(cf_2!$S$209:INDEX(cf_2!$S$209:$EO$209,1,ROW()-1)))/1000000 -> 0 | BF59: =(SUM(cf_1!$S$183:INDEX(cf_1!$S$183:$EO$183,1,ROW()-1))+SUM(cf_2!$S$183:INDEX(cf_2!$S$183:$EO$183,1,ROW()-1)))/1000000 -> 15426.267 | BG59: =(INDEX(КРЕДИТЫ!$S$52:$EO$52,1,ROW()-1)+INDEX(КРЕДИТЫ!$S$75:$EO$75,1,ROW()-1))/1000000 -> 0
AZ60: ='План продаж'!B80 -> 48030 | BA60: =IFERROR('План продаж'!G80,0) -> 0 | BB60: =IFERROR('План продаж'!I80/1000,0) -> 0 | BD60: =INDEX(КРЕДИТЫ!$S$3:$EO$3,1,ROW()-1) -> 48030 | BE60: =(SUM(cf_1!$S$9:INDEX(cf_1!$S$9:$EO$9,1,ROW()-1))+SUM(cf_2!$S$9:INDEX(cf_2!$S$9:$EO$9,1,ROW()-1))-SUM(cf_1!$S$209:INDEX(cf_1!$S$209:$EO$209,1,ROW()-1))-SUM(cf_2!$S$209:INDEX(cf_2!$S$209:$EO$209,1,ROW()-1)))/1000000 -> 0 | BF60: =(SUM(cf_1!$S$183:INDEX(cf_1!$S$183:$EO$183,1,ROW()-1))+SUM(cf_2!$S$183:INDEX(cf_2!$S$183:$EO$183,1,ROW()-1)))/1000000 -> 15426.267 | BG60: =(INDEX(КРЕДИТЫ!$S$52:$EO$52,1,ROW()-1)+INDEX(КРЕДИТЫ!$S$75:$EO$75,1,ROW()-1))/1000000 -> 0
AZ61: ='План продаж'!B81 -> 48061 | BA61: =IFERROR('План продаж'!G81,0) -> 0 | BB61: =IFERROR('План продаж'!I81/1000,0) -> 0 | BD61: =INDEX(КРЕДИТЫ!$S$3:$EO$3,1,ROW()-1) -> 48061 | BE61: =(SUM(cf_1!$S$9:INDEX(cf_1!$S$9:$EO$9,1,ROW()-1))+SUM(cf_2!$S$9:INDEX(cf_2!$S$9:$EO$9,1,ROW()-1))-SUM(cf_1!$S$209:INDEX(cf_1!$S$209:$EO$209,1,ROW()-1))-SUM(cf_2!$S$209:INDEX(cf_2!$S$209:$EO$209,1,ROW()-1)))/1000000 -> 0 | BF61: =(SUM(cf_1!$S$183:INDEX(cf_1!$S$183:$EO$183,1,ROW()-1))+SUM(cf_2!$S$183:INDEX(cf_2!$S$183:$EO$183,1,ROW()-1)))/1000000 -> 15426.267 | BG61: =(INDEX(КРЕДИТЫ!$S$52:$EO$52,1,ROW()-1)+INDEX(КРЕДИТЫ!$S$75:$EO$75,1,ROW()-1))/1000000 -> 0
... AZ96: ='План продаж'!B116 -> 49126 | BA96: =IFERROR('План продаж'!G116,0) -> 0 | BB96: =IFERROR('План продаж'!I116/1000,0) -> 0 | BD96: =INDEX(КРЕДИТЫ!$S$3:$EO$3,1,ROW()-1) -> 49126 | BE96: =(SUM(cf_1!$S$9:INDEX(cf_1!$S$9:$EO$9,1,ROW()-1))+SUM(cf_2!$S$9:INDEX(cf_2!$S$9:$EO$9,1,ROW()-1))-SUM(cf_1!$S$209:INDEX(cf_1!$S$209:$EO$209,1,ROW()-1))-SUM(cf_2!$S$209:INDEX(cf_2!$S$209:$EO$209,1,ROW()-1)))/1000000 -> 0 | BF96: =(SUM(cf_1!$S$183:INDEX(cf_1!$S$183:$EO$183,1,ROW()-1))+SUM(cf_2!$S$183:INDEX(cf_2!$S$183:$EO$183,1,ROW()-1)))/1000000 -> 15426.266 | BG96: =(INDEX(КРЕДИТЫ!$S$52:$EO$52,1,ROW()-1)+INDEX(КРЕДИТЫ!$S$75:$EO$75,1,ROW()-1))/1000000 -> 0
BD97: =INDEX(КРЕДИТЫ!$S$3:$EO$3,1,ROW()-1) -> 49157 | BE97: =(SUM(cf_1!$S$9:INDEX(cf_1!$S$9:$EO$9,1,ROW()-1))+SUM(cf_2!$S$9:INDEX(cf_2!$S$9:$EO$9,1,ROW()-1))-SUM(cf_1!$S$209:INDEX(cf_1!$S$209:$EO$209,1,ROW()-1))-SUM(cf_2!$S$209:INDEX(cf_2!$S$209:$EO$209,1,ROW()-1)))/1000000 -> 0 | BF97: =(SUM(cf_1!$S$183:INDEX(cf_1!$S$183:$EO$183,1,ROW()-1))+SUM(cf_2!$S$183:INDEX(cf_2!$S$183:$EO$183,1,ROW()-1)))/1000000 -> 15426.266 | BG97: =(INDEX(КРЕДИТЫ!$S$52:$EO$52,1,ROW()-1)+INDEX(КРЕДИТЫ!$S$75:$EO$75,1,ROW()-1))/1000000 -> 0
BD98: =INDEX(КРЕДИТЫ!$S$3:$EO$3,1,ROW()-1) -> 49188 | BE98: =(SUM(cf_1!$S$9:INDEX(cf_1!$S$9:$EO$9,1,ROW()-1))+SUM(cf_2!$S$9:INDEX(cf_2!$S$9:$EO$9,1,ROW()-1))-SUM(cf_1!$S$209:INDEX(cf_1!$S$209:$EO$209,1,ROW()-1))-SUM(cf_2!$S$209:INDEX(cf_2!$S$209:$EO$209,1,ROW()-1)))/1000000 -> 0 | BF98: =(SUM(cf_1!$S$183:INDEX(cf_1!$S$183:$EO$183,1,ROW()-1))+SUM(cf_2!$S$183:INDEX(cf_2!$S$183:$EO$183,1,ROW()-1)))/1000000 -> 15426.266 | BG98: =(INDEX(КРЕДИТЫ!$S$52:$EO$52,1,ROW()-1)+INDEX(КРЕДИТЫ!$S$75:$EO$75,1,ROW()-1))/1000000 -> 0
BD99: =INDEX(КРЕДИТЫ!$S$3:$EO$3,1,ROW()-1) -> 49218 | BE99: =(SUM(cf_1!$S$9:INDEX(cf_1!$S$9:$EO$9,1,ROW()-1))+SUM(cf_2!$S$9:INDEX(cf_2!$S$9:$EO$9,1,ROW()-1))-SUM(cf_1!$S$209:INDEX(cf_1!$S$209:$EO$209,1,ROW()-1))-SUM(cf_2!$S$209:INDEX(cf_2!$S$209:$EO$209,1,ROW()-1)))/1000000 -> 0 | BF99: =(SUM(cf_1!$S$183:INDEX(cf_1!$S$183:$EO$183,1,ROW()-1))+SUM(cf_2!$S$183:INDEX(cf_2!$S$183:$EO$183,1,ROW()-1)))/1000000 -> 15426.266 | BG99: =(INDEX(КРЕДИТЫ!$S$52:$EO$52,1,ROW()-1)+INDEX(КРЕДИТЫ!$S$75:$EO$75,1,ROW()-1))/1000000 -> 0
BD100: =INDEX(КРЕДИТЫ!$S$3:$EO$3,1,ROW()-1) -> 49249 | BE100: =(SUM(cf_1!$S$9:INDEX(cf_1!$S$9:$EO$9,1,ROW()-1))+SUM(cf_2!$S$9:INDEX(cf_2!$S$9:$EO$9,1,ROW()-1))-SUM(cf_1!$S$209:INDEX(cf_1!$S$209:$EO$209,1,ROW()-1))-SUM(cf_2!$S$209:INDEX(cf_2!$S$209:$EO$209,1,ROW()-1)))/1000000 -> 0 | BF100: =(SUM(cf_1!$S$183:INDEX(cf_1!$S$183:$EO$183,1,ROW()-1))+SUM(cf_2!$S$183:INDEX(cf_2!$S$183:$EO$183,1,ROW()-1)))/1000000 -> 15426.266 | BG100: =(INDEX(КРЕДИТЫ!$S$52:$EO$52,1,ROW()-1)+INDEX(КРЕДИТЫ!$S$75:$EO$75,1,ROW()-1))/1000000 -> 0
BD101: =INDEX(КРЕДИТЫ!$S$3:$EO$3,1,ROW()-1) -> 49279 | BE101: =(SUM(cf_1!$S$9:INDEX(cf_1!$S$9:$EO$9,1,ROW()-1))+SUM(cf_2!$S$9:INDEX(cf_2!$S$9:$EO$9,1,ROW()-1))-SUM(cf_1!$S$209:INDEX(cf_1!$S$209:$EO$209,1,ROW()-1))-SUM(cf_2!$S$209:INDEX(cf_2!$S$209:$EO$209,1,ROW()-1)))/1000000 -> 0 | BF101: =(SUM(cf_1!$S$183:INDEX(cf_1!$S$183:$EO$183,1,ROW()-1))+SUM(cf_2!$S$183:INDEX(cf_2!$S$183:$EO$183,1,ROW()-1)))/1000000 -> 15426.266 | BG101: =(INDEX(КРЕДИТЫ!$S$52:$EO$52,1,ROW()-1)+INDEX(КРЕДИТЫ!$S$75:$EO$75,1,ROW()-1))/1000000 -> 0
BD102: =INDEX(КРЕДИТЫ!$S$3:$EO$3,1,ROW()-1) -> 49310 | BE102: =(SUM(cf_1!$S$9:INDEX(cf_1!$S$9:$EO$9,1,ROW()-1))+SUM(cf_2!$S$9:INDEX(cf_2!$S$9:$EO$9,1,ROW()-1))-SUM(cf_1!$S$209:INDEX(cf_1!$S$209:$EO$209,1,ROW()-1))-SUM(cf_2!$S$209:INDEX(cf_2!$S$209:$EO$209,1,ROW()-1)))/1000000 -> 0 | BF102: =(SUM(cf_1!$S$183:INDEX(cf_1!$S$183:$EO$183,1,ROW()-1))+SUM(cf_2!$S$183:INDEX(cf_2!$S$183:$EO$183,1,ROW()-1)))/1000000 -> 15426.266 | BG102: =(INDEX(КРЕДИТЫ!$S$52:$EO$52,1,ROW()-1)+INDEX(КРЕДИТЫ!$S$75:$EO$75,1,ROW()-1))/1000000 -> 0
BD103: =INDEX(КРЕДИТЫ!$S$3:$EO$3,1,ROW()-1) -> 0 | BE103: =(SUM(cf_1!$S$9:INDEX(cf_1!$S$9:$EO$9,1,ROW()-1))+SUM(cf_2!$S$9:INDEX(cf_2!$S$9:$EO$9,1,ROW()-1))-SUM(cf_1!$S$209:INDEX(cf_1!$S$209:$EO$209,1,ROW()-1))-SUM(cf_2!$S$209:INDEX(cf_2!$S$209:$EO$209,1,ROW()-1)))/1000000 -> 0 | BF103: =(SUM(cf_1!$S$183:INDEX(cf_1!$S$183:$EO$183,1,ROW()-1))+SUM(cf_2!$S$183:INDEX(cf_2!$S$183:$EO$183,1,ROW()-1)))/1000000 -> 15426.266 | BG103: =(INDEX(КРЕДИТЫ!$S$52:$EO$52,1,ROW()-1)+INDEX(КРЕДИТЫ!$S$75:$EO$75,1,ROW()-1))/1000000 -> 0
BD104: =INDEX(КРЕДИТЫ!$S$3:$EO$3,1,ROW()-1) -> 0 | BE104: =(SUM(cf_1!$S$9:INDEX(cf_1!$S$9:$EO$9,1,ROW()-1))+SUM(cf_2!$S$9:INDEX(cf_2!$S$9:$EO$9,1,ROW()-1))-SUM(cf_1!$S$209:INDEX(cf_1!$S$209:$EO$209,1,ROW()-1))-SUM(cf_2!$S$209:INDEX(cf_2!$S$209:$EO$209,1,ROW()-1)))/1000000 -> 0 | BF104: =(SUM(cf_1!$S$183:INDEX(cf_1!$S$183:$EO$183,1,ROW()-1))+SUM(cf_2!$S$183:INDEX(cf_2!$S$183:$EO$183,1,ROW()-1)))/1000000 -> 15426.266 | BG104: =(INDEX(КРЕДИТЫ!$S$52:$EO$52,1,ROW()-1)+INDEX(КРЕДИТЫ!$S$75:$EO$75,1,ROW()-1))/1000000 -> 0
BD105: =INDEX(КРЕДИТЫ!$S$3:$EO$3,1,ROW()-1) -> 0 | BE105: =(SUM(cf_1!$S$9:INDEX(cf_1!$S$9:$EO$9,1,ROW()-1))+SUM(cf_2!$S$9:INDEX(cf_2!$S$9:$EO$9,1,ROW()-1))-SUM(cf_1!$S$209:INDEX(cf_1!$S$209:$EO$209,1,ROW()-1))-SUM(cf_2!$S$209:INDEX(cf_2!$S$209:$EO$209,1,ROW()-1)))/1000000 -> 0 | BF105: =(SUM(cf_1!$S$183:INDEX(cf_1!$S$183:$EO$183,1,ROW()-1))+SUM(cf_2!$S$183:INDEX(cf_2!$S$183:$EO$183,1,ROW()-1)))/1000000 -> 15426.266 | BG105: =(INDEX(КРЕДИТЫ!$S$52:$EO$52,1,ROW()-1)+INDEX(КРЕДИТЫ!$S$75:$EO$75,1,ROW()-1))/1000000 -> 0
BD106: =INDEX(КРЕДИТЫ!$S$3:$EO$3,1,ROW()-1) -> 0 | BE106: =(SUM(cf_1!$S$9:INDEX(cf_1!$S$9:$EO$9,1,ROW()-1))+SUM(cf_2!$S$9:INDEX(cf_2!$S$9:$EO$9,1,ROW()-1))-SUM(cf_1!$S$209:INDEX(cf_1!$S$209:$EO$209,1,ROW()-1))-SUM(cf_2!$S$209:INDEX(cf_2!$S$209:$EO$209,1,ROW()-1)))/1000000 -> 0 | BF106: =(SUM(cf_1!$S$183:INDEX(cf_1!$S$183:$EO$183,1,ROW()-1))+SUM(cf_2!$S$183:INDEX(cf_2!$S$183:$EO$183,1,ROW()-1)))/1000000 -> 15426.266 | BG106: =(INDEX(КРЕДИТЫ!$S$52:$EO$52,1,ROW()-1)+INDEX(КРЕДИТЫ!$S$75:$EO$75,1,ROW()-1))/1000000 -> 0
BD107: =INDEX(КРЕДИТЫ!$S$3:$EO$3,1,ROW()-1) -> 0 | BE107: =(SUM(cf_1!$S$9:INDEX(cf_1!$S$9:$EO$9,1,ROW()-1))+SUM(cf_2!$S$9:INDEX(cf_2!$S$9:$EO$9,1,ROW()-1))-SUM(cf_1!$S$209:INDEX(cf_1!$S$209:$EO$209,1,ROW()-1))-SUM(cf_2!$S$209:INDEX(cf_2!$S$209:$EO$209,1,ROW()-1)))/1000000 -> 0 | BF107: =(SUM(cf_1!$S$183:INDEX(cf_1!$S$183:$EO$183,1,ROW()-1))+SUM(cf_2!$S$183:INDEX(cf_2!$S$183:$EO$183,1,ROW()-1)))/1000000 -> 15426.266 | BG107: =(INDEX(КРЕДИТЫ!$S$52:$EO$52,1,ROW()-1)+INDEX(КРЕДИТЫ!$S$75:$EO$75,1,ROW()-1))/1000000 -> 0
BD108: =INDEX(КРЕДИТЫ!$S$3:$EO$3,1,ROW()-1) -> 0 | BE108: =(SUM(cf_1!$S$9:INDEX(cf_1!$S$9:$EO$9,1,ROW()-1))+SUM(cf_2!$S$9:INDEX(cf_2!$S$9:$EO$9,1,ROW()-1))-SUM(cf_1!$S$209:INDEX(cf_1!$S$209:$EO$209,1,ROW()-1))-SUM(cf_2!$S$209:INDEX(cf_2!$S$209:$EO$209,1,ROW()-1)))/1000000 -> 0 | BF108: =(SUM(cf_1!$S$183:INDEX(cf_1!$S$183:$EO$183,1,ROW()-1))+SUM(cf_2!$S$183:INDEX(cf_2!$S$183:$EO$183,1,ROW()-1)))/1000000 -> 15426.266 | BG108: =(INDEX(КРЕДИТЫ!$S$52:$EO$52,1,ROW()-1)+INDEX(КРЕДИТЫ!$S$75:$EO$75,1,ROW()-1))/1000000 -> 0
... BD128: =INDEX(КРЕДИТЫ!$S$3:$EO$3,1,ROW()-1) -> 0 | BE128: =(SUM(cf_1!$S$9:INDEX(cf_1!$S$9:$EO$9,1,ROW()-1))+SUM(cf_2!$S$9:INDEX(cf_2!$S$9:$EO$9,1,ROW()-1))-SUM(cf_1!$S$209:INDEX(cf_1!$S$209:$EO$209,1,ROW()-1))-SUM(cf_2!$S$209:INDEX(cf_2!$S$209:$EO$209,1,ROW()-1)))/1000000 -> 0 | BF128: =(SUM(cf_1!$S$183:INDEX(cf_1!$S$183:$EO$183,1,ROW()-1))+SUM(cf_2!$S$183:INDEX(cf_2!$S$183:$EO$183,1,ROW()-1)))/1000000 -> 15426.266 | BG128: =(INDEX(КРЕДИТЫ!$S$52:$EO$52,1,ROW()-1)+INDEX(КРЕДИТЫ!$S$75:$EO$75,1,ROW()-1))/1000000 -> 0

Sheet Расчет ВРИ (ТЭП)
A1: № | B1: Наименования | C1: Единицы измерения | D1: Показатель
A2: 1 | B2: Площадь территории проектирования | C2: га | D2: 1,155
A3: 2 | B3: Плотность от СПП | C3: тыс.кв.м./га | D3: 35
A4: 3 | B4: Плотность от НП | C4: тыс.кв.м./га | D4: 31,5
A5: 4 | B5: Население | C5: чел. | D5: 749 | E5: 28
A6: 5 | B6: Количество квартир | C6: шт. | D6: 357 | E6: 2.0980392
B7: СПП в ГНС:
A8: 6 | B8: СПП, всего: | C8: тыс.кв.м. | D8: 40411 | E8: 1154.6
A9: 7 | B9: СПП жилых зданий, в т.ч.: | C9: тыс.кв.м. | D9: 40411 | E9: 1
A10: 7.1 | B10: СПП жилая | C10: тыс.кв.м. | D10: 37986 | E10: 0.93999159
A11: 7.2 | B11: СПП нежилой части жилых зданий | C11: тыс.кв.м. | D11: 2425 | E11: 0.060008414
A12: 8 | B12: СПП нежилых зданий, в т.ч.: | C12: тыс.кв.м. | D12: 0
A13: 8.1 | B13: СПП общественных, производственных объектов | C13: тыс.кв.м. | D13: 0
A14: 8.2 | B14: СПП социальных объектов | C14: тыс.кв.м. | D14: 0
B15: Наземная площадь:
A16: 9 | B16: НП, всего: | C16: тыс.кв.м. | D16: 36370 | E16: 0.90000247
A17: 9.1 | B17: НП жилых зданий, в т.ч.: | C17: тыс.кв.м. | D17: 36370 | E17: 0.90000247
A18: 9.1.1 | B18: НП жилая | C18: тыс.кв.м. | D18: 34188 | E18: 0.9000158
A19: 9.1.2 | B19: НП нежилой части жилых зданий | C19: тыс.кв.м. | D19: 2182 | E19: 0.89979381
A20: 9.2 | B20: НП нежилых зданий, в т.ч.: | C20: тыс.кв.м. | D20: 0
A21: 9.2.1 | B21: НП общественных, производственных объектов | C21: тыс.кв.м. | D21: 0
A22: 9.2.2 | B22: НП социальных объектов | C22: тыс.кв.м. | D22: 0
B23: Единый показатель:
A24: 10 | B24: Площадь квартир | C24: тыс.кв.м. | D24: 24691 | E24: 0.68
A25: 11 | B25: Нежилая наземная площадь (ННП) | C25: тыс.кв.м. | D25: 2182 | E25: 0.8 | F25: 0.08
B26: Баланс территории:
A27: 12 | B27: Территория жилых зданий, в т.ч.: | C27: га | D27: 1,155 (100,0%)
A28: 12.1 | B28: участки многоквартирных жилых зданий | C28: га | D28: 1,155 (100,0%)
A29: 12.2 | B29: незастраиваемая территория | C29: га | D29: 0 (0,0%)
A30: 13 | B30: Участки социальных объектов | C30: га | D30: 0 (0,0%)
A31: 14 | B31: Участки общественных, производственных объектов | C31: га | D31: 0 (0,0%)
B32: Расчётная плотность территории от СПП:
A33: 15 | B33: жилых участков | C33: тыс.кв.м./га | D33: 35,00 | E33: 34.987879
A34: 16 | B34: социальных объектов | C34: тыс.кв.м./га | D34: 0,00
A35: 17 | B35: общественных, производственных объектов | C35: тыс.кв.м./га | D35: 0,00
B36: ДОО:
A37: 18 | B37: количество мест | C37: мест | D37: 0
A38: 19 | B38: СПП | C38: тыс.кв.м. | D38: 0,000
A39: 20 | B39: наземная площадь | C39: тыс.кв.м. | D39: 0,000
A40: 21 | B40: площадь земельного участка | C40: га | D40: 0,0000
B41: Школы:
A42: 22 | B42: количество мест | C42: мест | D42: 0
A43: 23 | B43: СПП | C43: тыс.кв.м. | D43: 0,000
A44: 24 | B44: наземная площадь | C44: тыс.кв.м. | D44: 0,000
A45: 25 | B45: площадь земельного участка | C45: га | D45: 0,0000
B46: Поликлиники:
A47: 26 | B47: мощность | C47: пос./см. | D47: 0
A48: 27 | B48: СПП | C48: тыс.кв.м. | D48: 0,000
A49: 28 | B49: наземная площадь | C49: тыс.кв.м. | D49: 0,000
A50: 29 | B50: площадь земельного участка | C50: га | D50: 0,0000
B51: Расчёт объектов обслуживания:
A52: 30 | B52: ДОО | C52: мест | D52: 33 | E52: 0.065
A53: 31 | B53: Школа | C53: мест | D53: 68 | E53: 0.135
A54: 32 | B54: Поликлиника смешанного типа | C54: пос./см. | D54: 15 | E54: 0.01775
A55: 33 | B55: Поликлиника взрослая | C55: пос./см. | D55: 10 | E55: 0.749
A56: 34 | B56: Поликлиника детская | C56: пос./см. | D56: 5 | E56: 149.8
A57: 35 | B57: Плоскостные спортивные сооружения | C57: га | D57: 0,0727
A58: 36 | B58: Крытые объекты спорта (ННП), в т.ч.: | C58: тыс.кв.м. | D58: 0,600
A59: 36.1 | B59: в радиусе пешеходной доступности до 500 м | C59: тыс.кв.м. | D59: 0,240
A60: 36.2 | B60: в радиусе пешеходной доступности до 1500 м | C60: тыс.кв.м. | D60: 0,360
A61: 37 | B61: Объекты торговли (ННП) | C61: тыс.кв.м. | D61: 0,203
A62: 38 | B62: Объекты бытового обслуживания населения (ННП) | C62: тыс.кв.м. | D62: 0,075
A63: 39 | B63: Объекты общественного питания (ННП) | C63: тыс.кв.м. | D63: 0,090
A64: 40 | B64: Объекты культуры и досуга (ННП) | C64: тыс.кв.м. | D64: 0,113
A65: 41 | B65: Объекты для размещения городских служб (ННП) | C65: тыс.кв.м. | D65: 0,068
B66: Расчёт машино-мест:
A67: 42 | B67: Места хранения и паркирования, в т.ч.: | C67: м/м | D67: 170 | E67: 2.1
A68: 42.1 | B68: Постоянные парковки | C68: м/м | D68: 145 | E68: 0.85294118
A69: 42.2 | B69: Гостевые парковки | C69: м/м | D69: 15 | E69: 0.088235294
A70: 42.3 | B70: Приобъектные парковки | C70: м/м | D70: 10 | E70: 0.058823529
A71: 43 | B71: Места кратковременной остановки | C71: м/м | D71: 6 | E71: 59.5
B72: Расчёт стоимости смены ВРИ: | C72: млн.руб. | D72: 2 141,838
A73: 44 | B73: Многоквартирная жилые здания | C73: млн.руб. | D73: 2141.838 | E73: =D73*1000 -> 2141838
A74: 45 | B74: Индивидуальные, блочные жилые здания | C74: млн.руб. | D74: 0,000
A75: 46 | B75: Хранение индивидуального транспорта | C75: млн.руб. | D75: 0,000
A76: 47 | B76: Объекты мультифункционального назначения | C76: млн.руб. | D76: 0,000
A77: 48 | B77: Объекты для временного проживания | C77: млн.руб. | D77: 0,000
A78: 49 | B78: Административные, офисные здания | C78: млн.руб. | D78: 0,000
A79: 50 | B79: Производственные здания | C79: млн.руб. | D79: 0,000
A80: 51 | B80: Социальные объекты | C80: млн.руб. | D80: 0,000
A81: 52 | B81: Льгота на стр-во жилья за создание МПТ | C81: млн.руб. | D81: 0,000
A82: 53 | B82: Льгота на стр-во жилья за передачу жилых помещений в собственность города Москвы | C82: млн.руб. | D82: 0,000
B83: Расчёт компенсации за социальные объекты: | C83: млн.руб. | D83: 988.447
A84: 54 | B84: ДОО | C84: млн.руб. | D84: 319.098 | E84: =D84/D52*1000 -> 9669.6364
A85: 55 | B85: Школа | C85: млн.руб. | D85: 509.568 | E85: =D85/D53*1000 -> 7493.6471
A86: 56 | B86: Поликлиника | C86: млн.руб. | D86: 159.781 | E86: =D86/D54*1000 -> 10652.067

Sheet ТЭП
B1: Начало проекта | C1: =Вводные!G7 -> 46266
B2: Общие ТЭП
B3: Показатель | C3: ГНС, кв.м. | D3: Общая площадь, кв.м. | E3: k выхода полезной площади | F3: Полезная площадь | G3: Продаваемая площадь, кв.м. | H3: Передаваемая площадь, кв.м. | I3: Штуки
B4: ИТОГО | C4: =C5+C16 -> 46011 | D4: =D5+D16 -> 41970 | F4: =F5+F16 -> 32473 | G4: =G5+G16 -> 32473 | H4: =H5+H16 -> 0 | I4: =I5+I16 -> 517
B5: Основные объекты | C5: =C6+C13+C9+C10+C11 -> 46011 | D5: =D6+D13+D9+D10+D11 -> 41970 | F5: =F6+F13+F9+F10+F11 -> 32473 | G5: =G6+G13+G9+G10+G11 -> 32473 | H5: =H6+H13+H9+H10+H11 -> 0 | I5: =I6+I13 -> 517
B6: Наземная часть | C6: =SUM(C7:C8) -> 40411 | D6: =SUM(D7:D8) -> 36370 | F6: =SUM(F7:F8) -> 26873 | G6: =SUM(G7:G8) -> 26873 | H6: =SUM(H7:H12) -> 0 | I6: =SUM(I7:I12) -> 357
B7: Квартиры | C7: =C26+C45 -> 37986 | D7: =D26+D45 -> 34188 | E7: =IFERROR(F7/D7,0) -> 0.72221247 | F7: =F26+F45 -> 24691 | G7: =G26+G45 -> 24691 | H7: =H26+H45 -> 0 | I7: =I26+I45 -> 357
B8: Коммерция 1 эт. | C8: =C27+C46 -> 2425 | D8: =D27+D46 -> 2182 | E8: =IFERROR(F8/D8,0) -> 1 | F8: =F27+F46 -> 2182 | G8: =G27+G46 -> 2182 | H8: =H27+H46 -> 0 | I8: =I27+I46 -> 0
B9: Коммерция ОСЗ | C9: =C28+C47 -> 0 | D9: =D28+D47 -> 0 | E9: =IFERROR(F9/D9,0) -> 0 | F9: =F28+F47 -> 0 | G9: =G28+G47 -> 0 | H9: =H28+H47 -> 0 | I9: =I28+I47 -> 0
B10: Офисы | C10: =C29+C48 -> 0 | D10: =D29+D48 -> 0 | E10: =IFERROR(F10/D10,0) -> 0 | F10: =F29+F48 -> 0 | G10: =G29+G48 -> 0 | H10: =H29+H48 -> 0 | I10: =I29+I48 -> 0
B11: Наземный паркинг | C11: =C30+C49 -> 0 | D11: =D30+D49 -> 0 | F11: =F30+F49 -> 0 | G11: =G30+G49 -> 0 | H11: =H30+H49 -> 0 | I11: =I30+I49 -> 0
B12: Прочие | C12: =C31+C50 -> 0 | D12: =D31+D50 -> 0 | F12: =F31+F50 -> 0 | G12: =G31+G50 -> 0 | H12: =H31+H50 -> 0 | I12: =I31+I50 -> 0
B13: Подземная часть | C13: =SUM(C14:C15) -> 5600 | D13: =SUM(D14:D15) -> 5600 | F13: =SUM(F14:F15) -> 5600 | G13: =SUM(G14:G15) -> 5600 | H13: =SUM(H14:H15) -> 0 | I13: =SUM(I14:I15) -> 160
B14: Подземный паркинг | C14: =C33+C52 -> 5600 | D14: =D33+D52 -> 5600 | F14: =F33+F52 -> 5600 | G14: =G33+G52 -> 5600 | H14: =H33+H52 -> 0 | I14: =I33+I52 -> 160
B15: Кладовки | C15: =C34+C53 -> 0 | D15: =D34+D53 -> 0 | F15: =F34+F53 -> 0 | G15: =G34+G53 -> 0 | H15: =H34+H53 -> 0 | I15: =I34+I53 -> 0
B16: Социальные объекты | C16: =SUM(C17:C19) -> 0 | D16: =SUM(D17:D19) -> 0 | F16: =SUM(F17:F19) -> 0 | G16: =SUM(G17:G19) -> 0 | H16: =SUM(H17:H19) -> 0 | I16: =SUM(I17:I19) -> 0
B17: ДОУ | C17: =C36+C55 -> 0 | D17: =D36+D55 -> 0 | F17: =F36+F55 -> 0 | G17: =G36+G55 -> 0 | H17: =H36+H55 -> 0 | I17: =I36+I55 -> 0
B18: СОШ | C18: =C37+C56 -> 0 | D18: =D37+D56 -> 0 | F18: =F37+F56 -> 0 | G18: =G37+G56 -> 0 | H18: =H37+H56 -> 0 | I18: =I37+I56 -> 0
B19: Поликлиника | C19: =C38+C57 -> 0 | D19: =D38+D57 -> 0 | F19: =F38+F57 -> 0 | G19: =G38+G57 -> 0 | H19: =H38+H57 -> 0 | I19: =I38+I57 -> 0
B21: 1 очередь | J21: РнС | K21: РВЭ | L21: Продажи
B22: Показатель | C22: ГНС, кв.м. | D22: Общая площадь, кв.м. | F22: Полезная площадь | G22: Продаваемая площадь, кв.м. | H22: Передаваемая площадь, кв.м. | I22: Штуки | J22: =СРОКИ!C17 -> 46813 | K22: =СРОКИ!C19 -> 47543 | L22: =СРОКИ!C16 -> 46813
B23: ИТОГО | C23: =C24+C35 -> 46011 | D23: =D24+D35 -> 41970 | F23: =F24+F35 -> 32473 | G23: =G24+G35 -> 32473 | H23: =H24+H35 -> 0 | I23: =I24+I35 -> 0 | K23: =IF(DATEDIF(EDATE(J22,0),EDATE(K22,0),"Y")>5,DATEDIF(EDATE(J22,0),EDATE(K22,0),"Y")&"л ",IF(DATEDIF(EDATE(J22,0),EDATE(K22,0),"Y")>0,DATEDIF(EDATE(J22,0),EDATE(K22,0),"Y")&"г ",""))& DATEDIF(EDATE(J22,0),EDATE(K22,0),"M")-DATEDIF(EDATE(J22,0),EDATE(K22,0),"Y")*12&" мес" -> 2г 0 мес
B24: Основные объекты | C24: =C25+C32+C28+C29+C30 -> 46011 | D24: =D25+D32+D28+D29+D30 -> 41970 | F24: =F25+F32+F28+F29+F30 -> 32473 | G24: =G25+G32+G28+G29+G30 -> 32473 | H24: =H25+H32+H28+H29+H30 -> 0
B25: Наземная часть | C25: =SUM(C26:C27) -> 40411 | D25: =SUM(D26:D27) -> 36370 | F25: =SUM(F26:F27) -> 26873 | G25: =SUM(G26:G27) -> 26873 | H25: =SUM(H26:H27) -> 0 | I25: =SUM(I26:I27) -> 357
B26: Квартиры | C26: ='Расчет ВРИ (ТЭП)'!D10 -> 37986 | D26: ='Расчет ВРИ (ТЭП)'!D18 -> 34188 | E26: ='Расчет ВРИ (ТЭП)'!E24 -> 0.68 | F26: ='Расчет ВРИ (ТЭП)'!D24 -> 24691 | G26: =F26 -> 24691 | H26: 0 | I26: ='Расчет ВРИ (ТЭП)'!D6 -> 357
B27: Коммерция 1 эт. | C27: ='Расчет ВРИ (ТЭП)'!D11 -> 2425 | D27: ='Расчет ВРИ (ТЭП)'!D19 -> 2182 | E27: 0.9 | F27: ='Расчет ВРИ (ТЭП)'!D25 -> 2182 | G27: =F27 -> 2182 | H27: 0
B28: Коммерция ОСЗ | C28: =IF(Вводные!G119="Да",Вводные!G120,0) -> 0 | D28: =C28 -> 0 | E28: =IFERROR(F28/D28,0) -> 0 | F28: =IF(Вводные!G119="Да",Вводные!G121,0) -> 0 | G28: =F28 -> 0 | H28: =0 -> 0 | I28: =0 -> 0
B29: Офисы | C29: =IF(Вводные!G106="Да",Вводные!G107,0) -> 0 | D29: =C29 -> 0 | E29: =IFERROR(F29/D29,0) -> 0 | F29: =IF(Вводные!G106="Да",Вводные!G108,0) -> 0 | G29: =F29 -> 0 | H29: =0 -> 0 | I29: =0 -> 0
B30: Наземный паркинг | C30: =IF(Вводные!G132="Да",Вводные!G144,0) -> 0 | D30: =C30 -> 0 | F30: =D30 -> 0 | G30: =F30 -> 0 | H30: =0 -> 0 | I30: =IF(Вводные!G132="Да",Вводные!G133,0) -> 0
B31: Прочие
B32: Подземная часть | C32: =SUM(C33:C34) -> 5600 | D32: =SUM(D33:D34) -> 5600 | F32: =SUM(F33:F34) -> 5600 | G32: =SUM(G33:G34) -> 5600 | H32: =SUM(H33:H34) -> 0 | I32: =SUM(I33:I34) -> 160
B33: Подземный паркинг | C33: =I33*35 -> 5600 | D33: =I33*35 -> 5600 | F33: =D33 -> 5600 | G33: =D33 -> 5600 | I33: ='Расчет ВРИ (ТЭП)'!D68+'Расчет ВРИ (ТЭП)'!D69 -> 160
B34: Кладовки
B35: Социальные объекты | C35: =SUM(C36:C38) -> 0 | D35: =SUM(D36:D38) -> 0 | F35: =SUM(F36:F38) -> 0 | G35: =SUM(G36:G38) -> 0 | H35: =SUM(H36:H38) -> 0 | I35: =SUM(I36:I38) -> 0
B36: ДОУ | C36: =IF(Вводные!G82="Строительство",Вводные!G148,0) -> 0 | D36: =C36 -> 0 | F36: =0 -> 0 | G36: =0 -> 0 | H36: =D36 -> 0 | I36: =IF(Вводные!G82="Строительство",Вводные!G84,0) -> 0
B37: СОШ | C37: =IF(Вводные!G82="Строительство",Вводные!G149,0) -> 0 | D37: =C37 -> 0 | F37: =0 -> 0 | G37: =0 -> 0 | H37: =D37 -> 0 | I37: =IF(Вводные!G82="Строительство",Вводные!G89,0) -> 0
B38: Поликлиника | C38: =IF(Вводные!G82="Строительство",Вводные!G150,0) -> 0 | D38: =C38 -> 0 | F38: =0 -> 0 | G38: =0 -> 0 | H38: =D38 -> 0 | I38: =IF(Вводные!G82="Строительство",Вводные!G94,0) -> 0
B40: 2 очередь | J40: РнС | K40: РВЭ | L40: РВЭ
B41: Показатель | C41: ГНС, кв.м. | D41: Общая площадь, кв.м. | F41: Полезная площадь | G41: Продаваемая площадь, кв.м. | H41: Передаваемая площадь, кв.м. | I41: Штуки
B42: ИТОГО | C42: =C43+C54 -> 0 | D42: =D43+D54 -> 0 | F42: =F43+F54 -> 0 | G42: =G43+G54 -> 0 | H42: =H43+H54 -> 0 | I42: =I43+I54 -> 0 | K42: =IF(DATEDIF(EDATE(J41,0),EDATE(K41,0),"Y")>5,DATEDIF(EDATE(J41,0),EDATE(K41,0),"Y")&"л ",IF(DATEDIF(EDATE(J41,0),EDATE(K41,0),"Y")>0,DATEDIF(EDATE(J41,0),EDATE(K41,0),"Y")&"г ",""))& DATEDIF(EDATE(J41,0),EDATE(K41,0),"M")-DATEDIF(EDATE(J41,0),EDATE(K41,0),"Y")*12&" мес" -> 0 мес
B43: Основные объекты | C43: =C44+C51 -> 0 | D43: =D44+D51 -> 0 | F43: =F44+F51 -> 0 | G43: =G44+G51 -> 0 | H43: =H44+H51 -> 0 | I43: =I44+I51 -> 0
B44: Наземная часть | C44: =SUM(C45:C50) -> 0 | D44: =SUM(D45:D50) -> 0 | F44: =SUM(F45:F50) -> 0 | G44: =SUM(G45:G50) -> 0 | H44: =SUM(H45:H50) -> 0 | I44: =SUM(I45:I50) -> 0
B45: Квартиры | E45: 0
B46: Коммерция 1 эт. | E46: 0
B47: Коммерция ОСЗ | C47: =0 -> 0 | D47: =0 -> 0 | E47: =IFERROR(F47/D47,0) -> 0 | F47: =0 -> 0 | G47: =0 -> 0 | H47: =0 -> 0 | I47: =0 -> 0
B48: Офисы | C48: =0 -> 0 | D48: =0 -> 0 | E48: =IFERROR(F48/D48,0) -> 0 | F48: =0 -> 0 | G48: =0 -> 0 | H48: =0 -> 0 | I48: =0 -> 0
B49: Наземный паркинг | C49: =0 -> 0 | D49: =0 -> 0 | F49: =0 -> 0 | G49: =0 -> 0 | H49: =0 -> 0 | I49: =0 -> 0
B50: Прочие
B51: Подземная часть | C51: =SUM(C52:C53) -> 0 | D51: =SUM(D52:D53) -> 0 | F51: =SUM(F52:F53) -> 0 | G51: =SUM(G52:G53) -> 0 | H51: =SUM(H52:H53) -> 0 | I51: =SUM(I52:I53) -> 0
B52: Подземный паркинг
B53: Кладовки
B54: Социальные объекты | C54: =SUM(C55:C57) -> 0 | D54: =SUM(D55:D57) -> 0 | F54: =SUM(F55:F57) -> 0 | G54: =SUM(G55:G57) -> 0 | H54: =SUM(H55:H57) -> 0 | I54: =SUM(I55:I57) -> 0
B55: ДОУ | C55: =0 -> 0 | D55: =0 -> 0 | F55: =0 -> 0 | G55: =0 -> 0 | H55: =0 -> 0 | I55: =0 -> 0
B56: СОШ | C56: =0 -> 0 | D56: =0 -> 0 | F56: =0 -> 0 | G56: =0 -> 0 | H56: =0 -> 0 | I56: =0 -> 0
B57: Поликлиника | C57: =0 -> 0 | D57: =0 -> 0 | F57: =0 -> 0 | G57: =0 -> 0 | H57: =0 -> 0 | I57: =0 -> 0

Sheet Календарь
A1: ПЛАТО — КАЛЕНДАРНЫЙ ГРАФИК ПРОЕКТА
A3: Событие / этап | B3: Начало | C3: Окончание | D3: Комментарий
A4: Сделка / начало проекта | B4: =Вводные!G7 -> 46266 | C4: =Вводные!G7 -> 46266 | D4: Покупка площадки
A5: ИРД | B5: =Вводные!G7 -> 46266 | C5: =EDATE(Вводные!G8,-1) -> 46784 | D5: Базовый срок — 18 месяцев
A6: БРИДЖ | B6: =Вводные!G7 -> 46266 | C6: =EDATE(Вводные!G8,Вводные!G50) -> 46813 | D6: До рефинансирования после РнС
A7: РнС | B7: =Вводные!G8 -> 46813 | C7: =Вводные!G8 -> 46813 | D7: Начало строительной стадии
A8: Строительство | B8: =Вводные!G8 -> 46813 | C8: =EDATE(Вводные!G8,Вводные!G9) -> 47543 | D8: Срок из листа «Вводные»
A9: Продажи | B9: =Вводные!G10 -> 46813 | C9: =EDATE(EDATE(Вводные!G8,Вводные!G9),Вводные!G51) -> 47727 | D9: Включая остаточные продажи
A10: РВЭ / РНВ | B10: =EDATE(Вводные!G8,Вводные!G9) -> 47543 | C10: =EDATE(Вводные!G8,Вводные!G9) -> 47543 | D10: Окончание строительства
A11: Окончание продаж | B11: =EDATE(EDATE(Вводные!G8,Вводные!G9),Вводные!G51) -> 47727 | C11: =EDATE(EDATE(Вводные!G8,Вводные!G9),Вводные!G51) -> 47727 | D11: Плановая дата
A14: Этап | B14: Старт | C14: Финиш | D14: Длительность, мес. | F14: =Вводные!G7 -> 46266 | G14: =EDATE(F14,1) -> 46296 | H14: =EDATE(G14,1) -> 46327 | I14: =EDATE(H14,1) -> 46357 | J14: =EDATE(I14,1) -> 46388 | K14: =EDATE(J14,1) -> 46419 | L14: =EDATE(K14,1) -> 46447 | M14: =EDATE(L14,1) -> 46478 | N14: =EDATE(M14,1) -> 46508 | ... BX14: =EDATE(BW14,1) -> 48396
A16: ИРД | B16: =Вводные!G7 -> 46266 | C16: =EDATE(Вводные!G8,-1) -> 46784 | D16: =Вводные!G48 -> 18 | F16: =--AND(F$14>=EOMONTH($B16,-1)+1,F$14<=EOMONTH($C16,0)) -> 1 | G16: =--AND(G$14>=EOMONTH($B16,-1)+1,G$14<=EOMONTH($C16,0)) -> 1 | H16: =--AND(H$14>=EOMONTH($B16,-1)+1,H$14<=EOMONTH($C16,0)) -> 1 | I16: =--AND(I$14>=EOMONTH($B16,-1)+1,I$14<=EOMONTH($C16,0)) -> 1 | J16: =--AND(J$14>=EOMONTH($B16,-1)+1,J$14<=EOMONTH($C16,0)) -> 1 | K16: =--AND(K$14>=EOMONTH($B16,-1)+1,K$14<=EOMONTH($C16,0)) -> 1 | L16: =--AND(L$14>=EOMONTH($B16,-1)+1,L$14<=EOMONTH($C16,0)) -> 1 | M16: =--AND(M$14>=EOMONTH($B16,-1)+1,M$14<=EOMONTH($C16,0)) -> 1 | ... BX16: =--AND(BX$14>=EOMONTH($B16,-1)+1,BX$14<=EOMONTH($C16,0)) -> 0
A17: БРИДЖ | B17: =Вводные!G7 -> 46266 | C17: =EDATE(Вводные!G8,Вводные!G50) -> 46813 | D17: =Ставки!G6 -> 18 | F17: =--AND(F$14>=EOMONTH($B17,-1)+1,F$14<=EOMONTH($C17,0)) -> 1 | G17: =--AND(G$14>=EOMONTH($B17,-1)+1,G$14<=EOMONTH($C17,0)) -> 1 | H17: =--AND(H$14>=EOMONTH($B17,-1)+1,H$14<=EOMONTH($C17,0)) -> 1 | I17: =--AND(I$14>=EOMONTH($B17,-1)+1,I$14<=EOMONTH($C17,0)) -> 1 | J17: =--AND(J$14>=EOMONTH($B17,-1)+1,J$14<=EOMONTH($C17,0)) -> 1 | K17: =--AND(K$14>=EOMONTH($B17,-1)+1,K$14<=EOMONTH($C17,0)) -> 1 | L17: =--AND(L$14>=EOMONTH($B17,-1)+1,L$14<=EOMONTH($C17,0)) -> 1 | M17: =--AND(M$14>=EOMONTH($B17,-1)+1,M$14<=EOMONTH($C17,0)) -> 1 | ... BX17: =--AND(BX$14>=EOMONTH($B17,-1)+1,BX$14<=EOMONTH($C17,0)) -> 0
A18: Строительство | B18: =Вводные!G8 -> 46813 | C18: =EDATE(Вводные!G8,Вводные!G9) -> 47543 | D18: =12*(YEAR(C18)-YEAR(B18))+MONTH(C18)-MONTH(B18) -> 24 | F18: =--AND(F$14>=EOMONTH($B18,-1)+1,F$14<=EOMONTH($C18,0)) -> 0 | G18: =--AND(G$14>=EOMONTH($B18,-1)+1,G$14<=EOMONTH($C18,0)) -> 0 | H18: =--AND(H$14>=EOMONTH($B18,-1)+1,H$14<=EOMONTH($C18,0)) -> 0 | I18: =--AND(I$14>=EOMONTH($B18,-1)+1,I$14<=EOMONTH($C18,0)) -> 0 | J18: =--AND(J$14>=EOMONTH($B18,-1)+1,J$14<=EOMONTH($C18,0)) -> 0 | K18: =--AND(K$14>=EOMONTH($B18,-1)+1,K$14<=EOMONTH($C18,0)) -> 0 | L18: =--AND(L$14>=EOMONTH($B18,-1)+1,L$14<=EOMONTH($C18,0)) -> 0 | M18: =--AND(M$14>=EOMONTH($B18,-1)+1,M$14<=EOMONTH($C18,0)) -> 0 | ... BX18: =--AND(BX$14>=EOMONTH($B18,-1)+1,BX$14<=EOMONTH($C18,0)) -> 0
A19: Продажи | B19: =Вводные!G10 -> 46813 | C19: =EDATE(EDATE(Вводные!G8,Вводные!G9),Вводные!G51) -> 47727 | D19: =12*(YEAR(C19)-YEAR(B19))+MONTH(C19)-MONTH(B19) -> 30 | F19: =--AND(F$14>=EOMONTH($B19,-1)+1,F$14<=EOMONTH($C19,0)) -> 0 | G19: =--AND(G$14>=EOMONTH($B19,-1)+1,G$14<=EOMONTH($C19,0)) -> 0 | H19: =--AND(H$14>=EOMONTH($B19,-1)+1,H$14<=EOMONTH($C19,0)) -> 0 | I19: =--AND(I$14>=EOMONTH($B19,-1)+1,I$14<=EOMONTH($C19,0)) -> 0 | J19: =--AND(J$14>=EOMONTH($B19,-1)+1,J$14<=EOMONTH($C19,0)) -> 0 | K19: =--AND(K$14>=EOMONTH($B19,-1)+1,K$14<=EOMONTH($C19,0)) -> 0 | L19: =--AND(L$14>=EOMONTH($B19,-1)+1,L$14<=EOMONTH($C19,0)) -> 0 | M19: =--AND(M$14>=EOMONTH($B19,-1)+1,M$14<=EOMONTH($C19,0)) -> 0 | ... BX19: =--AND(BX$14>=EOMONTH($B19,-1)+1,BX$14<=EOMONTH($C19,0)) -> 0
A20: Остаточные продажи | B20: =EDATE(Вводные!G8,Вводные!G9) -> 47543 | C20: =EDATE(EDATE(Вводные!G8,Вводные!G9),Вводные!G51) -> 47727 | D20: =12*(YEAR(C20)-YEAR(B20))+MONTH(C20)-MONTH(B20) -> 6 | F20: =--AND(F$14>=EOMONTH($B20,-1)+1,F$14<=EOMONTH($C20,0)) -> 0 | G20: =--AND(G$14>=EOMONTH($B20,-1)+1,G$14<=EOMONTH($C20,0)) -> 0 | H20: =--AND(H$14>=EOMONTH($B20,-1)+1,H$14<=EOMONTH($C20,0)) -> 0 | I20: =--AND(I$14>=EOMONTH($B20,-1)+1,I$14<=EOMONTH($C20,0)) -> 0 | J20: =--AND(J$14>=EOMONTH($B20,-1)+1,J$14<=EOMONTH($C20,0)) -> 0 | K20: =--AND(K$14>=EOMONTH($B20,-1)+1,K$14<=EOMONTH($C20,0)) -> 0 | L20: =--AND(L$14>=EOMONTH($B20,-1)+1,L$14<=EOMONTH($C20,0)) -> 0 | M20: =--AND(M$14>=EOMONTH($B20,-1)+1,M$14<=EOMONTH($C20,0)) -> 0 | ... BX20: =--AND(BX$14>=EOMONTH($B20,-1)+1,BX$14<=EOMONTH($C20,0)) -> 0
A23: Ключевая веха | B23: Дата
A24: Сделка | B24: =Вводные!G7 -> 46266 | F24: =--(F$14=EOMONTH($B24,-1)+1) -> 1 | G24: =--(G$14=EOMONTH($B24,-1)+1) -> 0 | H24: =--(H$14=EOMONTH($B24,-1)+1) -> 0 | I24: =--(I$14=EOMONTH($B24,-1)+1) -> 0 | J24: =--(J$14=EOMONTH($B24,-1)+1) -> 0 | K24: =--(K$14=EOMONTH($B24,-1)+1) -> 0 | L24: =--(L$14=EOMONTH($B24,-1)+1) -> 0 | M24: =--(M$14=EOMONTH($B24,-1)+1) -> 0 | ... BX24: =--(BX$14=EOMONTH($B24,-1)+1) -> 0
A25: РнС | B25: =Вводные!G8 -> 46813 | F25: =--(F$14=EOMONTH($B25,-1)+1) -> 0 | G25: =--(G$14=EOMONTH($B25,-1)+1) -> 0 | H25: =--(H$14=EOMONTH($B25,-1)+1) -> 0 | I25: =--(I$14=EOMONTH($B25,-1)+1) -> 0 | J25: =--(J$14=EOMONTH($B25,-1)+1) -> 0 | K25: =--(K$14=EOMONTH($B25,-1)+1) -> 0 | L25: =--(L$14=EOMONTH($B25,-1)+1) -> 0 | M25: =--(M$14=EOMONTH($B25,-1)+1) -> 0 | ... BX25: =--(BX$14=EOMONTH($B25,-1)+1) -> 0
A26: Погашение БРИДЖ | B26: =EDATE(Вводные!G8,Вводные!G50) -> 46813 | F26: =--(F$14=EOMONTH($B26,-1)+1) -> 0 | G26: =--(G$14=EOMONTH($B26,-1)+1) -> 0 | H26: =--(H$14=EOMONTH($B26,-1)+1) -> 0 | I26: =--(I$14=EOMONTH($B26,-1)+1) -> 0 | J26: =--(J$14=EOMONTH($B26,-1)+1) -> 0 | K26: =--(K$14=EOMONTH($B26,-1)+1) -> 0 | L26: =--(L$14=EOMONTH($B26,-1)+1) -> 0 | M26: =--(M$14=EOMONTH($B26,-1)+1) -> 0 | ... BX26: =--(BX$14=EOMONTH($B26,-1)+1) -> 0
A27: Старт продаж | B27: =Вводные!G10 -> 46813 | F27: =--(F$14=EOMONTH($B27,-1)+1) -> 0 | G27: =--(G$14=EOMONTH($B27,-1)+1) -> 0 | H27: =--(H$14=EOMONTH($B27,-1)+1) -> 0 | I27: =--(I$14=EOMONTH($B27,-1)+1) -> 0 | J27: =--(J$14=EOMONTH($B27,-1)+1) -> 0 | K27: =--(K$14=EOMONTH($B27,-1)+1) -> 0 | L27: =--(L$14=EOMONTH($B27,-1)+1) -> 0 | M27: =--(M$14=EOMONTH($B27,-1)+1) -> 0 | ... BX27: =--(BX$14=EOMONTH($B27,-1)+1) -> 0
A28: РВЭ / РНВ | B28: =EDATE(Вводные!G8,Вводные!G9) -> 47543 | F28: =--(F$14=EOMONTH($B28,-1)+1) -> 0 | G28: =--(G$14=EOMONTH($B28,-1)+1) -> 0 | H28: =--(H$14=EOMONTH($B28,-1)+1) -> 0 | I28: =--(I$14=EOMONTH($B28,-1)+1) -> 0 | J28: =--(J$14=EOMONTH($B28,-1)+1) -> 0 | K28: =--(K$14=EOMONTH($B28,-1)+1) -> 0 | L28: =--(L$14=EOMONTH($B28,-1)+1) -> 0 | M28: =--(M$14=EOMONTH($B28,-1)+1) -> 0 | ... BX28: =--(BX$14=EOMONTH($B28,-1)+1) -> 0
A29: Окончание продаж | B29: =EDATE(EDATE(Вводные!G8,Вводные!G9),Вводные!G51) -> 47727 | F29: =--(F$14=EOMONTH($B29,-1)+1) -> 0 | G29: =--(G$14=EOMONTH($B29,-1)+1) -> 0 | H29: =--(H$14=EOMONTH($B29,-1)+1) -> 0 | I29: =--(I$14=EOMONTH($B29,-1)+1) -> 0 | J29: =--(J$14=EOMONTH($B29,-1)+1) -> 0 | K29: =--(K$14=EOMONTH($B29,-1)+1) -> 0 | L29: =--(L$14=EOMONTH($B29,-1)+1) -> 0 | M29: =--(M$14=EOMONTH($B29,-1)+1) -> 0 | ... BX29: =--(BX$14=EOMONTH($B29,-1)+1) -> 0
A32: Срок ИРД, лаг старта продаж, лаг погашения БРИДЖ и остаточные продажи задаются на листе «Вводные». Все даты пересчитываются автоматически.

Sheet Цены
A1: ПЛАТО — ПОМЕСЯЧНАЯ ДИНАМИКА ЦЕН
A3: Месяц | B3: Квартиры, тыс. ₽/м² | C3: Коммерция, тыс. ₽/м² | D3: Машино-место, тыс. ₽/шт. | E3: Кладовая, тыс. ₽/шт. | F3: Статус
A4: =ПОДБОР_КВ.М!H2 -> 46266 | B4: =ПОДБОР_КВ.М!H64 -> 0 | C4: =ПОДБОР_КВ.М!H65 -> 0 | D4: =ПОДБОР_КВ.М!H66 -> 0 | E4: =ПОДБОР_КВ.М!H67 -> 0 | F4: =IF(A4<Вводные!G10,"До продаж",IF(A4<=EDATE(Вводные!G8,Вводные!G9),"Строительство","После РВЭ")) -> До продаж
A5: =ПОДБОР_КВ.М!I2 -> 46296 | B5: =ПОДБОР_КВ.М!I64 -> 0 | C5: =ПОДБОР_КВ.М!I65 -> 0 | D5: =ПОДБОР_КВ.М!I66 -> 0 | E5: =ПОДБОР_КВ.М!I67 -> 0 | F5: =IF(A5<Вводные!G10,"До продаж",IF(A5<=EDATE(Вводные!G8,Вводные!G9),"Строительство","После РВЭ")) -> До продаж
A6: =ПОДБОР_КВ.М!J2 -> 46327 | B6: =ПОДБОР_КВ.М!J64 -> 0 | C6: =ПОДБОР_КВ.М!J65 -> 0 | D6: =ПОДБОР_КВ.М!J66 -> 0 | E6: =ПОДБОР_КВ.М!J67 -> 0 | F6: =IF(A6<Вводные!G10,"До продаж",IF(A6<=EDATE(Вводные!G8,Вводные!G9),"Строительство","После РВЭ")) -> До продаж
A7: =ПОДБОР_КВ.М!K2 -> 46357 | B7: =ПОДБОР_КВ.М!K64 -> 0 | C7: =ПОДБОР_КВ.М!K65 -> 0 | D7: =ПОДБОР_КВ.М!K66 -> 0 | E7: =ПОДБОР_КВ.М!K67 -> 0 | F7: =IF(A7<Вводные!G10,"До продаж",IF(A7<=EDATE(Вводные!G8,Вводные!G9),"Строительство","После РВЭ")) -> До продаж
A8: =ПОДБОР_КВ.М!L2 -> 46388 | B8: =ПОДБОР_КВ.М!L64 -> 0 | C8: =ПОДБОР_КВ.М!L65 -> 0 | D8: =ПОДБОР_КВ.М!L66 -> 0 | E8: =ПОДБОР_КВ.М!L67 -> 0 | F8: =IF(A8<Вводные!G10,"До продаж",IF(A8<=EDATE(Вводные!G8,Вводные!G9),"Строительство","После РВЭ")) -> До продаж
A9: =ПОДБОР_КВ.М!M2 -> 46419 | B9: =ПОДБОР_КВ.М!M64 -> 0 | C9: =ПОДБОР_КВ.М!M65 -> 0 | D9: =ПОДБОР_КВ.М!M66 -> 0 | E9: =ПОДБОР_КВ.М!M67 -> 0 | F9: =IF(A9<Вводные!G10,"До продаж",IF(A9<=EDATE(Вводные!G8,Вводные!G9),"Строительство","После РВЭ")) -> До продаж
A10: =ПОДБОР_КВ.М!N2 -> 46447 | B10: =ПОДБОР_КВ.М!N64 -> 0 | C10: =ПОДБОР_КВ.М!N65 -> 0 | D10: =ПОДБОР_КВ.М!N66 -> 0 | E10: =ПОДБОР_КВ.М!N67 -> 0 | F10: =IF(A10<Вводные!G10,"До продаж",IF(A10<=EDATE(Вводные!G8,Вводные!G9),"Строительство","После РВЭ")) -> До продаж
A11: =ПОДБОР_КВ.М!O2 -> 46478 | B11: =ПОДБОР_КВ.М!O64 -> 0 | C11: =ПОДБОР_КВ.М!O65 -> 0 | D11: =ПОДБОР_КВ.М!O66 -> 0 | E11: =ПОДБОР_КВ.М!O67 -> 0 | F11: =IF(A11<Вводные!G10,"До продаж",IF(A11<=EDATE(Вводные!G8,Вводные!G9),"Строительство","После РВЭ")) -> До продаж
A12: =ПОДБОР_КВ.М!P2 -> 46508 | B12: =ПОДБОР_КВ.М!P64 -> 0 | C12: =ПОДБОР_КВ.М!P65 -> 0 | D12: =ПОДБОР_КВ.М!P66 -> 0 | E12: =ПОДБОР_КВ.М!P67 -> 0 | F12: =IF(A12<Вводные!G10,"До продаж",IF(A12<=EDATE(Вводные!G8,Вводные!G9),"Строительство","После РВЭ")) -> До продаж
A13: =ПОДБОР_КВ.М!Q2 -> 46539 | B13: =ПОДБОР_КВ.М!Q64 -> 0 | C13: =ПОДБОР_КВ.М!Q65 -> 0 | D13: =ПОДБОР_КВ.М!Q66 -> 0 | E13: =ПОДБОР_КВ.М!Q67 -> 0 | F13: =IF(A13<Вводные!G10,"До продаж",IF(A13<=EDATE(Вводные!G8,Вводные!G9),"Строительство","После РВЭ")) -> До продаж
A14: =ПОДБОР_КВ.М!R2 -> 46569 | B14: =ПОДБОР_КВ.М!R64 -> 0 | C14: =ПОДБОР_КВ.М!R65 -> 0 | D14: =ПОДБОР_КВ.М!R66 -> 0 | E14: =ПОДБОР_КВ.М!R67 -> 0 | F14: =IF(A14<Вводные!G10,"До продаж",IF(A14<=EDATE(Вводные!G8,Вводные!G9),"Строительство","После РВЭ")) -> До продаж
A15: =ПОДБОР_КВ.М!S2 -> 46600 | B15: =ПОДБОР_КВ.М!S64 -> 0 | C15: =ПОДБОР_КВ.М!S65 -> 0 | D15: =ПОДБОР_КВ.М!S66 -> 0 | E15: =ПОДБОР_КВ.М!S67 -> 0 | F15: =IF(A15<Вводные!G10,"До продаж",IF(A15<=EDATE(Вводные!G8,Вводные!G9),"Строительство","После РВЭ")) -> До продаж
A16: =ПОДБОР_КВ.М!T2 -> 46631 | B16: =ПОДБОР_КВ.М!T64 -> 0 | C16: =ПОДБОР_КВ.М!T65 -> 0 | D16: =ПОДБОР_КВ.М!T66 -> 0 | E16: =ПОДБОР_КВ.М!T67 -> 0 | F16: =IF(A16<Вводные!G10,"До продаж",IF(A16<=EDATE(Вводные!G8,Вводные!G9),"Строительство","После РВЭ")) -> До продаж
A17: =ПОДБОР_КВ.М!U2 -> 46661 | B17: =ПОДБОР_КВ.М!U64 -> 0 | C17: =ПОДБОР_КВ.М!U65 -> 0 | D17: =ПОДБОР_КВ.М!U66 -> 0 | E17: =ПОДБОР_КВ.М!U67 -> 0 | F17: =IF(A17<Вводные!G10,"До продаж",IF(A17<=EDATE(Вводные!G8,Вводные!G9),"Строительство","После РВЭ")) -> До продаж
A18: =ПОДБОР_КВ.М!V2 -> 46692 | B18: =ПОДБОР_КВ.М!V64 -> 0 | C18: =ПОДБОР_КВ.М!V65 -> 0 | D18: =ПОДБОР_КВ.М!V66 -> 0 | E18: =ПОДБОР_КВ.М!V67 -> 0 | F18: =IF(A18<Вводные!G10,"До продаж",IF(A18<=EDATE(Вводные!G8,Вводные!G9),"Строительство","После РВЭ")) -> До продаж
A19: =ПОДБОР_КВ.М!W2 -> 46722 | B19: =ПОДБОР_КВ.М!W64 -> 0 | C19: =ПОДБОР_КВ.М!W65 -> 0 | D19: =ПОДБОР_КВ.М!W66 -> 0 | E19: =ПОДБОР_КВ.М!W67 -> 0 | F19: =IF(A19<Вводные!G10,"До продаж",IF(A19<=EDATE(Вводные!G8,Вводные!G9),"Строительство","После РВЭ")) -> До продаж
A20: =ПОДБОР_КВ.М!X2 -> 46753 | B20: =ПОДБОР_КВ.М!X64 -> 0 | C20: =ПОДБОР_КВ.М!X65 -> 0 | D20: =ПОДБОР_КВ.М!X66 -> 0 | E20: =ПОДБОР_КВ.М!X67 -> 0 | F20: =IF(A20<Вводные!G10,"До продаж",IF(A20<=EDATE(Вводные!G8,Вводные!G9),"Строительство","После РВЭ")) -> До продаж
A21: =ПОДБОР_КВ.М!Y2 -> 46784 | B21: =ПОДБОР_КВ.М!Y64 -> 0 | C21: =ПОДБОР_КВ.М!Y65 -> 0 | D21: =ПОДБОР_КВ.М!Y66 -> 0 | E21: =ПОДБОР_КВ.М!Y67 -> 0 | F21: =IF(A21<Вводные!G10,"До продаж",IF(A21<=EDATE(Вводные!G8,Вводные!G9),"Строительство","После РВЭ")) -> До продаж
A22: =ПОДБОР_КВ.М!Z2 -> 46813 | B22: =ПОДБОР_КВ.М!Z64 -> 675 | C22: =ПОДБОР_КВ.М!Z65 -> 650 | D22: =ПОДБОР_КВ.М!Z66 -> 4000 | E22: =ПОДБОР_КВ.М!Z67 -> 1000 | F22: =IF(A22<Вводные!G10,"До продаж",IF(A22<=EDATE(Вводные!G8,Вводные!G9),"Строительство","После РВЭ")) -> Строительство
A23: =ПОДБОР_КВ.М!AA2 -> 46844 | B23: =ПОДБОР_КВ.М!AA64 -> 682.41948 | C23: =ПОДБОР_КВ.М!AA65 -> 657.14468 | D23: =ПОДБОР_КВ.М!AA66 -> 4043.9673 | E23: =ПОДБОР_КВ.М!AA67 -> 1010.9918 | F23: =IF(A23<Вводные!G10,"До продаж",IF(A23<=EDATE(Вводные!G8,Вводные!G9),"Строительство","После РВЭ")) -> Строительство
A24: =ПОДБОР_КВ.М!AB2 -> 46874 | B24: =ПОДБОР_КВ.М!AB64 -> 689.9205 | C24: =ПОДБОР_КВ.М!AB65 -> 664.36789 | D24: =ПОДБОР_КВ.М!AB66 -> 4088.4178 | E24: =ПОДБОР_КВ.М!AB67 -> 1022.1045 | F24: =IF(A24<Вводные!G10,"До продаж",IF(A24<=EDATE(Вводные!G8,Вводные!G9),"Строительство","После РВЭ")) -> Строительство
A25: =ПОДБОР_КВ.М!AC2 -> 46905 | B25: =ПОДБОР_КВ.М!AC64 -> 697.50398 | C25: =ПОДБОР_КВ.М!AC65 -> 671.6705 | D25: =ПОДБОР_КВ.М!AC66 -> 4133.3569 | E25: =ПОДБОР_КВ.М!AC67 -> 1033.3392 | F25: =IF(A25<Вводные!G10,"До продаж",IF(A25<=EDATE(Вводные!G8,Вводные!G9),"Строительство","После РВЭ")) -> Строительство
A26: =ПОДБОР_КВ.М!AD2 -> 46935 | B26: =ПОДБОР_КВ.М!AD64 -> 705.17082 | C26: =ПОДБОР_КВ.М!AD65 -> 679.05338 | D26: =ПОДБОР_КВ.М!AD66 -> 4178.79 | E26: =ПОДБОР_КВ.М!AD67 -> 1044.6975 | F26: =IF(A26<Вводные!G10,"До продаж",IF(A26<=EDATE(Вводные!G8,Вводные!G9),"Строительство","После РВЭ")) -> Строительство
A27: =ПОДБОР_КВ.М!AE2 -> 46966 | B27: =ПОДБОР_КВ.М!AE64 -> 712.92193 | C27: =ПОДБОР_КВ.М!AE65 -> 686.51741 | D27: =ПОДБОР_КВ.М!AE66 -> 4224.7225 | E27: =ПОДБОР_КВ.М!AE67 -> 1056.1806 | F27: =IF(A27<Вводные!G10,"До продаж",IF(A27<=EDATE(Вводные!G8,Вводные!G9),"Строительство","После РВЭ")) -> Строительство
A28: =ПОДБОР_КВ.М!AF2 -> 46997 | B28: =ПОДБОР_КВ.М!AF64 -> 720.75823 | C28: =ПОДБОР_КВ.М!AF65 -> 694.06348 | D28: =ПОДБОР_КВ.М!AF66 -> 4271.1599 | E28: =ПОДБОР_КВ.М!AF67 -> 1067.79 | F28: =IF(A28<Вводные!G10,"До продаж",IF(A28<=EDATE(Вводные!G8,Вводные!G9),"Строительство","После РВЭ")) -> Строительство
A29: =ПОДБОР_КВ.М!AG2 -> 47027 | B29: =ПОДБОР_КВ.М!AG64 -> 728.68067 | C29: =ПОДБОР_КВ.М!AG65 -> 701.6925 | D29: =ПОДБОР_КВ.М!AG66 -> 4318.1077 | E29: =ПОДБОР_КВ.М!AG67 -> 1079.5269 | F29: =IF(A29<Вводные!G10,"До продаж",IF(A29<=EDATE(Вводные!G8,Вводные!G9),"Строительство","После РВЭ")) -> Строительство
A30: =ПОДБОР_КВ.М!AH2 -> 47058 | B30: =ПОДБОР_КВ.М!AH64 -> 736.6902 | C30: =ПОДБОР_КВ.М!AH65 -> 709.40537 | D30: =ПОДБОР_КВ.М!AH66 -> 4365.5715 | E30: =ПОДБОР_КВ.М!AH67 -> 1091.3929 | F30: =IF(A30<Вводные!G10,"До продаж",IF(A30<=EDATE(Вводные!G8,Вводные!G9),"Строительство","После РВЭ")) -> Строительство
A31: =ПОДБОР_КВ.М!AI2 -> 47088 | B31: =ПОДБОР_КВ.М!AI64 -> 744.78776 | C31: =ПОДБОР_КВ.М!AI65 -> 717.20303 | D31: =ПОДБОР_КВ.М!AI66 -> 4413.5571 | E31: =ПОДБОР_КВ.М!AI67 -> 1103.3893 | F31: =IF(A31<Вводные!G10,"До продаж",IF(A31<=EDATE(Вводные!G8,Вводные!G9),"Строительство","После РВЭ")) -> Строительство
A32: =ПОДБОР_КВ.М!AJ2 -> 47119 | B32: =ПОДБОР_КВ.М!AJ64 -> 752.97433 | C32: =ПОДБОР_КВ.М!AJ65 -> 725.08639 | D32: =ПОДБОР_КВ.М!AJ66 -> 4462.0701 | E32: =ПОДБОР_КВ.М!AJ67 -> 1115.5175 | F32: =IF(A32<Вводные!G10,"До продаж",IF(A32<=EDATE(Вводные!G8,Вводные!G9),"Строительство","После РВЭ")) -> Строительство
A33: =ПОДБОР_КВ.М!AK2 -> 47150 | B33: =ПОДБОР_КВ.М!AK64 -> 761.25088 | C33: =ПОДБОР_КВ.М!AK65 -> 733.05641 | D33: =ПОДБОР_КВ.М!AK66 -> 4511.1163 | E33: =ПОДБОР_КВ.М!AK67 -> 1127.7791 | F33: =IF(A33<Вводные!G10,"До продаж",IF(A33<=EDATE(Вводные!G8,Вводные!G9),"Строительство","После РВЭ")) -> Строительство
A34: =ПОДБОР_КВ.М!AL2 -> 47178 | B34: =ПОДБОР_КВ.М!AL64 -> 769.61841 | C34: =ПОДБОР_КВ.М!AL65 -> 741.11403 | D34: =ПОДБОР_КВ.М!AL66 -> 4560.7017 | E34: =ПОДБОР_КВ.М!AL67 -> 1140.1754 | F34: =IF(A34<Вводные!G10,"До продаж",IF(A34<=EDATE(Вводные!G8,Вводные!G9),"Строительство","После РВЭ")) -> Строительство
A35: =ПОДБОР_КВ.М!AM2 -> 47209 | B35: =ПОДБОР_КВ.М!AM64 -> 778.07792 | C35: =ПОДБОР_КВ.М!AM65 -> 749.26021 | D35: =ПОДБОР_КВ.М!AM66 -> 4610.8321 | E35: =ПОДБОР_КВ.М!AM67 -> 1152.708 | F35: =IF(A35<Вводные!G10,"До продаж",IF(A35<=EDATE(Вводные!G8,Вводные!G9),"Строительство","После РВЭ")) -> Строительство
A36: =ПОДБОР_КВ.М!AN2 -> 47239 | B36: =ПОДБОР_КВ.М!AN64 -> 786.6304 | C36: =ПОДБОР_КВ.М!AN65 -> 757.49594 | D36: =ПОДБОР_КВ.М!AN66 -> 4661.5135 | E36: =ПОДБОР_КВ.М!AN67 -> 1165.3784 | F36: =IF(A36<Вводные!G10,"До продаж",IF(A36<=EDATE(Вводные!G8,Вводные!G9),"Строительство","После РВЭ")) -> Строительство
A37: =ПОДБОР_КВ.М!AO2 -> 47270 | B37: =ПОДБОР_КВ.М!AO64 -> 795.2769 | C37: =ПОДБОР_КВ.М!AO65 -> 765.8222 | D37: =ПОДБОР_КВ.М!AO66 -> 4712.752 | E37: =ПОДБОР_КВ.М!AO67 -> 1178.188 | F37: =IF(A37<Вводные!G10,"До продаж",IF(A37<=EDATE(Вводные!G8,Вводные!G9),"Строительство","После РВЭ")) -> Строительство
A38: =ПОДБОР_КВ.М!AP2 -> 47300 | B38: =ПОДБОР_КВ.М!AP64 -> 804.01844 | C38: =ПОДБОР_КВ.М!AP65 -> 774.23998 | D38: =ПОДБОР_КВ.М!AP66 -> 4764.5537 | E38: =ПОДБОР_КВ.М!AP67 -> 1191.1384 | F38: =IF(A38<Вводные!G10,"До продаж",IF(A38<=EDATE(Вводные!G8,Вводные!G9),"Строительство","После РВЭ")) -> Строительство
A39: =ПОДБОР_КВ.М!AQ2 -> 47331 | B39: =ПОДБОР_КВ.М!AQ64 -> 812.85606 | C39: =ПОДБОР_КВ.М!AQ65 -> 782.75028 | D39: =ПОДБОР_КВ.М!AQ66 -> 4816.9248 | E39: =ПОДБОР_КВ.М!AQ67 -> 1204.2312 | F39: =IF(A39<Вводные!G10,"До продаж",IF(A39<=EDATE(Вводные!G8,Вводные!G9),"Строительство","После РВЭ")) -> Строительство
A40: =ПОДБОР_КВ.М!AR2 -> 47362 | B40: =ПОДБОР_КВ.М!AR64 -> 821.79082 | C40: =ПОДБОР_КВ.М!AR65 -> 791.35413 | D40: =ПОДБОР_КВ.М!AR66 -> 4869.8715 | E40: =ПОДБОР_КВ.М!AR67 -> 1217.4679 | F40: =IF(A40<Вводные!G10,"До продаж",IF(A40<=EDATE(Вводные!G8,Вводные!G9),"Строительство","После РВЭ")) -> Строительство
A41: =ПОДБОР_КВ.М!AS2 -> 47392 | B41: =ПОДБОР_КВ.М!AS64 -> 830.8238 | C41: =ПОДБОР_КВ.М!AS65 -> 800.05254 | D41: =ПОДБОР_КВ.М!AS66 -> 4923.4003 | E41: =ПОДБОР_КВ.М!AS67 -> 1230.8501 | F41: =IF(A41<Вводные!G10,"До продаж",IF(A41<=EDATE(Вводные!G8,Вводные!G9),"Строительство","После РВЭ")) -> Строительство
A42: =ПОДБОР_КВ.М!AT2 -> 47423 | B42: =ПОДБОР_КВ.М!AT64 -> 839.95606 | C42: =ПОДБОР_КВ.М!AT65 -> 808.84657 | D42: =ПОДБОР_КВ.М!AT66 -> 4977.5174 | E42: =ПОДБОР_КВ.М!AT67 -> 1244.3793 | F42: =IF(A42<Вводные!G10,"До продаж",IF(A42<=EDATE(Вводные!G8,Вводные!G9),"Строительство","После РВЭ")) -> Строительство
A43: =ПОДБОР_КВ.М!AU2 -> 47453 | B43: =ПОДБОР_КВ.М!AU64 -> 849.1887 | C43: =ПОДБОР_КВ.М!AU65 -> 817.73727 | D43: =ПОДБОР_КВ.М!AU66 -> 5032.2293 | E43: =ПОДБОР_КВ.М!AU67 -> 1258.0573 | F43: =IF(A43<Вводные!G10,"До продаж",IF(A43<=EDATE(Вводные!G8,Вводные!G9),"Строительство","После РВЭ")) -> Строительство
A44: =ПОДБОР_КВ.М!AV2 -> 47484 | B44: =ПОДБОР_КВ.М!AV64 -> 858.52282 | C44: =ПОДБОР_КВ.М!AV65 -> 826.72568 | D44: =ПОДБОР_КВ.М!AV66 -> 5087.5427 | E44: =ПОДБОР_КВ.М!AV67 -> 1271.8857 | F44: =IF(A44<Вводные!G10,"До продаж",IF(A44<=EDATE(Вводные!G8,Вводные!G9),"Строительство","После РВЭ")) -> Строительство
A45: =ПОДБОР_КВ.М!AW2 -> 47515 | B45: =ПОДБОР_КВ.М!AW64 -> 867.95955 | C45: =ПОДБОР_КВ.М!AW65 -> 835.8129 | D45: =ПОДБОР_КВ.М!AW66 -> 5143.464 | E45: =ПОДБОР_КВ.М!AW67 -> 1285.866 | F45: =IF(A45<Вводные!G10,"До продаж",IF(A45<=EDATE(Вводные!G8,Вводные!G9),"Строительство","После РВЭ")) -> Строительство
A46: =ПОДБОР_КВ.М!AX2 -> 47543 | B46: =ПОДБОР_КВ.М!AX64 -> 877.5 | C46: =ПОДБОР_КВ.М!AX65 -> 845 | D46: =ПОДБОР_КВ.М!AX66 -> 5200 | E46: =ПОДБОР_КВ.М!AX67 -> 1300 | F46: =IF(A46<Вводные!G10,"До продаж",IF(A46<=EDATE(Вводные!G8,Вводные!G9),"Строительство","После РВЭ")) -> Строительство
A47: =ПОДБОР_КВ.М!AY2 -> 47574 | B47: =ПОДБОР_КВ.М!AY64 -> 879.66415 | C47: =ПОДБОР_КВ.М!AY65 -> 847.084 | D47: =ПОДБОР_КВ.М!AY66 -> 5212.8246 | E47: =ПОДБОР_КВ.М!AY67 -> 1303.2062 | F47: =IF(A47<Вводные!G10,"До продаж",IF(A47<=EDATE(Вводные!G8,Вводные!G9),"Строительство","После РВЭ")) -> После РВЭ
A48: =ПОДБОР_КВ.М!AZ2 -> 47604 | B48: =ПОДБОР_КВ.М!AZ64 -> 881.83364 | C48: =ПОДБОР_КВ.М!AZ65 -> 849.17314 | D48: =ПОДБОР_КВ.М!AZ66 -> 5225.6808 | E48: =ПОДБОР_КВ.М!AZ67 -> 1306.4202 | F48: =IF(A48<Вводные!G10,"До продаж",IF(A48<=EDATE(Вводные!G8,Вводные!G9),"Строительство","После РВЭ")) -> После РВЭ
A49: =ПОДБОР_КВ.М!BA2 -> 47635 | B49: =ПОДБОР_КВ.М!BA64 -> 884.00848 | C49: =ПОДБОР_КВ.М!BA65 -> 851.26743 | D49: =ПОДБОР_КВ.М!BA66 -> 5238.5688 | E49: =ПОДБОР_КВ.М!BA67 -> 1309.6422 | F49: =IF(A49<Вводные!G10,"До продаж",IF(A49<=EDATE(Вводные!G8,Вводные!G9),"Строительство","После РВЭ")) -> После РВЭ
A50: =ПОДБОР_КВ.М!BB2 -> 47665 | B50: =ПОДБОР_КВ.М!BB64 -> 886.18868 | C50: =ПОДБОР_КВ.М!BB65 -> 853.36688 | D50: =ПОДБОР_КВ.М!BB66 -> 5251.4885 | E50: =ПОДБОР_КВ.М!BB67 -> 1312.8721 | F50: =IF(A50<Вводные!G10,"До продаж",IF(A50<=EDATE(Вводные!G8,Вводные!G9),"Строительство","После РВЭ")) -> После РВЭ
A51: =ПОДБОР_КВ.М!BC2 -> 47696 | B51: =ПОДБОР_КВ.М!BC64 -> 888.37426 | C51: =ПОДБОР_КВ.М!BC65 -> 855.47151 | D51: =ПОДБОР_КВ.М!BC66 -> 5264.4401 | E51: =ПОДБОР_КВ.М!BC67 -> 1316.11 | F51: =IF(A51<Вводные!G10,"До продаж",IF(A51<=EDATE(Вводные!G8,Вводные!G9),"Строительство","После РВЭ")) -> После РВЭ
A52: =ПОДБОР_КВ.М!BD2 -> 47727 | B52: =ПОДБОР_КВ.М!BD64 -> 890.56523 | C52: =ПОДБОР_КВ.М!BD65 -> 857.58134 | D52: =ПОДБОР_КВ.М!BD66 -> 5277.4236 | E52: =ПОДБОР_КВ.М!BD67 -> 1319.3559 | F52: =IF(A52<Вводные!G10,"До продаж",IF(A52<=EDATE(Вводные!G8,Вводные!G9),"Строительство","После РВЭ")) -> После РВЭ
A53: =ПОДБОР_КВ.М!BE2 -> 47757 | B53: =ПОДБОР_КВ.М!BE64 -> 0 | C53: =ПОДБОР_КВ.М!BE65 -> 0 | D53: =ПОДБОР_КВ.М!BE66 -> 0 | E53: =ПОДБОР_КВ.М!BE67 -> 0 | F53: =IF(A53<Вводные!G10,"До продаж",IF(A53<=EDATE(Вводные!G8,Вводные!G9),"Строительство","После РВЭ")) -> После РВЭ
A54: =ПОДБОР_КВ.М!BF2 -> 47788 | B54: =ПОДБОР_КВ.М!BF64 -> 0 | C54: =ПОДБОР_КВ.М!BF65 -> 0 | D54: =ПОДБОР_КВ.М!BF66 -> 0 | E54: =ПОДБОР_КВ.М!BF67 -> 0 | F54: =IF(A54<Вводные!G10,"До продаж",IF(A54<=EDATE(Вводные!G8,Вводные!G9),"Строительство","После РВЭ")) -> После РВЭ
A55: =ПОДБОР_КВ.М!BG2 -> 47818 | B55: =ПОДБОР_КВ.М!BG64 -> 0 | C55: =ПОДБОР_КВ.М!BG65 -> 0 | D55: =ПОДБОР_КВ.М!BG66 -> 0 | E55: =ПОДБОР_КВ.М!BG67 -> 0 | F55: =IF(A55<Вводные!G10,"До продаж",IF(A55<=EDATE(Вводные!G8,Вводные!G9),"Строительство","После РВЭ")) -> После РВЭ
A56: =ПОДБОР_КВ.М!BH2 -> 47849 | B56: =ПОДБОР_КВ.М!BH64 -> 0 | C56: =ПОДБОР_КВ.М!BH65 -> 0 | D56: =ПОДБОР_КВ.М!BH66 -> 0 | E56: =ПОДБОР_КВ.М!BH67 -> 0 | F56: =IF(A56<Вводные!G10,"До продаж",IF(A56<=EDATE(Вводные!G8,Вводные!G9),"Строительство","После РВЭ")) -> После РВЭ
A57: =ПОДБОР_КВ.М!BI2 -> 47880 | B57: =ПОДБОР_КВ.М!BI64 -> 0 | C57: =ПОДБОР_КВ.М!BI65 -> 0 | D57: =ПОДБОР_КВ.М!BI66 -> 0 | E57: =ПОДБОР_КВ.М!BI67 -> 0 | F57: =IF(A57<Вводные!G10,"До продаж",IF(A57<=EDATE(Вводные!G8,Вводные!G9),"Строительство","После РВЭ")) -> После РВЭ
A58: =ПОДБОР_КВ.М!BJ2 -> 47908 | B58: =ПОДБОР_КВ.М!BJ64 -> 0 | C58: =ПОДБОР_КВ.М!BJ65 -> 0 | D58: =ПОДБОР_КВ.М!BJ66 -> 0 | E58: =ПОДБОР_КВ.М!BJ67 -> 0 | F58: =IF(A58<Вводные!G10,"До продаж",IF(A58<=EDATE(Вводные!G8,Вводные!G9),"Строительство","После РВЭ")) -> После РВЭ
A59: =ПОДБОР_КВ.М!BK2 -> 47939 | B59: =ПОДБОР_КВ.М!BK64 -> 0 | C59: =ПОДБОР_КВ.М!BK65 -> 0 | D59: =ПОДБОР_КВ.М!BK66 -> 0 | E59: =ПОДБОР_КВ.М!BK67 -> 0 | F59: =IF(A59<Вводные!G10,"До продаж",IF(A59<=EDATE(Вводные!G8,Вводные!G9),"Строительство","После РВЭ")) -> После РВЭ
A60: =ПОДБОР_КВ.М!BL2 -> 47969 | B60: =ПОДБОР_КВ.М!BL64 -> 0 | C60: =ПОДБОР_КВ.М!BL65 -> 0 | D60: =ПОДБОР_КВ.М!BL66 -> 0 | E60: =ПОДБОР_КВ.М!BL67 -> 0 | F60: =IF(A60<Вводные!G10,"До продаж",IF(A60<=EDATE(Вводные!G8,Вводные!G9),"Строительство","После РВЭ")) -> После РВЭ
A61: =ПОДБОР_КВ.М!BM2 -> 48000 | B61: =ПОДБОР_КВ.М!BM64 -> 0 | C61: =ПОДБОР_КВ.М!BM65 -> 0 | D61: =ПОДБОР_КВ.М!BM66 -> 0 | E61: =ПОДБОР_КВ.М!BM67 -> 0 | F61: =IF(A61<Вводные!G10,"До продаж",IF(A61<=EDATE(Вводные!G8,Вводные!G9),"Строительство","После РВЭ")) -> После РВЭ
A62: =ПОДБОР_КВ.М!BN2 -> 48030 | B62: =ПОДБОР_КВ.М!BN64 -> 0 | C62: =ПОДБОР_КВ.М!BN65 -> 0 | D62: =ПОДБОР_КВ.М!BN66 -> 0 | E62: =ПОДБОР_КВ.М!BN67 -> 0 | F62: =IF(A62<Вводные!G10,"До продаж",IF(A62<=EDATE(Вводные!G8,Вводные!G9),"Строительство","После РВЭ")) -> После РВЭ
A63: =ПОДБОР_КВ.М!BO2 -> 48061 | B63: =ПОДБОР_КВ.М!BO64 -> 0 | C63: =ПОДБОР_КВ.М!BO65 -> 0 | D63: =ПОДБОР_КВ.М!BO66 -> 0 | E63: =ПОДБОР_КВ.М!BO67 -> 0 | F63: =IF(A63<Вводные!G10,"До продаж",IF(A63<=EDATE(Вводные!G8,Вводные!G9),"Строительство","После РВЭ")) -> После РВЭ
A64: =ПОДБОР_КВ.М!BP2 -> 48092 | B64: =ПОДБОР_КВ.М!BP64 -> 0 | C64: =ПОДБОР_КВ.М!BP65 -> 0 | D64: =ПОДБОР_КВ.М!BP66 -> 0 | E64: =ПОДБОР_КВ.М!BP67 -> 0 | F64: =IF(A64<Вводные!G10,"До продаж",IF(A64<=EDATE(Вводные!G8,Вводные!G9),"Строительство","После РВЭ")) -> После РВЭ
A65: =ПОДБОР_КВ.М!BQ2 -> 48122 | B65: =ПОДБОР_КВ.М!BQ64 -> 0 | C65: =ПОДБОР_КВ.М!BQ65 -> 0 | D65: =ПОДБОР_КВ.М!BQ66 -> 0 | E65: =ПОДБОР_КВ.М!BQ67 -> 0 | F65: =IF(A65<Вводные!G10,"До продаж",IF(A65<=EDATE(Вводные!G8,Вводные!G9),"Строительство","После РВЭ")) -> После РВЭ
A66: =ПОДБОР_КВ.М!BR2 -> 48153 | B66: =ПОДБОР_КВ.М!BR64 -> 0 | C66: =ПОДБОР_КВ.М!BR65 -> 0 | D66: =ПОДБОР_КВ.М!BR66 -> 0 | E66: =ПОДБОР_КВ.М!BR67 -> 0 | F66: =IF(A66<Вводные!G10,"До продаж",IF(A66<=EDATE(Вводные!G8,Вводные!G9),"Строительство","После РВЭ")) -> После РВЭ
A67: =ПОДБОР_КВ.М!BS2 -> 48183 | B67: =ПОДБОР_КВ.М!BS64 -> 0 | C67: =ПОДБОР_КВ.М!BS65 -> 0 | D67: =ПОДБОР_КВ.М!BS66 -> 0 | E67: =ПОДБОР_КВ.М!BS67 -> 0 | F67: =IF(A67<Вводные!G10,"До продаж",IF(A67<=EDATE(Вводные!G8,Вводные!G9),"Строительство","После РВЭ")) -> После РВЭ
A68: =ПОДБОР_КВ.М!BT2 -> 48214 | B68: =ПОДБОР_КВ.М!BT64 -> 0 | C68: =ПОДБОР_КВ.М!BT65 -> 0 | D68: =ПОДБОР_КВ.М!BT66 -> 0 | E68: =ПОДБОР_КВ.М!BT67 -> 0 | F68: =IF(A68<Вводные!G10,"До продаж",IF(A68<=EDATE(Вводные!G8,Вводные!G9),"Строительство","После РВЭ")) -> После РВЭ
A69: =ПОДБОР_КВ.М!BU2 -> 48245 | B69: =ПОДБОР_КВ.М!BU64 -> 0 | C69: =ПОДБОР_КВ.М!BU65 -> 0 | D69: =ПОДБОР_КВ.М!BU66 -> 0 | E69: =ПОДБОР_КВ.М!BU67 -> 0 | F69: =IF(A69<Вводные!G10,"До продаж",IF(A69<=EDATE(Вводные!G8,Вводные!G9),"Строительство","После РВЭ")) -> После РВЭ
A70: =ПОДБОР_КВ.М!BV2 -> 48274 | B70: =ПОДБОР_КВ.М!BV64 -> 0 | C70: =ПОДБОР_КВ.М!BV65 -> 0 | D70: =ПОДБОР_КВ.М!BV66 -> 0 | E70: =ПОДБОР_КВ.М!BV67 -> 0 | F70: =IF(A70<Вводные!G10,"До продаж",IF(A70<=EDATE(Вводные!G8,Вводные!G9),"Строительство","После РВЭ")) -> После РВЭ
A71: =ПОДБОР_КВ.М!BW2 -> 48305 | B71: =ПОДБОР_КВ.М!BW64 -> 0 | C71: =ПОДБОР_КВ.М!BW65 -> 0 | D71: =ПОДБОР_КВ.М!BW66 -> 0 | E71: =ПОДБОР_КВ.М!BW67 -> 0 | F71: =IF(A71<Вводные!G10,"До продаж",IF(A71<=EDATE(Вводные!G8,Вводные!G9),"Строительство","После РВЭ")) -> После РВЭ
A72: =ПОДБОР_КВ.М!BX2 -> 48335 | B72: =ПОДБОР_КВ.М!BX64 -> 0 | C72: =ПОДБОР_КВ.М!BX65 -> 0 | D72: =ПОДБОР_КВ.М!BX66 -> 0 | E72: =ПОДБОР_КВ.М!BX67 -> 0 | F72: =IF(A72<Вводные!G10,"До продаж",IF(A72<=EDATE(Вводные!G8,Вводные!G9),"Строительство","После РВЭ")) -> После РВЭ
A73: =ПОДБОР_КВ.М!BY2 -> 48366 | B73: =ПОДБОР_КВ.М!BY64 -> 0 | C73: =ПОДБОР_КВ.М!BY65 -> 0 | D73: =ПОДБОР_КВ.М!BY66 -> 0 | E73: =ПОДБОР_КВ.М!BY67 -> 0 | F73: =IF(A73<Вводные!G10,"До продаж",IF(A73<=EDATE(Вводные!G8,Вводные!G9),"Строительство","После РВЭ")) -> После РВЭ
A74: =ПОДБОР_КВ.М!BZ2 -> 48396 | B74: =ПОДБОР_КВ.М!BZ64 -> 0 | C74: =ПОДБОР_КВ.М!BZ65 -> 0 | D74: =ПОДБОР_КВ.М!BZ66 -> 0 | E74: =ПОДБОР_КВ.М!BZ67 -> 0 | F74: =IF(A74<Вводные!G10,"До продаж",IF(A74<=EDATE(Вводные!G8,Вводные!G9),"Строительство","После РВЭ")) -> После РВЭ
A75: =ПОДБОР_КВ.М!CA2 -> 48427 | B75: =ПОДБОР_КВ.М!CA64 -> 0 | C75: =ПОДБОР_КВ.М!CA65 -> 0 | D75: =ПОДБОР_КВ.М!CA66 -> 0 | E75: =ПОДБОР_КВ.М!CA67 -> 0 | F75: =IF(A75<Вводные!G10,"До продаж",IF(A75<=EDATE(Вводные!G8,Вводные!G9),"Строительство","После РВЭ")) -> После РВЭ
A76: =ПОДБОР_КВ.М!CB2 -> 48458 | B76: =ПОДБОР_КВ.М!CB64 -> 0 | C76: =ПОДБОР_КВ.М!CB65 -> 0 | D76: =ПОДБОР_КВ.М!CB66 -> 0 | E76: =ПОДБОР_КВ.М!CB67 -> 0 | F76: =IF(A76<Вводные!G10,"До продаж",IF(A76<=EDATE(Вводные!G8,Вводные!G9),"Строительство","После РВЭ")) -> После РВЭ
A77: =ПОДБОР_КВ.М!CC2 -> 48488 | B77: =ПОДБОР_КВ.М!CC64 -> 0 | C77: =ПОДБОР_КВ.М!CC65 -> 0 | D77: =ПОДБОР_КВ.М!CC66 -> 0 | E77: =ПОДБОР_КВ.М!CC67 -> 0 | F77: =IF(A77<Вводные!G10,"До продаж",IF(A77<=EDATE(Вводные!G8,Вводные!G9),"Строительство","После РВЭ")) -> После РВЭ
A78: =ПОДБОР_КВ.М!CD2 -> 48519 | B78: =ПОДБОР_КВ.М!CD64 -> 0 | C78: =ПОДБОР_КВ.М!CD65 -> 0 | D78: =ПОДБОР_КВ.М!CD66 -> 0 | E78: =ПОДБОР_КВ.М!CD67 -> 0 | F78: =IF(A78<Вводные!G10,"До продаж",IF(A78<=EDATE(Вводные!G8,Вводные!G9),"Строительство","После РВЭ")) -> После РВЭ
A79: =ПОДБОР_КВ.М!CE2 -> 48549 | B79: =ПОДБОР_КВ.М!CE64 -> 0 | C79: =ПОДБОР_КВ.М!CE65 -> 0 | D79: =ПОДБОР_КВ.М!CE66 -> 0 | E79: =ПОДБОР_КВ.М!CE67 -> 0 | F79: =IF(A79<Вводные!G10,"До продаж",IF(A79<=EDATE(Вводные!G8,Вводные!G9),"Строительство","После РВЭ")) -> После РВЭ
A80: =ПОДБОР_КВ.М!CF2 -> 48580 | B80: =ПОДБОР_КВ.М!CF64 -> 0 | C80: =ПОДБОР_КВ.М!CF65 -> 0 | D80: =ПОДБОР_КВ.М!CF66 -> 0 | E80: =ПОДБОР_КВ.М!CF67 -> 0 | F80: =IF(A80<Вводные!G10,"До продаж",IF(A80<=EDATE(Вводные!G8,Вводные!G9),"Строительство","После РВЭ")) -> После РВЭ
A81: =ПОДБОР_КВ.М!CG2 -> 48611 | B81: =ПОДБОР_КВ.М!CG64 -> 0 | C81: =ПОДБОР_КВ.М!CG65 -> 0 | D81: =ПОДБОР_КВ.М!CG66 -> 0 | E81: =ПОДБОР_КВ.М!CG67 -> 0 | F81: =IF(A81<Вводные!G10,"До продаж",IF(A81<=EDATE(Вводные!G8,Вводные!G9),"Строительство","После РВЭ")) -> После РВЭ
A82: =ПОДБОР_КВ.М!CH2 -> 48639 | B82: =ПОДБОР_КВ.М!CH64 -> 0 | C82: =ПОДБОР_КВ.М!CH65 -> 0 | D82: =ПОДБОР_КВ.М!CH66 -> 0 | E82: =ПОДБОР_КВ.М!CH67 -> 0 | F82: =IF(A82<Вводные!G10,"До продаж",IF(A82<=EDATE(Вводные!G8,Вводные!G9),"Строительство","После РВЭ")) -> После РВЭ
A83: =ПОДБОР_КВ.М!CI2 -> 48670 | B83: =ПОДБОР_КВ.М!CI64 -> 0 | C83: =ПОДБОР_КВ.М!CI65 -> 0 | D83: =ПОДБОР_КВ.М!CI66 -> 0 | E83: =ПОДБОР_КВ.М!CI67 -> 0 | F83: =IF(A83<Вводные!G10,"До продаж",IF(A83<=EDATE(Вводные!G8,Вводные!G9),"Строительство","После РВЭ")) -> После РВЭ
A84: =ПОДБОР_КВ.М!CJ2 -> 48700 | B84: =ПОДБОР_КВ.М!CJ64 -> 0 | C84: =ПОДБОР_КВ.М!CJ65 -> 0 | D84: =ПОДБОР_КВ.М!CJ66 -> 0 | E84: =ПОДБОР_КВ.М!CJ67 -> 0 | F84: =IF(A84<Вводные!G10,"До продаж",IF(A84<=EDATE(Вводные!G8,Вводные!G9),"Строительство","После РВЭ")) -> После РВЭ
A85: =ПОДБОР_КВ.М!CK2 -> 48731 | B85: =ПОДБОР_КВ.М!CK64 -> 0 | C85: =ПОДБОР_КВ.М!CK65 -> 0 | D85: =ПОДБОР_КВ.М!CK66 -> 0 | E85: =ПОДБОР_КВ.М!CK67 -> 0 | F85: =IF(A85<Вводные!G10,"До продаж",IF(A85<=EDATE(Вводные!G8,Вводные!G9),"Строительство","После РВЭ")) -> После РВЭ
A86: =ПОДБОР_КВ.М!CL2 -> 48761 | B86: =ПОДБОР_КВ.М!CL64 -> 0 | C86: =ПОДБОР_КВ.М!CL65 -> 0 | D86: =ПОДБОР_КВ.М!CL66 -> 0 | E86: =ПОДБОР_КВ.М!CL67 -> 0 | F86: =IF(A86<Вводные!G10,"До продаж",IF(A86<=EDATE(Вводные!G8,Вводные!G9),"Строительство","После РВЭ")) -> После РВЭ
A87: =ПОДБОР_КВ.М!CM2 -> 48792 | B87: =ПОДБОР_КВ.М!CM64 -> 0 | C87: =ПОДБОР_КВ.М!CM65 -> 0 | D87: =ПОДБОР_КВ.М!CM66 -> 0 | E87: =ПОДБОР_КВ.М!CM67 -> 0 | F87: =IF(A87<Вводные!G10,"До продаж",IF(A87<=EDATE(Вводные!G8,Вводные!G9),"Строительство","После РВЭ")) -> После РВЭ
A88: =ПОДБОР_КВ.М!CN2 -> 48823 | B88: =ПОДБОР_КВ.М!CN64 -> 0 | C88: =ПОДБОР_КВ.М!CN65 -> 0 | D88: =ПОДБОР_КВ.М!CN66 -> 0 | E88: =ПОДБОР_КВ.М!CN67 -> 0 | F88: =IF(A88<Вводные!G10,"До продаж",IF(A88<=EDATE(Вводные!G8,Вводные!G9),"Строительство","После РВЭ")) -> После РВЭ
A89: =ПОДБОР_КВ.М!CO2 -> 48853 | B89: =ПОДБОР_КВ.М!CO64 -> 0 | C89: =ПОДБОР_КВ.М!CO65 -> 0 | D89: =ПОДБОР_КВ.М!CO66 -> 0 | E89: =ПОДБОР_КВ.М!CO67 -> 0 | F89: =IF(A89<Вводные!G10,"До продаж",IF(A89<=EDATE(Вводные!G8,Вводные!G9),"Строительство","После РВЭ")) -> После РВЭ
A90: =ПОДБОР_КВ.М!CP2 -> 48884 | B90: =ПОДБОР_КВ.М!CP64 -> 0 | C90: =ПОДБОР_КВ.М!CP65 -> 0 | D90: =ПОДБОР_КВ.М!CP66 -> 0 | E90: =ПОДБОР_КВ.М!CP67 -> 0 | F90: =IF(A90<Вводные!G10,"До продаж",IF(A90<=EDATE(Вводные!G8,Вводные!G9),"Строительство","После РВЭ")) -> После РВЭ
A91: =ПОДБОР_КВ.М!CQ2 -> 48914 | B91: =ПОДБОР_КВ.М!CQ64 -> 0 | C91: =ПОДБОР_КВ.М!CQ65 -> 0 | D91: =ПОДБОР_КВ.М!CQ66 -> 0 | E91: =ПОДБОР_КВ.М!CQ67 -> 0 | F91: =IF(A91<Вводные!G10,"До продаж",IF(A91<=EDATE(Вводные!G8,Вводные!G9),"Строительство","После РВЭ")) -> После РВЭ
A92: =ПОДБОР_КВ.М!CR2 -> 48945 | B92: =ПОДБОР_КВ.М!CR64 -> 0 | C92: =ПОДБОР_КВ.М!CR65 -> 0 | D92: =ПОДБОР_КВ.М!CR66 -> 0 | E92: =ПОДБОР_КВ.М!CR67 -> 0 | F92: =IF(A92<Вводные!G10,"До продаж",IF(A92<=EDATE(Вводные!G8,Вводные!G9),"Строительство","После РВЭ")) -> После РВЭ
A93: =ПОДБОР_КВ.М!CS2 -> 48976 | B93: =ПОДБОР_КВ.М!CS64 -> 0 | C93: =ПОДБОР_КВ.М!CS65 -> 0 | D93: =ПОДБОР_КВ.М!CS66 -> 0 | E93: =ПОДБОР_КВ.М!CS67 -> 0 | F93: =IF(A93<Вводные!G10,"До продаж",IF(A93<=EDATE(Вводные!G8,Вводные!G9),"Строительство","После РВЭ")) -> После РВЭ
A94: =ПОДБОР_КВ.М!CT2 -> 49004 | B94: =ПОДБОР_КВ.М!CT64 -> 0 | C94: =ПОДБОР_КВ.М!CT65 -> 0 | D94: =ПОДБОР_КВ.М!CT66 -> 0 | E94: =ПОДБОР_КВ.М!CT67 -> 0 | F94: =IF(A94<Вводные!G10,"До продаж",IF(A94<=EDATE(Вводные!G8,Вводные!G9),"Строительство","После РВЭ")) -> После РВЭ
A95: =ПОДБОР_КВ.М!CU2 -> 49035 | B95: =ПОДБОР_КВ.М!CU64 -> 0 | C95: =ПОДБОР_КВ.М!CU65 -> 0 | D95: =ПОДБОР_КВ.М!CU66 -> 0 | E95: =ПОДБОР_КВ.М!CU67 -> 0 | F95: =IF(A95<Вводные!G10,"До продаж",IF(A95<=EDATE(Вводные!G8,Вводные!G9),"Строительство","После РВЭ")) -> После РВЭ
A96: =ПОДБОР_КВ.М!CV2 -> 49065 | B96: =ПОДБОР_КВ.М!CV64 -> 0 | C96: =ПОДБОР_КВ.М!CV65 -> 0 | D96: =ПОДБОР_КВ.М!CV66 -> 0 | E96: =ПОДБОР_КВ.М!CV67 -> 0 | F96: =IF(A96<Вводные!G10,"До продаж",IF(A96<=EDATE(Вводные!G8,Вводные!G9),"Строительство","После РВЭ")) -> После РВЭ
A97: =ПОДБОР_КВ.М!CW2 -> 49096 | B97: =ПОДБОР_КВ.М!CW64 -> 0 | C97: =ПОДБОР_КВ.М!CW65 -> 0 | D97: =ПОДБОР_КВ.М!CW66 -> 0 | E97: =ПОДБОР_КВ.М!CW67 -> 0 | F97: =IF(A97<Вводные!G10,"До продаж",IF(A97<=EDATE(Вводные!G8,Вводные!G9),"Строительство","После РВЭ")) -> После РВЭ
A98: =ПОДБОР_КВ.М!CX2 -> 49126 | B98: =ПОДБОР_КВ.М!CX64 -> 0 | C98: =ПОДБОР_КВ.М!CX65 -> 0 | D98: =ПОДБОР_КВ.М!CX66 -> 0 | E98: =ПОДБОР_КВ.М!CX67 -> 0 | F98: =IF(A98<Вводные!G10,"До продаж",IF(A98<=EDATE(Вводные!G8,Вводные!G9),"Строительство","После РВЭ")) -> После РВЭ
A99: =ПОДБОР_КВ.М!CY2 -> 49157 | B99: =ПОДБОР_КВ.М!CY64 -> 0 | C99: =ПОДБОР_КВ.М!CY65 -> 0 | D99: =ПОДБОР_КВ.М!CY66 -> 0 | E99: =ПОДБОР_КВ.М!CY67 -> 0 | F99: =IF(A99<Вводные!G10,"До продаж",IF(A99<=EDATE(Вводные!G8,Вводные!G9),"Строительство","После РВЭ")) -> После РВЭ
A100: =ПОДБОР_КВ.М!CZ2 -> 49188 | B100: =ПОДБОР_КВ.М!CZ64 -> 0 | C100: =ПОДБОР_КВ.М!CZ65 -> 0 | D100: =ПОДБОР_КВ.М!CZ66 -> 0 | E100: =ПОДБОР_КВ.М!CZ67 -> 0 | F100: =IF(A100<Вводные!G10,"До продаж",IF(A100<=EDATE(Вводные!G8,Вводные!G9),"Строительство","После РВЭ")) -> После РВЭ
A101: =ПОДБОР_КВ.М!DA2 -> 49218 | B101: =ПОДБОР_КВ.М!DA64 -> 0 | C101: =ПОДБОР_КВ.М!DA65 -> 0 | D101: =ПОДБОР_КВ.М!DA66 -> 0 | E101: =ПОДБОР_КВ.М!DA67 -> 0 | F101: =IF(A101<Вводные!G10,"До продаж",IF(A101<=EDATE(Вводные!G8,Вводные!G9),"Строительство","После РВЭ")) -> После РВЭ
...

Sheet Финансирование
A1: ПЛАТО — ФИНАНСИРОВАНИЕ ПРОЕКТА
A3: Блок | B3: Показатель | C3: Значение | D3: Ед. изм. | E3: Источник | F3: Комментарий
A4: БРИДЖ | B4: Стоимость покупки | C4: =Вводные!G6 -> 700 | D4: млн ₽ | E4: Вводные | F4: Вводится на листе «Вводные»
A5: БРИДЖ | B5: Социальный платеж / обременения | C5: =IF(Вводные!G82="Денежная компенсация",IF(ABS('Расчет ВРИ (ТЭП)'!D83)>100000,'Расчет ВРИ (ТЭП)'!D83/1000,'Расчет ВРИ (ТЭП)'!D83),0) -> 988.447 | D5: млн ₽ | E5: Расчет ВРИ!D83 | F5: Только денежная компенсация: разовая выборка БРИДЖ до РнС. При строительстве строка равна 0; затраты финансируются через ПФ по помесячному графику.
A6: БРИДЖ | B6: Проектирование стадий П и РД | C6: =(Вводные!G24+Вводные!G25)*ТЭП!D4/1000 -> 209.85 | D6: млн ₽ | E6: ОТЧЕТ!C35 | F6: Рассчитывается из площади и нормативов
A7: БРИДЖ | B7: Расчетная потребность в БРИДЖ | C7: =SUM(C4:C6) -> 1898.297 | D7: млн ₽ | E7: Сумма трех строк выше | F7: Не является ручной вводной
A8: БРИДЖ | B8: Расчетный лимит БРИДЖ в кредитном модуле | C8: =КРЕДИТЫ!D41/1000000 -> 1898.297 | D8: млн ₽ | E8: КРЕДИТЫ!D41 | F8: Автоматически равен расчетной потребности
A9: БРИДЖ | B9: Фактическая выборка БРИДЖ | C9: =ОТЧЕТ!C25 -> 1048.6505 | D9: млн ₽ | E9: ОТЧЕТ!C25 | F9: Определяется помесячным денежным потоком
A10: БРИДЖ | B10: Запас / (превышение) лимита | C10: =C8-C9 -> 849.64646 | D10: млн ₽ | E10: Лимит минус выборка
A11: Справочно | B11: ИРД и согласования | C11: =Вводные!G23*ТЭП!D4/1000 -> 41.97 | D11: млн ₽ | E11: ОТЧЕТ!C34 | F11: Показано отдельно; в формулу БРИДЖ не включено
A12: ПФ | B12: Лимит проектного финансирования | C12: =КРЕДИТЫ!D67/1000000 -> 14270 | D12: млн ₽ | E12: КРЕДИТЫ!D67 | F12: Расчетный лимит ПФ определяется кредитным модулем и округляется до 10 млн ₽.
A13: ПФ | B13: Фактическая выборка ПФ | C13: 44807.021 | D13: млн ₽ | E13: ОТЧЕТ!C26 | F13: Рассчитывается моделью
A14: ПФ | B14: Запас / (превышение) лимита ПФ | C14: =C12-C13 -> -30537.021 | D14: млн ₽ | E14: Лимит минус выборка
A15: Долг | B15: Процентные расходы | C15: 8414.0609 | D15: млн ₽ | E15: ОТЧЕТ!C22
A16: Долг | B16: LLCR | C16: =ОТЧЕТ!C30 -> 1.1968375 | D16: x | E16: ОТЧЕТ!C30 | F16: Расчет и контроль переноса БРИДЖ — на листе «LLCR»
A17: Вход | B17: Стоимость смены ВРИ | C17: ='Расчет ВРИ (ТЭП)'!D73 -> 2141.838 | D17: млн ₽ | E17: Расчет ВРИ!D73 | F17: Отдельная инвестиционная нагрузка
A18: Вход | B18: Социальный платеж | C18: ='Расчет ВРИ (ТЭП)'!D83 -> 988.447 | D18: млн ₽ | E18: Расчет ВРИ!D83 | F18: Отдельная социальная нагрузка
A20: СРОКИ БРИДЖ, СТАВКИ И LLCR
A21: БРИДЖ | B21: Начало БРИДЖ | C21: =Вводные!G7 -> 46266 | D21: дата | E21: Вводные!G7 | F21: Дата покупки / старта проекта
A22: БРИДЖ | B22: Погашение БРИДЖ | C22: =КРЕДИТЫ!D40 -> 46813 | D22: дата | E22: КРЕДИТЫ!D40 | F22: РнС + настраиваемый лаг
A23: БРИДЖ | B23: Срок БРИДЖ | C23: =Ставки!G6 -> 18 | D23: мес. | E23: Ставки!G6 | F23: Считается автоматически
A24: ИРД | B24: Срок ИРД до РнС | C24: =Вводные!G48 -> 18 | D24: мес. | E24: Вводные!G49 | F24: Базовый сценарий — 18 месяцев
A25: Долг | B25: Средняя ставка БРИДЖ | C25: =Ставки!B5 -> 0.18924731 | D25: % год | E25: Ставки!B5 | F25: За период действия БРИДЖ
A26: Долг | B26: Средневзвешенная ставка ПФ | C26: =Ставки!B4 -> 0.058023046 | D26: % год | E26: Ставки!B4 | F26: Взвешена по остатку ПФ
A27: Долг | B27: Средневзвешенная совокупная ставка | C27: =Ставки!B6 -> 0.06810413 | D27: % год | E27: Ставки!B6 | F27: БРИДЖ + ПФ
A28: БРИДЖ | B28: Расчетный лимит БРИДЖ | C28: =Ставки!B7 -> 931.04345 | D28: млн ₽ | E28: Ставки!B7 | F28: Потребность по модели
A29: ПФ | B29: Пиковая выборка ПФ | C29: =Ставки!B9 -> 14264.843 | D29: млн ₽ | E29: Ставки!B9 | F29: Максимальный остаток
A30: Эскроу | B30: Среднее покрытие ПФ эскроу | C30: =Ставки!B11 -> 1.9901741 | D30: x | E30: Ставки!B11 | F30: Совокупный эскроу / ПФ
A31: LLCR | B31: LLCR с учетом БРИДЖ | C31: =LLCR!C18 -> 1.1968375 | D31: x | E31: LLCR!C18 | F31: С корректировкой переноса процентов БРИДЖ
A32: LLCR | B32: Корректировка двойного учета процентов БРИДЖ | C32: =LLCR!C16 -> 200.58366 | D32: млн ₽ | E32: LLCR!C16 | F32: Применяется при КРЕДИТЫ!D42 = 0

Sheet Ставки
A1: ПЛАТО — СТАВКИ, БРИДЖ, ПФ И ЭСКРОУ
A3: Показатель | B3: Значение | C3: Ед. изм. | D3: Комментарий | F3: БРИДЖ | G3: Значение | H3: Ед. изм. | I3: Комментарий
A4: Средневзвешенная ставка ПФ | B4: =IFERROR(SUMPRODUCT(G16:G87,H16:H87)/SUM(H16:H87),0) -> 0.058023046 | C4: % год | D4: Взвешена по ежемесячному остатку ПФ | F4: Начало БРИДЖ | G4: =Вводные!G7 -> 46266 | H4: дата | I4: Дата покупки / начала проекта
A5: Средняя ставка БРИДЖ за период | B5: =IFERROR(SUM(C16:C87)/COUNT(C16:C87),0) -> 0.18924731 | C5: % год | D5: Средняя ставка от покупки до рефинансирования | F5: Погашение БРИДЖ | G5: =EDATE(Вводные!G8,Вводные!G50) -> 46813 | H5: дата | I5: РнС + настраиваемый лаг
A6: Средневзвешенная совокупная ставка | B6: =IFERROR((SUMPRODUCT(C16:C87,D16:D87)+SUMPRODUCT(G16:G87,H16:H87))/(SUM(D16:D87)+SUM(H16:H87)),0) -> 0.06810413 | C6: % год | D6: БРИДЖ + ПФ | F6: Срок БРИДЖ | G6: =12*(YEAR(G5)-YEAR(G4))+MONTH(G5)-MONTH(G4) -> 18 | H6: мес. | I6: Считается автоматически
A7: Расчетный лимит БРИДЖ | B7: =Вводные!G6+'Расчет ВРИ (ТЭП)'!D83/1000-ОТЧЕТ!C35 -> 931.04345 | C7: млн ₽ | D7: Покупка + соцплатеж + проектирование | F7: Срок ИРД | G7: =Вводные!G48 -> 18 | H7: мес. | I7: Базовый сценарий — 18 месяцев
A8: Пиковая фактическая выборка БРИДЖ | B8: =MAX(E16:E87) -> 700.84525 | C8: млн ₽ | D8: Максимальный положительный остаток | F8: Дата РнС | G8: =Вводные!G8 -> 46813 | H8: дата | I8: Покупка + срок ИРД
A9: Пиковая выборка ПФ | B9: =MAX(H16:H87) -> 14264.843 | C9: млн ₽ | D9: Максимальный остаток ПФ
A10: Пик средств на эскроу | B10: =MAX(I16:I87) -> 16533.156 | C10: млн ₽ | D10: Максимальный остаток
A11: Среднее покрытие ПФ эскроу | B11: =IFERROR(SUM(I16:I87)/SUM(H16:H87),0) -> 1.9901741 | C11: x | D11: Совокупный эскроу / совокупный ПФ
A12: Процентные расходы проекта | B12: =LLCR!C17-LLCR!C14 -> 1232.1559 | C12: млн ₽ | D12: После корректировки переноса БРИДЖ
A15: Месяц | B15: Ключевая ставка | C15: Ставка БРИДЖ | D15: Расчетный БРИДЖ, млн ₽ | E15: Факт. остаток БРИДЖ, млн ₽ | F15: Базовая ставка ПФ | G15: Фактическая ставка ПФ | H15: Остаток ПФ, млн ₽ | I15: Эскроу, млн ₽ | J15: Покрытие эскроу / ПФ | K15: Проценты за месяц, млн ₽ | L15: Этап | N15: Месяц | O15: Ключевая ставка | P15: Ставка БРИДЖ | Q15: Фактическая ставка ПФ | T15: Месяц | U15: Остаток ПФ, млн ₽ | V15: Эскроу, млн ₽
A16: =Вводные!G7 -> 46266 | B16: =IF(A16<=EDATE(EDATE(Вводные!G8,Вводные!G9),Вводные!G51),IFERROR(КРЕДИТЫ!S11,0),"") -> 0.1425 | C16: =IF(AND(A16>=Вводные!G7,A16<EDATE(Вводные!G8,Вводные!G50)),B16+Вводные!G39,"") -> 0.2025 | D16: =IF(AND(A16>=Вводные!G7,A16<EDATE(Вводные!G8,Вводные!G50)),Вводные!G6+'Расчет ВРИ (ТЭП)'!D83/1000-ОТЧЕТ!C35,0) -> 931.04345 | E16: =IF(AND(A16>=Вводные!G7,A16<=EDATE(Вводные!G8,Вводные!G50)),MAX(0,IFERROR(КРЕДИТЫ!S38/1000000,0)),0) -> 0 | F16: =IF(A16<=EDATE(EDATE(Вводные!G8,Вводные!G9),Вводные!G51),IFERROR(КРЕДИТЫ!S15,0),"") -> 0.1875 | G16: =IF(H16>0,IFERROR(КРЕДИТЫ!S55,""),"") | H16: =MAX(0,IFERROR(КРЕДИТЫ!S52/1000000,0)) -> 0 | I16: =MAX(0,IFERROR(КРЕДИТЫ!S51/1000000,0)) -> 0 | J16: =IFERROR(I16/H16,0) -> 0 | K16: =IFERROR((КРЕДИТЫ!S43+КРЕДИТЫ!S63)/1000000,0) -> 0 | L16: =IF(A16<Вводные!G8,"ИРД / БРИДЖ",IF(A16<EDATE(Вводные!G8,Вводные!G9),"Строительство / ПФ",IF(A16<=EDATE(EDATE(Вводные!G8,Вводные!G9),Вводные!G51),"Остаточные продажи",""))) -> ИРД / БРИДЖ | N16: =CHOOSE(MONTH(A16),"янв","фев","мар","апр","май","июн","июл","авг","сен","окт","ноя","дек")&"-"&RIGHT(YEAR(A16),2) -> сен-26 | O16: =B16 -> 0.1425 | P16: =IF(C16="",NA(),C16) -> 0.2025 | Q16: =IF(G16="",NA(),G16) -> #N/A | T16: =CHOOSE(MONTH(A16),"янв","фев","мар","апр","май","июн","июл","авг","сен","окт","ноя","дек")&"-"&RIGHT(YEAR(A16),2) -> сен-26 | U16: =IF(A16>=Вводные!G8,H16,NA()) -> #N/A | V16: =IF(A16>=Вводные!G8,I16,NA()) -> #N/A
A17: =EDATE(A16,1) -> 46296 | B17: =IF(A17<=EDATE(EDATE(Вводные!G8,Вводные!G9),Вводные!G51),IFERROR(КРЕДИТЫ!T11,0),"") -> 0.1383871 | C17: =IF(AND(A17>=Вводные!G7,A17<EDATE(Вводные!G8,Вводные!G50)),B17+Вводные!G39,"") -> 0.1983871 | D17: =IF(AND(A17>=Вводные!G7,A17<EDATE(Вводные!G8,Вводные!G50)),Вводные!G6+'Расчет ВРИ (ТЭП)'!D83/1000-ОТЧЕТ!C35,0) -> 931.04345 | E17: =IF(AND(A17>=Вводные!G7,A17<=EDATE(Вводные!G8,Вводные!G50)),MAX(0,IFERROR(КРЕДИТЫ!T38/1000000,0)),0) -> 0 | F17: =IF(A17<=EDATE(EDATE(Вводные!G8,Вводные!G9),Вводные!G51),IFERROR(КРЕДИТЫ!T15,0),"") -> 0.1833871 | G17: =IF(H17>0,IFERROR(КРЕДИТЫ!T55,""),"") | H17: =MAX(0,IFERROR(КРЕДИТЫ!T52/1000000,0)) -> 0 | I17: =MAX(0,IFERROR(КРЕДИТЫ!T51/1000000,0)) -> 0 | J17: =IFERROR(I17/H17,0) -> 0 | K17: =IFERROR((КРЕДИТЫ!T43+КРЕДИТЫ!T63)/1000000,0) -> 0 | L17: =IF(A17<Вводные!G8,"ИРД / БРИДЖ",IF(A17<EDATE(Вводные!G8,Вводные!G9),"Строительство / ПФ",IF(A17<=EDATE(EDATE(Вводные!G8,Вводные!G9),Вводные!G51),"Остаточные продажи",""))) -> ИРД / БРИДЖ | N17: =CHOOSE(MONTH(A17),"янв","фев","мар","апр","май","июн","июл","авг","сен","окт","ноя","дек")&"-"&RIGHT(YEAR(A17),2) -> окт-26 | O17: =B17 -> 0.1383871 | P17: =IF(C17="",NA(),C17) -> 0.1983871 | Q17: =IF(G17="",NA(),G17) -> #N/A | T17: =CHOOSE(MONTH(A17),"янв","фев","мар","апр","май","июн","июл","авг","сен","окт","ноя","дек")&"-"&RIGHT(YEAR(A17),2) -> окт-26 | U17: =IF(A17>=Вводные!G8,H17,NA()) -> #N/A | V17: =IF(A17>=Вводные!G8,I17,NA()) -> #N/A
A18: =EDATE(A17,1) -> 46327 | B18: =IF(A18<=EDATE(EDATE(Вводные!G8,Вводные!G9),Вводные!G51),IFERROR(КРЕДИТЫ!U11,0),"") -> 0.1383871 | C18: =IF(AND(A18>=Вводные!G7,A18<EDATE(Вводные!G8,Вводные!G50)),B18+Вводные!G39,"") -> 0.1983871 | D18: =IF(AND(A18>=Вводные!G7,A18<EDATE(Вводные!G8,Вводные!G50)),Вводные!G6+'Расчет ВРИ (ТЭП)'!D83/1000-ОТЧЕТ!C35,0) -> 931.04345 | E18: =IF(AND(A18>=Вводные!G7,A18<=EDATE(Вводные!G8,Вводные!G50)),MAX(0,IFERROR(КРЕДИТЫ!U38/1000000,0)),0) -> 0.84525 | F18: =IF(A18<=EDATE(EDATE(Вводные!G8,Вводные!G9),Вводные!G51),IFERROR(КРЕДИТЫ!U15,0),"") -> 0.1833871 | G18: =IF(H18>0,IFERROR(КРЕДИТЫ!U55,""),"") | H18: =MAX(0,IFERROR(КРЕДИТЫ!U52/1000000,0)) -> 0 | I18: =MAX(0,IFERROR(КРЕДИТЫ!U51/1000000,0)) -> 0 | J18: =IFERROR(I18/H18,0) -> 0 | K18: =IFERROR((КРЕДИТЫ!U43+КРЕДИТЫ!U63)/1000000,0) -> 0 | L18: =IF(A18<Вводные!G8,"ИРД / БРИДЖ",IF(A18<EDATE(Вводные!G8,Вводные!G9),"Строительство / ПФ",IF(A18<=EDATE(EDATE(Вводные!G8,Вводные!G9),Вводные!G51),"Остаточные продажи",""))) -> ИРД / БРИДЖ | N18: =CHOOSE(MONTH(A18),"янв","фев","мар","апр","май","июн","июл","авг","сен","окт","ноя","дек")&"-"&RIGHT(YEAR(A18),2) -> ноя-26 | O18: =B18 -> 0.1383871 | P18: =IF(C18="",NA(),C18) -> 0.1983871 | Q18: =IF(G18="",NA(),G18) -> #N/A | T18: =CHOOSE(MONTH(A18),"янв","фев","мар","апр","май","июн","июл","авг","сен","окт","ноя","дек")&"-"&RIGHT(YEAR(A18),2) -> ноя-26 | U18: =IF(A18>=Вводные!G8,H18,NA()) -> #N/A | V18: =IF(A18>=Вводные!G8,I18,NA()) -> #N/A
A19: =EDATE(A18,1) -> 46357 | B19: =IF(A19<=EDATE(EDATE(Вводные!G8,Вводные!G9),Вводные!G51),IFERROR(КРЕДИТЫ!V11,0),"") -> 0.13564516 | C19: =IF(AND(A19>=Вводные!G7,A19<EDATE(Вводные!G8,Вводные!G50)),B19+Вводные!G39,"") -> 0.19564516 | D19: =IF(AND(A19>=Вводные!G7,A19<EDATE(Вводные!G8,Вводные!G50)),Вводные!G6+'Расчет ВРИ (ТЭП)'!D83/1000-ОТЧЕТ!C35,0) -> 931.04345 | E19: =IF(AND(A19>=Вводные!G7,A19<=EDATE(Вводные!G8,Вводные!G50)),MAX(0,IFERROR(КРЕДИТЫ!V38/1000000,0)),0) -> 700.84525 | F19: =IF(A19<=EDATE(EDATE(Вводные!G8,Вводные!G9),Вводные!G51),IFERROR(КРЕДИТЫ!V15,0),"") -> 0.18064516 | G19: =IF(H19>0,IFERROR(КРЕДИТЫ!V55,""),"") | H19: =MAX(0,IFERROR(КРЕДИТЫ!V52/1000000,0)) -> 0 | I19: =MAX(0,IFERROR(КРЕДИТЫ!V51/1000000,0)) -> 0 | J19: =IFERROR(I19/H19,0) -> 0 | K19: =IFERROR((КРЕДИТЫ!V43+КРЕДИТЫ!V63)/1000000,0) -> 0.013780756 | L19: =IF(A19<Вводные!G8,"ИРД / БРИДЖ",IF(A19<EDATE(Вводные!G8,Вводные!G9),"Строительство / ПФ",IF(A19<=EDATE(EDATE(Вводные!G8,Вводные!G9),Вводные!G51),"Остаточные продажи",""))) -> ИРД / БРИДЖ | N19: =CHOOSE(MONTH(A19),"янв","фев","мар","апр","май","июн","июл","авг","сен","окт","ноя","дек")&"-"&RIGHT(YEAR(A19),2) -> дек-26 | O19: =B19 -> 0.13564516 | P19: =IF(C19="",NA(),C19) -> 0.19564516 | Q19: =IF(G19="",NA(),G19) -> #N/A | T19: =CHOOSE(MONTH(A19),"янв","фев","мар","апр","май","июн","июл","авг","сен","окт","ноя","дек")&"-"&RIGHT(YEAR(A19),2) -> дек-26 | U19: =IF(A19>=Вводные!G8,H19,NA()) -> #N/A | V19: =IF(A19>=Вводные!G8,I19,NA()) -> #N/A
A20: =EDATE(A19,1) -> 46388 | B20: =IF(A20<=EDATE(EDATE(Вводные!G8,Вводные!G9),Вводные!G51),IFERROR(КРЕДИТЫ!W11,0),"") -> 0.13564516 | C20: =IF(AND(A20>=Вводные!G7,A20<EDATE(Вводные!G8,Вводные!G50)),B20+Вводные!G39,"") -> 0.19564516 | D20: =IF(AND(A20>=Вводные!G7,A20<EDATE(Вводные!G8,Вводные!G50)),Вводные!G6+'Расчет ВРИ (ТЭП)'!D83/1000-ОТЧЕТ!C35,0) -> 931.04345 | E20: =IF(AND(A20>=Вводные!G7,A20<=EDATE(Вводные!G8,Вводные!G50)),MAX(0,IFERROR(КРЕДИТЫ!W38/1000000,0)),0) -> 0.84525 | F20: =IF(A20<=EDATE(EDATE(Вводные!G8,Вводные!G9),Вводные!G51),IFERROR(КРЕДИТЫ!W15,0),"") -> 0.18064516 | G20: =IF(H20>0,IFERROR(КРЕДИТЫ!W55,""),"") | H20: =MAX(0,IFERROR(КРЕДИТЫ!W52/1000000,0)) -> 0 | I20: =MAX(0,IFERROR(КРЕДИТЫ!W51/1000000,0)) -> 0 | J20: =IFERROR(I20/H20,0) -> 0 | K20: =IFERROR((КРЕДИТЫ!W43+КРЕДИТЫ!W63)/1000000,0) -> 11.440196 | L20: =IF(A20<Вводные!G8,"ИРД / БРИДЖ",IF(A20<EDATE(Вводные!G8,Вводные!G9),"Строительство / ПФ",IF(A20<=EDATE(EDATE(Вводные!G8,Вводные!G9),Вводные!G51),"Остаточные продажи",""))) -> ИРД / БРИДЖ | N20: =CHOOSE(MONTH(A20),"янв","фев","мар","апр","май","июн","июл","авг","сен","окт","ноя","дек")&"-"&RIGHT(YEAR(A20),2) -> янв-27 | O20: =B20 -> 0.13564516 | P20: =IF(C20="",NA(),C20) -> 0.19564516 | Q20: =IF(G20="",NA(),G20) -> #N/A | T20: =CHOOSE(MONTH(A20),"янв","фев","мар","апр","май","июн","июл","авг","сен","окт","ноя","дек")&"-"&RIGHT(YEAR(A20),2) -> янв-27 | U20: =IF(A20>=Вводные!G8,H20,NA()) -> #N/A | V20: =IF(A20>=Вводные!G8,I20,NA()) -> #N/A
A21: =EDATE(A20,1) -> 46419 | B21: =IF(A21<=EDATE(EDATE(Вводные!G8,Вводные!G9),Вводные!G51),IFERROR(КРЕДИТЫ!X11,0),"") -> 0.13564516 | C21: =IF(AND(A21>=Вводные!G7,A21<EDATE(Вводные!G8,Вводные!G50)),B21+Вводные!G39,"") -> 0.19564516 | D21: =IF(AND(A21>=Вводные!G7,A21<EDATE(Вводные!G8,Вводные!G50)),Вводные!G6+'Расчет ВРИ (ТЭП)'!D83/1000-ОТЧЕТ!C35,0) -> 931.04345 | E21: =IF(AND(A21>=Вводные!G7,A21<=EDATE(Вводные!G8,Вводные!G50)),MAX(0,IFERROR(КРЕДИТЫ!X38/1000000,0)),0) -> 0.84525 | F21: =IF(A21<=EDATE(EDATE(Вводные!G8,Вводные!G9),Вводные!G51),IFERROR(КРЕДИТЫ!X15,0),"") -> 0.18064516 | G21: =IF(H21>0,IFERROR(КРЕДИТЫ!X55,""),"") | H21: =MAX(0,IFERROR(КРЕДИТЫ!X52/1000000,0)) -> 0 | I21: =MAX(0,IFERROR(КРЕДИТЫ!X51/1000000,0)) -> 0 | J21: =IFERROR(I21/H21,0) -> 0 | K21: =IFERROR((КРЕДИТЫ!X43+КРЕДИТЫ!X63)/1000000,0) -> 11.453977 | L21: =IF(A21<Вводные!G8,"ИРД / БРИДЖ",IF(A21<EDATE(Вводные!G8,Вводные!G9),"Строительство / ПФ",IF(A21<=EDATE(EDATE(Вводные!G8,Вводные!G9),Вводные!G51),"Остаточные продажи",""))) -> ИРД / БРИДЖ | N21: =CHOOSE(MONTH(A21),"янв","фев","мар","апр","май","июн","июл","авг","сен","окт","ноя","дек")&"-"&RIGHT(YEAR(A21),2) -> фев-27 | O21: =B21 -> 0.13564516 | P21: =IF(C21="",NA(),C21) -> 0.19564516 | Q21: =IF(G21="",NA(),G21) -> #N/A | T21: =CHOOSE(MONTH(A21),"янв","фев","мар","апр","май","июн","июл","авг","сен","окт","ноя","дек")&"-"&RIGHT(YEAR(A21),2) -> фев-27 | U21: =IF(A21>=Вводные!G8,H21,NA()) -> #N/A | V21: =IF(A21>=Вводные!G8,I21,NA()) -> #N/A
A22: =EDATE(A21,1) -> 46447 | B22: =IF(A22<=EDATE(EDATE(Вводные!G8,Вводные!G9),Вводные!G51),IFERROR(КРЕДИТЫ!Y11,0),"") -> 0.13153226 | C22: =IF(AND(A22>=Вводные!G7,A22<EDATE(Вводные!G8,Вводные!G50)),B22+Вводные!G39,"") -> 0.19153226 | D22: =IF(AND(A22>=Вводные!G7,A22<EDATE(Вводные!G8,Вводные!G50)),Вводные!G6+'Расчет ВРИ (ТЭП)'!D83/1000-ОТЧЕТ!C35,0) -> 931.04345 | E22: =IF(AND(A22>=Вводные!G7,A22<=EDATE(Вводные!G8,Вводные!G50)),MAX(0,IFERROR(КРЕДИТЫ!Y38/1000000,0)),0) -> 0.84525 | F22: =IF(A22<=EDATE(EDATE(Вводные!G8,Вводные!G9),Вводные!G51),IFERROR(КРЕДИТЫ!Y15,0),"") -> 0.17653226 | G22: =IF(H22>0,IFERROR(КРЕДИТЫ!Y55,""),"") | H22: =MAX(0,IFERROR(КРЕДИТЫ!Y52/1000000,0)) -> 0 | I22: =MAX(0,IFERROR(КРЕДИТЫ!Y51/1000000,0)) -> 0 | J22: =IFERROR(I22/H22,0) -> 0 | K22: =IFERROR((КРЕДИТЫ!Y43+КРЕДИТЫ!Y63)/1000000,0) -> 11.226679 | L22: =IF(A22<Вводные!G8,"ИРД / БРИДЖ",IF(A22<EDATE(Вводные!G8,Вводные!G9),"Строительство / ПФ",IF(A22<=EDATE(EDATE(Вводные!G8,Вводные!G9),Вводные!G51),"Остаточные продажи",""))) -> ИРД / БРИДЖ | N22: =CHOOSE(MONTH(A22),"янв","фев","мар","апр","май","июн","июл","авг","сен","окт","ноя","дек")&"-"&RIGHT(YEAR(A22),2) -> мар-27 | O22: =B22 -> 0.13153226 | P22: =IF(C22="",NA(),C22) -> 0.19153226 | Q22: =IF(G22="",NA(),G22) -> #N/A | T22: =CHOOSE(MONTH(A22),"янв","фев","мар","апр","май","июн","июл","авг","сен","окт","ноя","дек")&"-"&RIGHT(YEAR(A22),2) -> мар-27 | U22: =IF(A22>=Вводные!G8,H22,NA()) -> #N/A | V22: =IF(A22>=Вводные!G8,I22,NA()) -> #N/A
A23: =EDATE(A22,1) -> 46478 | B23: =IF(A23<=EDATE(EDATE(Вводные!G8,Вводные!G9),Вводные!G51),IFERROR(КРЕДИТЫ!Z11,0),"") -> 0.13153226 | C23: =IF(AND(A23>=Вводные!G7,A23<EDATE(Вводные!G8,Вводные!G50)),B23+Вводные!G39,"") -> 0.19153226 | D23: =IF(AND(A23>=Вводные!G7,A23<EDATE(Вводные!G8,Вводные!G50)),Вводные!G6+'Расчет ВРИ (ТЭП)'!D83/1000-ОТЧЕТ!C35,0) -> 931.04345 | E23: =IF(AND(A23>=Вводные!G7,A23<=EDATE(Вводные!G8,Вводные!G50)),MAX(0,IFERROR(КРЕДИТЫ!Z38/1000000,0)),0) -> 0.84525 | F23: =IF(A23<=EDATE(EDATE(Вводные!G8,Вводные!G9),Вводные!G51),IFERROR(КРЕДИТЫ!Z15,0),"") -> 0.17653226 | G23: =IF(H23>0,IFERROR(КРЕДИТЫ!Z55,""),"") | H23: =MAX(0,IFERROR(КРЕДИТЫ!Z52/1000000,0)) -> 0 | I23: =MAX(0,IFERROR(КРЕДИТЫ!Z51/1000000,0)) -> 0 | J23: =IFERROR(I23/H23,0) -> 0 | K23: =IFERROR((КРЕДИТЫ!Z43+КРЕДИТЫ!Z63)/1000000,0) -> 11.24017 | L23: =IF(A23<Вводные!G8,"ИРД / БРИДЖ",IF(A23<EDATE(Вводные!G8,Вводные!G9),"Строительство / ПФ",IF(A23<=EDATE(EDATE(Вводные!G8,Вводные!G9),Вводные!G51),"Остаточные продажи",""))) -> ИРД / БРИДЖ | N23: =CHOOSE(MONTH(A23),"янв","фев","мар","апр","май","июн","июл","авг","сен","окт","ноя","дек")&"-"&RIGHT(YEAR(A23),2) -> апр-27 | O23: =B23 -> 0.13153226 | P23: =IF(C23="",NA(),C23) -> 0.19153226 | Q23: =IF(G23="",NA(),G23) -> #N/A | T23: =CHOOSE(MONTH(A23),"янв","фев","мар","апр","май","июн","июл","авг","сен","окт","ноя","дек")&"-"&RIGHT(YEAR(A23),2) -> апр-27 | U23: =IF(A23>=Вводные!G8,H23,NA()) -> #N/A | V23: =IF(A23>=Вводные!G8,I23,NA()) -> #N/A
A24: =EDATE(A23,1) -> 46508 | B24: =IF(A24<=EDATE(EDATE(Вводные!G8,Вводные!G9),Вводные!G51),IFERROR(КРЕДИТЫ!AA11,0),"") -> 0.12879032 | C24: =IF(AND(A24>=Вводные!G7,A24<EDATE(Вводные!G8,Вводные!G50)),B24+Вводные!G39,"") -> 0.18879032 | D24: =IF(AND(A24>=Вводные!G7,A24<EDATE(Вводные!G8,Вводные!G50)),Вводные!G6+'Расчет ВРИ (ТЭП)'!D83/1000-ОТЧЕТ!C35,0) -> 931.04345 | E24: =IF(AND(A24>=Вводные!G7,A24<=EDATE(Вводные!G8,Вводные!G50)),MAX(0,IFERROR(КРЕДИТЫ!AA38/1000000,0)),0) -> 0.84525 | F24: =IF(A24<=EDATE(EDATE(Вводные!G8,Вводные!G9),Вводные!G51),IFERROR(КРЕДИТЫ!AA15,0),"") -> 0.17379032 | G24: =IF(H24>0,IFERROR(КРЕДИТЫ!AA55,""),"") | H24: =MAX(0,IFERROR(КРЕДИТЫ!AA52/1000000,0)) -> 0 | I24: =MAX(0,IFERROR(КРЕДИТЫ!AA51/1000000,0)) -> 0 | J24: =IFERROR(I24/H24,0) -> 0 | K24: =IFERROR((КРЕДИТЫ!AA43+КРЕДИТЫ!AA63)/1000000,0) -> 11.092556 | L24: =IF(A24<Вводные!G8,"ИРД / БРИДЖ",IF(A24<EDATE(Вводные!G8,Вводные!G9),"Строительство / ПФ",IF(A24<=EDATE(EDATE(Вводные!G8,Вводные!G9),Вводные!G51),"Остаточные продажи",""))) -> ИРД / БРИДЖ | N24: =CHOOSE(MONTH(A24),"янв","фев","мар","апр","май","июн","июл","авг","сен","окт","ноя","дек")&"-"&RIGHT(YEAR(A24),2) -> май-27 | O24: =B24 -> 0.12879032 | P24: =IF(C24="",NA(),C24) -> 0.18879032 | Q24: =IF(G24="",NA(),G24) -> #N/A | T24: =CHOOSE(MONTH(A24),"янв","фев","мар","апр","май","июн","июл","авг","сен","окт","ноя","дек")&"-"&RIGHT(YEAR(A24),2) -> май-27 | U24: =IF(A24>=Вводные!G8,H24,NA()) -> #N/A | V24: =IF(A24>=Вводные!G8,I24,NA()) -> #N/A
A25: =EDATE(A24,1) -> 46539 | B25: =IF(A25<=EDATE(EDATE(Вводные!G8,Вводные!G9),Вводные!G51),IFERROR(КРЕДИТЫ!AB11,0),"") -> 0.12879032 | C25: =IF(AND(A25>=Вводные!G7,A25<EDATE(Вводные!G8,Вводные!G50)),B25+Вводные!G39,"") -> 0.18879032 | D25: =IF(AND(A25>=Вводные!G7,A25<EDATE(Вводные!G8,Вводные!G50)),Вводные!G6+'Расчет ВРИ (ТЭП)'!D83/1000-ОТЧЕТ!C35,0) -> 931.04345 | E25: =IF(AND(A25>=Вводные!G7,A25<=EDATE(Вводные!G8,Вводные!G50)),MAX(0,IFERROR(КРЕДИТЫ!AB38/1000000,0)),0) -> 0.84525 | F25: =IF(A25<=EDATE(EDATE(Вводные!G8,Вводные!G9),Вводные!G51),IFERROR(КРЕДИТЫ!AB15,0),"") -> 0.17379032 | G25: =IF(H25>0,IFERROR(КРЕДИТЫ!AB55,""),"") | H25: =MAX(0,IFERROR(КРЕДИТЫ!AB52/1000000,0)) -> 0 | I25: =MAX(0,IFERROR(КРЕДИТЫ!AB51/1000000,0)) -> 0 | J25: =IFERROR(I25/H25,0) -> 0 | K25: =IFERROR((КРЕДИТЫ!AB43+КРЕДИТЫ!AB63)/1000000,0) -> 11.105854 | L25: =IF(A25<Вводные!G8,"ИРД / БРИДЖ",IF(A25<EDATE(Вводные!G8,Вводные!G9),"Строительство / ПФ",IF(A25<=EDATE(EDATE(Вводные!G8,Вводные!G9),Вводные!G51),"Остаточные продажи",""))) -> ИРД / БРИДЖ | N25: =CHOOSE(MONTH(A25),"янв","фев","мар","апр","май","июн","июл","авг","сен","окт","ноя","дек")&"-"&RIGHT(YEAR(A25),2) -> июн-27 | O25: =B25 -> 0.12879032 | P25: =IF(C25="",NA(),C25) -> 0.18879032 | Q25: =IF(G25="",NA(),G25) -> #N/A | T25: =CHOOSE(MONTH(A25),"янв","фев","мар","апр","май","июн","июл","авг","сен","окт","ноя","дек")&"-"&RIGHT(YEAR(A25),2) -> июн-27 | U25: =IF(A25>=Вводные!G8,H25,NA()) -> #N/A | V25: =IF(A25>=Вводные!G8,I25,NA()) -> #N/A
A26: =EDATE(A25,1) -> 46569 | B26: =IF(A26<=EDATE(EDATE(Вводные!G8,Вводные!G9),Вводные!G51),IFERROR(КРЕДИТЫ!AC11,0),"") -> 0.12879032 | C26: =IF(AND(A26>=Вводные!G7,A26<EDATE(Вводные!G8,Вводные!G50)),B26+Вводные!G39,"") -> 0.18879032 | D26: =IF(AND(A26>=Вводные!G7,A26<EDATE(Вводные!G8,Вводные!G50)),Вводные!G6+'Расчет ВРИ (ТЭП)'!D83/1000-ОТЧЕТ!C35,0) -> 931.04345 | E26: =IF(AND(A26>=Вводные!G7,A26<=EDATE(Вводные!G8,Вводные!G50)),MAX(0,IFERROR(КРЕДИТЫ!AC38/1000000,0)),0) -> 0.84525 | F26: =IF(A26<=EDATE(EDATE(Вводные!G8,Вводные!G9),Вводные!G51),IFERROR(КРЕДИТЫ!AC15,0),"") -> 0.17379032 | G26: =IF(H26>0,IFERROR(КРЕДИТЫ!AC55,""),"") | H26: =MAX(0,IFERROR(КРЕДИТЫ!AC52/1000000,0)) -> 0 | I26: =MAX(0,IFERROR(КРЕДИТЫ!AC51/1000000,0)) -> 0 | J26: =IFERROR(I26/H26,0) -> 0 | K26: =IFERROR((КРЕДИТЫ!AC43+КРЕДИТЫ!AC63)/1000000,0) -> 11.119152 | L26: =IF(A26<Вводные!G8,"ИРД / БРИДЖ",IF(A26<EDATE(Вводные!G8,Вводные!G9),"Строительство / ПФ",IF(A26<=EDATE(EDATE(Вводные!G8,Вводные!G9),Вводные!G51),"Остаточные продажи",""))) -> ИРД / БРИДЖ | N26: =CHOOSE(MONTH(A26),"янв","фев","мар","апр","май","июн","июл","авг","сен","окт","ноя","дек")&"-"&RIGHT(YEAR(A26),2) -> июл-27 | O26: =B26 -> 0.12879032 | P26: =IF(C26="",NA(),C26) -> 0.18879032 | Q26: =IF(G26="",NA(),G26) -> #N/A | T26: =CHOOSE(MONTH(A26),"янв","фев","мар","апр","май","июн","июл","авг","сен","окт","ноя","дек")&"-"&RIGHT(YEAR(A26),2) -> июл-27 | U26: =IF(A26>=Вводные!G8,H26,NA()) -> #N/A | V26: =IF(A26>=Вводные!G8,I26,NA()) -> #N/A
A27: =EDATE(A26,1) -> 46600 | B27: =IF(A27<=EDATE(EDATE(Вводные!G8,Вводные!G9),Вводные!G51),IFERROR(КРЕДИТЫ!AD11,0),"") -> 0.12467742 | C27: =IF(AND(A27>=Вводные!G7,A27<EDATE(Вводные!G8,Вводные!G50)),B27+Вводные!G39,"") -> 0.18467742 | D27: =IF(AND(A27>=Вводные!G7,A27<EDATE(Вводные!G8,Вводные!G50)),Вводные!G6+'Расчет ВРИ (ТЭП)'!D83/1000-ОТЧЕТ!C35,0) -> 931.04345 | E27: =IF(AND(A27>=Вводные!G7,A27<=EDATE(Вводные!G8,Вводные!G50)),MAX(0,IFERROR(КРЕДИТЫ!AD38/1000000,0)),0) -> 0.84525 | F27: =IF(A27<=EDATE(EDATE(Вводные!G8,Вводные!G9),Вводные!G51),IFERROR(КРЕДИТЫ!AD15,0),"") -> 0.16967742 | G27: =IF(H27>0,IFERROR(КРЕДИТЫ!AD55,""),"") | H27: =MAX(0,IFERROR(КРЕДИТЫ!AD52/1000000,0)) -> 0 | I27: =MAX(0,IFERROR(КРЕДИТЫ!AD51/1000000,0)) -> 0 | J27: =IFERROR(I27/H27,0) -> 0 | K27: =IFERROR((КРЕДИТЫ!AD43+КРЕДИТЫ!AD63)/1000000,0) -> 10.889923 | L27: =IF(A27<Вводные!G8,"ИРД / БРИДЖ",IF(A27<EDATE(Вводные!G8,Вводные!G9),"Строительство / ПФ",IF(A27<=EDATE(EDATE(Вводные!G8,Вводные!G9),Вводные!G51),"Остаточные продажи",""))) -> ИРД / БРИДЖ | N27: =CHOOSE(MONTH(A27),"янв","фев","мар","апр","май","июн","июл","авг","сен","окт","ноя","дек")&"-"&RIGHT(YEAR(A27),2) -> авг-27 | O27: =B27 -> 0.12467742 | P27: =IF(C27="",NA(),C27) -> 0.18467742 | Q27: =IF(G27="",NA(),G27) -> #N/A | T27: =CHOOSE(MONTH(A27),"янв","фев","мар","апр","май","июн","июл","авг","сен","окт","ноя","дек")&"-"&RIGHT(YEAR(A27),2) -> авг-27 | U27: =IF(A27>=Вводные!G8,H27,NA()) -> #N/A | V27: =IF(A27>=Вводные!G8,I27,NA()) -> #N/A
A28: =EDATE(A27,1) -> 46631 | B28: =IF(A28<=EDATE(EDATE(Вводные!G8,Вводные!G9),Вводные!G51),IFERROR(КРЕДИТЫ!AE11,0),"") -> 0.12467742 | C28: =IF(AND(A28>=Вводные!G7,A28<EDATE(Вводные!G8,Вводные!G50)),B28+Вводные!G39,"") -> 0.18467742 | D28: =IF(AND(A28>=Вводные!G7,A28<EDATE(Вводные!G8,Вводные!G50)),Вводные!G6+'Расчет ВРИ (ТЭП)'!D83/1000-ОТЧЕТ!C35,0) -> 931.04345 | E28: =IF(AND(A28>=Вводные!G7,A28<=EDATE(Вводные!G8,Вводные!G50)),MAX(0,IFERROR(КРЕДИТЫ!AE38/1000000,0)),0) -> 56.202234 | F28: =IF(A28<=EDATE(EDATE(Вводные!G8,Вводные!G9),Вводные!G51),IFERROR(КРЕДИТЫ!AE15,0),"") -> 0.16967742 | G28: =IF(H28>0,IFERROR(КРЕДИТЫ!AE55,""),"") | H28: =MAX(0,IFERROR(КРЕДИТЫ!AE52/1000000,0)) -> 0 | I28: =MAX(0,IFERROR(КРЕДИТЫ!AE51/1000000,0)) -> 0 | J28: =IFERROR(I28/H28,0) -> 0 | K28: =IFERROR((КРЕДИТЫ!AE43+КРЕДИТЫ!AE63)/1000000,0) -> 10.902932 | L28: =IF(A28<Вводные!G8,"ИРД / БРИДЖ",IF(A28<EDATE(Вводные!G8,Вводные!G9),"Строительство / ПФ",IF(A28<=EDATE(EDATE(Вводные!G8,Вводные!G9),Вводные!G51),"Остаточные продажи",""))) -> ИРД / БРИДЖ | N28: =CHOOSE(MONTH(A28),"янв","фев","мар","апр","май","июн","июл","авг","сен","окт","ноя","дек")&"-"&RIGHT(YEAR(A28),2) -> сен-27 | O28: =B28 -> 0.12467742 | P28: =IF(C28="",NA(),C28) -> 0.18467742 | Q28: =IF(G28="",NA(),G28) -> #N/A | T28: =CHOOSE(MONTH(A28),"янв","фев","мар","апр","май","июн","июл","авг","сен","окт","ноя","дек")&"-"&RIGHT(YEAR(A28),2) -> сен-27 | U28: =IF(A28>=Вводные!G8,H28,NA()) -> #N/A | V28: =IF(A28>=Вводные!G8,I28,NA()) -> #N/A
A29: =EDATE(A28,1) -> 46661 | B29: =IF(A29<=EDATE(EDATE(Вводные!G8,Вводные!G9),Вводные!G51),IFERROR(КРЕДИТЫ!AF11,0),"") -> 0.12193548 | C29: =IF(AND(A29>=Вводные!G7,A29<EDATE(Вводные!G8,Вводные!G50)),B29+Вводные!G39,"") -> 0.18193548 | D29: =IF(AND(A29>=Вводные!G7,A29<EDATE(Вводные!G8,Вводные!G50)),Вводные!G6+'Расчет ВРИ (ТЭП)'!D83/1000-ОТЧЕТ!C35,0) -> 931.04345 | E29: =IF(AND(A29>=Вводные!G7,A29<=EDATE(Вводные!G8,Вводные!G50)),MAX(0,IFERROR(КРЕДИТЫ!AF38/1000000,0)),0) -> 30.838671 | F29: =IF(A29<=EDATE(EDATE(Вводные!G8,Вводные!G9),Вводные!G51),IFERROR(КРЕДИТЫ!AF15,0),"") -> 0.16693548 | G29: =IF(H29>0,IFERROR(КРЕДИТЫ!AF55,""),"") | H29: =MAX(0,IFERROR(КРЕДИТЫ!AF52/1000000,0)) -> 0 | I29: =MAX(0,IFERROR(КРЕДИТЫ!AF51/1000000,0)) -> 0 | J29: =IFERROR(I29/H29,0) -> 0 | K29: =IFERROR((КРЕДИТЫ!AF43+КРЕДИТЫ!AF63)/1000000,0) -> 11.593152 | L29: =IF(A29<Вводные!G8,"ИРД / БРИДЖ",IF(A29<EDATE(Вводные!G8,Вводные!G9),"Строительство / ПФ",IF(A29<=EDATE(EDATE(Вводные!G8,Вводные!G9),Вводные!G51),"Остаточные продажи",""))) -> ИРД / БРИДЖ | N29: =CHOOSE(MONTH(A29),"янв","фев","мар","апр","май","июн","июл","авг","сен","окт","ноя","дек")&"-"&RIGHT(YEAR(A29),2) -> окт-27 | O29: =B29 -> 0.12193548 | P29: =IF(C29="",NA(),C29) -> 0.18193548 | Q29: =IF(G29="",NA(),G29) -> #N/A | T29: =CHOOSE(MONTH(A29),"янв","фев","мар","апр","май","июн","июл","авг","сен","окт","ноя","дек")&"-"&RIGHT(YEAR(A29),2) -> окт-27 | U29: =IF(A29>=Вводные!G8,H29,NA()) -> #N/A | V29: =IF(A29>=Вводные!G8,I29,NA()) -> #N/A
A30: =EDATE(A29,1) -> 46692 | B30: =IF(A30<=EDATE(EDATE(Вводные!G8,Вводные!G9),Вводные!G51),IFERROR(КРЕДИТЫ!AG11,0),"") -> 0.12193548 | C30: =IF(AND(A30>=Вводные!G7,A30<EDATE(Вводные!G8,Вводные!G50)),B30+Вводные!G39,"") -> 0.18193548 | D30: =IF(AND(A30>=Вводные!G7,A30<EDATE(Вводные!G8,Вводные!G50)),Вводные!G6+'Расчет ВРИ (ТЭП)'!D83/1000-ОТЧЕТ!C35,0) -> 931.04345 | E30: =IF(AND(A30>=Вводные!G7,A30<=EDATE(Вводные!G8,Вводные!G50)),MAX(0,IFERROR(КРЕДИТЫ!AG38/1000000,0)),0) -> 30.838671 | F30: =IF(A30<=EDATE(EDATE(Вводные!G8,Вводные!G9),Вводные!G51),IFERROR(КРЕДИТЫ!AG15,0),"") -> 0.16693548 | G30: =IF(H30>0,IFERROR(КРЕДИТЫ!AG55,""),"") | H30: =MAX(0,IFERROR(КРЕДИТЫ!AG52/1000000,0)) -> 0 | I30: =MAX(0,IFERROR(КРЕДИТЫ!AG51/1000000,0)) -> 0 | J30: =IFERROR(I30/H30,0) -> 0 | K30: =IFERROR((КРЕДИТЫ!AG43+КРЕДИТЫ!AG63)/1000000,0) -> 12.060706 | L30: =IF(A30<Вводные!G8,"ИРД / БРИДЖ",IF(A30<EDATE(Вводные!G8,Вводные!G9),"Строительство / ПФ",IF(A30<=EDATE(EDATE(Вводные!G8,Вводные!G9),Вводные!G51),"Остаточные продажи",""))) -> ИРД / БРИДЖ | N30: =CHOOSE(MONTH(A30),"янв","фев","мар","апр","май","июн","июл","авг","сен","окт","ноя","дек")&"-"&RIGHT(YEAR(A30),2) -> ноя-27 | O30: =B30 -> 0.12193548 | P30: =IF(C30="",NA(),C30) -> 0.18193548 | Q30: =IF(G30="",NA(),G30) -> #N/A | T30: =CHOOSE(MONTH(A30),"янв","фев","мар","апр","май","июн","июл","авг","сен","окт","ноя","дек")&"-"&RIGHT(YEAR(A30),2) -> ноя-27 | U30: =IF(A30>=Вводные!G8,H30,NA()) -> #N/A | V30: =IF(A30>=Вводные!G8,I30,NA()) -> #N/A
A31: =EDATE(A30,1) -> 46722 | B31: =IF(A31<=EDATE(EDATE(Вводные!G8,Вводные!G9),Вводные!G51),IFERROR(КРЕДИТЫ!AH11,0),"") -> 0.12193548 | C31: =IF(AND(A31>=Вводные!G7,A31<EDATE(Вводные!G8,Вводные!G50)),B31+Вводные!G39,"") -> 0.18193548 | D31: =IF(AND(A31>=Вводные!G7,A31<EDATE(Вводные!G8,Вводные!G50)),Вводные!G6+'Расчет ВРИ (ТЭП)'!D83/1000-ОТЧЕТ!C35,0) -> 931.04345 | E31: =IF(AND(A31>=Вводные!G7,A31<=EDATE(Вводные!G8,Вводные!G50)),MAX(0,IFERROR(КРЕДИТЫ!AH38/1000000,0)),0) -> 131.27482 | F31: =IF(A31<=EDATE(EDATE(Вводные!G8,Вводные!G9),Вводные!G51),IFERROR(КРЕДИТЫ!AH15,0),"") -> 0.16693548 | G31: =IF(H31>0,IFERROR(КРЕДИТЫ!AH55,""),"") | H31: =MAX(0,IFERROR(КРЕДИТЫ!AH52/1000000,0)) -> 0 | I31: =MAX(0,IFERROR(КРЕДИТЫ!AH51/1000000,0)) -> 0 | J31: =IFERROR(I31/H31,0) -> 0 | K31: =IFERROR((КРЕДИТЫ!AH43+КРЕДИТЫ!AH63)/1000000,0) -> 12.528261 | L31: =IF(A31<Вводные!G8,"ИРД / БРИДЖ",IF(A31<EDATE(Вводные!G8,Вводные!G9),"Строительство / ПФ",IF(A31<=EDATE(EDATE(Вводные!G8,Вводные!G9),Вводные!G51),"Остаточные продажи",""))) -> ИРД / БРИДЖ | N31: =CHOOSE(MONTH(A31),"янв","фев","мар","апр","май","июн","июл","авг","сен","окт","ноя","дек")&"-"&RIGHT(YEAR(A31),2) -> дек-27 | O31: =B31 -> 0.12193548 | P31: =IF(C31="",NA(),C31) -> 0.18193548 | Q31: =IF(G31="",NA(),G31) -> #N/A | T31: =CHOOSE(MONTH(A31),"янв","фев","мар","апр","май","июн","июл","авг","сен","окт","ноя","дек")&"-"&RIGHT(YEAR(A31),2) -> дек-27 | U31: =IF(A31>=Вводные!G8,H31,NA()) -> #N/A | V31: =IF(A31>=Вводные!G8,I31,NA()) -> #N/A
A32: =EDATE(A31,1) -> 46753 | B32: =IF(A32<=EDATE(EDATE(Вводные!G8,Вводные!G9),Вводные!G51),IFERROR(КРЕДИТЫ!AI11,0),"") -> 0.11782258 | C32: =IF(AND(A32>=Вводные!G7,A32<EDATE(Вводные!G8,Вводные!G50)),B32+Вводные!G39,"") -> 0.17782258 | D32: =IF(AND(A32>=Вводные!G7,A32<EDATE(Вводные!G8,Вводные!G50)),Вводные!G6+'Расчет ВРИ (ТЭП)'!D83/1000-ОТЧЕТ!C35,0) -> 931.04345 | E32: =IF(AND(A32>=Вводные!G7,A32<=EDATE(Вводные!G8,Вводные!G50)),MAX(0,IFERROR(КРЕДИТЫ!AI38/1000000,0)),0) -> 45.52182 | F32: =IF(A32<=EDATE(EDATE(Вводные!G8,Вводные!G9),Вводные!G51),IFERROR(КРЕДИТЫ!AI15,0),"") -> 0.16282258 | G32: =IF(H32>0,IFERROR(КРЕДИТЫ!AI55,""),"") | H32: =MAX(0,IFERROR(КРЕДИТЫ!AI52/1000000,0)) -> 0 | I32: =MAX(0,IFERROR(КРЕДИТЫ!AI51/1000000,0)) -> 0 | J32: =IFERROR(I32/H32,0) -> 0 | K32: =IFERROR((КРЕДИТЫ!AI43+КРЕДИТЫ!AI63)/1000000,0) -> 14.190344 | L32: =IF(A32<Вводные!G8,"ИРД / БРИДЖ",IF(A32<EDATE(Вводные!G8,Вводные!G9),"Строительство / ПФ",IF(A32<=EDATE(EDATE(Вводные!G8,Вводные!G9),Вводные!G51),"Остаточные продажи",""))) -> ИРД / БРИДЖ | N32: =CHOOSE(MONTH(A32),"янв","фев","мар","апр","май","июн","июл","авг","сен","окт","ноя","дек")&"-"&RIGHT(YEAR(A32),2) -> янв-28 | O32: =B32 -> 0.11782258 | P32: =IF(C32="",NA(),C32) -> 0.17782258 | Q32: =IF(G32="",NA(),G32) -> #N/A | T32: =CHOOSE(MONTH(A32),"янв","фев","мар","апр","май","июн","июл","авг","сен","окт","ноя","дек")&"-"&RIGHT(YEAR(A32),2) -> янв-28 | U32: =IF(A32>=Вводные!G8,H32,NA()) -> #N/A | V32: =IF(A32>=Вводные!G8,I32,NA()) -> #N/A
A33: =EDATE(A32,1) -> 46784 | B33: =IF(A33<=EDATE(EDATE(Вводные!G8,Вводные!G9),Вводные!G51),IFERROR(КРЕДИТЫ!AJ11,0),"") -> 0.11782258 | C33: =IF(AND(A33>=Вводные!G7,A33<EDATE(Вводные!G8,Вводные!G50)),B33+Вводные!G39,"") -> 0.17782258 | D33: =IF(AND(A33>=Вводные!G7,A33<EDATE(Вводные!G8,Вводные!G50)),Вводные!G6+'Расчет ВРИ (ТЭП)'!D83/1000-ОТЧЕТ!C35,0) -> 931.04345 | E33: =IF(AND(A33>=Вводные!G7,A33<=EDATE(Вводные!G8,Вводные!G50)),MAX(0,IFERROR(КРЕДИТЫ!AJ38/1000000,0)),0) -> 45.52182 | F33: =IF(A33<=EDATE(EDATE(Вводные!G8,Вводные!G9),Вводные!G51),IFERROR(КРЕДИТЫ!AJ15,0),"") -> 0.16282258 | G33: =IF(H33>0,IFERROR(КРЕДИТЫ!AJ55,""),"") | H33: =MAX(0,IFERROR(КРЕДИТЫ!AJ52/1000000,0)) -> 0 | I33: =MAX(0,IFERROR(КРЕДИТЫ!AJ51/1000000,0)) -> 0 | J33: =IFERROR(I33/H33,0) -> 0 | K33: =IFERROR((КРЕДИТЫ!AJ43+КРЕДИТЫ!AJ63)/1000000,0) -> 14.864911 | L33: =IF(A33<Вводные!G8,"ИРД / БРИДЖ",IF(A33<EDATE(Вводные!G8,Вводные!G9),"Строительство / ПФ",IF(A33<=EDATE(EDATE(Вводные!G8,Вводные!G9),Вводные!G51),"Остаточные продажи",""))) -> ИРД / БРИДЖ | N33: =CHOOSE(MONTH(A33),"янв","фев","мар","апр","май","июн","июл","авг","сен","окт","ноя","дек")&"-"&RIGHT(YEAR(A33),2) -> фев-28 | O33: =B33 -> 0.11782258 | P33: =IF(C33="",NA(),C33) -> 0.17782258 | Q33: =IF(G33="",NA(),G33) -> #N/A | T33: =CHOOSE(MONTH(A33),"янв","фев","мар","апр","май","июн","июл","авг","сен","окт","ноя","дек")&"-"&RIGHT(YEAR(A33),2) -> фев-28 | U33: =IF(A33>=Вводные!G8,H33,NA()) -> #N/A | V33: =IF(A33>=Вводные!G8,I33,NA()) -> #N/A
A34: =EDATE(A33,1) -> 46813 | B34: =IF(A34<=EDATE(EDATE(Вводные!G8,Вводные!G9),Вводные!G51),IFERROR(КРЕДИТЫ!AK11,0),"") -> 0.11508065 | C34: =IF(AND(A34>=Вводные!G7,A34<EDATE(Вводные!G8,Вводные!G50)),B34+Вводные!G39,"") | D34: =IF(AND(A34>=Вводные!G7,A34<EDATE(Вводные!G8,Вводные!G50)),Вводные!G6+'Расчет ВРИ (ТЭП)'!D83/1000-ОТЧЕТ!C35,0) -> 0 | E34: =IF(AND(A34>=Вводные!G7,A34<=EDATE(Вводные!G8,Вводные!G50)),MAX(0,IFERROR(КРЕДИТЫ!AK38/1000000,0)),0) -> 0 | F34: =IF(A34<=EDATE(EDATE(Вводные!G8,Вводные!G9),Вводные!G51),IFERROR(КРЕДИТЫ!AK15,0),"") -> 0.16008065 | G34: =IF(H34>0,IFERROR(КРЕДИТЫ!AK55,""),"") -> 0.13586136 | H34: =MAX(0,IFERROR(КРЕДИТЫ!AK52/1000000,0)) -> 2573.0352 | I34: =MAX(0,IFERROR(КРЕДИТЫ!AK51/1000000,0)) -> 541.50786 | J34: =IFERROR(I34/H34,0) -> 0.21045489 | K34: =IFERROR((КРЕДИТЫ!AK43+КРЕДИТЫ!AK63)/1000000,0) -> 49.304942 | L34: =IF(A34<Вводные!G8,"ИРД / БРИДЖ",IF(A34<EDATE(Вводные!G8,Вводные!G9),"Строительство / ПФ",IF(A34<=EDATE(EDATE(Вводные!G8,Вводные!G9),Вводные!G51),"Остаточные продажи",""))) -> Строительство / ПФ | N34: =CHOOSE(MONTH(A34),"янв","фев","мар","апр","май","июн","июл","авг","сен","окт","ноя","дек")&"-"&RIGHT(YEAR(A34),2) -> мар-28 | O34: =B34 -> 0.11508065 | P34: =IF(C34="",NA(),C34) -> #N/A | Q34: =IF(G34="",NA(),G34) -> 0.13586136 | T34: =CHOOSE(MONTH(A34),"янв","фев","мар","апр","май","июн","июл","авг","сен","окт","ноя","дек")&"-"&RIGHT(YEAR(A34),2) -> мар-28 | U34: =IF(A34>=Вводные!G8,H34,NA()) -> 2573.0352 | V34: =IF(A34>=Вводные!G8,I34,NA()) -> 541.50786
A35: =EDATE(A34,1) -> 46844 | B35: =IF(A35<=EDATE(EDATE(Вводные!G8,Вводные!G9),Вводные!G51),IFERROR(КРЕДИТЫ!AL11,0),"") -> 0.11508065 | C35: =IF(AND(A35>=Вводные!G7,A35<EDATE(Вводные!G8,Вводные!G50)),B35+Вводные!G39,"") | D35: =IF(AND(A35>=Вводные!G7,A35<EDATE(Вводные!G8,Вводные!G50)),Вводные!G6+'Расчет ВРИ (ТЭП)'!D83/1000-ОТЧЕТ!C35,0) -> 0 | E35: =IF(AND(A35>=Вводные!G7,A35<=EDATE(Вводные!G8,Вводные!G50)),MAX(0,IFERROR(КРЕДИТЫ!AL38/1000000,0)),0) -> 0 | F35: =IF(A35<=EDATE(EDATE(Вводные!G8,Вводные!G9),Вводные!G51),IFERROR(КРЕДИТЫ!AL15,0),"") -> 0.16008065 | G35: =IF(H35>0,IFERROR(КРЕДИТЫ!AL55,""),"") -> 0.12845108 | H35: =MAX(0,IFERROR(КРЕДИТЫ!AL52/1000000,0)) -> 3986.1086 | I35: =MAX(0,IFERROR(КРЕДИТЫ!AL51/1000000,0)) -> 1095.5698 | J35: =IFERROR(I35/H35,0) -> 0.27484695 | K35: =IFERROR((КРЕДИТЫ!AL43+КРЕДИТЫ!AL63)/1000000,0) -> 51.611482 | L35: =IF(A35<Вводные!G8,"ИРД / БРИДЖ",IF(A35<EDATE(Вводные!G8,Вводные!G9),"Строительство / ПФ",IF(A35<=EDATE(EDATE(Вводные!G8,Вводные!G9),Вводные!G51),"Остаточные продажи",""))) -> Строительство / ПФ | N35: =CHOOSE(MONTH(A35),"янв","фев","мар","апр","май","июн","июл","авг","сен","окт","ноя","дек")&"-"&RIGHT(YEAR(A35),2) -> апр-28 | O35: =B35 -> 0.11508065 | P35: =IF(C35="",NA(),C35) -> #N/A | Q35: =IF(G35="",NA(),G35) -> 0.12845108 | T35: =CHOOSE(MONTH(A35),"янв","фев","мар","апр","май","июн","июл","авг","сен","окт","ноя","дек")&"-"&RIGHT(YEAR(A35),2) -> апр-28 | U35: =IF(A35>=Вводные!G8,H35,NA()) -> 3986.1086 | V35: =IF(A35>=Вводные!G8,I35,NA()) -> 1095.5698
A36: =EDATE(A35,1) -> 46874 | B36: =IF(A36<=EDATE(EDATE(Вводные!G8,Вводные!G9),Вводные!G51),IFERROR(КРЕДИТЫ!AM11,0),"") -> 0.11508065 | C36: =IF(AND(A36>=Вводные!G7,A36<EDATE(Вводные!G8,Вводные!G50)),B36+Вводные!G39,"") | D36: =IF(AND(A36>=Вводные!G7,A36<EDATE(Вводные!G8,Вводные!G50)),Вводные!G6+'Расчет ВРИ (ТЭП)'!D83/1000-ОТЧЕТ!C35,0) -> 0 | E36: =IF(AND(A36>=Вводные!G7,A36<=EDATE(Вводные!G8,Вводные!G50)),MAX(0,IFERROR(КРЕДИТЫ!AM38/1000000,0)),0) -> 0 | F36: =IF(A36<=EDATE(EDATE(Вводные!G8,Вводные!G9),Вводные!G51),IFERROR(КРЕДИТЫ!AM15,0),"") -> 0.16008065 | G36: =IF(H36>0,IFERROR(КРЕДИТЫ!AM55,""),"") -> 0.11886182 | H36: =MAX(0,IFERROR(КРЕДИТЫ!AM52/1000000,0)) -> 4404.6961 | I36: =MAX(0,IFERROR(КРЕДИТЫ!AM51/1000000,0)) -> 1577.6448 | J36: =IFERROR(I36/H36,0) -> 0.35817335 | K36: =IFERROR((КРЕДИТЫ!AM43+КРЕДИТЫ!AM63)/1000000,0) -> 52.561396 | L36: =IF(A36<Вводные!G8,"ИРД / БРИДЖ",IF(A36<EDATE(Вводные!G8,Вводные!G9),"Строительство / ПФ",IF(A36<=EDATE(EDATE(Вводные!G8,Вводные!G9),Вводные!G51),"Остаточные продажи",""))) -> Строительство / ПФ | N36: =CHOOSE(MONTH(A36),"янв","фев","мар","апр","май","июн","июл","авг","сен","окт","ноя","дек")&"-"&RIGHT(YEAR(A36),2) -> май-28 | O36: =B36 -> 0.11508065 | P36: =IF(C36="",NA(),C36) -> #N/A | Q36: =IF(G36="",NA(),G36) -> 0.11886182 | T36: =CHOOSE(MONTH(A36),"янв","фев","мар","апр","май","июн","июл","авг","сен","окт","ноя","дек")&"-"&RIGHT(YEAR(A36),2) -> май-28 | U36: =IF(A36>=Вводные!G8,H36,NA()) -> 4404.6961 | V36: =IF(A36>=Вводные!G8,I36,NA()) -> 1577.6448
A37: =EDATE(A36,1) -> 46905 | B37: =IF(A37<=EDATE(EDATE(Вводные!G8,Вводные!G9),Вводные!G51),IFERROR(КРЕДИТЫ!AN11,0),"") -> 0.11096774 | C37: =IF(AND(A37>=Вводные!G7,A37<EDATE(Вводные!G8,Вводные!G50)),B37+Вводные!G39,"") | D37: =IF(AND(A37>=Вводные!G7,A37<EDATE(Вводные!G8,Вводные!G50)),Вводные!G6+'Расчет ВРИ (ТЭП)'!D83/1000-ОТЧЕТ!C35,0) -> 0 | E37: =IF(AND(A37>=Вводные!G7,A37<=EDATE(Вводные!G8,Вводные!G50)),MAX(0,IFERROR(КРЕДИТЫ!AN38/1000000,0)),0) -> 0 | F37: =IF(A37<=EDATE(EDATE(Вводные!G8,Вводные!G9),Вводные!G51),IFERROR(КРЕДИТЫ!AN15,0),"") -> 0.15596774 | G37: =IF(H37>0,IFERROR(КРЕДИТЫ!AN55,""),"") -> 0.10832665 | H37: =MAX(0,IFERROR(КРЕДИТЫ!AN52/1000000,0)) -> 4823.2835 | I37: =MAX(0,IFERROR(КРЕДИТЫ!AN51/1000000,0)) -> 2070.7506 | J37: =IFERROR(I37/H37,0) -> 0.42932383 | K37: =IFERROR((КРЕДИТЫ!AN43+КРЕДИТЫ!AN63)/1000000,0) -> 52.345765 | L37: =IF(A37<Вводные!G8,"ИРД / БРИДЖ",IF(A37<EDATE(Вводные!G8,Вводные!G9),"Строительство / ПФ",IF(A37<=EDATE(EDATE(Вводные!G8,Вводные!G9),Вводные!G51),"Остаточные продажи",""))) -> Строительство / ПФ | N37: =CHOOSE(MONTH(A37),"янв","фев","мар","апр","май","июн","июл","авг","сен","окт","ноя","дек")&"-"&RIGHT(YEAR(A37),2) -> июн-28 | O37: =B37 -> 0.11096774 | P37: =IF(C37="",NA(),C37) -> #N/A | Q37: =IF(G37="",NA(),G37) -> 0.10832665 | T37: =CHOOSE(MONTH(A37),"янв","фев","мар","апр","май","июн","июл","авг","сен","окт","ноя","дек")&"-"&RIGHT(YEAR(A37),2) -> июн-28 | U37: =IF(A37>=Вводные!G8,H37,NA()) -> 4823.2835 | V37: =IF(A37>=Вводные!G8,I37,NA()) -> 2070.7506
A38: =EDATE(A37,1) -> 46935 | B38: =IF(A38<=EDATE(EDATE(Вводные!G8,Вводные!G9),Вводные!G51),IFERROR(КРЕДИТЫ!AO11,0),"") -> 0.11096774 | C38: =IF(AND(A38>=Вводные!G7,A38<EDATE(Вводные!G8,Вводные!G50)),B38+Вводные!G39,"") | D38: =IF(AND(A38>=Вводные!G7,A38<EDATE(Вводные!G8,Вводные!G50)),Вводные!G6+'Расчет ВРИ (ТЭП)'!D83/1000-ОТЧЕТ!C35,0) -> 0 | E38: =IF(AND(A38>=Вводные!G7,A38<=EDATE(Вводные!G8,Вводные!G50)),MAX(0,IFERROR(КРЕДИТЫ!AO38/1000000,0)),0) -> 0 | F38: =IF(A38<=EDATE(EDATE(Вводные!G8,Вводные!G9),Вводные!G51),IFERROR(КРЕДИТЫ!AO15,0),"") -> 0.15596774 | G38: =IF(H38>0,IFERROR(КРЕДИТЫ!AO55,""),"") -> 0.1014548 | H38: =MAX(0,IFERROR(КРЕДИТЫ!AO52/1000000,0)) -> 5241.871 | I38: =MAX(0,IFERROR(КРЕДИТЫ!AO51/1000000,0)) -> 2575.0712 | J38: =IFERROR(I38/H38,0) -> 0.49125039 | K38: =IFERROR((КРЕДИТЫ!AO43+КРЕДИТЫ!AO63)/1000000,0) -> 53.081957 | L38: =IF(A38<Вводные!G8,"ИРД / БРИДЖ",IF(A38<EDATE(Вводные!G8,Вводные!G9),"Строительство / ПФ",IF(A38<=EDATE(EDATE(Вводные!G8,Вводные!G9),Вводные!G51),"Остаточные продажи",""))) -> Строительство / ПФ | N38: =CHOOSE(MONTH(A38),"янв","фев","мар","апр","май","июн","июл","авг","сен","окт","ноя","дек")&"-"&RIGHT(YEAR(A38),2) -> июл-28 | O38: =B38 -> 0.11096774 | P38: =IF(C38="",NA(),C38) -> #N/A | Q38: =IF(G38="",NA(),G38) -> 0.1014548 | T38: =CHOOSE(MONTH(A38),"янв","фев","мар","апр","май","июн","июл","авг","сен","окт","ноя","дек")&"-"&RIGHT(YEAR(A38),2) -> июл-28 | U38: =IF(A38>=Вводные!G8,H38,NA()) -> 5241.871 | V38: =IF(A38>=Вводные!G8,I38,NA()) -> 2575.0712
A39: =EDATE(A38,1) -> 46966 | B39: =IF(A39<=EDATE(EDATE(Вводные!G8,Вводные!G9),Вводные!G51),IFERROR(КРЕДИТЫ!AP11,0),"") -> 0.10822581 | C39: =IF(AND(A39>=Вводные!G7,A39<EDATE(Вводные!G8,Вводные!G50)),B39+Вводные!G39,"") | D39: =IF(AND(A39>=Вводные!G7,A39<EDATE(Вводные!G8,Вводные!G50)),Вводные!G6+'Расчет ВРИ (ТЭП)'!D83/1000-ОТЧЕТ!C35,0) -> 0 | E39: =IF(AND(A39>=Вводные!G7,A39<=EDATE(Вводные!G8,Вводные!G50)),MAX(0,IFERROR(КРЕДИТЫ!AP38/1000000,0)),0) -> 0 | F39: =IF(A39<=EDATE(EDATE(Вводные!G8,Вводные!G9),Вводные!G51),IFERROR(КРЕДИТЫ!AP15,0),"") -> 0.15322581 | G39: =IF(H39>0,IFERROR(КРЕДИТЫ!AP55,""),"") -> 0.094131019 | H39: =MAX(0,IFERROR(КРЕДИТЫ!AP52/1000000,0)) -> 5660.4584 | I39: =MAX(0,IFERROR(КРЕДИТЫ!AP51/1000000,0)) -> 3090.7932 | J39: =IFERROR(I39/H39,0) -> 0.54603232 | K39: =IFERROR((КРЕДИТЫ!AP43+КРЕДИТЫ!AP63)/1000000,0) -> 53.04713 | L39: =IF(A39<Вводные!G8,"ИРД / БРИДЖ",IF(A39<EDATE(Вводные!G8,Вводные!G9),"Строительство / ПФ",IF(A39<=EDATE(EDATE(Вводные!G8,Вводные!G9),Вводные!G51),"Остаточные продажи",""))) -> Строительство / ПФ | N39: =CHOOSE(MONTH(A39),"янв","фев","мар","апр","май","июн","июл","авг","сен","окт","ноя","дек")&"-"&RIGHT(YEAR(A39),2) -> авг-28 | O39: =B39 -> 0.10822581 | P39: =IF(C39="",NA(),C39) -> #N/A | Q39: =IF(G39="",NA(),G39) -> 0.094131019 | T39: =CHOOSE(MONTH(A39),"янв","фев","мар","апр","май","июн","июл","авг","сен","окт","ноя","дек")&"-"&RIGHT(YEAR(A39),2) -> авг-28 | U39: =IF(A39>=Вводные!G8,H39,NA()) -> 5660.4584 | V39: =IF(A39>=Вводные!G8,I39,NA()) -> 3090.7932
A40: =EDATE(A39,1) -> 46997 | B40: =IF(A40<=EDATE(EDATE(Вводные!G8,Вводные!G9),Вводные!G51),IFERROR(КРЕДИТЫ!AQ11,0),"") -> 0.10822581 | C40: =IF(AND(A40>=Вводные!G7,A40<EDATE(Вводные!G8,Вводные!G50)),B40+Вводные!G39,"") | D40: =IF(AND(A40>=Вводные!G7,A40<EDATE(Вводные!G8,Вводные!G50)),Вводные!G6+'Расчет ВРИ (ТЭП)'!D83/1000-ОТЧЕТ!C35,0) -> 0 | E40: =IF(AND(A40>=Вводные!G7,A40<=EDATE(Вводные!G8,Вводные!G50)),MAX(0,IFERROR(КРЕДИТЫ!AQ38/1000000,0)),0) -> 0 | F40: =IF(A40<=EDATE(EDATE(Вводные!G8,Вводные!G9),Вводные!G51),IFERROR(КРЕДИТЫ!AQ15,0),"") -> 0.15322581 | G40: =IF(H40>0,IFERROR(КРЕДИТЫ!AQ55,""),"") -> 0.087171721 | H40: =MAX(0,IFERROR(КРЕДИТЫ!AQ52/1000000,0)) -> 6079.0459 | I40: =MAX(0,IFERROR(КРЕДИТЫ!AQ51/1000000,0)) -> 3710.2594 | J40: =IFERROR(I40/H40,0) -> 0.61033581 | K40: =IFERROR((КРЕДИТЫ!AQ43+КРЕДИТЫ!AQ63)/1000000,0) -> 52.642154 | L40: =IF(A40<Вводные!G8,"ИРД / БРИДЖ",IF(A40<EDATE(Вводные!G8,Вводные!G9),"Строительство / ПФ",IF(A40<=EDATE(EDATE(Вводные!G8,Вводные!G9),Вводные!G51),"Остаточные продажи",""))) -> Строительство / ПФ | N40: =CHOOSE(MONTH(A40),"янв","фев","мар","апр","май","июн","июл","авг","сен","окт","ноя","дек")&"-"&RIGHT(YEAR(A40),2) -> сен-28 | O40: =B40 -> 0.10822581 | P40: =IF(C40="",NA(),C40) -> #N/A | Q40: =IF(G40="",NA(),G40) -> 0.087171721 | T40: =CHOOSE(MONTH(A40),"янв","фев","мар","апр","май","июн","июл","авг","сен","окт","ноя","дек")&"-"&RIGHT(YEAR(A40),2) -> сен-28 | U40: =IF(A40>=Вводные!G8,H40,NA()) -> 6079.0459 | V40: =IF(A40>=Вводные!G8,I40,NA()) -> 3710.2594
A41: =EDATE(A40,1) -> 47027 | B41: =IF(A41<=EDATE(EDATE(Вводные!G8,Вводные!G9),Вводные!G51),IFERROR(КРЕДИТЫ!AR11,0),"") -> 0.10822581 | C41: =IF(AND(A41>=Вводные!G7,A41<EDATE(Вводные!G8,Вводные!G50)),B41+Вводные!G39,"") | D41: =IF(AND(A41>=Вводные!G7,A41<EDATE(Вводные!G8,Вводные!G50)),Вводные!G6+'Расчет ВРИ (ТЭП)'!D83/1000-ОТЧЕТ!C35,0) -> 0 | E41: =IF(AND(A41>=Вводные!G7,A41<=EDATE(Вводные!G8,Вводные!G50)),MAX(0,IFERROR(КРЕДИТЫ!AR38/1000000,0)),0) -> 0 | F41: =IF(A41<=EDATE(EDATE(Вводные!G8,Вводные!G9),Вводные!G51),IFERROR(КРЕДИТЫ!AR15,0),"") -> 0.15322581 | G41: =IF(H41>0,IFERROR(КРЕДИТЫ!AR55,""),"") -> 0.080878186 | H41: =MAX(0,IFERROR(КРЕДИТЫ!AR52/1000000,0)) -> 6497.6333 | I41: =MAX(0,IFERROR(КРЕДИТЫ!AR51/1000000,0)) -> 4343.588 | J41: =IFERROR(I41/H41,0) -> 0.6684877 | K41: =IFERROR((КРЕДИТЫ!AR43+КРЕДИТЫ!AR63)/1000000,0) -> 52.089555 | L41: =IF(A41<Вводные!G8,"ИРД / БРИДЖ",IF(A41<EDATE(Вводные!G8,Вводные!G9),"Строительство / ПФ",IF(A41<=EDATE(EDATE(Вводные!G8,Вводные!G9),Вводные!G51),"Остаточные продажи",""))) -> Строительство / ПФ | N41: =CHOOSE(MONTH(A41),"янв","фев","мар","апр","май","июн","июл","авг","сен","окт","ноя","дек")&"-"&RIGHT(YEAR(A41),2) -> окт-28 | O41: =B41 -> 0.10822581 | P41: =IF(C41="",NA(),C41) -> #N/A | Q41: =IF(G41="",NA(),G41) -> 0.080878186 | T41: =CHOOSE(MONTH(A41),"янв","фев","мар","апр","май","июн","июл","авг","сен","окт","ноя","дек")&"-"&RIGHT(YEAR(A41),2) -> окт-28 | U41: =IF(A41>=Вводные!G8,H41,NA()) -> 6497.6333 | V41: =IF(A41>=Вводные!G8,I41,NA()) -> 4343.588
A42: =EDATE(A41,1) -> 47058 | B42: =IF(A42<=EDATE(EDATE(Вводные!G8,Вводные!G9),Вводные!G51),IFERROR(КРЕДИТЫ!AS11,0),"") -> 0.1041129 | C42: =IF(AND(A42>=Вводные!G7,A42<EDATE(Вводные!G8,Вводные!G50)),B42+Вводные!G39,"") | D42: =IF(AND(A42>=Вводные!G7,A42<EDATE(Вводные!G8,Вводные!G50)),Вводные!G6+'Расчет ВРИ (ТЭП)'!D83/1000-ОТЧЕТ!C35,0) -> 0 | E42: =IF(AND(A42>=Вводные!G7,A42<=EDATE(Вводные!G8,Вводные!G50)),MAX(0,IFERROR(КРЕДИТЫ!AS38/1000000,0)),0) -> 0 | F42: =IF(A42<=EDATE(EDATE(Вводные!G8,Вводные!G9),Вводные!G51),IFERROR(КРЕДИТЫ!AS15,0),"") -> 0.1491129 | G42: =IF(H42>0,IFERROR(КРЕДИТЫ!AS55,""),"") -> 0.073981067 | H42: =MAX(0,IFERROR(КРЕДИТЫ!AS52/1000000,0)) -> 6916.2208 | I42: =MAX(0,IFERROR(КРЕДИТЫ!AS51/1000000,0)) -> 4991.0084 | J42: =IFERROR(I42/H42,0) -> 0.72163809 | K42: =IFERROR((КРЕДИТЫ!AS43+КРЕДИТЫ!AS63)/1000000,0) -> 50.650994 | L42: =IF(A42<Вводные!G8,"ИРД / БРИДЖ",IF(A42<EDATE(Вводные!G8,Вводные!G9),"Строительство / ПФ",IF(A42<=EDATE(EDATE(Вводные!G8,Вводные!G9),Вводные!G51),"Остаточные продажи",""))) -> Строительство / ПФ | N42: =CHOOSE(MONTH(A42),"янв","фев","мар","апр","май","июн","июл","авг","сен","окт","ноя","дек")&"-"&RIGHT(YEAR(A42),2) -> ноя-28 | O42: =B42 -> 0.1041129 | P42: =IF(C42="",NA(),C42) -> #N/A | Q42: =IF(G42="",NA(),G42) -> 0.073981067 | T42: =CHOOSE(MONTH(A42),"янв","фев","мар","апр","май","июн","июл","авг","сен","окт","ноя","дек")&"-"&RIGHT(YEAR(A42),2) -> ноя-28 | U42: =IF(A42>=Вводные!G8,H42,NA()) -> 6916.2208 | V42: =IF(A42>=Вводные!G8,I42,NA()) -> 4991.0084
A43: =EDATE(A42,1) -> 47088 | B43: =IF(A43<=EDATE(EDATE(Вводные!G8,Вводные!G9),Вводные!G51),IFERROR(КРЕДИТЫ!AT11,0),"") -> 0.1041129 | C43: =IF(AND(A43>=Вводные!G7,A43<EDATE(Вводные!G8,Вводные!G50)),B43+Вводные!G39,"") | D43: =IF(AND(A43>=Вводные!G7,A43<EDATE(Вводные!G8,Вводные!G50)),Вводные!G6+'Расчет ВРИ (ТЭП)'!D83/1000-ОТЧЕТ!C35,0) -> 0 | E43: =IF(AND(A43>=Вводные!G7,A43<=EDATE(Вводные!G8,Вводные!G50)),MAX(0,IFERROR(КРЕДИТЫ!AT38/1000000,0)),0) -> 0 | F43: =IF(A43<=EDATE(EDATE(Вводные!G8,Вводные!G9),Вводные!G51),IFERROR(КРЕДИТЫ!AT15,0),"") -> 0.1491129 | G43: =IF(H43>0,IFERROR(КРЕДИТЫ!AT55,""),"") -> 0.068875692 | H43: =MAX(0,IFERROR(КРЕДИТЫ!AT52/1000000,0)) -> 7334.8083 | I43: =MAX(0,IFERROR(КРЕДИТЫ!AT51/1000000,0)) -> 5652.7533 | J43: =IFERROR(I43/H43,0) -> 0.77067499 | K43: =IFERROR((КРЕДИТЫ!AT43+КРЕДИТЫ!AT63)/1000000,0) -> 49.885908 | L43: =IF(A43<Вводные!G8,"ИРД / БРИДЖ",IF(A43<EDATE(Вводные!G8,Вводные!G9),"Строительство / ПФ",IF(A43<=EDATE(EDATE(Вводные!G8,Вводные!G9),Вводные!G51),"Остаточные продажи",""))) -> Строительство / ПФ | N43: =CHOOSE(MONTH(A43),"янв","фев","мар","апр","май","июн","июл","авг","сен","окт","ноя","дек")&"-"&RIGHT(YEAR(A43),2) -> дек-28 | O43: =B43 -> 0.1041129 | P43: =IF(C43="",NA(),C43) -> #N/A | Q43: =IF(G43="",NA(),G43) -> 0.068875692 | T43: =CHOOSE(MONTH(A43),"янв","фев","мар","апр","май","июн","июл","авг","сен","окт","ноя","дек")&"-"&RIGHT(YEAR(A43),2) -> дек-28 | U43: =IF(A43>=Вводные!G8,H43,NA()) -> 7334.8083 | V43: =IF(A43>=Вводные!G8,I43,NA()) -> 5652.7533
A44: =EDATE(A43,1) -> 47119 | B44: =IF(A44<=EDATE(EDATE(Вводные!G8,Вводные!G9),Вводные!G51),IFERROR(КРЕДИТЫ!AU11,0),"") -> 0.10137097 | C44: =IF(AND(A44>=Вводные!G7,A44<EDATE(Вводные!G8,Вводные!G50)),B44+Вводные!G39,"") | D44: =IF(AND(A44>=Вводные!G7,A44<EDATE(Вводные!G8,Вводные!G50)),Вводные!G6+'Расчет ВРИ (ТЭП)'!D83/1000-ОТЧЕТ!C35,0) -> 0 | E44: =IF(AND(A44>=Вводные!G7,A44<=EDATE(Вводные!G8,Вводные!G50)),MAX(0,IFERROR(КРЕДИТЫ!AU38/1000000,0)),0) -> 0 | F44: =IF(A44<=EDATE(EDATE(Вводные!G8,Вводные!G9),Вводные!G51),IFERROR(КРЕДИТЫ!AU15,0),"") -> 0.14637097 | G44: =IF(H44>0,IFERROR(КРЕДИТЫ!AU55,""),"") -> 0.064930405 | H44: =MAX(0,IFERROR(КРЕДИТЫ!AU52/1000000,0)) -> 7753.3957 | I44: =MAX(0,IFERROR(КРЕДИТЫ!AU51/1000000,0)) -> 6229.0113 | J44: =IFERROR(I44/H44,0) -> 0.80339139 | K44: =IFERROR((КРЕДИТЫ!AU43+КРЕДИТЫ!AU63)/1000000,0) -> 49.554339 | L44: =IF(A44<Вводные!G8,"ИРД / БРИДЖ",IF(A44<EDATE(Вводные!G8,Вводные!G9),"Строительство / ПФ",IF(A44<=EDATE(EDATE(Вводные!G8,Вводные!G9),Вводные!G51),"Остаточные продажи",""))) -> Строительство / ПФ | N44: =CHOOSE(MONTH(A44),"янв","фев","мар","апр","май","июн","июл","авг","сен","окт","ноя","дек")&"-"&RIGHT(YEAR(A44),2) -> янв-29 | O44: =B44 -> 0.10137097 | P44: =IF(C44="",NA(),C44) -> #N/A | Q44: =IF(G44="",NA(),G44) -> 0.064930405 | T44: =CHOOSE(MONTH(A44),"янв","фев","мар","апр","май","июн","июл","авг","сен","окт","ноя","дек")&"-"&RIGHT(YEAR(A44),2) -> янв-29 | U44: =IF(A44>=Вводные!G8,H44,NA()) -> 7753.3957 | V44: =IF(A44>=Вводные!G8,I44,NA()) -> 6229.0113
A45: =EDATE(A44,1) -> 47150 | B45: =IF(A45<=EDATE(EDATE(Вводные!G8,Вводные!G9),Вводные!G51),IFERROR(КРЕДИТЫ!AV11,0),"") -> 0.10137097 | C45: =IF(AND(A45>=Вводные!G7,A45<EDATE(Вводные!G8,Вводные!G50)),B45+Вводные!G39,"") | D45: =IF(AND(A45>=Вводные!G7,A45<EDATE(Вводные!G8,Вводные!G50)),Вводные!G6+'Расчет ВРИ (ТЭП)'!D83/1000-ОТЧЕТ!C35,0) -> 0 | E45: =IF(AND(A45>=Вводные!G7,A45<=EDATE(Вводные!G8,Вводные!G50)),MAX(0,IFERROR(КРЕДИТЫ!AV38/1000000,0)),0) -> 0 | F45: =IF(A45<=EDATE(EDATE(Вводные!G8,Вводные!G9),Вводные!G51),IFERROR(КРЕДИТЫ!AV15,0),"") -> 0.14637097 | G45: =IF(H45>0,IFERROR(КРЕДИТЫ!AV55,""),"") -> 0.060531074 | H45: =MAX(0,IFERROR(КРЕДИТЫ!AV52/1000000,0)) -> 8171.9832 | I45: =MAX(0,IFERROR(КРЕДИТЫ!AV51/1000000,0)) -> 6919.9514 | J45: =IFERROR(I45/H45,0) -> 0.84678972 | K45: =IFERROR((КРЕДИТЫ!AV43+КРЕДИТЫ!AV63)/1000000,0) -> 48.567792 | L45: =IF(A45<Вводные!G8,"ИРД / БРИДЖ",IF(A45<EDATE(Вводные!G8,Вводные!G9),"Строительство / ПФ",IF(A45<=EDATE(EDATE(Вводные!G8,Вводные!G9),Вводные!G51),"Остаточные продажи",""))) -> Строительство / ПФ | N45: =CHOOSE(MONTH(A45),"янв","фев","мар","апр","май","июн","июл","авг","сен","окт","ноя","дек")&"-"&RIGHT(YEAR(A45),2) -> фев-29 | O45: =B45 -> 0.10137097 | P45: =IF(C45="",NA(),C45) -> #N/A | Q45: =IF(G45="",NA(),G45) -> 0.060531074 | T45: =CHOOSE(MONTH(A45),"янв","фев","мар","апр","май","июн","июл","авг","сен","окт","ноя","дек")&"-"&RIGHT(YEAR(A45),2) -> фев-29 | U45: =IF(A45>=Вводные!G8,H45,NA()) -> 8171.9832 | V45: =IF(A45>=Вводные!G8,I45,NA()) -> 6919.9514
A46: =EDATE(A45,1) -> 47178 | B46: =IF(A46<=EDATE(EDATE(Вводные!G8,Вводные!G9),Вводные!G51),IFERROR(КРЕДИТЫ!AW11,0),"") -> 0.10137097 | C46: =IF(AND(A46>=Вводные!G7,A46<EDATE(Вводные!G8,Вводные!G50)),B46+Вводные!G39,"") | D46: =IF(AND(A46>=Вводные!G7,A46<EDATE(Вводные!G8,Вводные!G50)),Вводные!G6+'Расчет ВРИ (ТЭП)'!D83/1000-ОТЧЕТ!C35,0) -> 0 | E46: =IF(AND(A46>=Вводные!G7,A46<=EDATE(Вводные!G8,Вводные!G50)),MAX(0,IFERROR(КРЕДИТЫ!AW38/1000000,0)),0) -> 0 | F46: =IF(A46<=EDATE(EDATE(Вводные!G8,Вводные!G9),Вводные!G51),IFERROR(КРЕДИТЫ!AW15,0),"") -> 0.14637097 | G46: =IF(H46>0,IFERROR(КРЕДИТЫ!AW55,""),"") -> 0.056382951 | H46: =MAX(0,IFERROR(КРЕДИТЫ!AW52/1000000,0)) -> 8590.5706 | I46: =MAX(0,IFERROR(КРЕДИТЫ!AW51/1000000,0)) -> 7625.935 | J46: =IFERROR(I46/H46,0) -> 0.88770995 | K46: =IFERROR((КРЕДИТЫ!AW43+КРЕДИТЫ!AW63)/1000000,0) -> 47.434174 | L46: =IF(A46<Вводные!G8,"ИРД / БРИДЖ",IF(A46<EDATE(Вводные!G8,Вводные!G9),"Строительство / ПФ",IF(A46<=EDATE(EDATE(Вводные!G8,Вводные!G9),Вводные!G51),"Остаточные продажи",""))) -> Строительство / ПФ | N46: =CHOOSE(MONTH(A46),"янв","фев","мар","апр","май","июн","июл","авг","сен","окт","ноя","дек")&"-"&RIGHT(YEAR(A46),2) -> мар-29 | O46: =B46 -> 0.10137097 | P46: =IF(C46="",NA(),C46) -> #N/A | Q46: =IF(G46="",NA(),G46) -> 0.056382951 | T46: =CHOOSE(MONTH(A46),"янв","фев","мар","апр","май","июн","июл","авг","сен","окт","ноя","дек")&"-"&RIGHT(YEAR(A46),2) -> мар-29 | U46: =IF(A46>=Вводные!G8,H46,NA()) -> 8590.5706 | V46: =IF(A46>=Вводные!G8,I46,NA()) -> 7625.935
A47: =EDATE(A46,1) -> 47209 | B47: =IF(A47<=EDATE(EDATE(Вводные!G8,Вводные!G9),Вводные!G51),IFERROR(КРЕДИТЫ!AX11,0),"") -> 0.1 | C47: =IF(AND(A47>=Вводные!G7,A47<EDATE(Вводные!G8,Вводные!G50)),B47+Вводные!G39,"") | D47: =IF(AND(A47>=Вводные!G7,A47<EDATE(Вводные!G8,Вводные!G50)),Вводные!G6+'Расчет ВРИ (ТЭП)'!D83/1000-ОТЧЕТ!C35,0) -> 0 | E47: =IF(AND(A47>=Вводные!G7,A47<=EDATE(Вводные!G8,Вводные!G50)),MAX(0,IFERROR(КРЕДИТЫ!AX38/1000000,0)),0) -> 0 | F47: =IF(A47<=EDATE(EDATE(Вводные!G8,Вводные!G9),Вводные!G51),IFERROR(КРЕДИТЫ!AX15,0),"") -> 0.145 | G47: =IF(H47>0,IFERROR(КРЕДИТЫ!AX55,""),"") -> 0.052347513 | H47: =MAX(0,IFERROR(КРЕДИТЫ!AX52/1000000,0)) -> 9009.1581 | I47: =MAX(0,IFERROR(КРЕДИТЫ!AX51/1000000,0)) -> 8347.209 | J47: =IFERROR(I47/H47,0) -> 0.92652487 | K47: =IFERROR((КРЕДИТЫ!AX43+КРЕДИТЫ!AX63)/1000000,0) -> 46.067099 | L47: =IF(A47<Вводные!G8,"ИРД / БРИДЖ",IF(A47<EDATE(Вводные!G8,Вводные!G9),"Строительство / ПФ",IF(A47<=EDATE(EDATE(Вводные!G8,Вводные!G9),Вводные!G51),"Остаточные продажи",""))) -> Строительство / ПФ | N47: =CHOOSE(MONTH(A47),"янв","фев","мар","апр","май","июн","июл","авг","сен","окт","ноя","дек")&"-"&RIGHT(YEAR(A47),2) -> апр-29 | O47: =B47 -> 0.1 | P47: =IF(C47="",NA(),C47) -> #N/A | Q47: =IF(G47="",NA(),G47) -> 0.052347513 | T47: =CHOOSE(MONTH(A47),"янв","фев","мар","апр","май","июн","июл","авг","сен","окт","ноя","дек")&"-"&RIGHT(YEAR(A47),2) -> апр-29 | U47: =IF(A47>=Вводные!G8,H47,NA()) -> 9009.1581 | V47: =IF(A47>=Вводные!G8,I47,NA()) -> 8347.209
A48: =EDATE(A47,1) -> 47239 | B48: =IF(A48<=EDATE(EDATE(Вводные!G8,Вводные!G9),Вводные!G51),IFERROR(КРЕДИТЫ!AY11,0),"") -> 0.1 | C48: =IF(AND(A48>=Вводные!G7,A48<EDATE(Вводные!G8,Вводные!G50)),B48+Вводные!G39,"") | D48: =IF(AND(A48>=Вводные!G7,A48<EDATE(Вводные!G8,Вводные!G50)),Вводные!G6+'Расчет ВРИ (ТЭП)'!D83/1000-ОТЧЕТ!C35,0) -> 0 | E48: =IF(AND(A48>=Вводные!G7,A48<=EDATE(Вводные!G8,Вводные!G50)),MAX(0,IFERROR(КРЕДИТЫ!AY38/1000000,0)),0) -> 0 | F48: =IF(A48<=EDATE(EDATE(Вводные!G8,Вводные!G9),Вводные!G51),IFERROR(КРЕДИТЫ!AY15,0),"") -> 0.145 | G48: =IF(H48>0,IFERROR(КРЕДИТЫ!AY55,""),"") -> 0.049796327 | H48: =MAX(0,IFERROR(КРЕДИТЫ!AY52/1000000,0)) -> 9427.7455 | I48: =MAX(0,IFERROR(КРЕДИТЫ!AY51/1000000,0)) -> 8975.56 | J48: =IFERROR(I48/H48,0) -> 0.95203673 | K48: =IFERROR((КРЕДИТЫ!AY43+КРЕДИТЫ!AY63)/1000000,0) -> 45.682585 | L48: =IF(A48<Вводные!G8,"ИРД / БРИДЖ",IF(A48<EDATE(Вводные!G8,Вводные!G9),"Строительство / ПФ",IF(A48<=EDATE(EDATE(Вводные!G8,Вводные!G9),Вводные!G51),"Остаточные продажи",""))) -> Строительство / ПФ | N48: =CHOOSE(MONTH(A48),"янв","фев","мар","апр","май","июн","июл","авг","сен","окт","ноя","дек")&"-"&RIGHT(YEAR(A48),2) -> май-29 | O48: =B48 -> 0.1 | P48: =IF(C48="",NA(),C48) -> #N/A | Q48: =IF(G48="",NA(),G48) -> 0.049796327 | T48: =CHOOSE(MONTH(A48),"янв","фев","мар","апр","май","июн","июл","авг","сен","окт","ноя","дек")&"-"&RIGHT(YEAR(A48),2) -> май-29 | U48: =IF(A48>=Вводные!G8,H48,NA()) -> 9427.7455 | V48: =IF(A48>=Вводные!G8,I48,NA()) -> 8975.56
